Workbook
Name Full: #REF!
Name Glossary: #REF!
Name scope: #REF!
Name TopOfTable_Table_2: #REF!

Sheet sensitivity>>
A1: Se

Sheet cost_hyper
B1: =B7 -> econ cost 0.5 | C1: =C7 -> econ cost 1 | D1: =D7 -> econ cost 2 | F1: =F7 -> vacc cost 0.5 | G1: =G7 -> vacc cost 1 | H1: =H7 -> vacc cost 2 | J1: =J7 -> hosp cost 0.5 | K1: =K7 -> hosp cost 1 | L1: =L7 -> hosp cost 2
A2: Hosp Cost | B2: 5.84392 | C2: 5.83635 | D2: 5.822396 | F2: 5.828895 | G2: 5.83635 | H2: 5.842176 | J2: 2.916813 | K2: 5.83635 | L2: 11.665745 | P2: 0 Hosp Cost | Q2: 5.84392 | R2: 0 Hosp Cost | S2: 5.822396 | T2: 0 Hosp Cost | U2: 5.828895 | V2: 0 Hosp Cost | W2: 5.842176 | X2: 0 Hosp Cost | Y2: 2.916813 | Z2: 0 Hosp Cost | AA2: 11.665745
A3: Policy Cost | B3: 4.018653 | C3: 4.170264 | D3: 4.601928 | F3: 3.087738 | G3: 4.170264 | H3: 6.222306 | J3: 4.189087 | K3: 4.170264 | L3: 4.202002 | P3: 1 Policy Cost | Q3: 4.018653 | R3: 1 Policy Cost | S3: 4.601928 | T3: 1 Policy Cost | U3: 3.087738 | V3: 1 Policy Cost | W3: 6.222306 | X3: 1 Policy Cost | Y3: 4.189087 | Z3: 1 Policy Cost | AA3: 4.202002
A4: Econ Cost | B4: 14.854796 | C4: 29.697205 | D4: 59.349877 | F4: 29.683279 | G4: 29.697205 | H4: 29.706603 | J4: 29.690989 | K4: 29.697205 | L4: 29.689624 | P4: 2 Econ Cost | Q4: 14.854796 | R4: 2 Econ Cost | S4: 59.349877 | T4: 2 Econ Cost | U4: 29.683279 | V4: 2 Econ Cost | W4: 29.706603 | X4: 2 Econ Cost | Y4: 29.690989 | Z4: 2 Econ Cost | AA4: 29.689624
A5: Total Cost | B5: 24.717369 | C5: 39.70382 | D5: 69.774202 | F5: 38.599911 | G5: 39.70382 | H5: 41.771085 | J5: 36.796889 | K5: 39.70382 | L5: 45.557371 | P5: 3 Total Cost | Q5: 24.717369 | R5: 3 Total Cost | S5: 69.774202 | T5: 3 Total Cost | U5: 38.599911 | V5: 3 Total Cost | W5: 41.771085 | X5: 3 Total Cost | Y5: 36.796889 | Z5: 3 Total Cost | AA5: 45.557371
A7: ori | B7: econ cost 0.5 | C7: econ cost 1 | D7: econ cost 2 | F7: vacc cost 0.5 | G7: vacc cost 1 | H7: vacc cost 2 | J7: hosp cost 0.5 | K7: hosp cost 1 | L7: hosp cost 2 | P7: econ cost 0.5 | R7: econ cost 2 | T7: vacc cost 0.5 | V7: vacc cost 2 | X7: hosp cost 0.5 | Z7: hosp cost 2
A8: =base_vacc!L3 -> 0.02778321 | B8: =AVERAGE(P8:Q8) -> 0.0248226 | C8: =A8 -> 0.02778321 | D8: =AVERAGE(R8:S8) -> 0.02483845 | F8: =AVERAGE(T8:U8) -> 0.0248233 | G8: =A8 -> 0.02778321 | H8: =AVERAGE(V8:W8) -> 0.02482215 | J8: =AVERAGE(X8:Y8) -> 0.02482265 | K8: =A8 -> 0.02778321 | L8: =AVERAGE(Z8:AA8) -> 0.02482335 | M8: =ROUND(L8,4)&"," -> 0.0248, | P8: 0.024833 | Q8: 0.0248122 | R8: 0.0248472 | S8: 0.0248297 | T8: 0.0248336 | U8: 0.024813 | V8: 0.0248326 | W8: 0.0248117 | X8: 0.024833 | Y8: 0.0248123 | Z8: 0.0248337 | AA8: 0.024813
A9: =base_vacc!L4 -> 0.027776404 | B9: =AVERAGE(P9:Q9) -> 0.0248241 | C9: =A9 -> 0.027776404 | D9: =AVERAGE(R9:S9) -> 0.02484115 | F9: =AVERAGE(T9:U9) -> 0.02482485 | G9: =A9 -> 0.027776404 | H9: =AVERAGE(V9:W9) -> 0.0248234 | J9: =AVERAGE(X9:Y9) -> 0.02482405 | K9: =A9 -> 0.027776404 | L9: =AVERAGE(Z9:AA9) -> 0.02482495 | M9: =ROUND(L9,4)&"," -> 0.0248, | P9: 0.0248368 | Q9: 0.0248114 | R9: 0.0248518 | S9: 0.0248305 | T9: 0.0248374 | U9: 0.0248123 | V9: 0.0248361 | W9: 0.0248107 | X9: 0.0248367 | Y9: 0.0248114 | Z9: 0.0248376 | AA9: 0.0248123
A10: =base_vacc!L5 -> 0.02776844 | B10: =AVERAGE(P10:Q10) -> 0.0248166 | C10: =A10 -> 0.02776844 | D10: =AVERAGE(R10:S10) -> 0.0248365 | F10: =AVERAGE(T10:U10) -> 0.0248174 | G10: =A10 -> 0.02776844 | H10: =AVERAGE(V10:W10) -> 0.0248157 | J10: =AVERAGE(X10:Y10) -> 0.0248164 | K10: =A10 -> 0.02776844 | L10: =AVERAGE(Z10:AA10) -> 0.0248177 | M10: =ROUND(L10,4)&"," -> 0.0248, | P10: 0.0248279 | Q10: 0.0248053 | R10: 0.0248457 | S10: 0.0248273 | T10: 0.0248286 | U10: 0.0248062 | V10: 0.0248271 | W10: 0.0248043 | X10: 0.0248277 | Y10: 0.0248051 | Z10: 0.0248289 | AA10: 0.0248065
A11: =base_vacc!L6 -> 0.027758411 | B11: =AVERAGE(P11:Q11) -> 0.0248091 | C11: =A11 -> 0.027758411 | D11: =AVERAGE(R11:S11) -> 0.02483075 | F11: =AVERAGE(T11:U11) -> 0.0248102 | G11: =A11 -> 0.027758411 | H11: =AVERAGE(V11:W11) -> 0.024808 | J11: =AVERAGE(X11:Y11) -> 0.02480895 | K11: =A11 -> 0.027758411 | L11: =AVERAGE(Z11:AA11) -> 0.02481045 | M11: =ROUND(L11,4)&"," -> 0.0248, | P11: 0.0248215 | Q11: 0.0247967 | R11: 0.0248407 | S11: 0.0248208 | T11: 0.0248224 | U11: 0.024798 | V11: 0.0248204 | W11: 0.0247956 | X11: 0.0248213 | Y11: 0.0247966 | Z11: 0.0248227 | AA11: 0.0247982
A12: =base_vacc!L7 -> 0.027740514 | B12: =AVERAGE(P12:Q12) -> 0.02480045 | C12: =A12 -> 0.027740514 | D12: =AVERAGE(R12:S12) -> 0.02482385 | F12: =AVERAGE(T12:U12) -> 0.02480205 | G12: =A12 -> 0.027740514 | H12: =AVERAGE(V12:W12) -> 0.02479925 | J12: =AVERAGE(X12:Y12) -> 0.02480055 | K12: =A12 -> 0.027740514 | L12: =AVERAGE(Z12:AA12) -> 0.02480235 | M12: =ROUND(L12,4)&"," -> 0.0248, | P12: 0.0248116 | Q12: 0.0247893 | R12: 0.024832 | S12: 0.0248157 | T12: 0.024813 | U12: 0.0247911 | V12: 0.0248104 | W12: 0.0247881 | X12: 0.0248116 | Y12: 0.0247895 | Z12: 0.0248133 | AA12: 0.0247914
A13: =base_vacc!L8 -> 0.027715634 | B13: =AVERAGE(P13:Q13) -> 0.0247878 | C13: =A13 -> 0.027715634 | D13: =AVERAGE(R13:S13) -> 0.02481565 | F13: =AVERAGE(T13:U13) -> 0.02479005 | G13: =A13 -> 0.027715634 | H13: =AVERAGE(V13:W13) -> 0.02478635 | J13: =AVERAGE(X13:Y13) -> 0.02478805 | K13: =A13 -> 0.027715634 | L13: =AVERAGE(Z13:AA13) -> 0.02479035 | M13: =ROUND(L13,4)&"," -> 0.0248, | P13: 0.024803 | Q13: 0.0247726 | R13: 0.0248285 | S13: 0.0248028 | T13: 0.024805 | U13: 0.0247751 | V13: 0.0248016 | W13: 0.0247711 | X13: 0.0248031 | Y13: 0.024773 | Z13: 0.0248053 | AA13: 0.0247754
A14: =base_vacc!L9 -> 0.02768686 | B14: =AVERAGE(P14:Q14) -> 0.02477305 | C14: =A14 -> 0.02768686 | D14: =AVERAGE(R14:S14) -> 0.02480325 | F14: =AVERAGE(T14:U14) -> 0.0247765 | G14: =A14 -> 0.02768686 | H14: =AVERAGE(V14:W14) -> 0.0247715 | J14: =AVERAGE(X14:Y14) -> 0.0247739 | K14: =A14 -> 0.02768686 | L14: =AVERAGE(Z14:AA14) -> 0.0247766 | M14: =ROUND(L14,4)&"," -> 0.0248, | P14: 0.0247858 | Q14: 0.0247603 | R14: 0.0248152 | S14: 0.0247913 | T14: 0.0247891 | U14: 0.0247639 | V14: 0.0247843 | W14: 0.0247587 | X14: 0.0247866 | Y14: 0.0247612 | Z14: 0.0247892 | AA14: 0.024764
A15: =base_vacc!L10 -> 0.027651986 | B15: =AVERAGE(P15:Q15) -> 0.0247539 | C15: =A15 -> 0.027651986 | D15: =AVERAGE(R15:S15) -> 0.0247916 | F15: =AVERAGE(T15:U15) -> 0.0247589 | G15: =A15 -> 0.027651986 | H15: =AVERAGE(V15:W15) -> 0.02475205 | J15: =AVERAGE(X15:Y15) -> 0.0247555 | K15: =A15 -> 0.027651986 | L15: =AVERAGE(Z15:AA15) -> 0.0247589 | M15: =ROUND(L15,4)&"," -> 0.0248, | P15: 0.024766 | Q15: 0.0247418 | R15: 0.0248016 | S15: 0.0247816 | T15: 0.0247709 | U15: 0.0247469 | V15: 0.0247641 | W15: 0.02474 | X15: 0.0247675 | Y15: 0.0247435 | Z15: 0.0247709 | AA15: 0.0247469
A16: =base_vacc!L11 -> 0.027605466 | B16: =AVERAGE(P16:Q16) -> 0.02473275 | C16: =A16 -> 0.027605466 | D16: =AVERAGE(R16:S16) -> 0.02477755 | F16: =AVERAGE(T16:U16) -> 0.02474065 | G16: =A16 -> 0.027605466 | H16: =AVERAGE(V16:W16) -> 0.02473085 | J16: =AVERAGE(X16:Y16) -> 0.02473605 | K16: =A16 -> 0.027605466 | L16: =AVERAGE(Z16:AA16) -> 0.0247402 | M16: =ROUND(L16,4)&"," -> 0.0247, | P16: 0.0247353 | Q16: 0.0247302 | R16: 0.0247858 | S16: 0.0247693 | T16: 0.0247441 | U16: 0.0247372 | V16: 0.0247334 | W16: 0.0247283 | X16: 0.0247391 | Y16: 0.024733 | Z16: 0.0247436 | AA16: 0.0247368
A17: =base_vacc!L12 -> 0.027535294 | B17: =AVERAGE(P17:Q17) -> 0.02470645 | C17: =A17 -> 0.027535294 | D17: =AVERAGE(R17:S17) -> 0.0247557 | F17: =AVERAGE(T17:U17) -> 0.02471785 | G17: =A17 -> 0.027535294 | H17: =AVERAGE(V17:W17) -> 0.02470415 | J17: =AVERAGE(X17:Y17) -> 0.02471165 | K17: =A17 -> 0.027535294 | L17: =AVERAGE(Z17:AA17) -> 0.0247169 | M17: =ROUND(L17,4)&"," -> 0.0247, | P17: 0.0247189 | Q17: 0.024694 | R17: 0.0247701 | S17: 0.0247413 | T17: 0.0247303 | U17: 0.0247054 | V17: 0.0247168 | W17: 0.0246915 | X17: 0.0247243 | Y17: 0.024699 | Z17: 0.0247293 | AA17: 0.0247045
A18: =base_vacc!L13 -> 0.027460909 | B18: =AVERAGE(P18:Q18) -> 0.0246499 | C18: =A18 -> 0.027460909 | D18: =AVERAGE(R18:S18) -> 0.0247213 | F18: =AVERAGE(T18:U18) -> 0.02467215 | G18: =A18 -> 0.027460909 | H18: =AVERAGE(V18:W18) -> 0.0246486 | J18: =AVERAGE(X18:Y18) -> 0.0246625 | K18: =A18 -> 0.027460909 | L18: =AVERAGE(Z18:AA18) -> 0.02466915 | M18: =ROUND(L18,4)&"," -> 0.0247, | P18: 0.0246626 | Q18: 0.0246372 | R18: 0.0247288 | S18: 0.0247138 | T18: 0.0246842 | U18: 0.0246601 | V18: 0.0246606 | W18: 0.0246366 | X18: 0.0246744 | Y18: 0.0246506 | Z18: 0.0246818 | AA18: 0.0246565
A19: =base_vacc!L14 -> 0.027376611 | B19: =AVERAGE(P19:Q19) -> 0.0246019 | C19: =A19 -> 0.027376611 | D19: =AVERAGE(R19:S19) -> 0.02466245 | F19: =AVERAGE(T19:U19) -> 0.0246348 | G19: =A19 -> 0.027376611 | H19: =AVERAGE(V19:W19) -> 0.02460185 | J19: =AVERAGE(X19:Y19) -> 0.0246217 | K19: =A19 -> 0.027376611 | L19: =AVERAGE(Z19:AA19) -> 0.0246297 | M19: =ROUND(L19,4)&"," -> 0.0246, | P19: 0.0246416 | Q19: 0.0245622 | R19: 0.0246973 | S19: 0.0246276 | T19: 0.0246676 | U19: 0.024602 | V19: 0.0246396 | W19: 0.0245641 | X19: 0.0246561 | Y19: 0.0245873 | Z19: 0.0246642 | AA19: 0.0245952
... A67: =base_vacc!L62 -> 0.004243431 | B67: =AVERAGE(P67:Q67) -> 0.00515867 | C67: =A67 -> 0.004243431 | D67: =AVERAGE(R67:S67) -> 0.00515873 | F67: =AVERAGE(T67:U67) -> 0.0051433 | G67: =A67 -> 0.004243431 | H67: =AVERAGE(V67:W67) -> 0.005173145 | J67: =AVERAGE(X67:Y67) -> 0.00515867 | K67: =A67 -> 0.004243431 | L67: =AVERAGE(Z67:AA67) -> 0.00515867 | M67: =ROUND(L67,4)&"," -> 0.0052, | P67: 0.00516653 | Q67: 0.00515081 | R67: 0.00516662 | S67: 0.00515084 | T67: 0.00515004 | U67: 0.00513656 | V67: 0.00518203 | W67: 0.00516426 | X67: 0.00516653 | Y67: 0.00515081 | Z67: 0.00516653 | AA67: 0.00515081

Sheet para_val
B1: =B7 -> sigma=0.01 | C1: =C7 -> sigma=0.05 (base) | D1: =D7 -> sigma=0.1 | E1: =E7 -> sigma=0.2 | F1: =F7 -> sigma=0.3 | G1: =G7 -> sigma=0.4 | H1: =H7 -> sigma=0.5 | J1: =J7 -> beta3*0.1 | K1: =K7 -> beta3*0.5 | L1: =L7 -> beta3*1 (base) | M1: =M7 -> beta3*2 | N1: =N7 -> beta3*3 | P1: =P7 -> delta3*0.5 | Q1: =Q7 -> delta3*1 | R1: =R7 -> delta3*2 | S1: =S7 -> delta1*0.5 | T1: =T7 -> delta1*2 | U1: =U7 -> delta23*0.5 | V1: =V7 -> delta23*2
A2: Hosp Cost | B2: 5.519248 | C2: 5.83635 | D2: 6.038377 | E2: 6.730515 | F2: 7.576262 | G2: 8.61775 | H2: 9.915519 | J2: 3.021547 | K2: 3.884077 | L2: 5.83635 | M2: 17.821244 | N2: 50.982044 | P2: 28.053339 | Q2: =C2 -> 5.83635 | R2: 1.776207 | S2: 23.772361 | T2: 2.132929 | U2: 7.259313 | V2: 5.178956
A3: Policy Cost | B3: 4.074666 | C3: 4.170264 | D3: 4.271672 | E3: 4.534862 | F3: 4.85714 | G3: 5.267555 | H3: 5.751265 | J3: 3.15276 | K3: 3.465212 | L3: 4.170264 | M3: 8.692018 | N3: 21.19033 | P3: 6.904405 | Q3: =C3 -> 4.170264 | R3: 3.470562 | S3: 6.832825 | T3: 3.472372 | U3: 4.204561 | V3: 4.182084
A4: Econ Cost | B4: 27.988069 | C4: 29.697205 | D4: 30.801153 | E4: 34.549299 | F4: 39.12923 | G4: 44.779469 | H4: 51.818102 | J4: 14.470685 | K4: 19.124871 | L4: 29.697205 | M4: 94.57006 | N4: 274.95426 | P4: 97.071066 | Q4: =C4 -> 29.697205 | R4: 14.440788 | S4: 95.994437 | T4: 14.540292 | U4: 30.060926 | V4: 29.477529
A5: Total Cost | B5: 37.581983 | C5: 39.70382 | D5: 41.111203 | E5: 45.814675 | F5: 51.562632 | G5: 58.664773 | H5: 67.484886 | J5: 20.644993 | K5: 26.47416 | L5: 39.70382 | M5: 121.08332 | N5: 347.12664 | P5: 132.02881 | Q5: =C5 -> 39.70382 | R5: 19.687558 | S5: 126.59962 | T5: 20.145593 | U5: 41.5248 | V5: 38.838569
A7: ori | B7: sigma=0.01 | C7: sigma=0.05 (base) | D7: sigma=0.1 | E7: sigma=0.2 | F7: sigma=0.3 | G7: sigma=0.4 | H7: sigma=0.5 | J7: beta3*0.1 | K7: beta3*0.5 | L7: beta3*1 (base) | M7: beta3*2 | N7: beta3*3 | P7: delta3*0.5 | Q7: delta3*1 | R7: delta3*2 | S7: delta1*0.5 | T7: delta1*2 | U7: delta23*0.5 | V7: delta23*2 | AA7: sigma0.01 | AC7: sigma0.1 | AE7: sigma*0.75 | AG7: sigma0.2 | AI7: sigma0.3 | AK7: sigma0.4 | AM7: sigma0.5 | AP7: beta3*0.1 | AR7: beta3*0.5 | AT7: beta3*2 | AV7: beta3*3 | AY7: beta1*0.5 | BA7: beta1*2 | BD7: delta3*0.5 | BF7: delta3*2 | BI7: delta1*0.5 | BK7: delta1*2 | BM7: delta23*0.5 | BO7: delta23*2
A8: =base_vacc!L3 -> 0.02778321 | B8: =AVERAGE(AA8:AB8) -> 0.02482285 | C8: =A8 -> 0.02778321 | D8: =AVERAGE(AC8:AD8) -> 0.02482295 | E8: =AVERAGE(AG8:AH8) -> 0.02482305 | F8: =AVERAGE(AI8:AJ8) -> 0.02482315 | G8: =AVERAGE(AK8:AL8) -> 0.02482355 | H8: =AVERAGE(AM8:AN8) -> 0.02482355 | J8: =AVERAGE(AP8:AQ8) -> 0.0248225 | K8: =AVERAGE(AR8:AS8) -> 0.02482255 | L8: =A8 -> 0.02778321 | M8: =AVERAGE(AT8:AU8) -> 0.0248258 | N8: =AVERAGE(AV8:AW8) -> 0.0248321 | P8: =AVERAGE(BD8:BE8) -> 0.0248257 | Q8: =A8 -> 0.02778321 | R8: =AVERAGE(BF8:BG8) -> 0.02482235 | S8: =AVERAGE(BI8:BJ8) -> 0.02482555 | T8: =AVERAGE(BK8:BL8) -> 0.02482245 | U8: =AVERAGE(BM8:BN8) -> 0.02482305 | V8: =AVERAGE(BO8:BP8) -> 0.02482275 | X8: =ROUND(V8,4)&"," -> 0.0248, | AA8: 0.0248332 | AB8: 0.0248125 | AC8: 0.0248333 | AD8: 0.0248126 | AE8: 0.0248339 | AF8: 0.0248132 | AG8: 0.0248334 | AH8: 0.0248127 | AI8: 0.0248335 | AJ8: 0.0248128 | AK8: 0.0248339 | AL8: 0.0248132 | AM8: 0.0248339 | AN8: 0.0248132 | AP8: 0.0248329 | AQ8: 0.0248121 | AR8: 0.0248329 | AS8: 0.0248122 | AT8: 0.0248359 | AU8: 0.0248157 | AV8: 0.024841 | AW8: 0.0248232 | AY8: 0.0248329 | AZ8: 0.0248122 | BA8: 0.0248359 | BB8: 0.0248157 | BD8: 0.0248359 | BE8: 0.0248155 | BF8: 0.0248327 | BG8: 0.024812 | BI8: 0.0248358 | BJ8: 0.0248153 | BK8: 0.0248328 | BL8: 0.0248121 | BM8: 0.0248334 | BN8: 0.0248127 | BO8: 0.0248331 | BP8: 0.0248124
A9: =base_vacc!L4 -> 0.027776404 | B9: =AVERAGE(AA9:AB9) -> 0.0248243 | C9: =A9 -> 0.027776404 | D9: =AVERAGE(AC9:AD9) -> 0.02482435 | E9: =AVERAGE(AG9:AH9) -> 0.02482445 | F9: =AVERAGE(AI9:AJ9) -> 0.0248246 | G9: =AVERAGE(AK9:AL9) -> 0.024825 | H9: =AVERAGE(AM9:AN9) -> 0.024825 | J9: =AVERAGE(AP9:AQ9) -> 0.0248239 | K9: =AVERAGE(AR9:AS9) -> 0.02482395 | L9: =A9 -> 0.027776404 | M9: =AVERAGE(AT9:AU9) -> 0.02482805 | N9: =AVERAGE(AV9:AW9) -> 0.02483585 | P9: =AVERAGE(BD9:BE9) -> 0.02482835 | Q9: =A9 -> 0.027776404 | R9: =AVERAGE(BF9:BG9) -> 0.0248236 | S9: =AVERAGE(BI9:BJ9) -> 0.0248278 | T9: =AVERAGE(BK9:BL9) -> 0.0248238 | U9: =AVERAGE(BM9:BN9) -> 0.02482485 | V9: =AVERAGE(BO9:BP9) -> 0.0248241 | X9: =ROUND(V9,4)&"," -> 0.0248, | AA9: 0.0248369 | AB9: 0.0248117 | AC9: 0.024837 | AD9: 0.0248117 | AE9: 0.0248377 | AF9: 0.0248123 | AG9: 0.0248371 | AH9: 0.0248118 | AI9: 0.0248373 | AJ9: 0.0248119 | AK9: 0.0248377 | AL9: 0.0248123 | AM9: 0.0248377 | AN9: 0.0248123 | AP9: 0.0248365 | AQ9: 0.0248113 | AR9: 0.0248366 | AS9: 0.0248113 | AT9: 0.0248405 | AU9: 0.0248156 | AV9: 0.024847 | AW9: 0.0248247 | AY9: 0.0248366 | AZ9: 0.0248113 | BA9: 0.0248405 | BB9: 0.0248156 | BD9: 0.0248409 | BE9: 0.0248158 | BF9: 0.0248363 | BG9: 0.0248109 | BI9: 0.0248404 | BJ9: 0.0248152 | BK9: 0.0248365 | BL9: 0.0248111 | BM9: 0.0248374 | BN9: 0.0248123 | BO9: 0.0248367 | BP9: 0.0248115
A10: =base_vacc!L5 -> 0.02776844 | B10: =AVERAGE(AA10:AB10) -> 0.0248168 | C10: =A10 -> 0.02776844 | D10: =AVERAGE(AC10:AD10) -> 0.0248169 | E10: =AVERAGE(AG10:AH10) -> 0.024817 | F10: =AVERAGE(AI10:AJ10) -> 0.02481715 | G10: =AVERAGE(AK10:AL10) -> 0.02481755 | H10: =AVERAGE(AM10:AN10) -> 0.02481755 | J10: =AVERAGE(AP10:AQ10) -> 0.0248165 | K10: =AVERAGE(AR10:AS10) -> 0.0248165 | L10: =A10 -> 0.02776844 | M10: =AVERAGE(AT10:AU10) -> 0.02482085 | N10: =AVERAGE(AV10:AW10) -> 0.02482975 | P10: =AVERAGE(BD10:BE10) -> 0.02482165 | Q10: =A10 -> 0.02776844 | R10: =AVERAGE(BF10:BG10) -> 0.02481605 | S10: =AVERAGE(BI10:BJ10) -> 0.02482075 | T10: =AVERAGE(BK10:BL10) -> 0.02481625 | U10: =AVERAGE(BM10:BN10) -> 0.02481765 | V10: =AVERAGE(BO10:BP10) -> 0.0248165 | X10: =ROUND(V10,4)&"," -> 0.0248, | AA10: 0.0248281 | AB10: 0.0248055 | AC10: 0.0248282 | AD10: 0.0248056 | AE10: 0.0248288 | AF10: 0.0248063 | AG10: 0.0248283 | AH10: 0.0248057 | AI10: 0.0248284 | AJ10: 0.0248059 | AK10: 0.0248288 | AL10: 0.0248063 | AM10: 0.0248288 | AN10: 0.0248063 | AP10: 0.0248278 | AQ10: 0.0248052 | AR10: 0.0248278 | AS10: 0.0248052 | AT10: 0.0248316 | AU10: 0.0248101 | AV10: 0.0248389 | AW10: 0.0248206 | AY10: 0.0248278 | AZ10: 0.0248052 | BA10: 0.0248315 | BB10: 0.02481 | BD10: 0.0248324 | BE10: 0.0248109 | BF10: 0.0248274 | BG10: 0.0248047 | BI10: 0.0248316 | BJ10: 0.0248099 | BK10: 0.0248276 | BL10: 0.0248049 | BM10: 0.0248288 | BN10: 0.0248065 | BO10: 0.0248278 | BP10: 0.0248052
A11: =base_vacc!L6 -> 0.027758411 | B11: =AVERAGE(AA11:AB11) -> 0.0248094 | C11: =A11 -> 0.027758411 | D11: =AVERAGE(AC11:AD11) -> 0.0248095 | E11: =AVERAGE(AG11:AH11) -> 0.0248096 | F11: =AVERAGE(AI11:AJ11) -> 0.02480975 | G11: =AVERAGE(AK11:AL11) -> 0.0248102 | H11: =AVERAGE(AM11:AN11) -> 0.0248102 | J11: =AVERAGE(AP11:AQ11) -> 0.024809 | K11: =AVERAGE(AR11:AS11) -> 0.02480905 | L11: =A11 -> 0.027758411 | M11: =AVERAGE(AT11:AU11) -> 0.0248144 | N11: =AVERAGE(AV11:AW11) -> 0.02482545 | P11: =AVERAGE(BD11:BE11) -> 0.02481585 | Q11: =A11 -> 0.027758411 | R11: =AVERAGE(BF11:BG11) -> 0.02480825 | S11: =AVERAGE(BI11:BJ11) -> 0.02481445 | T11: =AVERAGE(BK11:BL11) -> 0.02480855 | U11: =AVERAGE(BM11:BN11) -> 0.02481055 | V11: =AVERAGE(BO11:BP11) -> 0.02480895 | X11: =ROUND(V11,4)&"," -> 0.0248, | AA11: 0.0248217 | AB11: 0.0247971 | AC11: 0.0248218 | AD11: 0.0247972 | AE11: 0.0248226 | AF11: 0.0247978 | AG11: 0.0248219 | AH11: 0.0247973 | AI11: 0.0248221 | AJ11: 0.0247974 | AK11: 0.0248226 | AL11: 0.0247978 | AM11: 0.0248226 | AN11: 0.0247978 | AP11: 0.0248212 | AQ11: 0.0247968 | AR11: 0.0248213 | AS11: 0.0247968 | AT11: 0.0248265 | AU11: 0.0248023 | AV11: 0.0248359 | AW11: 0.024815 | AY11: 0.0248213 | AZ11: 0.0247968 | BA11: 0.0248264 | BB11: 0.0248022 | BD11: 0.0248279 | BE11: 0.0248038 | BF11: 0.0248207 | BG11: 0.0247958 | BI11: 0.0248266 | BJ11: 0.0248023 | BK11: 0.024821 | BL11: 0.0247961 | BM11: 0.0248227 | BN11: 0.0247984 | BO11: 0.0248213 | BP11: 0.0247966
A12: =base_vacc!L7 -> 0.027740514 | B12: =AVERAGE(AA12:AB12) -> 0.02480105 | C12: =A12 -> 0.027740514 | D12: =AVERAGE(AC12:AD12) -> 0.02480115 | E12: =AVERAGE(AG12:AH12) -> 0.02480125 | F12: =AVERAGE(AI12:AJ12) -> 0.0248014 | G12: =AVERAGE(AK12:AL12) -> 0.0248018 | H12: =AVERAGE(AM12:AN12) -> 0.0248018 | J12: =AVERAGE(AP12:AQ12) -> 0.0248008 | K12: =AVERAGE(AR12:AS12) -> 0.02480075 | L12: =A12 -> 0.027740514 | M12: =AVERAGE(AT12:AU12) -> 0.02480655 | N12: =AVERAGE(AV12:AW12) -> 0.02482035 | P12: =AVERAGE(BD12:BE12) -> 0.02480865 | Q12: =A12 -> 0.027740514 | R12: =AVERAGE(BF12:BG12) -> 0.0248 | S12: =AVERAGE(BI12:BJ12) -> 0.0248068 | T12: =AVERAGE(BK12:BL12) -> 0.02480035 | U12: =AVERAGE(BM12:BN12) -> 0.02480255 | V12: =AVERAGE(BO12:BP12) -> 0.02480045 | X12: =ROUND(V12,4)&"," -> 0.0248, | AA12: 0.0248121 | AB12: 0.02479 | AC12: 0.0248122 | AD12: 0.0247901 | AE12: 0.0248129 | AF12: 0.0247907 | AG12: 0.0248123 | AH12: 0.0247902 | AI12: 0.0248125 | AJ12: 0.0247903 | AK12: 0.0248129 | AL12: 0.0247907 | AM12: 0.0248129 | AN12: 0.0247907 | AP12: 0.0248119 | AQ12: 0.0247897 | AR12: 0.0248118 | AS12: 0.0247897 | AT12: 0.0248171 | AU12: 0.024796 | AV12: 0.0248291 | AW12: 0.0248116 | AY12: 0.0248118 | AZ12: 0.0247897 | BA12: 0.024817 | BB12: 0.0247959 | BD12: 0.0248192 | BE12: 0.0247981 | BF12: 0.0248113 | BG12: 0.0247887 | BI12: 0.0248175 | BJ12: 0.0247961 | BK12: 0.0248116 | BL12: 0.0247891 | BM12: 0.0248135 | BN12: 0.0247916 | BO12: 0.0248115 | BP12: 0.0247894
A13: =base_vacc!L8 -> 0.027715634 | B13: =AVERAGE(AA13:AB13) -> 0.02478875 | C13: =A13 -> 0.027715634 | D13: =AVERAGE(AC13:AD13) -> 0.0247889 | E13: =AVERAGE(AG13:AH13) -> 0.024789 | F13: =AVERAGE(AI13:AJ13) -> 0.0247892 | G13: =AVERAGE(AK13:AL13) -> 0.0247896 | H13: =AVERAGE(AM13:AN13) -> 0.0247896 | J13: =AVERAGE(AP13:AQ13) -> 0.02478835 | K13: =AVERAGE(AR13:AS13) -> 0.0247882 | L13: =A13 -> 0.027715634 | M13: =AVERAGE(AT13:AU13) -> 0.0247958 | N13: =AVERAGE(AV13:AW13) -> 0.02481335 | P13: =AVERAGE(BD13:BE13) -> 0.0247989 | Q13: =A13 -> 0.027715634 | R13: =AVERAGE(BF13:BG13) -> 0.02478785 | S13: =AVERAGE(BI13:BJ13) -> 0.02479615 | T13: =AVERAGE(BK13:BL13) -> 0.0247882 | U13: =AVERAGE(BM13:BN13) -> 0.02479075 | V13: =AVERAGE(BO13:BP13) -> 0.0247879 | X13: =ROUND(V13,4)&"," -> 0.0248, | AA13: 0.0248038 | AB13: 0.0247737 | AC13: 0.0248039 | AD13: 0.0247739 | AE13: 0.0248046 | AF13: 0.0247746 | AG13: 0.024804 | AH13: 0.024774 | AI13: 0.0248042 | AJ13: 0.0247742 | AK13: 0.0248046 | AL13: 0.0247746 | AM13: 0.0248046 | AN13: 0.0247746 | AP13: 0.0248033 | AQ13: 0.0247734 | AR13: 0.0248032 | AS13: 0.0247732 | AT13: 0.0248101 | AU13: 0.0247815 | AV13: 0.0248257 | AW13: 0.024801 | AY13: 0.0248032 | AZ13: 0.0247732 | BA13: 0.02481 | BB13: 0.0247813 | BD13: 0.0248132 | BE13: 0.0247846 | BF13: 0.0248032 | BG13: 0.0247725 | BI13: 0.0248107 | BJ13: 0.0247816 | BK13: 0.0248035 | BL13: 0.0247729 | BM13: 0.0248056 | BN13: 0.0247759 | BO13: 0.024803 | BP13: 0.0247728
A14: =base_vacc!L9 -> 0.02768686 | B14: =AVERAGE(AA14:AB14) -> 0.0247747 | C14: =A14 -> 0.02768686 | D14: =AVERAGE(AC14:AD14) -> 0.0247749 | E14: =AVERAGE(AG14:AH14) -> 0.02477505 | F14: =AVERAGE(AI14:AJ14) -> 0.02477525 | G14: =AVERAGE(AK14:AL14) -> 0.02477555 | H14: =AVERAGE(AM14:AN14) -> 0.02477555 | J14: =AVERAGE(AP14:AQ14) -> 0.02477375 | K14: =AVERAGE(AR14:AS14) -> 0.0247738 | L14: =A14 -> 0.02768686 | M14: =AVERAGE(AT14:AU14) -> 0.02478265 | N14: =AVERAGE(AV14:AW14) -> 0.0248043 | P14: =AVERAGE(BD14:BE14) -> 0.02478725 | Q14: =A14 -> 0.02768686 | R14: =AVERAGE(BF14:BG14) -> 0.0247723 | S14: =AVERAGE(BI14:BJ14) -> 0.0247836 | T14: =AVERAGE(BK14:BL14) -> 0.02477275 | U14: =AVERAGE(BM14:BN14) -> 0.0247773 | V14: =AVERAGE(BO14:BP14) -> 0.02477365 | X14: =ROUND(V14,4)&"," -> 0.0248, | AA14: 0.0247874 | AB14: 0.024762 | AC14: 0.0247876 | AD14: 0.0247622 | AE14: 0.0247882 | AF14: 0.0247629 | AG14: 0.0247877 | AH14: 0.0247624 | AI14: 0.0247879 | AJ14: 0.0247626 | AK14: 0.0247882 | AL14: 0.0247629 | AM14: 0.0247882 | AN14: 0.0247629 | AP14: 0.0247868 | AQ14: 0.0247607 | AR14: 0.0247866 | AS14: 0.024761 | AT14: 0.0247949 | AU14: 0.0247704 | AV14: 0.0248146 | AW14: 0.024794 | AY14: 0.0247867 | AZ14: 0.0247611 | BA14: 0.0247947 | BB14: 0.0247701 | BD14: 0.0247995 | BE14: 0.024775 | BF14: 0.0247856 | BG14: 0.024759 | BI14: 0.024796 | BJ14: 0.0247712 | BK14: 0.024786 | BL14: 0.0247595 | BM14: 0.0247899 | BN14: 0.0247647 | BO14: 0.0247864 | BP14: 0.0247609
A15: =base_vacc!L10 -> 0.027651986 | B15: =AVERAGE(AA15:AB15) -> 0.02475655 | C15: =A15 -> 0.027651986 | D15: =AVERAGE(AC15:AD15) -> 0.0247568 | E15: =AVERAGE(AG15:AH15) -> 0.0247569 | F15: =AVERAGE(AI15:AJ15) -> 0.0247571 | G15: =AVERAGE(AK15:AL15) -> 0.0247574 | H15: =AVERAGE(AM15:AN15) -> 0.0247574 | J15: =AVERAGE(AP15:AQ15) -> 0.0247559 | K15: =AVERAGE(AR15:AS15) -> 0.0247558 | L15: =A15 -> 0.027651986 | M15: =AVERAGE(AT15:AU15) -> 0.0247665 | N15: =AVERAGE(AV15:AW15) -> 0.02479435 | P15: =AVERAGE(BD15:BE15) -> 0.02477335 | Q15: =A15 -> 0.027651986 | R15: =AVERAGE(BF15:BG15) -> 0.0247548 | S15: =AVERAGE(BI15:BJ15) -> 0.0247683 | T15: =AVERAGE(BK15:BL15) -> 0.0247553 | U15: =AVERAGE(BM15:BN15) -> 0.0247598 | V15: =AVERAGE(BO15:BP15) -> 0.02475515 | X15: =ROUND(V15,4)&"," -> 0.0248, | AA15: 0.0247686 | AB15: 0.0247445 | AC15: 0.0247688 | AD15: 0.0247448 | AE15: 0.0247693 | AF15: 0.0247455 | AG15: 0.0247689 | AH15: 0.0247449 | AI15: 0.0247691 | AJ15: 0.0247451 | AK15: 0.0247693 | AL15: 0.0247455 | AM15: 0.0247693 | AN15: 0.0247455 | AP15: 0.0247679 | AQ15: 0.0247439 | AR15: 0.0247679 | AS15: 0.0247437 | AT15: 0.024778 | AU15: 0.024755 | AV15: 0.0248051 | AW15: 0.0247836 | AY15: 0.024768 | AZ15: 0.0247437 | BA15: 0.0247777 | BB15: 0.0247547 | BD15: 0.0247855 | BE15: 0.0247612 | BF15: 0.0247668 | BG15: 0.0247428 | BI15: 0.0247805 | BJ15: 0.0247561 | BK15: 0.0247673 | BL15: 0.0247433 | BM15: 0.0247718 | BN15: 0.0247478 | BO15: 0.0247672 | BP15: 0.0247431
A16: =base_vacc!L11 -> 0.027605466 | B16: =AVERAGE(AA16:AB16) -> 0.02473725 | C16: =A16 -> 0.027605466 | D16: =AVERAGE(AC16:AD16) -> 0.0247376 | E16: =AVERAGE(AG16:AH16) -> 0.02473785 | F16: =AVERAGE(AI16:AJ16) -> 0.02473815 | G16: =AVERAGE(AK16:AL16) -> 0.0247383 | H16: =AVERAGE(AM16:AN16) -> 0.0247383 | J16: =AVERAGE(AP16:AQ16) -> 0.0247343 | K16: =AVERAGE(AR16:AS16) -> 0.0247358 | L16: =A16 -> 0.027605466 | M16: =AVERAGE(AT16:AU16) -> 0.02474735 | N16: =AVERAGE(AV16:AW16) -> 0.02477905 | P16: =AVERAGE(BD16:BE16) -> 0.0247586 | Q16: =A16 -> 0.027605466 | R16: =AVERAGE(BF16:BG16) -> 0.02473295 | S16: =AVERAGE(BI16:BJ16) -> 0.0247514 | T16: =AVERAGE(BK16:BL16) -> 0.0247336 | U16: =AVERAGE(BM16:BN16) -> 0.0247418 | V16: =AVERAGE(BO16:BP16) -> 0.0247353 | X16: =ROUND(V16,4)&"," -> 0.0247, | AA16: 0.0247404 | AB16: 0.0247341 | AC16: 0.0247408 | AD16: 0.0247344 | AE16: 0.0247414 | AF16: 0.0247352 | AG16: 0.024741 | AH16: 0.0247347 | AI16: 0.0247414 | AJ16: 0.0247349 | AK16: 0.0247414 | AL16: 0.0247352 | AM16: 0.0247414 | AN16: 0.0247352 | AP16: 0.024735 | AQ16: 0.0247336 | AR16: 0.0247378 | AS16: 0.0247338 | AT16: 0.0247511 | AU16: 0.0247436 | AV16: 0.0247816 | AW16: 0.0247765 | AY16: 0.0247379 | AZ16: 0.0247338 | BA16: 0.0247507 | BB16: 0.0247433 | BD16: 0.0247648 | BE16: 0.0247524 | BF16: 0.0247348 | BG16: 0.0247311 | BI16: 0.0247567 | BJ16: 0.0247461 | BK16: 0.0247356 | BL16: 0.0247316 | BM16: 0.0247456 | BN16: 0.024738 | BO16: 0.0247381 | BP16: 0.0247325
A17: =base_vacc!L12 -> 0.027535294 | B17: =AVERAGE(AA17:AB17) -> 0.02471325 | C17: =A17 -> 0.027535294 | D17: =AVERAGE(AC17:AD17) -> 0.0247136 | E17: =AVERAGE(AG17:AH17) -> 0.0247139 | F17: =AVERAGE(AI17:AJ17) -> 0.02471425 | G17: =AVERAGE(AK17:AL17) -> 0.02471455 | H17: =AVERAGE(AM17:AN17) -> 0.02471455 | J17: =AVERAGE(AP17:AQ17) -> 0.0247095 | K17: =AVERAGE(AR17:AS17) -> 0.0247119 | L17: =A17 -> 0.027535294 | M17: =AVERAGE(AT17:AU17) -> 0.0247264 | N17: =AVERAGE(AV17:AW17) -> 0.0247702 | P17: =AVERAGE(BD17:BE17) -> 0.0247415 | Q17: =A17 -> 0.027535294 | R17: =AVERAGE(BF17:BG17) -> 0.02470715 | S17: =AVERAGE(BI17:BJ17) -> 0.0247319 | T17: =AVERAGE(BK17:BL17) -> 0.0247079 | U17: =AVERAGE(BM17:BN17) -> 0.02471875 | V17: =AVERAGE(BO17:BP17) -> 0.02471085 | X17: =ROUND(V17,4)&"," -> 0.0247, | AA17: 0.0247258 | AB17: 0.0247007 | AC17: 0.0247261 | AD17: 0.0247011 | AE17: 0.0247266 | AF17: 0.0247025 | AG17: 0.0247263 | AH17: 0.0247015 | AI17: 0.0247266 | AJ17: 0.0247019 | AK17: 0.0247266 | AL17: 0.0247025 | AM17: 0.0247266 | AN17: 0.0247025 | AP17: 0.0247187 | AQ17: 0.0247003 | AR17: 0.0247237 | AS17: 0.0247001 | AT17: 0.0247382 | AU17: 0.0247146 | AV17: 0.0247809 | AW17: 0.0247595 | AY17: 0.0247238 | AZ17: 0.0247001 | BA17: 0.0247377 | BB17: 0.0247141 | BD17: 0.0247536 | BE17: 0.0247294 | BF17: 0.0247166 | BG17: 0.0246977 | BI17: 0.0247443 | BJ17: 0.0247195 | BK17: 0.0247174 | BL17: 0.0246984 | BM17: 0.0247312 | BN17: 0.0247063 | BO17: 0.0247235 | BP17: 0.0246982
A18: =base_vacc!L13 -> 0.027460909 | B18: =AVERAGE(AA18:AB18) -> 0.02466435 | C18: =A18 -> 0.027460909 | D18: =AVERAGE(AC18:AD18) -> 0.02466505 | E18: =AVERAGE(AG18:AH18) -> 0.02466565 | F18: =AVERAGE(AI18:AJ18) -> 0.0246662 | G18: =AVERAGE(AK18:AL18) -> 0.02466635 | H18: =AVERAGE(AM18:AN18) -> 0.02466635 | J18: =AVERAGE(AP18:AQ18) -> 0.02465765 | K18: =AVERAGE(AR18:AS18) -> 0.0246605 | L18: =A18 -> 0.027460909 | M18: =AVERAGE(AT18:AU18) -> 0.02467655 | N18: =AVERAGE(AV18:AW18) -> 0.0247321 | P18: =AVERAGE(BD18:BE18) -> 0.0247047 | Q18: =A18 -> 0.027460909 | R18: =AVERAGE(BF18:BG18) -> 0.02465515 | S18: =AVERAGE(BI18:BJ18) -> 0.0246883 | T18: =AVERAGE(BK18:BL18) -> 0.02465625 | U18: =AVERAGE(BM18:BN18) -> 0.02467295 | V18: =AVERAGE(BO18:BP18) -> 0.02466045 | X18: =ROUND(V18,4)&"," -> 0.0247, | AA18: 0.0246763 | AB18: 0.0246524 | AC18: 0.0246774 | AD18: 0.0246527 | AE18: 0.0246803 | AF18: 0.0246525 | AG18: 0.0246785 | AH18: 0.0246528 | AI18: 0.0246795 | AJ18: 0.0246529 | AK18: 0.0246803 | AL18: 0.0246524 | AM18: 0.0246803 | AN18: 0.0246524 | AP18: 0.0246605 | AQ18: 0.0246548 | AR18: 0.0246685 | AS18: 0.0246525 | AT18: 0.0246939 | AU18: 0.0246592 | AV18: 0.0247567 | AW18: 0.0247075 | AY18: 0.0246687 | AZ18: 0.0246526 | BA18: 0.0246931 | BB18: 0.0246583 | BD18: 0.024722 | BE18: 0.0246874 | BF18: 0.0246578 | BG18: 0.0246525 | BI18: 0.0247064 | BJ18: 0.0246702 | BK18: 0.0246591 | BL18: 0.0246534 | BM18: 0.024685 | BN18: 0.0246609 | BO18: 0.0246722 | BP18: 0.0246487
A19: =base_vacc!L14 -> 0.027376611 | B19: =AVERAGE(AA19:AB19) -> 0.02462405 | C19: =A19 -> 0.027376611 | D19: =AVERAGE(AC19:AD19) -> 0.0246248 | E19: =AVERAGE(AG19:AH19) -> 0.02462525 | F19: =AVERAGE(AI19:AJ19) -> 0.02462575 | G19: =AVERAGE(AK19:AL19) -> 0.0246252 | H19: =AVERAGE(AM19:AN19) -> 0.0246252 | J19: =AVERAGE(AP19:AQ19) -> 0.02462555 | K19: =AVERAGE(AR19:AS19) -> 0.02462515 | L19: =A19 -> 0.027376611 | M19: =AVERAGE(AT19:AU19) -> 0.0246262 | N19: =AVERAGE(AV19:AW19) -> 0.02466 | P19: =AVERAGE(BD19:BE19) -> 0.02467765 | Q19: =A19 -> 0.027376611 | R19: =AVERAGE(BF19:BG19) -> 0.0246188 | S19: =AVERAGE(BI19:BJ19) -> 0.0246554 | T19: =AVERAGE(BK19:BL19) -> 0.0246198 | U19: =AVERAGE(BM19:BN19) -> 0.02463515 | V19: =AVERAGE(BO19:BP19) -> 0.0246192 | X19: =ROUND(V19,4)&"," -> 0.0246, | AA19: 0.0246587 | AB19: 0.0245894 | AC19: 0.0246592 | AD19: 0.0245904 | AE19: 0.0246606 | AF19: 0.02459 | AG19: 0.0246597 | AH19: 0.0245908 | AI19: 0.0246603 | AJ19: 0.0245912 | AK19: 0.0246606 | AL19: 0.0245898 | AM19: 0.0246606 | AN19: 0.0245898 | AP19: 0.0246575 | AQ19: 0.0245936 | AR19: 0.024658 | AS19: 0.0245923 | AT19: 0.0246785 | AU19: 0.0245739 | AV19: 0.0247508 | AW19: 0.0245692 | AY19: 0.0246581 | AZ19: 0.0245925 | BA19: 0.0246775 | BB19: 0.0245725 | BD19: 0.0247089 | BE19: 0.0246464 | BF19: 0.0246528 | BG19: 0.0245848 | BI19: 0.0246907 | BJ19: 0.0246201 | BK19: 0.0246538 | BL19: 0.0245858 | BM19: 0.0246678 | BN19: 0.0246025 | BO19: 0.0246545 | BP19: 0.0245839
... A67: =base_vacc!L62 -> 0.004243431 | B67: =AVERAGE(AA67:AB67) -> 0.00515867 | C67: =A67 -> 0.004243431 | D67: =AVERAGE(AC67:AD67) -> 0.00515867 | E67: =AVERAGE(AG67:AH67) -> 0.00515867 | F67: =AVERAGE(AI67:AJ67) -> 0.00515867 | G67: =AVERAGE(AK67:AL67) -> 0.00515869 | H67: =AVERAGE(AM67:AN67) -> 0.00515869 | J67: =AVERAGE(AP67:AQ67) -> 0.005158615 | K67: =AVERAGE(AR67:AS67) -> 0.00515863 | L67: =A67 -> 0.004243431 | M67: =AVERAGE(AT67:AU67) -> 0.005158665 | N67: =AVERAGE(AV67:AW67) -> 0.00515866 | P67: =AVERAGE(BD67:BE67) -> 0.00515867 | Q67: =A67 -> 0.004243431 | R67: =AVERAGE(BF67:BG67) -> 0.00515862 | S67: =AVERAGE(BI67:BJ67) -> 0.005158675 | T67: =AVERAGE(BK67:BL67) -> 0.00515862 | U67: =AVERAGE(BM67:BN67) -> 0.00515867 | V67: =AVERAGE(BO67:BP67) -> 0.00515867 | X67: =ROUND(V67,4)&"," -> 0.0052, | AA67: 0.00516653 | AB67: 0.00515081 | AC67: 0.00516653 | AD67: 0.00515081 | AE67: 0.00516657 | AF67: 0.00515081 | AG67: 0.00516653 | AH67: 0.00515081 | AI67: 0.00516653 | AJ67: 0.00515081 | AK67: 0.00516657 | AL67: 0.00515081 | AM67: 0.00516657 | AN67: 0.00515081 | AP67: 0.00516645 | AQ67: 0.00515078 | AR67: 0.00516647 | AS67: 0.00515079 | AT67: 0.00516654 | AU67: 0.00515079 | AV67: 0.00516654 | AW67: 0.00515078 | AY67: 0.00516647 | AZ67: 0.00515079 | BA67: 0.00516653 | BB67: 0.00515079 | BD67: 0.00516654 | BE67: 0.0051508 | BF67: 0.00516645 | BG67: 0.00515079 | BI67: 0.00516655 | BJ67: 0.0051508 | BK67: 0.00516645 | BL67: 0.00515079 | BM67: 0.00516653 | BN67: 0.00515081 | BO67: 0.00516653 | BP67: 0.00515081

Sheet Results>>

Sheet reg control
C2: top | K2: k0 = 0.0067 | L2: k0 = 0.0053 | N2: k0 low 0.0053 | O2: k0 high 0.0067 | S2: Strategy 1 | T2: Strategy 2 | U2: Optimal Control
C3: k0 = 0.0067 | F3: vaccination_rate | I3: bottom | K3: k1 = -0.1006 | L3: k1 = -0.1676 | M3: baseline | N3: k1 high -0.1006 | O3: k1 low -0.1676 | S3: Constant Vaccination | T3: Actual alpha | U3: control_1 | V3: control_2 | W3: control_3 | X3: control_4 | Y3: control_5 | AB3: avg over rounds
C4: k1 = -0.1006 | F4: 0.02779241 | I4: k0 = 0.0053 | J4: 1 | K4: =F4 -> 0.02779241 | L4: 0.02779236 | M4: =AB4 -> 0.02447724 | N4: 0.02779235 | O4: 0.02779241 | S4: =$F$3 -> vaccination_rate | T4: =[1]Reg_30days!AJ32 -> 0 | U4: 0.0245031 | V4: 0.0244278 | W4: 0.0244835 | X4: 0.0244886 | Y4: 0.0244832 | AB4: =AVERAGE(U4:Y4) -> 0.02447724
F5: 0.02779357 | I5: k1 = -0.1676 | J5: 2 | K5: =F5 -> 0.02779357 | L5: 0.02779371 | M5: =AB5 -> 0.02438572 | N5: 0.02779351 | O5: 0.02779376 | S5: =$F$3 -> vaccination_rate | T5: =[1]Reg_30days!AJ33 -> 0 | U5: 0.0244224 | V5: 0.0243765 | W5: 0.0243693 | X5: 0.0243777 | Y5: 0.0243827 | AB5: =AVERAGE(U5:Y5) -> 0.02438572
F6: 0.02777892 | J6: 3 | K6: =F6 -> 0.02777892 | L6: 0.02777925 | M6: =AB6 -> 0.0242678 | N6: 0.02777886 | O6: 0.0277793 | S6: =$F$3 -> vaccination_rate | T6: =[1]Reg_30days!AJ34 -> 0 | U6: 0.0243032 | V6: 0.0242313 | W6: 0.0242684 | X6: 0.0242707 | Y6: 0.0242654 | AB6: =AVERAGE(U6:Y6) -> 0.0242678
F7: 0.02776494 | J7: 4 | K7: =F7 -> 0.02776494 | L7: 0.02776547 | M7: =AB7 -> 0.02410956 | N7: 0.02776487 | O7: 0.02776553 | S7: =$F$3 -> vaccination_rate | T7: =[1]Reg_30days!AJ35 -> 0 | U7: 0.0241285 | V7: 0.0241053 | W7: 0.0240692 | X7: 0.024107 | Y7: 0.0241378 | AB7: =AVERAGE(U7:Y7) -> 0.02410956
F8: 0.02774444 | J8: 5 | K8: =F8 -> 0.02774444 | L8: 0.02774524 | M8: =AB8 -> 0.02387136 | N8: 0.02774436 | O8: 0.0277453 | S8: =$F$3 -> vaccination_rate | T8: =[1]Reg_30days!AJ36 -> 0 | U8: 0.02399 | V8: 0.0237615 | W8: 0.0239481 | X8: 0.0239716 | Y8: 0.0236856 | AB8: =AVERAGE(U8:Y8) -> 0.02387136
F9: 0.02771779 | J9: 6 | K9: =F9 -> 0.02771779 | L9: 0.02771905 | M9: =AB9 -> 0.02355274 | N9: 0.02771771 | O9: 0.02771912 | S9: =$F$3 -> vaccination_rate | T9: =[1]Reg_30days!AJ37 -> 0 | U9: 0.0239124 | V9: 0.023483 | W9: 0.0234279 | X9: 0.0233801 | Y9: 0.0235603 | AB9: =AVERAGE(U9:Y9) -> 0.02355274
F10: 0.02769106 | J10: 7 | K10: =F10 -> 0.02769106 | L10: 0.02769274 | M10: =AB10 -> 0.02338316 | N10: 0.02769097 | O10: 0.0276928 | S10: =$F$3 -> vaccination_rate | T10: =[1]Reg_30days!AJ38 -> 0 | U10: 0.0235616 | V10: 0.0234558 | W10: 0.0234109 | X10: 0.0231867 | Y10: 0.0233008 | AB10: =AVERAGE(U10:Y10) -> 0.02338316
F11: 0.02765664 | J11: 8 | K11: =F11 -> 0.02765664 | L11: 0.02765901 | M11: =AB11 -> 0.02316708 | N11: 0.02765656 | O11: 0.02765907 | S11: =$F$3 -> vaccination_rate | T11: =[1]Reg_30days!AJ39 -> 0 | U11: 0.0231953 | V11: 0.0231481 | W11: 0.02331 | X11: 0.0231032 | Y11: 0.0230788 | AB11: =AVERAGE(U11:Y11) -> 0.02316708
F12: 0.02761797 | J12: 9 | K12: =F12 -> 0.02761797 | L12: 0.02762101 | M12: =AB12 -> 0.02305654 | N12: 0.02761784 | O12: 0.0276211 | S12: =$F$3 -> vaccination_rate | T12: =[1]Reg_30days!AJ40 -> 0 | U12: 0.0230804 | V12: 0.0229861 | W12: 0.0233851 | X12: 0.0229123 | Y12: 0.0229188 | AB12: =AVERAGE(U12:Y12) -> 0.02305654
F13: 0.02759025 | J13: 10 | K13: =F13 -> 0.02759025 | L13: 0.02759398 | M13: =AB13 -> 0.02285692 | N13: 0.02759015 | O13: 0.02759403 | S13: =$F$3 -> vaccination_rate | T13: =[1]Reg_30days!AJ41 -> 0 | U13: 0.022797 | V13: 0.0226103 | W13: 0.0232388 | X13: 0.0229475 | Y13: 0.022691 | AB13: =AVERAGE(U13:Y13) -> 0.02285692
F14: 0.02758413 | J14: 11 | K14: =F14 -> 0.02758413 | L14: 0.02758989 | M14: =AB14 -> 0.02267136 | N14: 0.02758616 | O14: 0.02758931 | S14: =$F$3 -> vaccination_rate | T14: =[1]Reg_30days!AJ42 -> 0 | U14: 0.0225398 | V14: 0.0225778 | W14: 0.0229953 | X14: 0.0226186 | Y14: 0.0226253 | AB14: =AVERAGE(U14:Y14) -> 0.02267136
F15: 0.02747588 | J15: 12 | K15: =F15 -> 0.02747588 | L15: 0.02748173 | M15: =AB15 -> 0.02247434 | N15: 0.02747582 | O15: 0.02748176 | S15: =$F$3 -> vaccination_rate | T15: =[1]Reg_30days!AJ43 -> 0 | U15: 0.0223361 | V15: 0.0225738 | W15: 0.022726 | X15: 0.0224946 | Y15: 0.0222412 | AB15: =AVERAGE(U15:Y15) -> 0.02247434
F16: 0.02734684 | J16: 13 | K16: =F16 -> 0.02734684 | L16: 0.02735633 | M16: =AB16 -> 0.02239424 | N16: 0.02734733 | O16: 0.027356 | S16: =$F$3 -> vaccination_rate | T16: =[1]Reg_30days!AJ44 -> 0 | U16: 0.0221573 | V16: 0.0222858 | W16: 0.0225789 | X16: 0.0226736 | Y16: 0.0222756 | AB16: =AVERAGE(U16:Y16) -> 0.02239424
F17: 0.02724283 | J17: 14 | K17: =F17 -> 0.02724283 | L17: 0.0272533 | M17: =AB17 -> 0.02230826 | N17: 0.02724293 | O17: 0.02725343 | S17: =$F$3 -> vaccination_rate | T17: =[1]Reg_30days!AJ45 -> 0 | U17: 0.0226141 | V17: 0.0222929 | W17: 0.0225579 | X17: 0.0223482 | Y17: 0.0217282 | AB17: =AVERAGE(U17:Y17) -> 0.02230826
... F63: 0.00424856 | J63: 60 | K63: =F63 -> 0.00424856 | L63: 0.00424851 | M63: =AB63 -> 0.005159404 | N63: 0.00424854 | O63: 0.00424854 | S63: =$F$3 -> vaccination_rate | T63: =[1]Reg_30days!AJ91 -> 0 | U63: 0.00516643 | V63: 0.00515081 | W63: 0.00516471 | X63: 0.00515668 | Y63: 0.00515839 | AB63: =AVERAGE(U63:Y63) -> 0.005159404
S70: upper
E71: lower | AE71: base | AQ71: k1low | BC71: k0 low
AQ72: k0 high | BC72: k1 high
G84: Strategy | H84: Total Cost | I84: Healthcare | J84: Policy | K84: Economic | L84: Cost reduction
G85: No Vaccination | H85: 38.72 | I85: 9.5 | J85: 1.66 | K85: 27.56 | L85: =1-H88/H85 -> 0.17742769
G86: Constant Vaccination | H86: 34.28 | I86: 8.13 | J86: 3.08 | K86: 23.07 | L86: =1-H88/H86 -> 0.070886814
G87: Actual (Government) | H87: 31.4 | I87: 4.93 | J87: 3.35 | K87: 23.12
G88: Optimal | H88: 31.85 | I88: 4.42 | J88: 5.89 | K88: 21.54
E101: standard
E111: peak infected | F111: hosp | G111: icu
D112: no | AQ112: Strategy | AR112: Peak Infected | AS112: Peak Mild | AT112: Peak Hosp | AU112: Peak ICU | AV112: Peak Infected | AW112: Peak Mild | AX112: Peak Hosp | AY112: Peak ICU | BC112: Strategy | BD112: Peak Infected | BE112: Peak Mild | BF112: Peak Hosp | BG112: Peak ICU | BH112: Peak Infected | BI112: Peak Mild | BJ112: Peak Hosp | BK112: Peak ICU
D113: constant | AQ113: No Vaccination | AR113: 0.5662 | AS113: 0.5421 | AT113: 0.02185 | AU113: 0.01598 | AV113: =1-AR116/AR113 -> 0.0060049452 | AW113: =1-AS116/AS113 -> -0.027116768 | AX113: =1-AT116/AT113 -> 0.65629291 | AY113: =1-AU116/AU113 -> 0.8097622 | BC113: No Vaccination | BD113: 0.5662 | BE113: 0.5421 | BF113: 0.02185 | BG113: 0.01598 | BH113: =1-BD116/BD113 -> 0.0060049452 | BI113: =1-BE116/BE113 -> -0.026194429 | BJ113: =1-BF116/BF113 -> 0.65629291 | BK113: =1-BG116/BG113 -> 0.79411765
D114: optimal | S114: Strategy | T114: Peak Infected | U114: Peak Mild | V114: Peak Hosp | W114: Peak ICU | X114: Peak Infected | Y114: Peak Mild | Z114: Peak Hosp | AA114: Peak ICU | AQ114: Constant Vaccination | AR114: 0.5632 | AS114: 0.5395 | AT114: 0.02161 | AU114: 0.01551 | AV114: =1-AR116/AR114 -> 0.00071022727 | AW114: =1-AS116/AS114 -> -0.032066728 | AX114: =1-AT116/AT114 -> 0.65247571 | AY114: =1-AU116/AU114 -> 0.80399742 | BC114: Constant Vaccination | BD114: 0.5632 | BE114: 0.5395 | BF114: 0.02161 | BG114: 0.01551 | BH114: =1-BD116/BD114 -> 0.00071022727 | BI114: =1-BE116/BE114 -> -0.031139944 | BJ114: =1-BF116/BF114 -> 0.65247571 | BK114: =1-BG116/BG114 -> 0.78787879
F115: Strategy | G115: Peak Infected | H115: Peak Mild | I115: Peak Hosp | J115: Peak ICU | K115: Peak Infected | L115: Peak Mild | M115: Peak Hosp | N115: Peak ICU | S115: No Vaccination | T115: 0.5662 | U115: 0.5421 | V115: 0.02185 | W115: 0.01598 | X115: =1-T118/T115 -> 0.0061815613 | Y115: =1-U118/U115 -> -0.023058476 | Z115: =1-V118/V115 -> 0.65583524 | AA115: =1-W118/W115 -> 0.73404255 | AE115: Strategy | AF115: Peak Infected | AG115: Peak Mild | AH115: Peak Hosp | AI115: Peak ICU | AJ115: Peak Infected | AK115: Peak Mild | AL115: Peak Hosp | AM115: Peak ICU | AQ115: Actual (Government) | AR115: 0.5649 | AS115: 0.5564 | AT115: 0.00752 | AU115: 0.0043 | BC115: Actual (Government) | BD115: 0.5649 | BE115: 0.5569 | BF115: 0.00752 | BG115: 0.00408
F116: No Vaccination | G116: 0.5662 | H116: 0.5421 | I116: 0.02185 | J116: 0.01598 | K116: =1-G119/G116 -> 0.0058283292 | L116: =1-H119/H116 -> -0.02951485 | M116: =1-I119/I116 -> 0.65629291 | N116: =1-J119/J116 -> 0.83291615 | S116: Constant Vaccination | T116: 0.5632 | U116: 0.5395 | V116: 0.02161 | W116: 0.01551 | X116: =1-T118/T116 -> 0.00088778409 | Y116: =1-U118/U116 -> -0.027988879 | Z116: =1-V118/V116 -> 0.65201296 | AA116: =1-W118/W116 -> 0.72598324 | AE116: No Vaccination | AF116: 0.5662 | AG116: 0.5421 | AH116: 0.02185 | AI116: 0.01598 | AJ116: =1-AF119/AF116 -> 0.0060049452 | AK116: =1-AG119/AG116 -> -0.026563365 | AL116: =1-AH119/AH116 -> 0.65629291 | AM116: =1-AI119/AI116 -> 0.80162703 | AQ116: Optimal | AR116: 0.5628 | AS116: 0.5568 | AT116: 0.00751 | AU116: 0.00304 | BC116: Optimal | BD116: 0.5628 | BE116: 0.5563 | BF116: 0.00751 | BG116: 0.00329
F117: Constant Vaccination | G117: 0.5632 | H117: 0.5395 | I117: 0.02161 | J117: 0.01551 | K117: =1-G119/G117 -> 0.00053267045 | L117: =1-H119/H117 -> -0.034476367 | M117: =1-I119/I117 -> 0.65247571 | N117: =1-J119/J117 -> 0.827853 | S117: Actual (Government) | T117: 0.5648 | U117: 0.5552 | V117: 0.00757 | W117: 0.00512 | AE117: Constant Vaccination | AF117: 0.5632 | AG117: 0.5395 | AH117: 0.02161 | AI117: 0.01551 | AJ117: =1-AF119/AF117 -> 0.00071022727 | AK117: =1-AG119/AG117 -> -0.031510658 | AL117: =1-AH119/AH117 -> 0.65247571 | AM117: =1-AI119/AI117 -> 0.79561573
F118: Actual (Government) | G118: 0.565 | H118: 0.5581 | I118: 0.00751 | J118: 0.0034 | S118: Optimal | T118: 0.5627 | U118: 0.5546 | V118: 0.00752 | W118: 0.00425 | AE118: Actual (Government) | AF118: 0.5649 | AG118: 0.5567 | AH118: 0.00752 | AI118: 0.00419
F119: Optimal | G119: 0.5629 | H119: 0.5581 | I119: 0.00751 | J119: 0.00267 | AE119: Optimal | AF119: 0.5628 | AG119: 0.5565 | AH119: 0.00751 | AI119: 0.00317 | AQ119: Table 3: Peak Infection (Mean, absolute numbers) | BC119: Table 3: Peak Infection (Mean, absolute numbers)
F121: Strategy | G121: Peak Infected | H121: Peak Mild | I121: Peak Hosp | J121: Peak ICU | K121: Peak Infected | L121: Peak Mild | M121: Peak Hosp | N121: Peak ICU | AQ121: Strategy | AR121: Peak Infected | AS121: Peak Mild | AT121: Peak Hosp | AU121: Peak ICU | BC121: Strategy | BD121: Peak Infected | BE121: Peak Mild | BF121: Peak Hosp | BG121: Peak ICU
F122: No Vaccination | G122: 37539 | H122: 35941 | I122: 1448 | J122: 1059 | K122: =1-G125/G122 -> 0.0058072937 | L122: =1-H125/H122 -> -0.029437133 | M122: =1-I125/I122 -> 0.65607735 | N122: =1-J125/J122 -> 0.83286119 | AE122: Table 3: Peak Infection (Mean, absolute numbers) | AQ122: No Vaccination | AR122: 37539 | AS122: 35941 | AT122: 1448 | AU122: 1059 | BC122: No Vaccination | BD122: 37539 | BE122: 35941 | BF122: 1448 | BG122: 1059
F123: Constant Vaccination | G123: 37338 | H123: 35769 | I123: 1433 | J123: 1028 | K123: =1-G125/G123 -> 0.00045530023 | L123: =1-H125/H123 -> -0.034387319 | M123: =1-I125/I123 -> 0.65247732 | N123: =1-J125/J123 -> 0.82782101 | S123: Strategy | T123: Peak Infected | U123: Peak Mild | V123: Peak Hosp | W123: Peak ICU | AQ123: Constant Vaccination | AR123: 37338 | AS123: 35769 | AT123: 1433 | AU123: 1028 | BC123: Constant Vaccination | BD123: 37338 | BE123: 35769 | BF123: 1433 | BG123: 1028
F124: Actual (Government) | G124: 37460 | H124: 37002 | I124: 498 | J124: 225 | S124: No Vaccination | T124: 37539 | U124: 35941 | V124: 1448 | W124: 1059 | AE124: Strategy | AF124: Peak Infected | AG124: Peak Mild | AH124: Peak Hosp | AI124: Peak ICU | AQ124: Actual (Government) | AR124: 37452 | AS124: 36889 | AT124: 498 | AU124: 285 | BC124: Actual (Government) | BD124: 37454 | BE124: 36923 | BF124: 498 | BG124: 271
F125: Optimal | G125: 37321 | H125: 36999 | I125: 498 | J125: 177 | S125: Constant Vaccination | T125: 37338 | U125: 35769 | V125: 1433 | W125: 1028 | AE125: No Vaccination | AF125: 37539 | AG125: 35941 | AH125: 1448 | AI125: 1059 | AQ125: Optimal | AR125: 37315 | AS125: 36916 | AT125: 498 | AU125: 202 | BC125: Optimal | BD125: 37313 | BE125: 36879 | BF125: 498 | BG125: 218
S126: Actual (Government) | T126: 37446 | U126: 36811 | V126: 502 | W126: 339 | AE126: Constant Vaccination | AF126: 37338 | AG126: 35769 | AH126: 1433 | AI126: 1028
S127: Optimal | T127: 37305 | U127: 36769 | V127: 498 | W127: 282 | AE127: Actual (Government) | AF127: 37453 | AG127: 36906 | AH127: 498 | AI127: 278
AE128: Optimal | AF128: 37314 | AG128: 36898 | AH128: 498 | AI128: 210
F138: Strategy | G138: Hospital | H138: Vaccination | I138: Quarantine | J138: Economic | K138: Total | L138: Cost reduction
F139: No Vaccination | G139: 9.5 | H139: 0 | I139: 1.66 | J139: 27.56 | K139: 38.72 | L139: =1-K142/K139 -> 0.17665289 | S139: Strategy | T139: Hospital | U139: Vaccination | V139: Quarantine | W139: Economic | X139: Total | Y139: Cost reduction
F140: Constant Vaccination | G140: 8.13 | H140: 1.71 | I140: 1.37 | J140: 23.07 | K140: 34.28 | L140: =1-K142/K140 -> 0.070011669 | S140: No Vaccination | T140: 9.5 | U140: 0 | V140: 1.66 | W140: 27.56 | X140: 38.72 | Y140: =1-X143/X140 -> 0.16296488
F141: Actual (Government) | G141: 4.93 | H141: 1.96 | I141: 1.39 | J141: 23.12 | K141: 31.4 | S141: Constant Vaccination | T141: 8.13 | U141: 1.71 | V141: 1.37 | W141: 23.07 | X141: 34.28 | Y141: =1-X143/X141 -> 0.054550758
F142: Optimal | G142: 4.42 | H142: 4.63 | I142: 1.29 | J142: 21.54 | K142: 31.88 | S142: Actual (Government) | T142: 5.48 | U142: 1.96 | V142: 1.39 | W142: 23.07 | X142: 31.89 | AE142: Strategy | AF142: Hospital | AG142: Vaccination | AH142: Quarantine | AI142: Economic | AJ142: Total | AK142: Cost reduction | BC142: Strategy | BD142: Hospital | BE142: Vaccination | BF142: Quarantine | BG142: Economic | BH142: Total | BI142: Cost reduction
S143: Optimal | T143: 4.99 | U143: 4.64 | V143: 1.29 | W143: 21.5 | X143: 32.41 | AE143: No Vaccination | AF143: 9.5 | AG143: 0 | AH143: 1.66 | AI143: 27.56 | AJ143: 38.72 | AK143: =1-AJ146/AJ143 -> 0.2231405 | AQ143: Strategy | AR143: Hospital | AS143: Vaccination | AT143: Quarantine | AU143: Economic | AV143: Total | AW143: Cost reduction | BC143: No Vaccination | BD143: 9.5 | BE143: 0 | BF143: 1.66 | BG143: 27.56 | BH143: 38.72 | BI143: =1-BH146/BH143 -> 0.16942149
AE144: Constant Vaccination | AF144: 8.13 | AG144: 1.71 | AH144: 1.37 | AI144: 23.07 | AJ144: 34.28 | AK144: =1-AJ146/AJ144 -> 0.12252042 | AQ144: No Vaccination | AR144: 9.5 | AS144: 0 | AT144: 1.66 | AU144: 27.56 | AV144: 38.72 | AW144: =1-AV147/AV144 -> 0.17174587 | BC144: Constant Vaccination | BD144: 8.13 | BE144: 1.71 | BF144: 1.37 | BG144: 23.07 | BH144: 34.28 | BI144: =1-BH146/BH144 -> 0.061843641
AE145: Actual (Government) | AF145: 5.21 | AG145: 1.96 | AH145: 1.39 | AI145: 23.09 | AJ145: 31.65 | AQ145: Constant Vaccination | AR145: 8.13 | AS145: 1.71 | AT145: 1.37 | AU145: 23.07 | AV145: 34.28 | AW145: =1-AV147/AV145 -> 0.064469078 | BC145: Actual (Government) | BD145: 5.2 | BE145: 1.96 | BF145: 1.39 | BG145: 23.1 | BH145: 31.64
AE146: Optimal | AF146: 4.72 | AG146: 2.45 | AH146: 1.3 | AI146: 21.62 | AJ146: 30.08 | AQ146: Actual (Government) | AR146: 5.21 | AS146: 1.96 | AT146: 1.39 | AU146: 23.09 | AV146: 31.65 | BC146: Optimal | BD146: 4.72 | BE146: 4.63 | BF146: 1.29 | BG146: 21.52 | BH146: 32.16
F147: k0 low 0.0053 | G147: k0 high 0.0067 | AQ147: Optimal | AR147: 4.63 | AS147: 4.63 | AT147: 1.29 | AU147: 21.52 | AV147: 32.07
B148: optimal compare to | C148: top | D148: bottom | E148: avg | F148: k1 high -0.1006 | G148: k1 low -0.1676
A149: Cost reduction | B149: No Vaccination | C149: =L139 -> 0.17665289 | D149: =Y140 -> 0.16296488 | E149: =AK143 -> 0.2231405 | F149: =AW144 -> 0.17174587 | G149: =BI143 -> 0.16942149
B150: Constant Vaccination | C150: =L140 -> 0.070011669 | D150: =Y141 -> 0.054550758 | E150: =AK144 -> 0.12252042 | F150: =AW145 -> 0.064469078 | G150: =BI144 -> 0.061843641
A151: Peak Hosp reduction | B151: No Vaccination | C151: =M116 -> 0.65629291 | D151: =Z115 -> 0.65583524 | E151: =AL116 -> 0.65629291 | F151: =AX113 -> 0.65629291 | G151: =BJ113 -> 0.65629291
B152: Constant Vaccination | C152: =M117 -> 0.65247571 | D152: =Z116 -> 0.65201296 | E152: =AL117 -> 0.65247571 | F152: =AX114 -> 0.65247571 | G152: =BJ114 -> 0.65247571
A153: Peak ICU reduction | B153: No Vaccination | C153: =N116 -> 0.83291615 | D153: =AA115 -> 0.73404255 | E153: =AM116 -> 0.80162703 | F153: =AY113 -> 0.8097622 | G153: =BK113 -> 0.79411765
B154: Constant Vaccination | C154: =N117 -> 0.827853 | D154: =AA116 -> 0.72598324 | E154: =AM117 -> 0.79561573 | F154: =AY114 -> 0.80399742 | G154: =BK114 -> 0.78787879

Sheet reg cost
C1: high, high | D1: low,low | F1: low, high | G1: high, low
C2: k0 = 0.0067 | D2: k0 = 0.0053 | F2: k0 low 0.0053 | G2: k0 high 0.0067
C3: k1 = -0.1006 | D3: k1 = -0.1676 | F3: k1 high -0.1006 | G3: k1 low -0.1676 | J3: =0.0009+0.00009*5 -> 0.00135
J4: =0.0123+0.00123*5 -> 0.01845
C9: high, high | K9: low,low | S9: low, high | AA9: high, low | AI9: baseline
C10: Outcome Metric | D10: No Vacc | E10: Constant | F10: Actual | G10: Optimal | H10: Actual vs No | I10: Optimal vs No | K10: Outcome Metric | L10: No Vacc | M10: Constant | N10: Actual | O10: Optimal | P10: Actual vs No | Q10: Optimal vs No | S10: Outcome Metric | T10: No Vacc | U10: Constant | V10: Actual | W10: Optimal | X10: Actual vs No | Y10: Optimal vs No | AA10: Outcome Metric | AB10: No Vacc | AC10: Constant | AD10: Actual | AE10: Optimal | AF10: Actual vs No | AG10: Optimal vs No | AI10: Outcome Metric | AJ10: No Vacc | AK10: Constant | AL10: Actual | AM10: Optimal | AN10: Actual vs No | AO10: Optimal vs No
C12: Epidemiological outcomes | K12: Epidemiological outcomes | S12: Epidemiological outcomes | AA12: Epidemiological outcomes | AI12: Epidemiological outcomes
C13: Peak infection prevalence (%) | D13: 0.566 | E13: 0.563 | F13: 0.565 | G13: 0.563 | H13: -0.002 | I13: -0.006 | K13: Peak infection prevalence (%) | L13: 0.566 | M13: 0.563 | N13: 0.565 | O13: 0.563 | P13: -0.002 | Q13: -0.006 | S13: Peak infection prevalence (%) | T13: 0.566 | U13: 0.563 | V13: 0.565 | W13: 0.563 | X13: -0.002 | Y13: -0.006 | AA13: Peak infection prevalence (%) | AB13: 0.566 | AC13: 0.563 | AD13: 0.565 | AE13: 0.563 | AF13: -0.002 | AG13: -0.006 | AI13: Peak infection prevalence (%) | AJ13: 0.566 | AK13: 0.563 | AL13: 0.565 | AM13: 0.563 | AN13: -0.002 | AO13: -0.006
C14: Peak hospitalised (persons) | D14: 1448 | E14: 1433 | F14: 502 | G14: 498 | H14: -0.653 | I14: -0.656 | K14: Peak hospitalised (persons) | L14: 1448 | M14: 1433 | N14: 498 | O14: 498 | P14: -0.656 | Q14: -0.656 | S14: Peak hospitalised (persons) | T14: 1448 | U14: 1433 | V14: 498 | W14: 498 | X14: -0.656 | Y14: -0.656 | AA14: Peak hospitalised (persons) | AB14: 1448 | AC14: 1433 | AD14: 498 | AE14: 498 | AF14: -0.656 | AG14: -0.656 | AI14: Peak hospitalised (persons) | AJ14: 1448 | AK14: 1433 | AL14: 498 | AM14: 498 | AN14: -0.656 | AO14: -0.656
C15: Peak ICU (persons) | D15: 1059 | E15: 1028 | F15: 339 | G15: 282 | H15: -0.68 | I15: -0.734 | K15: Peak ICU (persons) | L15: 1059 | M15: 1028 | N15: 225 | O15: 177 | P15: -0.787 | Q15: -0.833 | S15: Peak ICU (persons) | T15: 1059 | U15: 1028 | V15: 271 | W15: 219 | X15: -0.744 | Y15: -0.794 | AA15: Peak ICU (persons) | AB15: 1059 | AC15: 1028 | AD15: 285 | AE15: 202 | AF15: -0.731 | AG15: -0.809 | AI15: Peak ICU (persons) | AJ15: 1059 | AK15: 1028 | AL15: 278 | AM15: 210 | AN15: -0.738 | AO15: -0.802 | AP15: =AO15-AN15 -> -0.064
C16: Cumulative hospital-days | D16: 27456 | E16: 23439 | F16: 7155 | G16: 5944 | H16: -0.739 | I16: -0.784 | K16: Cumulative hospital-days | L16: 27456 | M16: 23439 | N16: 3750 | O16: 2432 | P16: -0.863 | Q16: -0.911 | S16: Cumulative hospital-days | T16: 27456 | U16: 23439 | V16: 5388 | W16: 4274 | X16: -0.804 | Y16: -0.844 | AA16: Cumulative hospital-days | AB16: 27456 | AC16: 23439 | AD16: 5511 | AE16: 3819 | AF16: -0.799 | AG16: -0.861 | AI16: Cumulative hospital-days | AJ16: 27456 | AK16: 23439 | AL16: 5450 | AM16: 4042 | AN16: -0.802 | AO16: -0.853 | AP16: =AO16-AN16 -> -0.051
C17: Cumulative ICU-days | D17: 27063 | E17: 23496 | F17: 7689 | G17: 6517 | H17: -0.716 | I17: -0.759 | K17: Cumulative ICU-days | L17: 27063 | M17: 23496 | N17: 4379 | O17: 3095 | P17: -0.838 | Q17: -0.886 | S17: Cumulative ICU-days | T17: 27063 | U17: 23496 | V17: 5973 | W17: 4892 | X17: -0.779 | Y17: -0.819 | AA17: Cumulative ICU-days | AB17: 27063 | AC17: 23496 | AD17: 6089 | AE17: 4444 | AF17: -0.775 | AG17: -0.836 | AI17: Cumulative ICU-days | AJ17: 27063 | AK17: 23496 | AL17: 6031 | AM17: 4663 | AN17: -0.777 | AO17: -0.828
C18: Cumulative deaths | D18: 110.9 | E18: 96 | F18: 29.9 | G18: 25 | H18: -0.73 | I18: -0.774 | K18: Cumulative deaths | L18: 110.9 | M18: 96 | N18: 16.1 | O18: 10.7 | P18: -0.855 | Q18: -0.903 | S18: Cumulative deaths | T18: 110.9 | U18: 96 | V18: 22.8 | W18: 18.2 | X18: -0.795 | Y18: -0.836 | AA18: Cumulative deaths | AB18: 110.9 | AC18: 96 | AD18: 23.2 | AE18: 16.4 | AF18: -0.79 | AG18: -0.852 | AI18: Cumulative deaths | AJ18: 110.9 | AK18: 96 | AL18: 23 | AM18: 17.3 | AN18: -0.793 | AO18: -0.844
C20: Cost outcomes (units) | K20: Cost outcomes (units) | S20: Cost outcomes (units) | AA20: Cost outcomes (units) | AI20: Cost outcomes (units)
C21: Vaccination costs | D21: 0 | E21: 1.71 | F21: 1.96 | G21: 2.42 | H21: – | I21: – | K21: Vaccination costs | L21: 0 | M21: 1.71 | N21: 1.96 | O21: 2.43 | P21: – | Q21: – | S21: Vaccination costs | T21: 0 | U21: 1.71 | V21: 1.96 | W21: 2.42 | X21: – | Y21: – | AA21: Vaccination costs | AB21: 0 | AC21: 1.71 | AD21: 1.96 | AE21: 2.43 | AF21: – | AG21: – | AI21: Vaccination costs | AJ21: 0 | AK21: 1.71 | AL21: 1.96 | AM21: 2.45 | AN21: – | AO21: –
C22: Quarantine costs | D22: 1.66 | E22: 1.37 | F22: 1.39 | G22: 1.29 | H22: -0.165 | I22: -0.221 | K22: Quarantine costs | L22: 1.66 | M22: 1.37 | N22: 1.39 | O22: 1.3 | P22: -0.161 | Q22: -0.218 | S22: Quarantine costs | T22: 1.66 | U22: 1.37 | V22: 1.39 | W22: 1.3 | X22: -0.163 | Y22: -0.219 | AA22: Quarantine costs | AB22: 1.66 | AC22: 1.37 | AD22: 1.39 | AE22: 1.3 | AF22: -0.163 | AG22: -0.219 | AI22: Quarantine costs | AJ22: 1.66 | AK22: 1.37 | AL22: 1.39 | AM22: 1.3 | AN22: -0.163 | AO22: -0.219
C23: Healthcare costs | D23: 9.5 | E23: 8.13 | F23: 5.48 | G23: 5.03 | H23: -0.424 | I23: -0.471 | K23: Healthcare costs | L23: 9.5 | M23: 8.13 | N23: 4.93 | O23: 4.46 | P23: -0.481 | Q23: -0.531 | S23: Healthcare costs | T23: 9.5 | U23: 8.13 | V23: 5.2 | W23: 4.76 | X23: -0.453 | Y23: -0.499 | AA23: Healthcare costs | AB23: 9.5 | AC23: 8.13 | AD23: 5.21 | AE23: 4.68 | AF23: -0.451 | AG23: -0.507 | AI23: Healthcare costs | AJ23: 9.5 | AK23: 8.13 | AL23: 5.21 | AM23: 4.72 | AN23: -0.452 | AO23: -0.503
C24: Economic productivity loss | D24: 27.56 | E24: 23.07 | F24: 23.07 | G24: 21.6 | H24: -0.163 | I24: -0.216 | K24: Economic productivity loss | L24: 27.56 | M24: 23.07 | N24: 23.12 | O24: 21.64 | P24: -0.161 | Q24: -0.215 | S24: Economic productivity loss | T24: 27.56 | U24: 23.07 | V24: 23.1 | W24: 21.62 | X24: -0.162 | Y24: -0.215 | AA24: Economic productivity loss | AB24: 27.56 | AC24: 23.07 | AD24: 23.09 | AE24: 21.62 | AF24: -0.162 | AG24: -0.215 | AI24: Economic productivity loss | AJ24: 27.56 | AK24: 23.07 | AL24: 23.09 | AM24: 21.62 | AN24: -0.162 | AO24: -0.216
C25: Total cost | D25: 38.72 | E25: 34.28 | F25: 31.89 | G25: 30.35 | H25: -0.176 | I25: -0.216 | K25: Total cost | L25: 38.72 | M25: 34.28 | N25: 31.4 | O25: 29.82 | P25: -0.189 | Q25: -0.23 | S25: Total cost | T25: 38.72 | U25: 34.28 | V25: 31.64 | W25: 30.1 | X25: -0.183 | Y25: -0.223 | AA25: Total cost | AB25: 38.72 | AC25: 34.28 | AD25: 31.65 | AE25: 30.03 | AF25: -0.182 | AG25: -0.224 | AI25: Total cost | AJ25: 38.72 | AK25: 34.28 | AL25: 31.65 | AM25: 30.08 | AN25: -0.183 | AO25: -0.223

Sheet range
B1: min-max*70% | C1: min-max*80% | E1: min-max*90% | F1: min-max (base) | L1: min-max*70% | R1: min-max*80% | X1: min-max*90% | AD1: min-max (base) | AJ1: min-max 0.85 | AP1: min-max 1.15 | AZ1: no vacc | BA1: constant vacc | BB1: actual vacc | BC1: min-max*70% | BD1: min-max*80% | BE1: min-max*90% | BF1: min-max (base)
A2: Hosp Cost | B2: =P3 -> 6.268083 | C2: =V3 -> 6.087827 | E2: =AB3 -> 5.758631 | F2: =AH3 -> 5.610668 | M2: no vacc | N2: constant vacc | O2: actual vacc | P2: opt vacc | R2: Type | S2: no vacc | T2: constant vacc | U2: actual vacc | V2: opt vacc | X2: Type | Y2: no vacc | Z2: constant vacc | AA2: actual vacc | AB2: opt vacc | AE2: no vacc | AF2: constant vacc | AG2: actual vacc | AH2: opt vacc | AK2: no vacc | AL2: constant vacc | AM2: actual vacc | AN2: opt vacc | AQ2: no vacc | AR2: constant vacc | AS2: actual vacc | AT2: opt vacc | BC2: opt vacc
A3: Policy Cost | B3: =P4 -> 3.574413 | C3: =V4 -> 3.796195 | E3: =AB4 -> 4.26938 | F3: =AH4 -> 4.513925 | L3: Hosp Cost | M3: 11.616842 | N3: 9.249465 | O3: 5.627283 | P3: 6.268083 | R3: 0 Hosp Cost | S3: 11.616842 | T3: 9.249465 | U3: 5.627283 | V3: 6.087827 | X3: 0 Hosp Cost | Y3: 11.616842 | Z3: 9.249465 | AA3: 5.627283 | AB3: 5.758631 | AE3: 11.616842 | AF3: 9.249465 | AG3: 6.374409 | AH3: 5.610668 | AK3: 11.616842 | AL3: 9.249465 | AM3: 6.374409 | AN3: 5.610668 | AQ3: 11.616842 | AR3: 9.249465 | AS3: 6.374409 | AT3: 5.610668 | AY3: Hosp Cost | AZ3: =M3 -> 11.616842 | BA3: =N3 -> 9.249465 | BB3: =O3 -> 5.627283 | BC3: =P3 -> 6.268083 | BD3: =V3 -> 6.087827 | BE3: =AB3 -> 5.758631 | BF3: =AH3 -> 5.610668
A4: Econ Cost | B4: =P5 -> 31.211228 | C4: =V5 -> 30.573665 | E4: =AB5 -> 29.429176 | F4: =AH5 -> 28.924867 | L4: Policy Cost | M4: 2.757488 | N4: 3.077856 | O4: 4.46062 | P4: 3.574413 | R4: 1 Policy Cost | S4: 2.757488 | T4: 3.077856 | U4: 4.46062 | V4: 3.796195 | X4: 1 Policy Cost | Y4: 2.757488 | Z4: 3.077856 | AA4: 4.46062 | AB4: 4.26938 | AE4: 2.757488 | AF4: 3.077856 | AG4: 3.979546 | AH4: 4.513925 | AK4: 2.757488 | AL4: 3.077856 | AM4: 3.979546 | AN4: 4.513925 | AQ4: 2.757488 | AR4: 3.077856 | AS4: 3.979546 | AT4: 4.513925 | AY4: Policy Cost | AZ4: =M4 -> 2.757488 | BA4: =N4 -> 3.077856 | BB4: =O4 -> 4.46062 | BC4: =P4 -> 3.574413 | BD4: =V4 -> 3.796195 | BE4: =AB4 -> 4.26938 | BF4: =AH4 -> 4.513925
A5: Total Cost | B5: =P6 -> 41.053725 | C5: =V6 -> 40.457688 | E5: =AB6 -> 39.457186 | F5: =AH6 -> 39.049459 | L5: Econ Cost | M5: 42.917935 | N5: 33.642296 | O5: 28.965808 | P5: 31.211228 | R5: 2 Econ Cost | S5: 42.917935 | T5: 33.642296 | U5: 28.965808 | V5: 30.573665 | X5: 2 Econ Cost | Y5: 42.917935 | Z5: 33.642296 | AA5: 28.965808 | AB5: 29.429176 | AE5: 42.917935 | AF5: 33.642296 | AG5: 31.83938 | AH5: 28.924867 | AK5: 42.917935 | AL5: 33.642296 | AM5: 31.83938 | AN5: 28.924867 | AQ5: 42.917935 | AR5: 33.642296 | AS5: 31.83938 | AT5: 28.924867 | AY5: Econ Cost | AZ5: =M5 -> 42.917935 | BA5: =N5 -> 33.642296 | BB5: =O5 -> 28.965808 | BC5: =P5 -> 31.211228 | BD5: =V5 -> 30.573665 | BE5: =AB5 -> 29.429176 | BF5: =AH5 -> 28.924867
L6: Total Cost | M6: 57.292265 | N6: 45.969617 | O6: 39.053711 | P6: 41.053725 | R6: 3 Total Cost | S6: 57.292265 | T6: 45.969617 | U6: 39.053711 | V6: 40.457688 | X6: 3 Total Cost | Y6: 57.292265 | Z6: 45.969617 | AA6: 39.053711 | AB6: 39.457186 | AE6: 57.292265 | AF6: 45.969617 | AG6: 42.193335 | AH6: 39.049459 | AK6: 57.292265 | AL6: 45.969617 | AM6: 42.193335 | AN6: 39.049459 | AQ6: 57.292265 | AR6: 45.969617 | AS6: 42.193335 | AT6: 39.049459 | AY6: Total Cost | AZ6: =M6 -> 57.292265 | BA6: =N6 -> 45.969617 | BB6: =O6 -> 39.053711 | BC6: =P6 -> 41.053725 | BD6: =V6 -> 40.457688 | BE6: =AB6 -> 39.457186 | BF6: =AH6 -> 39.049459
L8: Hosp Cost Savings | M8: =1-$P3/M3 -> 0.46043142 | N8: =1-$P3/N3 -> 0.32233021 | O8: =1-$P3/O3 -> -0.11387378 | S8: =1-$P3/S3 -> 0.46043142 | T8: =1-$P3/T3 -> 0.32233021 | U8: =1-$P3/U3 -> -0.11387378 | Y8: =1-$P3/Y3 -> 0.46043142 | Z8: =1-$P3/Z3 -> 0.32233021 | AA8: =1-$P3/AA3 -> -0.11387378 | AE8: =1-$AH3/AE3 -> 0.51702296 | AF8: =1-$AH3/AF3 -> 0.39340621 | AG8: =1-$AH3/AG3 -> 0.11981362 | AK8: =1-$AH3/AK3 -> 0.51702296 | AL8: =1-$AH3/AL3 -> 0.39340621 | AM8: =1-$AH3/AM3 -> 0.11981362 | AQ8: =1-$AH3/AQ3 -> 0.51702296 | AR8: =1-$AH3/AR3 -> 0.39340621 | AS8: =1-$AH3/AS3 -> 0.11981362
L9: Policy Cost Savings | M9: =1-$P4/M4 -> -0.29625696 | N9: =1-$P4/N4 -> -0.16133211 | O9: =1-$P4/O4 -> 0.1986735 | S9: =1-$P4/S4 -> -0.29625696 | T9: =1-$P4/T4 -> -0.16133211 | U9: =1-$P4/U4 -> 0.1986735 | Y9: =1-$P4/Y4 -> -0.29625696 | Z9: =1-$P4/Z4 -> -0.16133211 | AA9: =1-$P4/AA4 -> 0.1986735 | AE9: =1-$AH4/AE4 -> -0.63696995 | AF9: =1-$AH4/AF4 -> -0.46658096 | AG9: =1-$AH4/AG4 -> -0.1342814 | AK9: =1-$AH4/AK4 -> -0.63696995 | AL9: =1-$AH4/AL4 -> -0.46658096 | AM9: =1-$AH4/AM4 -> -0.1342814 | AQ9: =1-$AH4/AQ4 -> -0.63696995 | AR9: =1-$AH4/AR4 -> -0.46658096 | AS9: =1-$AH4/AS4 -> -0.1342814
L10: Econ Cost Savings | M10: =1-$P5/M5 -> 0.27276958 | N10: =1-$P5/N5 -> 0.07226225 | O10: =1-$P5/O5 -> -0.077519674 | S10: =1-$P5/S5 -> 0.27276958 | T10: =1-$P5/T5 -> 0.07226225 | U10: =1-$P5/U5 -> -0.077519674 | Y10: =1-$P5/Y5 -> 0.27276958 | Z10: =1-$P5/Z5 -> 0.07226225 | AA10: =1-$P5/AA5 -> -0.077519674 | AE10: =1-$AH5/AE5 -> 0.32604243 | AF10: =1-$AH5/AF5 -> 0.14022316 | AG10: =1-$AH5/AG5 -> 0.091537995 | AK10: =1-$AH5/AK5 -> 0.32604243 | AL10: =1-$AH5/AL5 -> 0.14022316 | AM10: =1-$AH5/AM5 -> 0.091537995 | AQ10: =1-$AH5/AQ5 -> 0.32604243 | AR10: =1-$AH5/AR5 -> 0.14022316 | AS10: =1-$AH5/AS5 -> 0.091537995
A11: diff | B11: 0.012 | C11: 0.0092 | E11: 0.0106 | F11: 0.0078 | L11: Total Cost Savings | M11: =1-$P6/M6 -> 0.28343337 | N11: =1-$P6/N6 -> 0.10693785 | O11: =1-$P6/O6 -> -0.051211881 | S11: =1-$P6/S6 -> 0.28343337 | T11: =1-$P6/T6 -> 0.10693785 | U11: =1-$P6/U6 -> -0.051211881 | Y11: =1-$P6/Y6 -> 0.28343337 | Z11: =1-$P6/Z6 -> 0.10693785 | AA11: =1-$P6/AA6 -> -0.051211881 | AE11: =1-$AH6/AE6 -> 0.31841656 | AF11: =1-$AH6/AF6 -> 0.15053765 | AG11: =1-$AH6/AG6 -> 0.074511199 | AK11: =1-$AH6/AK6 -> 0.31841656 | AL11: =1-$AH6/AL6 -> 0.15053765 | AM11: =1-$AH6/AM6 -> 0.074511199 | AQ11: =1-$AH6/AQ6 -> 0.31841656 | AR11: =1-$AH6/AR6 -> 0.15053765 | AS11: =1-$AH6/AS6 -> 0.074511199
A12: mid | B12: 0.016 | C12: 0.0132 | E12: 0.0146 | F12: 0.0118 | L12: new6 | R12: new4 | X12: new5 | AD12: new1 | AJ12: new1 | AP12: new1
B13: min-max*70% | C13: min-max*80% | D13: min-max*85% | E13: min-max*90% | F13: min-max (base) | G13: min-max*115% | L13: min-max*70% | R13: min-max*80% | X13: min-max*90% | AD13: min-max (base) | AJ13: min-max 0.85 | AP13: min-max 1.15
B14: =AVERAGE(L14:P14) -> 0.0198651 | C14: =AVERAGE(R14:V14) -> 0.0218458 | D14: =AVERAGE(AJ14:AN14) -> 0.02383136 | E14: =AVERAGE(X14:AB14) -> 0.0258058 | F14: =AVERAGE(AD14:AH14) -> 0.02778504 | G14: =AVERAGE(AP14:AT14) -> 0.0317465 | H14: =ROUND(E14,4)&"," -> 0.0258, | L14: 0.0198709 | M14: 0.0198553 | N14: 0.0198696 | O14: 0.0198619 | P14: 0.0198678 | R14: 0.0218525 | S14: 0.0218344 | T14: 0.021851 | U14: 0.0218421 | V14: 0.021849 | X14: 0.0258143 | Y14: 0.0257911 | Z14: 0.0258124 | AA14: 0.0258011 | AB14: 0.0258101 | AD14: 0.0277946 | AE14: 0.0277686 | AF14: 0.0277924 | AG14: 0.0277797 | AH14: 0.0277899 | AJ14: 0.0238206 | AK14: 0.0238331 | AL14: 0.0238252 | AM14: 0.0238204 | AN14: 0.0238575 | AP14: 0.0317299 | AQ14: 0.0317495 | AR14: 0.0317367 | AS14: 0.0317294 | AT14: 0.031787
B15: =AVERAGE(L15:P15) -> 0.01986832 | C15: =AVERAGE(R15:V15) -> 0.02184908 | D15: =AVERAGE(AJ15:AN15) -> 0.02383718 | E15: =AVERAGE(X15:AB15) -> 0.02580882 | F15: =AVERAGE(AD15:AH15) -> 0.02778774 | G15: =AVERAGE(AP15:AT15) -> 0.03175088 | H15: =ROUND(E15,4)&"," -> 0.0258, | L15: 0.0198745 | M15: 0.0198556 | N15: 0.0198763 | O15: 0.019864 | P15: 0.0198712 | R15: 0.0218563 | S15: 0.0218343 | T15: 0.0218582 | U15: 0.0218441 | V15: 0.0218525 | X15: 0.0258182 | Y15: 0.0257898 | Z15: 0.0258202 | AA15: 0.0258026 | AB15: 0.0258133 | AD15: 0.0277982 | AE15: 0.0277666 | AF15: 0.0278003 | AG15: 0.0277808 | AH15: 0.0277928 | AJ15: 0.0238228 | AK15: 0.0238355 | AL15: 0.0238365 | AM15: 0.0238363 | AN15: 0.0238548 | AP15: 0.0317284 | AQ15: 0.0317487 | AR15: 0.031749 | AS15: 0.031748 | AT15: 0.0317803
B16: =AVERAGE(L16:P16) -> 0.01986366 | C16: =AVERAGE(R16:V16) -> 0.02184328 | D16: =AVERAGE(AJ16:AN16) -> 0.02382668 | E16: =AVERAGE(X16:AB16) -> 0.02580032 | F16: =AVERAGE(AD16:AH16) -> 0.02777764 | G16: =AVERAGE(AP16:AT16) -> 0.0317303 | H16: =ROUND(E16,4)&"," -> 0.0258, | L16: 0.0198685 | M16: 0.019852 | N16: 0.0198724 | O16: 0.0198598 | P16: 0.0198656 | R16: 0.021849 | S16: 0.0218297 | T16: 0.0218532 | U16: 0.0218388 | V16: 0.0218457 | X16: 0.025808 | Y16: 0.0257825 | Z16: 0.0258126 | AA16: 0.0257948 | AB16: 0.0258037 | AD16: 0.0277864 | AE16: 0.0277577 | AF16: 0.0277911 | AG16: 0.0277714 | AH16: 0.0277816 | AJ16: 0.0238123 | AK16: 0.0238251 | AL16: 0.023826 | AM16: 0.0238225 | AN16: 0.0238475 | AP16: 0.0317082 | AQ16: 0.031729 | AR16: 0.031727 | AS16: 0.0317227 | AT16: 0.0317646
B17: =AVERAGE(L17:P17) -> 0.01985994 | C17: =AVERAGE(R17:V17) -> 0.02183842 | D17: =AVERAGE(AJ17:AN17) -> 0.02381724 | E17: =AVERAGE(X17:AB17) -> 0.02579254 | F17: =AVERAGE(AD17:AH17) -> 0.02776806 | G17: =AVERAGE(AP17:AT17) -> 0.03170932 | H17: =ROUND(E17,4)&"," -> 0.0258, | L17: 0.0198648 | M17: 0.0198468 | N17: 0.0198699 | O17: 0.0198545 | P17: 0.0198637 | R17: 0.0218442 | S17: 0.0218231 | T17: 0.0218497 | U17: 0.0218321 | V17: 0.021843 | X17: 0.0258005 | Y17: 0.0257727 | Z17: 0.0258065 | AA17: 0.0257844 | AB17: 0.0257986 | AD17: 0.0277772 | AE17: 0.0277457 | AF17: 0.0277835 | AG17: 0.0277589 | AH17: 0.027775 | AJ17: 0.0238037 | AK17: 0.0238165 | AL17: 0.0238131 | AM17: 0.0238141 | AN17: 0.0238388 | AP17: 0.0316884 | AQ17: 0.0317078 | AR17: 0.0317012 | AS17: 0.031704 | AT17: 0.0317452
B18: =AVERAGE(L18:P18) -> 0.01985436 | C18: =AVERAGE(R18:V18) -> 0.02183138 | D18: =AVERAGE(AJ18:AN18) -> 0.02380656 | E18: =AVERAGE(X18:AB18) -> 0.02578174 | F18: =AVERAGE(AD18:AH18) -> 0.02775492 | G18: =AVERAGE(AP18:AT18) -> 0.03168316 | H18: =ROUND(E18,4)&"," -> 0.0258, | L18: 0.0198586 | M18: 0.0198428 | N18: 0.0198651 | O18: 0.0198472 | P18: 0.0198581 | R18: 0.0218367 | S18: 0.0218178 | T18: 0.0218436 | U18: 0.021823 | V18: 0.0218358 | X18: 0.0257892 | Y18: 0.0257642 | Z18: 0.0257969 | AA18: 0.0257708 | AB18: 0.0257876 | AD18: 0.0277638 | AE18: 0.0277353 | AF18: 0.0277716 | AG18: 0.0277424 | AH18: 0.0277615 | AJ18: 0.023792 | AK18: 0.0238032 | AL18: 0.0238026 | AM18: 0.0238052 | AN18: 0.0238298 | AP18: 0.0316627 | AQ18: 0.0316778 | AR18: 0.0316754 | AS18: 0.0316766 | AT18: 0.0317233
B19: =AVERAGE(L19:P19) -> 0.01984712 | C19: =AVERAGE(R19:V19) -> 0.02182236 | D19: =AVERAGE(AJ19:AN19) -> 0.02379346 | E19: =AVERAGE(X19:AB19) -> 0.02576812 | F19: =AVERAGE(AD19:AH19) -> 0.02773842 | G19: =AVERAGE(AP19:AT19) -> 0.0316516 | H19: =ROUND(E19,4)&"," -> 0.0258, | L19: 0.0198537 | M19: 0.0198326 | N19: 0.0198597 | O19: 0.0198403 | P19: 0.0198493 | R19: 0.0218304 | S19: 0.0218052 | T19: 0.021837 | U19: 0.021814 | V19: 0.0218252 | X19: 0.0257794 | Y19: 0.0257452 | Z19: 0.0257872 | AA19: 0.0257564 | AB19: 0.0257724 | AD19: 0.0277518 | AE19: 0.0277123 | AF19: 0.0277599 | AG19: 0.0277247 | AH19: 0.0277434 | AJ19: 0.0237817 | AK19: 0.0237865 | AL19: 0.0237908 | AM19: 0.0237891 | AN19: 0.0238192 | AP19: 0.0316379 | AQ19: 0.0316372 | AR19: 0.0316446 | AS19: 0.0316393 | AT19: 0.031699
B20: =AVERAGE(L20:P20) -> 0.01983856 | C20: =AVERAGE(R20:V20) -> 0.02181148 | D20: =AVERAGE(AJ20:AN20) -> 0.02377416 | E20: =AVERAGE(X20:AB20) -> 0.02575126 | F20: =AVERAGE(AD20:AH20) -> 0.02771784 | G20: =AVERAGE(AP20:AT20) -> 0.03160518 | H20: =ROUND(E20,4)&"," -> 0.0258, | L20: 0.0198435 | M20: 0.0198258 | N20: 0.01985 | O20: 0.0198309 | P20: 0.0198426 | R20: 0.0218177 | S20: 0.0217964 | T20: 0.0218248 | U20: 0.021802 | V20: 0.0218165 | X20: 0.0257604 | Y20: 0.0257314 | Z20: 0.0257681 | AA20: 0.0257379 | AB20: 0.0257585 | AD20: 0.0277288 | AE20: 0.0276953 | AF20: 0.0277367 | AG20: 0.027702 | AH20: 0.0277264 | AJ20: 0.0237611 | AK20: 0.0237704 | AL20: 0.023772 | AM20: 0.0237608 | AN20: 0.0238065 | AP20: 0.0315907 | AQ20: 0.031595 | AR20: 0.0315969 | AS20: 0.031575 | AT20: 0.0316683
B21: =AVERAGE(L21:P21) -> 0.01982836 | C21: =AVERAGE(R21:V21) -> 0.02179862 | D21: =AVERAGE(AJ21:AN21) -> 0.02375374 | E21: =AVERAGE(X21:AB21) -> 0.02573194 | F21: =AVERAGE(AD21:AH21) -> 0.0276945 | G21: =AVERAGE(AP21:AT21) -> 0.03155218 | H21: =ROUND(E21,4)&"," -> 0.0257, | L21: 0.0198325 | M21: 0.0198151 | N21: 0.0198442 | O21: 0.0198201 | P21: 0.0198299 | R21: 0.0218036 | S21: 0.0217828 | T21: 0.0218174 | U21: 0.0217886 | V21: 0.0218007 | X21: 0.0257383 | Y21: 0.025711 | Z21: 0.0257572 | AA21: 0.0257179 | AB21: 0.0257353 | AD21: 0.0277015 | AE21: 0.0276707 | AF21: 0.0277235 | AG21: 0.0276778 | AH21: 0.027699 | AJ21: 0.0237373 | AK21: 0.0237497 | AL21: 0.0237482 | AM21: 0.0237409 | AN21: 0.0237926 | AP21: 0.0315313 | AQ21: 0.0315403 | AR21: 0.0315298 | AS21: 0.0315256 | AT21: 0.0316339
B22: =AVERAGE(L22:P22) -> 0.01981658 | C22: =AVERAGE(R22:V22) -> 0.02178366 | D22: =AVERAGE(AJ22:AN22) -> 0.02372822 | E22: =AVERAGE(X22:AB22) -> 0.02570854 | F22: =AVERAGE(AD22:AH22) -> 0.0276657 | G22: =AVERAGE(AP22:AT22) -> 0.0314817 | H22: =ROUND(E22,4)&"," -> 0.0257, | L22: 0.0198171 | M22: 0.019809 | N22: 0.0198355 | O22: 0.0198053 | P22: 0.019816 | R22: 0.0217836 | S22: 0.0217751 | T22: 0.0218068 | U22: 0.0217701 | V22: 0.0217827 | X22: 0.0257054 | Y22: 0.0256987 | Z22: 0.0257414 | AA22: 0.0256907 | AB22: 0.0257065 | AD22: 0.0276604 | AE22: 0.0276556 | AF22: 0.0277047 | AG22: 0.0276448 | AH22: 0.027663 | AJ22: 0.0237033 | AK22: 0.0237273 | AL22: 0.023718 | AM22: 0.0237175 | AN22: 0.023775 | AP22: 0.0314404 | AQ22: 0.0314777 | AR22: 0.0314484 | AS22: 0.0314589 | AT22: 0.0315831
B23: =AVERAGE(L23:P23) -> 0.01979752 | C23: =AVERAGE(R23:V23) -> 0.02175908 | D23: =AVERAGE(AJ23:AN23) -> 0.02370344 | E23: =AVERAGE(X23:AB23) -> 0.0256687 | F23: =AVERAGE(AD23:AH23) -> 0.02761574 | G23: =AVERAGE(AP23:AT23) -> 0.031413 | H23: =ROUND(E23,4)&"," -> 0.0257, | L23: 0.019808 | M23: 0.0197905 | N23: 0.0198184 | O23: 0.0197816 | P23: 0.0197891 | R23: 0.0217723 | S23: 0.021751 | T23: 0.0217844 | U23: 0.0217394 | V23: 0.0217483 | X23: 0.025688 | Y23: 0.0256591 | Z23: 0.0257037 | AA23: 0.0256413 | AB23: 0.0256514 | AD23: 0.0276388 | AE23: 0.0276058 | AF23: 0.0276569 | AG23: 0.0275826 | AH23: 0.0275946 | AJ23: 0.0236833 | AK23: 0.023713 | AL23: 0.0236773 | AM23: 0.0236763 | AN23: 0.0237673 | AP23: 0.0313838 | AQ23: 0.0314301 | AR23: 0.0313258 | AS23: 0.0313654 | AT23: 0.0315599
B24: =AVERAGE(L24:P24) -> 0.0197705 | C24: =AVERAGE(R24:V24) -> 0.02172476 | D24: =AVERAGE(AJ24:AN24) -> 0.02366538 | E24: =AVERAGE(X24:AB24) -> 0.02561426 | F24: =AVERAGE(AD24:AH24) -> 0.0275478 | G24: =AVERAGE(AP24:AT24) -> 0.03131528 | H24: =ROUND(E24,4)&"," -> 0.0256, | L24: 0.0197824 | M24: 0.0197621 | N24: 0.0197689 | O24: 0.0197644 | P24: 0.0197747 | R24: 0.0217383 | S24: 0.0217149 | T24: 0.0217238 | U24: 0.0217174 | V24: 0.0217294 | X24: 0.0256301 | Y24: 0.025604 | Z24: 0.0256104 | AA24: 0.0256073 | AB24: 0.0256195 | AD24: 0.0275643 | AE24: 0.0275391 | AF24: 0.02754 | AG24: 0.02754 | AH24: 0.0275556 | AJ24: 0.0236169 | AK24: 0.023708 | AL24: 0.0236582 | AM24: 0.0236123 | AN24: 0.0237315 | AP24: 0.0311917 | AQ24: 0.0314344 | AR24: 0.0312966 | AS24: 0.0311904 | AT24: 0.0314633
B25: =AVERAGE(L25:P25) -> 0.01974946 | C25: =AVERAGE(R25:V25) -> 0.0216972 | D25: =AVERAGE(AJ25:AN25) -> 0.02361198 | E25: =AVERAGE(X25:AB25) -> 0.02556912 | F25: =AVERAGE(AD25:AH25) -> 0.0274928 | G25: =AVERAGE(AP25:AT25) -> 0.03115254 | H25: =ROUND(E25,4)&"," -> 0.0256, | L25: 0.0197727 | M25: 0.0197247 | N25: 0.0197799 | O25: 0.0197305 | P25: 0.0197395 | R25: 0.0217255 | S25: 0.0216677 | T25: 0.0217361 | U25: 0.0216746 | V25: 0.0216821 | X25: 0.0256091 | Y25: 0.0255308 | Z25: 0.0256277 | AA25: 0.025538 | AB25: 0.02554 | AD25: 0.0275381 | AE25: 0.0274522 | AF25: 0.0275633 | AG25: 0.0274556 | AH25: 0.0274548 | AJ25: 0.0235906 | AK25: 0.0236509 | AL25: 0.0235976 | AM25: 0.0235273 | AN25: 0.0236935 | AP25: 0.0311142 | AQ25: 0.0312325 | AR25: 0.0311104 | AS25: 0.0309594 | AT25: 0.0313462
... B73: =AVERAGE(L73:P73) -> 0.004123386 | C73: =AVERAGE(R73:V73) -> 0.004143408 | D73: =AVERAGE(AJ73:AN73) -> 0.004184262 | E73: =AVERAGE(X73:AB73) -> 0.004186072 | F73: =AVERAGE(AD73:AH73) -> 0.004208692 | G73: =AVERAGE(AP73:AT73) -> 0.00429183 | H73: =ROUND(E73,4)&"," -> 0.0042, | L73: 0.00412891 | M73: 0.00411692 | N73: 0.0041273 | O73: 0.0041214 | P73: 0.0041224 | R73: 0.00414988 | S73: 0.00413573 | T73: 0.00414824 | U73: 0.00414101 | V73: 0.00414218 | X73: 0.00419467 | Y73: 0.00417585 | Z73: 0.00419255 | AA73: 0.00418288 | AB73: 0.00418441 | AD73: 0.00421842 | AE73: 0.00419712 | AF73: 0.00421605 | AG73: 0.00420508 | AH73: 0.00420679 | AJ73: 0.00417181 | AK73: 0.0041922 | AL73: 0.00417283 | AM73: 0.00415877 | AN73: 0.0042257 | AP73: 0.00426857 | AQ73: 0.00430773 | AR73: 0.00427138 | AS73: 0.0042554 | AT73: 0.00435607

Sheet range (2)
B1: min-max*70% | C1: min-max*85% | F1: min-max (base) | G1: min-max*115% | L1: min-max*70% | R1: min-max*80% | X1: min-max*90% | AD1: min-max (base) | AJ1: min-max 0.85 | AP1: min-max 1.15 | AZ1: no vacc | BA1: constant vacc | BB1: actual vacc | BC1: min-max*70% | BD1: min-max*80% | BE1: min-max*90% | BF1: min-max (base)
A2: Vaccination costs | B2: =P3 -> 1.58 | C2: =AN3 -> 1.97 | F2: =AH3 -> 2.45 | G2: =AT3 -> 2.91 | M2: no vacc | N2: constant vacc | O2: actual vacc | P2: opt vacc | R2: Type | S2: no vacc | T2: constant vacc | U2: actual vacc | V2: opt vacc | X2: Type | Y2: no vacc | Z2: constant vacc | AA2: actual vacc | AB2: opt vacc | AE2: no vacc | AF2: constant vacc | AG2: actual vacc | AH2: opt vacc | AK2: no vacc | AL2: constant vacc | AM2: actual vacc | AN2: opt vacc | AQ2: no vacc | AR2: constant vacc | AS2: actual vacc | AT2: opt vacc | BC2: opt vacc
A3: Quarantine costs | B3: =P4 -> 1.37 | C3: =AN4 -> 1.33 | F3: =AH4 -> 1.3 | G3: =AT4 -> 1.26 | L3: Vaccination costs | M3: 0 | N3: 1.71 | O3: 1.96 | P3: 1.58 | R3: 0 Hosp Cost | S3: 11.616842 | T3: 9.249465 | U3: 5.627283 | V3: 6.087827 | X3: 0 Hosp Cost | Y3: 11.616842 | Z3: 9.249465 | AA3: 5.627283 | AB3: 5.758631 | AD3: Vaccination costs | AE3: 0 | AF3: 1.71 | AG3: 1.96 | AH3: 2.45 | AJ3: Vaccination costs | AK3: 0 | AL3: 1.71 | AM3: 1.96 | AN3: 1.97 | AP3: Vaccination costs | AQ3: 0 | AR3: 1.71 | AS3: 1.96 | AT3: 2.91 | AY3: Hosp Cost | AZ3: =M3 -> 0 | BA3: =N3 -> 1.71 | BB3: =O3 -> 1.96 | BC3: =P3 -> 1.58 | BD3: =V3 -> 6.087827 | BE3: =AB3 -> 5.758631 | BF3: =AH3 -> 2.45
A4: Healthcare costs | B4: =P5 -> 5.15 | C4: =AN5 -> 4.93 | F4: =AH5 -> 4.72 | G4: =AT5 -> 4.53 | L4: Quarantine costs | M4: 1.66 | N4: 1.37 | O4: 1.39 | P4: 1.37 | R4: 1 Policy Cost | S4: 2.757488 | T4: 3.077856 | U4: 4.46062 | V4: 3.796195 | X4: 1 Policy Cost | Y4: 2.757488 | Z4: 3.077856 | AA4: 4.46062 | AB4: 4.26938 | AD4: Quarantine costs | AE4: 1.66 | AF4: 1.37 | AG4: 1.39 | AH4: 1.3 | AJ4: Quarantine costs | AK4: 1.66 | AL4: 1.37 | AM4: 1.39 | AN4: 1.33 | AP4: Quarantine costs | AQ4: 1.66 | AR4: 1.37 | AS4: 1.39 | AT4: 1.26 | AY4: Policy Cost | AZ4: =M4 -> 1.66 | BA4: =N4 -> 1.37 | BB4: =O4 -> 1.39 | BC4: =P4 -> 1.37 | BD4: =V4 -> 3.796195 | BE4: =AB4 -> 4.26938 | BF4: =AH4 -> 1.3
A5: Economic productivity loss | B5: =P6 -> 22.84 | C5: =AN6 -> 22.19 | F5: =AH6 -> 21.62 | G5: =AT6 -> 21.12 | L5: Healthcare costs | M5: 9.5 | N5: 8.13 | O5: 5.21 | P5: 5.15 | R5: 2 Econ Cost | S5: 42.917935 | T5: 33.642296 | U5: 28.965808 | V5: 30.573665 | X5: 2 Econ Cost | Y5: 42.917935 | Z5: 33.642296 | AA5: 28.965808 | AB5: 29.429176 | AD5: Healthcare costs | AE5: 9.5 | AF5: 8.13 | AG5: 5.21 | AH5: 4.72 | AJ5: Healthcare costs | AK5: 9.5 | AL5: 8.13 | AM5: 5.21 | AN5: 4.93 | AP5: Healthcare costs | AQ5: 9.5 | AR5: 8.13 | AS5: 5.21 | AT5: 4.53 | AY5: Econ Cost | AZ5: =M5 -> 9.5 | BA5: =N5 -> 8.13 | BB5: =O5 -> 5.21 | BC5: =P5 -> 5.15 | BD5: =V5 -> 30.573665 | BE5: =AB5 -> 29.429176 | BF5: =AH5 -> 4.72
A6: Total cost | B6: =P7 -> 30.95 | C6: =AN7 -> 30.42 | F6: =AH7 -> 30.08 | G6: =AT7 -> 29.83 | L6: Economic productivity loss | M6: 27.56 | N6: 23.07 | O6: 23.09 | P6: 22.84 | R6: 3 Total Cost | S6: 57.292265 | T6: 45.969617 | U6: 39.053711 | V6: 40.457688 | X6: 3 Total Cost | Y6: 57.292265 | Z6: 45.969617 | AA6: 39.053711 | AB6: 39.457186 | AD6: Economic productivity loss | AE6: 27.56 | AF6: 23.07 | AG6: 23.09 | AH6: 21.62 | AJ6: Economic productivity loss | AK6: 27.56 | AL6: 23.07 | AM6: 23.09 | AN6: 22.19 | AP6: Economic productivity loss | AQ6: 27.56 | AR6: 23.07 | AS6: 23.09 | AT6: 21.12 | AY6: Total Cost | AZ6: =M6 -> 27.56 | BA6: =N6 -> 23.07 | BB6: =O6 -> 23.09 | BC6: =P6 -> 22.84 | BD6: =V6 -> 40.457688 | BE6: =AB6 -> 39.457186 | BF6: =AH6 -> 21.62
L7: Total cost | M7: 38.72 | N7: 34.28 | O7: 31.65 | P7: 30.95 | AD7: Total cost | AE7: 38.72 | AF7: 34.28 | AG7: 31.65 | AH7: 30.08 | AJ7: Total cost | AK7: 38.72 | AL7: 34.28 | AM7: 31.65 | AN7: 30.42 | AP7: Total cost | AQ7: 38.72 | AR7: 34.28 | AS7: 31.65 | AT7: 29.83
L9: Vaccination saving | M9: =1-$P3/M3 -> #DIV/0! | N9: =1-$P3/N3 -> 0.076023392 | O9: =1-$P3/O3 -> 0.19387755 | S9: =1-$P3/S3 -> 0.86399058 | T9: =1-$P3/T3 -> 0.82917931 | U9: =1-$P3/U3 -> 0.71922507 | Y9: =1-$P3/Y3 -> 0.86399058 | Z9: =1-$P3/Z3 -> 0.82917931 | AA9: =1-$P3/AA3 -> 0.71922507 | AE9: =1-$AH3/AE3 -> #DIV/0! | AF9: =1-$AH3/AF3 -> -0.43274854 | AG9: =1-$AH3/AG3 -> -0.25 | AK9: =1-$AH3/AK3 -> #DIV/0! | AL9: =1-$AH3/AL3 -> -0.43274854 | AM9: =1-$AH3/AM3 -> -0.25 | AQ9: =1-$AH3/AQ3 -> #DIV/0! | AR9: =1-$AH3/AR3 -> -0.43274854 | AS9: =1-$AH3/AS3 -> -0.25
L10: Quarantine saving | M10: =1-$P4/M4 -> 0.1746988 | N10: =1-$P4/N4 -> 0 | O10: =1-$P4/O4 -> 0.014388489 | S10: =1-$P4/S4 -> 0.503171 | T10: =1-$P4/T4 -> 0.55488496 | U10: =1-$P4/U4 -> 0.69286781 | Y10: =1-$P4/Y4 -> 0.503171 | Z10: =1-$P4/Z4 -> 0.55488496 | AA10: =1-$P4/AA4 -> 0.69286781 | AE10: =1-$AH4/AE4 -> 0.21686747 | AF10: =1-$AH4/AF4 -> 0.051094891 | AG10: =1-$AH4/AG4 -> 0.064748201 | AK10: =1-$AH4/AK4 -> 0.21686747 | AL10: =1-$AH4/AL4 -> 0.051094891 | AM10: =1-$AH4/AM4 -> 0.064748201 | AQ10: =1-$AH4/AQ4 -> 0.21686747 | AR10: =1-$AH4/AR4 -> 0.051094891 | AS10: =1-$AH4/AS4 -> 0.064748201
L11: Healthcare saving | M11: =1-$P5/M5 -> 0.45789474 | N11: =1-$P5/N5 -> 0.36654367 | O11: =1-$P5/O5 -> 0.011516315 | S11: =1-$P5/S5 -> 0.88000355 | T11: =1-$P5/T5 -> 0.84691889 | U11: =1-$P5/U5 -> 0.82220417 | Y11: =1-$P5/Y5 -> 0.88000355 | Z11: =1-$P5/Z5 -> 0.84691889 | AA11: =1-$P5/AA5 -> 0.82220417 | AE11: =1-$AH5/AE5 -> 0.50315789 | AF11: =1-$AH5/AF5 -> 0.41943419 | AG11: =1-$AH5/AG5 -> 0.094049904 | AK11: =1-$AH5/AK5 -> 0.50315789 | AL11: =1-$AH5/AL5 -> 0.41943419 | AM11: =1-$AH5/AM5 -> 0.094049904 | AQ11: =1-$AH5/AQ5 -> 0.50315789 | AR11: =1-$AH5/AR5 -> 0.41943419 | AS11: =1-$AH5/AS5 -> 0.094049904
L12: Economic saving | M12: =1-$P6/M6 -> 0.1712627 | N12: =1-$P6/N6 -> 0.0099696576 | O12: =1-$P6/O6 -> 0.010827198 | S12: =1-$P6/S6 -> 0.60134235 | T12: =1-$P6/T6 -> 0.50315009 | U12: =1-$P6/U6 -> 0.41516441 | Y12: =1-$P6/Y6 -> 0.60134235 | Z12: =1-$P6/Z6 -> 0.50315009 | AA12: =1-$P6/AA6 -> 0.41516441 | AE12: =1-$AH6/AE6 -> 0.21552975 | AF12: =1-$AH6/AF6 -> 0.062852189 | AG12: =1-$AH6/AG6 -> 0.063663924 | AK12: =1-$AH6/AK6 -> 0.21552975 | AL12: =1-$AH6/AL6 -> 0.062852189 | AM12: =1-$AH6/AM6 -> 0.063663924 | AQ12: =1-$AH6/AQ6 -> 0.21552975 | AR12: =1-$AH6/AR6 -> 0.062852189 | AS12: =1-$AH6/AS6 -> 0.063663924
L13: Total saving | M13: =1-$P7/M7 -> 0.20067149 | N13: =1-$P7/N7 -> 0.09714119 | O13: =1-$P7/O7 -> 0.022116904 | S13: =1-$P7/S7 -> #DIV/0! | T13: =1-$P7/T7 -> #DIV/0! | U13: =1-$P7/U7 -> #DIV/0! | Y13: =1-$P7/Y7 -> #DIV/0! | Z13: =1-$P7/Z7 -> #DIV/0! | AA13: =1-$P7/AA7 -> #DIV/0! | AE13: =1-$AH7/AE7 -> 0.2231405 | AF13: =1-$AH7/AF7 -> 0.12252042 | AG13: =1-$AH7/AG7 -> 0.049605055 | AK13: =1-$AH7/AK7 -> 0.2231405 | AL13: =1-$AH7/AL7 -> 0.12252042 | AM13: =1-$AH7/AM7 -> 0.049605055 | AQ13: =1-$AH7/AQ7 -> 0.2231405 | AR13: =1-$AH7/AR7 -> 0.12252042 | AS13: =1-$AH7/AS7 -> 0.049605055
L15: Vaccination saving | M15: =M3-$P3 -> -1.58 | N15: =N3-$P3 -> 0.13 | O15: =O3-$P3 -> 0.38 | P15: =SUM(N15:N16) -> 0.13 | AD15: Vaccination saving | AE15: =AE3-$AH3 -> -2.45 | AF15: =AF3-$AH3 -> -0.74 | AG15: =AG3-$AH3 -> -0.49 | AH15: =SUM(AF15:AF16) -> -0.67 | AJ15: Vaccination saving | AK15: =AK3-$AN3 -> -1.97 | AL15: =AL3-$AN3 -> -0.26 | AM15: =AM3-$AN3 -> -0.01 | AN15: =SUM(AL15:AL16) -> -0.22 | AP15: Vaccination saving | AQ15: =AQ3-$AT3 -> -2.91 | AR15: =AR3-$AT3 -> -1.2 | AS15: =AS3-$AT3 -> -0.95 | AT15: =SUM(AR15:AR16) -> -1.09
L16: Quarantine saving | M16: =M4-$P4 -> 0.29 | N16: =N4-$P4 -> 0 | O16: =O4-$P4 -> 0.02 | AD16: Quarantine saving | AE16: =AE4-$AH4 -> 0.36 | AF16: =AF4-$AH4 -> 0.07 | AG16: =AG4-$AH4 -> 0.09 | AJ16: Quarantine saving | AK16: =AK4-$AN4 -> 0.33 | AL16: =AL4-$AN4 -> 0.04 | AM16: =AM4-$AN4 -> 0.06 | AP16: Quarantine saving | AQ16: =AQ4-$AT4 -> 0.4 | AR16: =AR4-$AT4 -> 0.11 | AS16: =AS4-$AT4 -> 0.13
L17: Healthcare saving | M17: =M5-$P5 -> 4.35 | N17: =N5-$P5 -> 2.98 | O17: =O5-$P5 -> 0.06 | AD17: Healthcare saving | AE17: =AE5-$AH5 -> 4.78 | AF17: =AF5-$AH5 -> 3.41 | AG17: =AG5-$AH5 -> 0.49 | AJ17: Healthcare saving | AK17: =AK5-$AN5 -> 4.57 | AL17: =AL5-$AN5 -> 3.2 | AM17: =AM5-$AN5 -> 0.28 | AP17: Healthcare saving | AQ17: =AQ5-$AT5 -> 4.97 | AR17: =AR5-$AT5 -> 3.6 | AS17: =AS5-$AT5 -> 0.68
L18: Economic saving | M18: =M6-$P6 -> 4.72 | N18: =N6-$P6 -> 0.23 | O18: =O6-$P6 -> 0.25 | AD18: Economic saving | AE18: =AE6-$AH6 -> 5.94 | AF18: =AF6-$AH6 -> 1.45 | AG18: =AG6-$AH6 -> 1.47 | AJ18: Economic saving | AK18: =AK6-$AN6 -> 5.37 | AL18: =AL6-$AN6 -> 0.88 | AM18: =AM6-$AN6 -> 0.9 | AP18: Economic saving | AQ18: =AQ6-$AT6 -> 6.44 | AR18: =AR6-$AT6 -> 1.95 | AS18: =AS6-$AT6 -> 1.97
A19: diff | B19: 0.012 | C19: 0.0092 | E19: 0.0106 | F19: 0.0078 | L19: Total saving | M19: =M7-$P7 -> 7.77 | N19: =N7-$P7 -> 3.33 | O19: =O7-$P7 -> 0.7 | AD19: Total saving | AE19: =AE7-$AH7 -> 8.64 | AF19: =AF7-$AH7 -> 4.2 | AG19: =AG7-$AH7 -> 1.57 | AJ19: Total saving | AK19: =AK7-$AN7 -> 8.3 | AL19: =AL7-$AN7 -> 3.86 | AM19: =AM7-$AN7 -> 1.23 | AP19: Total saving | AQ19: =AQ7-$AT7 -> 8.89 | AR19: =AR7-$AT7 -> 4.45 | AS19: =AS7-$AT7 -> 1.82
A20: mid | B20: 0.016 | C20: 0.0132 | E20: 0.0146 | F20: 0.0118 | L20: new6 | R20: new4 | X20: new5 | AD20: new1 | AJ20: new1 | AP20: new1
B21: min-max*70% | C21: min-max*80% | D21: min-max*85% | E21: min-max*90% | F21: min-max (base) | G21: min-max*115% | L21: min-max*70% | R21: min-max*80% | X21: min-max*90% | AD21: min-max (base) | AJ21: min-max 0.85 | AP21: min-max 1.15
B22: =AVERAGE(L22:P22) -> 0.0198651 | C22: =AVERAGE(R22:V22) -> 0.0218458 | D22: =AVERAGE(AJ22:AN22) -> 0.02383136 | E22: =AVERAGE(X22:AB22) -> 0.0258058 | F22: =AVERAGE(AD22:AH22) -> 0.02778504 | G22: =AVERAGE(AP22:AT22) -> 0.0317465 | H22: =ROUND(E22,4)&"," -> 0.0258, | L22: 0.0198709 | M22: 0.0198553 | N22: 0.0198696 | O22: 0.0198619 | P22: 0.0198678 | R22: 0.0218525 | S22: 0.0218344 | T22: 0.021851 | U22: 0.0218421 | V22: 0.021849 | X22: 0.0258143 | Y22: 0.0257911 | Z22: 0.0258124 | AA22: 0.0258011 | AB22: 0.0258101 | AD22: 0.0277946 | AE22: 0.0277686 | AF22: 0.0277924 | AG22: 0.0277797 | AH22: 0.0277899 | AJ22: 0.0238206 | AK22: 0.0238331 | AL22: 0.0238252 | AM22: 0.0238204 | AN22: 0.0238575 | AP22: 0.0317299 | AQ22: 0.0317495 | AR22: 0.0317367 | AS22: 0.0317294 | AT22: 0.031787
B23: =AVERAGE(L23:P23) -> 0.01986832 | C23: =AVERAGE(R23:V23) -> 0.02184908 | D23: =AVERAGE(AJ23:AN23) -> 0.02383718 | E23: =AVERAGE(X23:AB23) -> 0.02580882 | F23: =AVERAGE(AD23:AH23) -> 0.02778774 | G23: =AVERAGE(AP23:AT23) -> 0.03175088 | H23: =ROUND(E23,4)&"," -> 0.0258, | L23: 0.0198745 | M23: 0.0198556 | N23: 0.0198763 | O23: 0.019864 | P23: 0.0198712 | R23: 0.0218563 | S23: 0.0218343 | T23: 0.0218582 | U23: 0.0218441 | V23: 0.0218525 | X23: 0.0258182 | Y23: 0.0257898 | Z23: 0.0258202 | AA23: 0.0258026 | AB23: 0.0258133 | AD23: 0.0277982 | AE23: 0.0277666 | AF23: 0.0278003 | AG23: 0.0277808 | AH23: 0.0277928 | AJ23: 0.0238228 | AK23: 0.0238355 | AL23: 0.0238365 | AM23: 0.0238363 | AN23: 0.0238548 | AP23: 0.0317284 | AQ23: 0.0317487 | AR23: 0.031749 | AS23: 0.031748 | AT23: 0.0317803
B24: =AVERAGE(L24:P24) -> 0.01986366 | C24: =AVERAGE(R24:V24) -> 0.02184328 | D24: =AVERAGE(AJ24:AN24) -> 0.02382668 | E24: =AVERAGE(X24:AB24) -> 0.02580032 | F24: =AVERAGE(AD24:AH24) -> 0.02777764 | G24: =AVERAGE(AP24:AT24) -> 0.0317303 | H24: =ROUND(E24,4)&"," -> 0.0258, | L24: 0.0198685 | M24: 0.019852 | N24: 0.0198724 | O24: 0.0198598 | P24: 0.0198656 | R24: 0.021849 | S24: 0.0218297 | T24: 0.0218532 | U24: 0.0218388 | V24: 0.0218457 | X24: 0.025808 | Y24: 0.0257825 | Z24: 0.0258126 | AA24: 0.0257948 | AB24: 0.0258037 | AD24: 0.0277864 | AE24: 0.0277577 | AF24: 0.0277911 | AG24: 0.0277714 | AH24: 0.0277816 | AJ24: 0.0238123 | AK24: 0.0238251 | AL24: 0.023826 | AM24: 0.0238225 | AN24: 0.0238475 | AP24: 0.0317082 | AQ24: 0.031729 | AR24: 0.031727 | AS24: 0.0317227 | AT24: 0.0317646
B25: =AVERAGE(L25:P25) -> 0.01985994 | C25: =AVERAGE(R25:V25) -> 0.02183842 | D25: =AVERAGE(AJ25:AN25) -> 0.02381724 | E25: =AVERAGE(X25:AB25) -> 0.02579254 | F25: =AVERAGE(AD25:AH25) -> 0.02776806 | G25: =AVERAGE(AP25:AT25) -> 0.03170932 | H25: =ROUND(E25,4)&"," -> 0.0258, | L25: 0.0198648 | M25: 0.0198468 | N25: 0.0198699 | O25: 0.0198545 | P25: 0.0198637 | R25: 0.0218442 | S25: 0.0218231 | T25: 0.0218497 | U25: 0.0218321 | V25: 0.021843 | X25: 0.0258005 | Y25: 0.0257727 | Z25: 0.0258065 | AA25: 0.0257844 | AB25: 0.0257986 | AD25: 0.0277772 | AE25: 0.0277457 | AF25: 0.0277835 | AG25: 0.0277589 | AH25: 0.027775 | AJ25: 0.0238037 | AK25: 0.0238165 | AL25: 0.0238131 | AM25: 0.0238141 | AN25: 0.0238388 | AP25: 0.0316884 | AQ25: 0.0317078 | AR25: 0.0317012 | AS25: 0.031704 | AT25: 0.0317452
B26: =AVERAGE(L26:P26) -> 0.01985436 | C26: =AVERAGE(R26:V26) -> 0.02183138 | D26: =AVERAGE(AJ26:AN26) -> 0.02380656 | E26: =AVERAGE(X26:AB26) -> 0.02578174 | F26: =AVERAGE(AD26:AH26) -> 0.02775492 | G26: =AVERAGE(AP26:AT26) -> 0.03168316 | H26: =ROUND(E26,4)&"," -> 0.0258, | L26: 0.0198586 | M26: 0.0198428 | N26: 0.0198651 | O26: 0.0198472 | P26: 0.0198581 | R26: 0.0218367 | S26: 0.0218178 | T26: 0.0218436 | U26: 0.021823 | V26: 0.0218358 | X26: 0.0257892 | Y26: 0.0257642 | Z26: 0.0257969 | AA26: 0.0257708 | AB26: 0.0257876 | AD26: 0.0277638 | AE26: 0.0277353 | AF26: 0.0277716 | AG26: 0.0277424 | AH26: 0.0277615 | AJ26: 0.023792 | AK26: 0.0238032 | AL26: 0.0238026 | AM26: 0.0238052 | AN26: 0.0238298 | AP26: 0.0316627 | AQ26: 0.0316778 | AR26: 0.0316754 | AS26: 0.0316766 | AT26: 0.0317233
B27: =AVERAGE(L27:P27) -> 0.01984712 | C27: =AVERAGE(R27:V27) -> 0.02182236 | D27: =AVERAGE(AJ27:AN27) -> 0.02379346 | E27: =AVERAGE(X27:AB27) -> 0.02576812 | F27: =AVERAGE(AD27:AH27) -> 0.02773842 | G27: =AVERAGE(AP27:AT27) -> 0.0316516 | H27: =ROUND(E27,4)&"," -> 0.0258, | L27: 0.0198537 | M27: 0.0198326 | N27: 0.0198597 | O27: 0.0198403 | P27: 0.0198493 | R27: 0.0218304 | S27: 0.0218052 | T27: 0.021837 | U27: 0.021814 | V27: 0.0218252 | X27: 0.0257794 | Y27: 0.0257452 | Z27: 0.0257872 | AA27: 0.0257564 | AB27: 0.0257724 | AD27: 0.0277518 | AE27: 0.0277123 | AF27: 0.0277599 | AG27: 0.0277247 | AH27: 0.0277434 | AJ27: 0.0237817 | AK27: 0.0237865 | AL27: 0.0237908 | AM27: 0.0237891 | AN27: 0.0238192 | AP27: 0.0316379 | AQ27: 0.0316372 | AR27: 0.0316446 | AS27: 0.0316393 | AT27: 0.031699
B28: =AVERAGE(L28:P28) -> 0.01983856 | C28: =AVERAGE(R28:V28) -> 0.02181148 | D28: =AVERAGE(AJ28:AN28) -> 0.02377416 | E28: =AVERAGE(X28:AB28) -> 0.02575126 | F28: =AVERAGE(AD28:AH28) -> 0.02771784 | G28: =AVERAGE(AP28:AT28) -> 0.03160518 | H28: =ROUND(E28,4)&"," -> 0.0258, | L28: 0.0198435 | M28: 0.0198258 | N28: 0.01985 | O28: 0.0198309 | P28: 0.0198426 | R28: 0.0218177 | S28: 0.0217964 | T28: 0.0218248 | U28: 0.021802 | V28: 0.0218165 | X28: 0.0257604 | Y28: 0.0257314 | Z28: 0.0257681 | AA28: 0.0257379 | AB28: 0.0257585 | AD28: 0.0277288 | AE28: 0.0276953 | AF28: 0.0277367 | AG28: 0.027702 | AH28: 0.0277264 | AJ28: 0.0237611 | AK28: 0.0237704 | AL28: 0.023772 | AM28: 0.0237608 | AN28: 0.0238065 | AP28: 0.0315907 | AQ28: 0.031595 | AR28: 0.0315969 | AS28: 0.031575 | AT28: 0.0316683
B29: =AVERAGE(L29:P29) -> 0.01982836 | C29: =AVERAGE(R29:V29) -> 0.02179862 | D29: =AVERAGE(AJ29:AN29) -> 0.02375374 | E29: =AVERAGE(X29:AB29) -> 0.02573194 | F29: =AVERAGE(AD29:AH29) -> 0.0276945 | G29: =AVERAGE(AP29:AT29) -> 0.03155218 | H29: =ROUND(E29,4)&"," -> 0.0257, | L29: 0.0198325 | M29: 0.0198151 | N29: 0.0198442 | O29: 0.0198201 | P29: 0.0198299 | R29: 0.0218036 | S29: 0.0217828 | T29: 0.0218174 | U29: 0.0217886 | V29: 0.0218007 | X29: 0.0257383 | Y29: 0.025711 | Z29: 0.0257572 | AA29: 0.0257179 | AB29: 0.0257353 | AD29: 0.0277015 | AE29: 0.0276707 | AF29: 0.0277235 | AG29: 0.0276778 | AH29: 0.027699 | AJ29: 0.0237373 | AK29: 0.0237497 | AL29: 0.0237482 | AM29: 0.0237409 | AN29: 0.0237926 | AP29: 0.0315313 | AQ29: 0.0315403 | AR29: 0.0315298 | AS29: 0.0315256 | AT29: 0.0316339
B30: =AVERAGE(L30:P30) -> 0.01981658 | C30: =AVERAGE(R30:V30) -> 0.02178366 | D30: =AVERAGE(AJ30:AN30) -> 0.02372822 | E30: =AVERAGE(X30:AB30) -> 0.02570854 | F30: =AVERAGE(AD30:AH30) -> 0.0276657 | G30: =AVERAGE(AP30:AT30) -> 0.0314817 | H30: =ROUND(E30,4)&"," -> 0.0257, | L30: 0.0198171 | M30: 0.019809 | N30: 0.0198355 | O30: 0.0198053 | P30: 0.019816 | R30: 0.0217836 | S30: 0.0217751 | T30: 0.0218068 | U30: 0.0217701 | V30: 0.0217827 | X30: 0.0257054 | Y30: 0.0256987 | Z30: 0.0257414 | AA30: 0.0256907 | AB30: 0.0257065 | AD30: 0.0276604 | AE30: 0.0276556 | AF30: 0.0277047 | AG30: 0.0276448 | AH30: 0.027663 | AJ30: 0.0237033 | AK30: 0.0237273 | AL30: 0.023718 | AM30: 0.0237175 | AN30: 0.023775 | AP30: 0.0314404 | AQ30: 0.0314777 | AR30: 0.0314484 | AS30: 0.0314589 | AT30: 0.0315831
B31: =AVERAGE(L31:P31) -> 0.01979752 | C31: =AVERAGE(R31:V31) -> 0.02175908 | D31: =AVERAGE(AJ31:AN31) -> 0.02370344 | E31: =AVERAGE(X31:AB31) -> 0.0256687 | F31: =AVERAGE(AD31:AH31) -> 0.02761574 | G31: =AVERAGE(AP31:AT31) -> 0.031413 | H31: =ROUND(E31,4)&"," -> 0.0257, | L31: 0.019808 | M31: 0.0197905 | N31: 0.0198184 | O31: 0.0197816 | P31: 0.0197891 | R31: 0.0217723 | S31: 0.021751 | T31: 0.0217844 | U31: 0.0217394 | V31: 0.0217483 | X31: 0.025688 | Y31: 0.0256591 | Z31: 0.0257037 | AA31: 0.0256413 | AB31: 0.0256514 | AD31: 0.0276388 | AE31: 0.0276058 | AF31: 0.0276569 | AG31: 0.0275826 | AH31: 0.0275946 | AJ31: 0.0236833 | AK31: 0.023713 | AL31: 0.0236773 | AM31: 0.0236763 | AN31: 0.0237673 | AP31: 0.0313838 | AQ31: 0.0314301 | AR31: 0.0313258 | AS31: 0.0313654 | AT31: 0.0315599
B32: =AVERAGE(L32:P32) -> 0.0197705 | C32: =AVERAGE(R32:V32) -> 0.02172476 | D32: =AVERAGE(AJ32:AN32) -> 0.02366538 | E32: =AVERAGE(X32:AB32) -> 0.02561426 | F32: =AVERAGE(AD32:AH32) -> 0.0275478 | G32: =AVERAGE(AP32:AT32) -> 0.03131528 | H32: =ROUND(E32,4)&"," -> 0.0256, | L32: 0.0197824 | M32: 0.0197621 | N32: 0.0197689 | O32: 0.0197644 | P32: 0.0197747 | R32: 0.0217383 | S32: 0.0217149 | T32: 0.0217238 | U32: 0.0217174 | V32: 0.0217294 | X32: 0.0256301 | Y32: 0.025604 | Z32: 0.0256104 | AA32: 0.0256073 | AB32: 0.0256195 | AD32: 0.0275643 | AE32: 0.0275391 | AF32: 0.02754 | AG32: 0.02754 | AH32: 0.0275556 | AJ32: 0.0236169 | AK32: 0.023708 | AL32: 0.0236582 | AM32: 0.0236123 | AN32: 0.0237315 | AP32: 0.0311917 | AQ32: 0.0314344 | AR32: 0.0312966 | AS32: 0.0311904 | AT32: 0.0314633
B33: =AVERAGE(L33:P33) -> 0.01974946 | C33: =AVERAGE(R33:V33) -> 0.0216972 | D33: =AVERAGE(AJ33:AN33) -> 0.02361198 | E33: =AVERAGE(X33:AB33) -> 0.02556912 | F33: =AVERAGE(AD33:AH33) -> 0.0274928 | G33: =AVERAGE(AP33:AT33) -> 0.03115254 | H33: =ROUND(E33,4)&"," -> 0.0256, | L33: 0.0197727 | M33: 0.0197247 | N33: 0.0197799 | O33: 0.0197305 | P33: 0.0197395 | R33: 0.0217255 | S33: 0.0216677 | T33: 0.0217361 | U33: 0.0216746 | V33: 0.0216821 | X33: 0.0256091 | Y33: 0.0255308 | Z33: 0.0256277 | AA33: 0.025538 | AB33: 0.02554 | AD33: 0.0275381 | AE33: 0.0274522 | AF33: 0.0275633 | AG33: 0.0274556 | AH33: 0.0274548 | AJ33: 0.0235906 | AK33: 0.0236509 | AL33: 0.0235976 | AM33: 0.0235273 | AN33: 0.0236935 | AP33: 0.0311142 | AQ33: 0.0312325 | AR33: 0.0311104 | AS33: 0.0309594 | AT33: 0.0313462
... B81: =AVERAGE(L81:P81) -> 0.004123386 | C81: =AVERAGE(R81:V81) -> 0.004143408 | D81: =AVERAGE(AJ81:AN81) -> 0.004184262 | E81: =AVERAGE(X81:AB81) -> 0.004186072 | F81: =AVERAGE(AD81:AH81) -> 0.004208692 | G81: =AVERAGE(AP81:AT81) -> 0.00429183 | H81: =ROUND(E81,4)&"," -> 0.0042, | L81: 0.00412891 | M81: 0.00411692 | N81: 0.0041273 | O81: 0.0041214 | P81: 0.0041224 | R81: 0.00414988 | S81: 0.00413573 | T81: 0.00414824 | U81: 0.00414101 | V81: 0.00414218 | X81: 0.00419467 | Y81: 0.00417585 | Z81: 0.00419255 | AA81: 0.00418288 | AB81: 0.00418441 | AD81: 0.00421842 | AE81: 0.00419712 | AF81: 0.00421605 | AG81: 0.00420508 | AH81: 0.00420679 | AJ81: 0.00417181 | AK81: 0.0041922 | AL81: 0.00417283 | AM81: 0.00415877 | AN81: 0.0042257 | AP81: 0.00426857 | AQ81: 0.00430773 | AR81: 0.00427138 | AS81: 0.0042554 | AT81: 0.00435607

Sheet range_setting
A1: Point | B1: Column1 | C1: Rank | D1: Percent | F1: Column1
A2: 20 | B2: 0.027254024 | C2: 1 | D2: 1 | I2: range | K2: min | L2: max | M2: diff | N2: mid
A3: 21 | B3: 0.027149173 | C3: 2 | D3: 0.983 | F3: Mean | G3: 0.016896333 | I3: old | J3: min-max*90% | K3: =N3-M3 -> 0.005 | L3: =N3+M3 -> 0.025 | M3: 0.01 | N3: 0.015
A4: 22 | B4: 0.026844426 | C4: 3 | D4: 0.966 | F4: Standard Error | G4: 0.00084125736 | I4: new1 | J4: min-max | K4: =N4-M4 -> 0.004 | L4: =N4+M4 -> 0.028 | M4: 0.012 | N4: 0.016
A5: 19 | B5: 0.02681191 | C5: 4 | D5: 0.949 | F5: Median | G5: 0.017361007 | I5: new2 | J5: 0-max | K5: =N5-M5 -> 0 | L5: =N5+M5 -> 0.028 | M5: 0.014 | N5: 0.014
A6: 18 | B6: 0.026643545 | C6: 5 | D6: 0.932 | F6: Mode | I6: new3 | J6: 95%CI | K6: =N6-M6 -> 0.004 | L6: =N6+M6 -> 0.03 | M6: 0.013 | N6: 0.017
A7: 23 | B7: 0.026352638 | C7: 6 | D7: 0.915 | F7: Standard Deviation | G7: 0.0065163515 | I7: new4 | J7: min-max*80% | K7: 0.004 | L7: =L4*0.8 -> 0.0224 | M7: =L7-N7 -> 0.0092 | N7: =(L7+K7)/2 -> 0.0132
A8: 17 | B8: 0.025850144 | C8: 7 | D8: 0.898 | F8: Sample Variance | G8: 4.2462837e-05 | I8: new5 | J8: min-max*90% | K8: 0.004 | L8: =L4*0.9 -> 0.0252 | M8: =L8-N8 -> 0.0106 | N8: =(L8+K8)/2 -> 0.0146
A9: 24 | B9: 0.025807821 | C9: 8 | D9: 0.881 | F9: Kurtosis | G9: -1.0157402 | I9: new6 | J9: min-max*70% | K9: =K4 -> 0.004 | L9: =L4*0.7 -> 0.0196 | M9: =L9-N9 -> 0.0078 | N9: =(L9+K9)/2 -> 0.0118
A10: 25 | B10: 0.025170466 | C10: 9 | D10: 0.864 | F10: Skewness | G10: -0.097976087
A11: 16 | B11: 0.024767235 | C11: 10 | D11: 0.847 | F11: Range | G11: 0.022492405
A12: 26 | B12: 0.024392045 | C12: 11 | D12: 0.83 | F12: Minimum | G12: 0.0047616186
A13: 27 | B13: 0.023980076 | C13: 12 | D13: 0.813 | F13: Maximum | G13: 0.027254024
A14: 15 | B14: 0.0236201 | C14: 13 | D14: 0.796 | F14: Sum | G14: 1.01378
A15: 14 | B15: 0.022735849 | C15: 14 | D15: 0.779 | F15: Count | G15: 60
A16: 13 | B16: 0.021674524 | C16: 15 | D16: 0.762
A17: 28 | B17: 0.021123966 | C17: 16 | D17: 0.745
A18: 29 | B18: 0.021056157 | C18: 17 | D18: 0.728
A19: 30 | B19: 0.020739005 | C19: 18 | D19: 0.711
A20: 12 | B20: 0.020574637 | C20: 19 | D20: 0.694
A21: 31 | B21: 0.020314954 | C21: 20 | D21: 0.677
A22: 11 | B22: 0.020085908 | C22: 21 | D22: 0.661
A23: 10 | B23: 0.019534493 | C23: 22 | D23: 0.644
A24: 32 | B24: 0.019498183 | C24: 23 | D24: 0.627
A25: 35 | B25: 0.019411451 | C25: 24 | D25: 0.61
A26: 33 | B26: 0.019011593 | C26: 25 | D26: 0.593
A27: 9 | B27: 0.018746479 | C27: 26 | D27: 0.576
... A41: 3 | B41: 0.014105239 | C41: 40 | D41: 0.338
A42: 43 | B42: 0.013460634 | C42: 41 | D42: 0.322 | I42: =EXP(-0.09+0.5*0.04*0.04) -> 0.91466262 | J42: =I42*(1-I42^10)/(1-I42) -> 6.3255006
A43: 2 | B43: 0.013190538 | C43: 42 | D43: 0.305 | I43: =EXP(-0.09*10+0.5*10*0.04*0.04) -> 0.40983526 | J43: =0.45*I43/J42 -> 0.029155933
A44: 44 | B44: 0.012693866 | C44: 43 | D44: 0.288 | I44: =I42^10 -> 0.40983526 | J44: =0.45*I43 -> 0.18442587
A45: 1 | B45: 0.012596397 | C45: 44 | D45: 0.271
A46: 45 | B46: 0.011594615 | C46: 45 | D46: 0.254
A47: 46 | B47: 0.011148707 | C47: 46 | D47: 0.237
A48: 48 | B48: 0.010765196 | C48: 47 | D48: 0.22
A49: 47 | B49: 0.010607764 | C49: 48 | D49: 0.203
A50: 49 | B50: 0.010089855 | C50: 49 | D50: 0.186
A51: 50 | B51: 0.009677083 | C51: 50 | D51: 0.169
A52: 51 | B52: 0.009275441 | C52: 51 | D52: 0.152
A53: 52 | B53: 0.0091487939 | C53: 52 | D53: 0.135
A54: 54 | B54: 0.0086731908 | C54: 53 | D54: 0.118
A55: 53 | B55: 0.0086375322 | C55: 54 | D55: 0.101
A56: 55 | B56: 0.0074121788 | C56: 55 | D56: 0.084
... A61: 60 | B61: 0.0047616186 | C61: 60 | D61: 0

Sheet init_popn
B1: Vaccied=0 | C1: Vaccied=0.1 | D1: Vaccied=0.2 | E1: Vaccied=0.3 | F1: Vaccied=0.4 | G1: Vaccied=0.43 (base) | H1: Vaccied=0.5 | I1: Vaccied=0.6 | J1: Vaccied=0.7 | K1: Vaccied=0.725 | L1: Vaccied=0.75 | N1: Vaccied=0.8 | O1: Vaccied=0.825 | P1: Vaccied=0.85 | Q1: Vaccied=0.875 | R1: Vaccied=0.9 | S1: Vaccied=0.925 | T1: Vaccied=0.95 | X1: Type no vacc constant vacc actual vacc opt vacc | AC1: Type no vacc constant vacc actual vacc opt vacc | AH1: Type no vacc constant vacc actual vacc opt vacc | AM1: Type no vacc constant vacc actual vacc opt vacc | AR1: Type no vacc constant vacc actual vacc opt vacc | AW1: Type no vacc constant vacc actual vacc opt vacc | BB1: Type no vacc constant vacc actual vacc opt vacc | BG1: Type no vacc constant vacc actual vacc opt vacc | BL1: Type no vacc constant vacc actual vacc opt vacc | BQ1: Type no vacc constant vacc actual vacc opt vacc | CA1: Type no vacc constant vacc actual vacc opt vacc | CF1: Type no vacc constant vacc actual vacc opt vacc | CK1: Type no vacc constant vacc actual vacc opt vacc | CP1: Type no vacc constant vacc actual vacc opt vacc | CU1: Type no vacc constant vacc actual vacc opt vacc | CZ1: Type no vacc constant vacc actual vacc opt vacc | DE1: Type no vacc constant vacc actual vacc opt vacc
A2: Hosp Cost | B2: 12.078913 | C2: 9.913672 | D2: 8.236742 | E2: 6.935924 | F2: 5.923057 | G2: =beta!D2 -> 5.610668 | H2: 5.129347 | I2: 4.506886 | J2: 4.022173 | K2: 4.040637 | L2: 3.92214 | N2: 3.68624 | O2: 3.64017 | P2: 3.617685 | Q2: 3.613985 | R2: 3.518188 | S2: 3.562214 | T2: 3.48743 | X2: 0 Hosp Cost 61.138916 27.861600 12.287796 12.078913 | AC2: 0 Hosp Cost 40.154908 20.896551 10.050937 9.913672 | AH2: 0 Hosp Cost 26.671553 15.957403 8.323303 8.236742 | AM2: 0 Hosp Cost 18.225702 12.458416 6.985991 6.935924 | AR2: 0 Hosp Cost 12.986633 9.969111 5.946544 5.923057 | AW2: 0 Hosp Cost 9.719184 8.181688 5.133878 5.129347 | BB2: 0 Hosp Cost 7.641201 6.880532 4.493824 4.506886 | BG2: 0 Hosp Cost 6.277179 5.916813 3.985353 4.022173 | BL2: 0 Hosp Cost 6.011664 5.715878 3.874984 4.040637 | BQ2: 0 Hosp Cost 5.769545 5.528289 3.770467 3.922140 | CA2: 0 Hosp Cost 5.345156 5.188790 3.577515 3.686240 | CF2: 0 Hosp Cost 5.158516 5.034947 3.488409 3.640170 | CK2: 0 Hosp Cost 4.986451 4.890567 3.403805 3.617685 | CP2: 0 Hosp Cost 4.827401 4.754890 3.323422 3.613985 | CU2: 0 Hosp Cost 4.680003 4.627227 3.246997 3.518188 | CZ2: 0 Hosp Cost 4.543058 4.506950 3.174285 3.562214 | DE2: 0 Hosp Cost 4.415518 4.393489 3.105058 3.487430
A3: Policy Cost | B3: 7.301036 | C3: 6.451505 | D3: 5.770802 | E3: 5.195539 | F3: 4.68738 | G3: =beta!D3 -> 4.513925 | H3: 4.206768 | I3: 3.698483 | J3: 3.11575 | K3: 2.354131 | L3: 2.313429 | N3: 2.324702 | O3: 2.064784 | P3: 1.774543 | Q3: 1.486136 | R3: 1.454425 | S3: 1.123685 | T3: 1.044098 | X3: 1 Policy Cost 17.148215 7.961400 6.878049 7.301036 | AC3: 1 Policy Cost 10.873150 6.104777 6.065288 6.451505 | AH3: 1 Policy Cost 6.941999 4.806380 5.438216 5.770802 | AM3: 1 Policy Cost 4.555463 3.898732 4.953162 5.195539 | AR3: 1 Policy Cost 3.123383 3.260828 4.576329 4.687380 | AW3: 1 Policy Cost 2.257900 2.807735 4.281832 4.206768 | BB3: 1 Policy Cost 1.722197 2.481055 4.049991 3.698483 | BG3: 1 Policy Cost 1.378026 2.241167 3.865916 3.115750 | BL3: 1 Policy Cost 1.311785 2.191410 3.825977 2.354131 | BQ3: 1 Policy Cost 1.251604 2.145048 3.788161 2.313429 | CA3: 1 Policy Cost 1.146645 2.061375 3.718363 2.324702 | CF3: 1 Policy Cost 1.100705 2.023565 3.686135 2.064784 | CK3: 1 Policy Cost 1.058474 1.988143 3.655540 1.774543 | CP3: 1 Policy Cost 1.019545 1.954914 3.626472 1.486136 | CU3: 1 Policy Cost 0.983561 1.923700 3.598837 1.454425 | CZ3: 1 Policy Cost 0.950213 1.894339 3.572544 1.123685 | DE3: 1 Policy Cost 0.919228 1.866684 3.547510 1.044098
A4: Econ Cost | B4: 64.13407 | C4: 52.357517 | D4: 43.238098 | E4: 36.155046 | F4: 30.629695 | G4: =beta!D4 -> 28.924867 | H4: 26.289164 | I4: 22.85971 | J4: 20.133287 | K4: 19.739085 | L4: 19.128121 | N4: 17.985046 | O4: 17.535729 | P4: 17.122985 | Q4: 16.73496 | R4: 16.256072 | S4: 15.889185 | T4: 15.442267 | X4: 2 Econ Cost 248.341669 105.700863 64.777519 64.134070 | AC4: 2 Econ Cost 159.563783 78.444618 52.768387 52.357517 | AH4: 2 Econ Cost 103.508560 59.298799 43.484856 43.238098 | AM4: 2 Econ Cost 69.135933 45.856818 36.289659 36.155046 | AR4: 2 Econ Cost 48.285855 36.370752 30.688326 30.629695 | AW4: 2 Econ Cost 35.552899 29.606712 26.301274 26.289164 | BB4: 2 Econ Cost 27.598439 24.711408 22.839398 22.859710 | BG4: 2 Econ Cost 22.447981 21.102924 20.083649 20.133287 | BL4: 2 Econ Cost 21.452243 20.352539 19.484672 19.739085 | BQ4: 2 Econ Cost 20.546162 19.652636 18.917139 19.128121 | CA4: 2 Econ Cost 18.962304 18.387545 17.868524 17.985046 | CF4: 2 Econ Cost 18.267448 17.814952 17.383831 17.535729 | CK4: 2 Econ Cost 17.627743 17.277959 16.923344 17.122985 | CP4: 2 Econ Cost 17.037167 16.773665 16.485546 16.734960 | CU4: 2 Econ Cost 16.490464 16.299437 16.069025 16.256072 | CZ4: 2 Econ Cost 15.983045 15.852878 15.672459 15.889185 | DE4: 2 Econ Cost 15.510891 15.431811 15.294618 15.442267
A5: Total Cost | B5: =SUM(B2:B4) -> 83.514019 | C5: =SUM(C2:C4) -> 68.722694 | D5: =SUM(D2:D4) -> 57.245642 | E5: =SUM(E2:E4) -> 48.286509 | F5: =SUM(F2:F4) -> 41.240132 | G5: =SUM(G2:G4) -> 39.04946 | H5: =SUM(H2:H4) -> 35.625279 | I5: =SUM(I2:I4) -> 31.065079 | ... T5: =SUM(T2:T4) -> 19.973795 | X5: 3 Total Cost 326.628800 141.523862 83.943364 83.514019 | AC5: 3 Total Cost 210.591841 105.445946 68.884611 68.722694 | AH5: 3 Total Cost 137.122113 80.062583 57.246375 57.245641 | AM5: 3 Total Cost 91.917098 62.213966 48.228813 48.286509 | AR5: 3 Total Cost 64.395871 49.600690 41.211199 41.240132 | AW5: 3 Total Cost 47.529983 40.596135 35.716984 35.625280 | BB5: 3 Total Cost 36.961836 34.072995 31.383213 31.065079 | BG5: 3 Total Cost 30.103185 29.260904 27.934919 27.271209 | BL5: 3 Total Cost 28.775692 28.259827 27.185634 26.133854 | BQ5: 3 Total Cost 27.567311 27.325973 26.475766 25.363690 | CA5: 3 Total Cost 25.454105 25.637710 25.164401 23.995988 | CF5: 3 Total Cost 24.526668 24.873464 24.558376 23.240683 | CK5: 3 Total Cost 23.672668 24.156669 23.982689 22.515213 | CP5: 3 Total Cost 22.884113 23.483470 23.435440 21.835081 | CU5: 3 Total Cost 22.154029 22.850364 22.914858 21.228685 | CZ5: 3 Total Cost 21.476316 22.254167 22.419289 20.575084 | DE5: 3 Total Cost 20.845638 21.691984 21.947187 19.973795
A7: ori | B7: Vaccied=0 | C7: Vaccied=0.1 | D7: Vaccied=0.2 | E7: Vaccied=0.3 | F7: Vaccied=0.4 | G7: Vaccied=0.43 (base) | H7: Vaccied=0.5 | I7: Vaccied=0.6 | J7: Vaccied=0.7 | K7: Vaccied=0.725 | L7: Vaccied=0.75 | N7: Vaccied=0.8 | O7: Vaccied=0.825 | P7: Vaccied=0.85 | Q7: Vaccied=0.875 | R7: Vaccied=0.9 | S7: Vaccied=0.925 | T7: Vaccied=0.95 | X7: Vaccied=0 | AC7: Vaccied=0.1 | AH7: Vaccied=0.2 | AM7: Vaccied=0.3 | AR7: Vaccied=0.4 | AW7: Vaccied=0.5 | BB7: Vaccied=0.6 | BG7: Vaccied=0.7 | BL7: Vaccied=0.725 | BQ7: Vaccied=0.75 | BV7: Vaccied=0.775 | CA7: Vaccied=0.8 | CF7: Vaccied=0.825 | CK7: Vaccied=0.85 | CP7: Vaccied=0.875 | CU7: Vaccied=0.9 | CZ7: Vaccied=0.925 | DE7: Vaccied=0.95
A8: =range!F14 -> 0.02778504 | B8: =AVERAGE(X8:AB8) -> 0.027804 | C8: =AVERAGE(AC8:AG8) -> 0.0278019 | D8: =AVERAGE(AH8:AL8) -> 0.02779882 | E8: =AVERAGE(AM8:AQ8) -> 0.02779448 | F8: =AVERAGE(AR8:AV8) -> 0.02778826 | G8: =A8 -> 0.02778504 | H8: =AVERAGE(AW8:BA8) -> 0.02777768 | I8: =AVERAGE(BB8:BF8) -> 0.02775612 | J8: =AVERAGE(BG8:BK8) -> 0.0276865 | K8: =AVERAGE(BL8:BP8) -> 0.02683746 | L8: =AVERAGE(BQ8:BU8) -> 0.02683746 | M8: =L8 -> 0.02683746 | N8: =AVERAGE(CA8:CE8) -> 0.02709208 | O8: =AVERAGE(CF8:CJ8) -> 0.02615 | P8: =AVERAGE(CK8:CO8) -> 0.0228796 | Q8: =AVERAGE(CP8:CT8) -> 0.01440268 | R8: =AVERAGE(CU8:CY8) -> 0.007367 | S8: =AVERAGE(CZ8:DD8) -> 0.005180638 | T8: =AVERAGE(DE8:DI8) -> 0.004566624 | U8: =ROUND(G8,4)&"," -> 0.0278, | X8: 0.0278131 | Y8: 0.0277912 | Z8: 0.0278108 | AA8: 0.0277986 | AB8: 0.0278063 | AC8: 0.0278111 | AD8: 0.0277889 | AE8: 0.0278086 | AF8: 0.0277965 | AG8: 0.0278044 | AH8: 0.0278079 | AI8: 0.0277853 | AJ8: 0.0278057 | AK8: 0.0277933 | AL8: 0.0278019 | AM8: 0.0278034 | AN8: 0.0277799 | AO8: 0.0278017 | AP8: 0.027789 | AQ8: 0.0277984 | AR8: 0.0277976 | AS8: 0.0277723 | AT8: 0.0277956 | AU8: 0.027783 | AV8: 0.0277928 | AW8: 0.0277874 | AX8: 0.0277605 | AY8: 0.0277853 | AZ8: 0.0277719 | BA8: 0.0277833 | BB8: 0.0277667 | BC8: 0.027737 | BD8: 0.027764 | BE8: 0.0277488 | BF8: 0.0277641 | BG8: 0.0276969 | BH8: 0.0276619 | BI8: 0.0276946 | BJ8: 0.0276772 | BK8: 0.0277019 | BL8: 0.0268128 | BM8: 0.0267219 | BN8: 0.0268649 | BO8: 0.0268518 | BP8: 0.0269359 | BQ8: 0.0268128 | BR8: 0.0267219 | BS8: 0.0268649 | BT8: 0.0268518 | BU8: 0.0269359 | CA8: 0.027081 | CB8: 0.0270051 | CC8: 0.0271142 | CD8: 0.0270955 | CE8: 0.0271646 | CF8: 0.0260877 | CG8: 0.0259489 | CH8: 0.0261941 | CI8: 0.0261929 | CJ8: 0.0263264 | CK8: 0.0226684 | CL8: 0.0223607 | CM8: 0.0229082 | CN8: 0.0230632 | CO8: 0.0233975 | CP8: 0.0141442 | CQ8: 0.013649 | CR8: 0.0142958 | CS8: 0.0146801 | CT8: 0.0152443 | CU8: 0.0073085 | CV8: 0.00707908 | CW8: 0.00728308 | CX8: 0.00748537 | CY8: 0.00767897 | CZ8: 0.00519326 | DA8: 0.00508604 | DB8: 0.00518121 | DC8: 0.00519905 | DD8: 0.00524363 | DE8: 0.00457723 | DF8: 0.00452699 | DG8: 0.00458559 | DH8: 0.00457083 | DI8: 0.00457248
A9: =range!F15 -> 0.02778774 | B9: =AVERAGE(X9:AB9) -> 0.02780932 | C9: =AVERAGE(AC9:AG9) -> 0.02780642 | D9: =AVERAGE(AH9:AL9) -> 0.02780318 | E9: =AVERAGE(AM9:AQ9) -> 0.02779836 | F9: =AVERAGE(AR9:AV9) -> 0.0277914 | G9: =A9 -> 0.02778774 | H9: =AVERAGE(AW9:BA9) -> 0.0277794 | I9: =AVERAGE(BB9:BF9) -> 0.02775418 | J9: =AVERAGE(BG9:BK9) -> 0.02766906 | K9: =AVERAGE(BL9:BP9) -> 0.0264419 | L9: =AVERAGE(BQ9:BU9) -> 0.0264419 | M9: =L9 -> 0.0264419 | N9: =AVERAGE(CA9:CE9) -> 0.0268322 | O9: =AVERAGE(CF9:CJ9) -> 0.02537744 | P9: =AVERAGE(CK9:CO9) -> 0.02138878 | Q9: =AVERAGE(CP9:CT9) -> 0.01497128 | R9: =AVERAGE(CU9:CY9) -> 0.008322838 | S9: =AVERAGE(CZ9:DD9) -> 0.005416016 | T9: =AVERAGE(DE9:DI9) -> 0.00463496 | U9: =ROUND(G9,4)&"," -> 0.0278, | X9: 0.0278184 | Y9: 0.0277917 | Z9: 0.0278242 | AA9: 0.0278015 | AB9: 0.0278108 | AC9: 0.0278163 | AD9: 0.0277891 | AE9: 0.0278193 | AF9: 0.0277984 | AG9: 0.027809 | AH9: 0.027813 | AI9: 0.0277852 | AJ9: 0.0278161 | AK9: 0.0277953 | AL9: 0.0278063 | AM9: 0.0278082 | AN9: 0.0277792 | AO9: 0.0278112 | AP9: 0.0277908 | AQ9: 0.0278024 | AR9: 0.0278017 | AS9: 0.0277707 | AT9: 0.027804 | AU9: 0.0277844 | AV9: 0.0277962 | AW9: 0.02779 | AX9: 0.0277574 | AY9: 0.0277921 | AZ9: 0.0277722 | BA9: 0.0277853 | BB9: 0.0277653 | BC9: 0.02773 | BD9: 0.0277675 | BE9: 0.0277459 | BF9: 0.0277622 | BG9: 0.0276773 | BH9: 0.027642 | BI9: 0.0276821 | BJ9: 0.0276594 | BK9: 0.0276845 | BL9: 0.0263647 | BM9: 0.0264469 | BN9: 0.0263252 | BO9: 0.0264986 | BP9: 0.0265741 | BQ9: 0.0263647 | BR9: 0.0264469 | BS9: 0.0263252 | BT9: 0.0264986 | BU9: 0.0265741 | CA9: 0.0267828 | CB9: 0.0268173 | CC9: 0.0267794 | CD9: 0.0268613 | CE9: 0.0269202 | CF9: 0.0252152 | CG9: 0.025434 | CH9: 0.0250868 | CI9: 0.0254983 | CJ9: 0.0256529 | CK9: 0.0209523 | CL9: 0.0213862 | CM9: 0.0207349 | CN9: 0.021808 | CO9: 0.0220625 | CP9: 0.014758 | CQ9: 0.0144962 | CR9: 0.0147025 | CS9: 0.0153632 | CT9: 0.0155365 | CU9: 0.00868456 | CV9: 0.00774897 | CW9: 0.00821057 | CX9: 0.0084235 | CY9: 0.00854659 | CZ9: 0.0055015 | DA9: 0.00525072 | DB9: 0.00541934 | DC9: 0.00542984 | DD9: 0.00547868 | DE9: 0.00465818 | DF9: 0.00457609 | DG9: 0.00466062 | DH9: 0.00463786 | DI9: 0.00464205
A10: =range!F16 -> 0.02777764 | B10: =AVERAGE(X10:AB10) -> 0.02780304 | C10: =AVERAGE(AC10:AG10) -> 0.02779984 | D10: =AVERAGE(AH10:AL10) -> 0.02779558 | E10: =AVERAGE(AM10:AQ10) -> 0.02778988 | F10: =AVERAGE(AR10:AV10) -> 0.02778186 | G10: =A10 -> 0.02777764 | H10: =AVERAGE(AW10:BA10) -> 0.02776768 | I10: =AVERAGE(BB10:BF10) -> 0.02773722 | J10: =AVERAGE(BG10:BK10) -> 0.02763154 | K10: =AVERAGE(BL10:BP10) -> 0.0259792 | L10: =AVERAGE(BQ10:BU10) -> 0.0259792 | M10: =L10 -> 0.0259792 | N10: =AVERAGE(CA10:CE10) -> 0.02650234 | O10: =AVERAGE(CF10:CJ10) -> 0.02466194 | P10: =AVERAGE(CK10:CO10) -> 0.02062516 | Q10: =AVERAGE(CP10:CT10) -> 0.01462184 | R10: =AVERAGE(CU10:CY10) -> 0.008541068 | S10: =AVERAGE(CZ10:DD10) -> 0.00549428 | T10: =AVERAGE(DE10:DI10) -> 0.004666678 | U10: =ROUND(G10,4)&"," -> 0.0278, | X10: 0.0278102 | Y10: 0.0277868 | Z10: 0.0278211 | AA10: 0.0277939 | AB10: 0.0278032 | AC10: 0.0278076 | AD10: 0.0277838 | AE10: 0.0278156 | AF10: 0.0277918 | AG10: 0.0278004 | AH10: 0.0278034 | AI10: 0.027779 | AJ10: 0.0278104 | AK10: 0.0277881 | AL10: 0.027797 | AM10: 0.0277978 | AN10: 0.0277722 | AO10: 0.027804 | AP10: 0.0277829 | AQ10: 0.0277925 | AR10: 0.0277904 | AS10: 0.0277626 | AT10: 0.0277954 | AU10: 0.0277756 | AV10: 0.0277853 | AW10: 0.0277769 | AX10: 0.0277467 | AY10: 0.027781 | AZ10: 0.027761 | BA10: 0.0277728 | BB10: 0.0277483 | BC10: 0.0277136 | BD10: 0.0277498 | BE10: 0.0277291 | BF10: 0.0277453 | BG10: 0.0276453 | BH10: 0.0276016 | BI10: 0.0276399 | BJ10: 0.0276203 | BK10: 0.0276506 | BL10: 0.0261466 | BM10: 0.0258875 | BN10: 0.0257147 | BO10: 0.0259717 | BP10: 0.0261755 | BQ10: 0.0261466 | BR10: 0.0258875 | BS10: 0.0257147 | BT10: 0.0259717 | BU10: 0.0261755 | CA10: 0.0266102 | CB10: 0.0264183 | CC10: 0.0263628 | CD10: 0.0264862 | CE10: 0.0266342 | CF10: 0.0249303 | CG10: 0.0245488 | CH10: 0.024142 | CI10: 0.0246943 | CJ10: 0.0249943 | CK10: 0.0205921 | CL10: 0.0204875 | CM10: 0.0203379 | CN10: 0.0205943 | CO10: 0.021114 | CP10: 0.0143566 | CQ10: 0.0142736 | CR10: 0.0142972 | CS10: 0.014986 | CT10: 0.0151958 | CU10: 0.00876203 | CV10: 0.00808263 | CW10: 0.00836177 | CX10: 0.00880869 | CY10: 0.00869022 | CZ10: 0.00555908 | DA10: 0.0053427 | DB10: 0.00551282 | DC10: 0.00554116 | DD10: 0.00551564 | DE10: 0.00468107 | DF10: 0.00462437 | DG10: 0.00469177 | DH10: 0.00465736 | DI10: 0.00467882
A11: =range!F17 -> 0.02776806 | B11: =AVERAGE(X11:AB11) -> 0.02779452 | C11: =AVERAGE(AC11:AG11) -> 0.02779258 | D11: =AVERAGE(AH11:AL11) -> 0.02778856 | E11: =AVERAGE(AM11:AQ11) -> 0.0277823 | F11: =AVERAGE(AR11:AV11) -> 0.027773 | G11: =A11 -> 0.02776806 | H11: =AVERAGE(AW11:BA11) -> 0.02775616 | I11: =AVERAGE(BB11:BF11) -> 0.0277183 | J11: =AVERAGE(BG11:BK11) -> 0.02757942 | K11: =AVERAGE(BL11:BP11) -> 0.02517968 | L11: =AVERAGE(BQ11:BU11) -> 0.02517968 | M11: =L11 -> 0.02517968 | N11: =AVERAGE(CA11:CE11) -> 0.02591214 | O11: =AVERAGE(CF11:CJ11) -> 0.02351498 | P11: =AVERAGE(CK11:CO11) -> 0.01946974 | Q11: =AVERAGE(CP11:CT11) -> 0.01437846 | R11: =AVERAGE(CU11:CY11) -> 0.00893145 | S11: =AVERAGE(CZ11:DD11) -> 0.00565652 | T11: =AVERAGE(DE11:DI11) -> 0.004714468 | U11: =ROUND(G11,4)&"," -> 0.0278, | X11: 0.0278032 | Y11: 0.0277778 | Z11: 0.0278072 | AA11: 0.0277852 | AB11: 0.0277992 | AC11: 0.0278007 | AD11: 0.0277746 | AE11: 0.0278084 | AF11: 0.0277828 | AG11: 0.0277964 | AH11: 0.0277965 | AI11: 0.0277691 | AJ11: 0.0278053 | AK11: 0.027779 | AL11: 0.0277929 | AM11: 0.0277904 | AN11: 0.0277618 | AO11: 0.0277985 | AP11: 0.027773 | AQ11: 0.0277878 | AR11: 0.0277819 | AS11: 0.0277512 | AT11: 0.0277885 | AU11: 0.027764 | AV11: 0.0277794 | AW11: 0.0277657 | AX11: 0.0277333 | AY11: 0.0277709 | AZ11: 0.0277466 | BA11: 0.0277643 | BB11: 0.0277298 | BC11: 0.0276932 | BD11: 0.0277311 | BE11: 0.0277079 | BF11: 0.0277295 | BG11: 0.0275938 | BH11: 0.0275478 | BI11: 0.0275846 | BJ11: 0.027572 | BK11: 0.0275989 | BL11: 0.0253131 | BM11: 0.0251033 | BN11: 0.0248585 | BO11: 0.0252653 | BP11: 0.0253582 | BQ11: 0.0253131 | BR11: 0.0251033 | BS11: 0.0248585 | BT11: 0.0252653 | BU11: 0.0253582 | CA11: 0.0260161 | CB11: 0.0258373 | CC11: 0.0257058 | CD11: 0.0259797 | CE11: 0.0260218 | CF11: 0.0236152 | CG11: 0.0234615 | CH11: 0.0229778 | CI11: 0.0237078 | CJ11: 0.0238126 | CK11: 0.0191887 | CL11: 0.0194802 | CM11: 0.0188454 | CN11: 0.0198849 | CO11: 0.0199495 | CP11: 0.0142047 | CQ11: 0.0141839 | CR11: 0.0141079 | CS11: 0.0145366 | CT11: 0.0148592 | CU11: 0.00892759 | CV11: 0.00865433 | CW11: 0.00877544 | CX11: 0.00882132 | CY11: 0.00947857 | CZ11: 0.00565273 | DA11: 0.00552997 | DB11: 0.00565623 | DC11: 0.00561508 | DD11: 0.00582859 | DE11: 0.00471378 | DF11: 0.00468529 | DG11: 0.00474104 | DH11: 0.00471456 | DI11: 0.00471767
A12: =range!F18 -> 0.02775492 | B12: =AVERAGE(X12:AB12) -> 0.0277863 | C12: =AVERAGE(AC12:AG12) -> 0.02778306 | D12: =AVERAGE(AH12:AL12) -> 0.02777826 | E12: =AVERAGE(AM12:AQ12) -> 0.02777146 | F12: =AVERAGE(AR12:AV12) -> 0.02776076 | G12: =A12 -> 0.02775492 | H12: =AVERAGE(AW12:BA12) -> 0.0277404 | I12: =AVERAGE(BB12:BF12) -> 0.02769268 | J12: =AVERAGE(BG12:BK12) -> 0.0275029 | K12: =AVERAGE(BL12:BP12) -> 0.0241409 | L12: =AVERAGE(BQ12:BU12) -> 0.0241409 | M12: =L12 -> 0.0241409 | N12: =AVERAGE(CA12:CE12) -> 0.02504506 | O12: =AVERAGE(CF12:CJ12) -> 0.02233586 | P12: =AVERAGE(CK12:CO12) -> 0.01834654 | Q12: =AVERAGE(CP12:CT12) -> 0.01390032 | R12: =AVERAGE(CU12:CY12) -> 0.009156404 | S12: =AVERAGE(CZ12:DD12) -> 0.005789288 | T12: =AVERAGE(DE12:DI12) -> 0.004723264 | U12: =ROUND(G12,4)&"," -> 0.0278, | X12: 0.0277913 | Y12: 0.0277704 | Z12: 0.0278051 | AA12: 0.0277759 | AB12: 0.0277888 | AC12: 0.0277887 | AD12: 0.0277675 | AE12: 0.0278012 | AF12: 0.0277715 | AG12: 0.0277864 | AH12: 0.0277848 | AI12: 0.0277617 | AJ12: 0.0277957 | AK12: 0.0277662 | AL12: 0.0277829 | AM12: 0.0277785 | AN12: 0.0277535 | AO12: 0.027789 | AP12: 0.0277591 | AQ12: 0.0277772 | AR12: 0.0277691 | AS12: 0.0277416 | AT12: 0.0277778 | AU12: 0.0277484 | AV12: 0.0277669 | AW12: 0.0277504 | AX12: 0.0277202 | AY12: 0.0277564 | AZ12: 0.0277271 | BA12: 0.0277479 | BB12: 0.0277062 | BC12: 0.0276701 | BD12: 0.0277076 | BE12: 0.0276778 | BF12: 0.0277017 | BG12: 0.0275305 | BH12: 0.0274758 | BI12: 0.0275031 | BJ12: 0.0274909 | BK12: 0.0275142 | BL12: 0.024366 | BM12: 0.0238496 | BN12: 0.0237012 | BO12: 0.0243184 | BP12: 0.0244693 | BQ12: 0.024366 | BR12: 0.0238496 | BS12: 0.0237012 | BT12: 0.0243184 | BU12: 0.0244693 | CA12: 0.0253089 | CB12: 0.0248126 | CC12: 0.0246496 | CD12: 0.0252116 | CE12: 0.0252426 | CF12: 0.0224026 | CG12: 0.0220674 | CH12: 0.02173 | CI12: 0.0225284 | CJ12: 0.0229509 | CK12: 0.0181432 | CL12: 0.0185044 | CM12: 0.0174743 | CN12: 0.0185895 | CO12: 0.0190213 | CP12: 0.0135016 | CQ12: 0.0143415 | CR12: 0.0136658 | CS12: 0.0135144 | CT12: 0.0144783 | CU12: 0.00879547 | CV12: 0.00934745 | CW12: 0.00938722 | CX12: 0.00843103 | CY12: 0.00982085 | CZ12: 0.00570545 | DA12: 0.00576342 | DB12: 0.00597473 | DC12: 0.00546921 | DD12: 0.00603363 | DE12: 0.00471895 | DF12: 0.00471836 | DG12: 0.00477048 | DH12: 0.00465033 | DI12: 0.0047582
A13: =range!F19 -> 0.02773842 | B13: =AVERAGE(X13:AB13) -> 0.02777364 | C13: =AVERAGE(AC13:AG13) -> 0.02777022 | D13: =AVERAGE(AH13:AL13) -> 0.0277653 | E13: =AVERAGE(AM13:AQ13) -> 0.0277578 | F13: =AVERAGE(AR13:AV13) -> 0.02774532 | G13: =A13 -> 0.02773842 | H13: =AVERAGE(AW13:BA13) -> 0.02772106 | I13: =AVERAGE(BB13:BF13) -> 0.02766118 | J13: =AVERAGE(BG13:BK13) -> 0.02740308 | K13: =AVERAGE(BL13:BP13) -> 0.02308794 | L13: =AVERAGE(BQ13:BU13) -> 0.02308794 | M13: =L13 -> 0.02308794 | N13: =AVERAGE(CA13:CE13) -> 0.02405676 | O13: =AVERAGE(CF13:CJ13) -> 0.02130692 | P13: =AVERAGE(CK13:CO13) -> 0.01766066 | Q13: =AVERAGE(CP13:CT13) -> 0.0135841 | R13: =AVERAGE(CU13:CY13) -> 0.009175896 | S13: =AVERAGE(CZ13:DD13) -> 0.005800638 | T13: =AVERAGE(DE13:DI13) -> 0.004723626 | U13: =ROUND(G13,4)&"," -> 0.0277, | X13: 0.0277858 | Y13: 0.0277529 | Z13: 0.0277957 | AA13: 0.0277602 | AB13: 0.0277736 | AC13: 0.0277823 | AD13: 0.0277494 | AE13: 0.0277921 | AF13: 0.027757 | AG13: 0.0277703 | AH13: 0.027777 | AI13: 0.0277434 | AJ13: 0.0277869 | AK13: 0.0277525 | AL13: 0.0277667 | AM13: 0.0277691 | AN13: 0.0277344 | AO13: 0.0277795 | AP13: 0.0277449 | AQ13: 0.0277611 | AR13: 0.0277578 | AS13: 0.0277201 | AT13: 0.0277668 | AU13: 0.0277322 | AV13: 0.0277497 | AW13: 0.0277364 | AX13: 0.0276931 | AY13: 0.0277427 | AZ13: 0.0277058 | BA13: 0.0277273 | BB13: 0.0276838 | BC13: 0.0276278 | BD13: 0.0276823 | BE13: 0.0276411 | BF13: 0.0276709 | BG13: 0.0274562 | BH13: 0.0273508 | BI13: 0.0274091 | BJ13: 0.0273664 | BK13: 0.0274329 | BL13: 0.0232522 | BM13: 0.0232456 | BN13: 0.0225337 | BO13: 0.0226838 | BP13: 0.0237244 | BQ13: 0.0232522 | BR13: 0.0232456 | BS13: 0.0225337 | BT13: 0.0226838 | BU13: 0.0237244 | CA13: 0.0244138 | CB13: 0.0241065 | CC13: 0.0234835 | CD13: 0.0236826 | CE13: 0.0245974 | CF13: 0.0211383 | CG13: 0.0214603 | CH13: 0.0207905 | CI13: 0.021065 | CJ13: 0.0220805 | CK13: 0.0173196 | CL13: 0.0174428 | CM13: 0.0175241 | CN13: 0.0174974 | CO13: 0.0185194 | CP13: 0.0134709 | CQ13: 0.013551 | CR13: 0.0139894 | CS13: 0.0129122 | CT13: 0.013997 | CU13: 0.00906443 | CV13: 0.00895016 | CW13: 0.00949726 | CX13: 0.00867943 | CY13: 0.0096882 | CZ13: 0.00580492 | DA13: 0.00564021 | DB13: 0.00591283 | DC13: 0.0056068 | DD13: 0.00603843 | DE13: 0.00475509 | DF13: 0.00470552 | DG13: 0.0047319 | DH13: 0.00469996 | DI13: 0.00472566
A14: =range!F20 -> 0.02771784 | B14: =AVERAGE(X14:AB14) -> 0.02775792 | C14: =AVERAGE(AC14:AG14) -> 0.02775446 | D14: =AVERAGE(AH14:AL14) -> 0.02774894 | E14: =AVERAGE(AM14:AQ14) -> 0.0277403 | F14: =AVERAGE(AR14:AV14) -> 0.02772586 | G14: =A14 -> 0.02771784 | H14: =AVERAGE(AW14:BA14) -> 0.02769668 | I14: =AVERAGE(BB14:BF14) -> 0.02762024 | J14: =AVERAGE(BG14:BK14) -> 0.02727052 | K14: =AVERAGE(BL14:BP14) -> 0.02215484 | L14: =AVERAGE(BQ14:BU14) -> 0.02215484 | M14: =L14 -> 0.02215484 | N14: =AVERAGE(CA14:CE14) -> 0.02319584 | O14: =AVERAGE(CF14:CJ14) -> 0.02041634 | P14: =AVERAGE(CK14:CO14) -> 0.01715172 | Q14: =AVERAGE(CP14:CT14) -> 0.01324058 | R14: =AVERAGE(CU14:CY14) -> 0.009234056 | S14: =AVERAGE(CZ14:DD14) -> 0.00599597 | T14: =AVERAGE(DE14:DI14) -> 0.00474603 | U14: =ROUND(G14,4)&"," -> 0.0277, | X14: 0.0277674 | Y14: 0.0277368 | Z14: 0.027779 | AA14: 0.0277454 | AB14: 0.027761 | AC14: 0.0277636 | AD14: 0.0277349 | AE14: 0.0277744 | AF14: 0.0277413 | AG14: 0.0277581 | AH14: 0.0277582 | AI14: 0.0277298 | AJ14: 0.0277688 | AK14: 0.0277354 | AL14: 0.0277525 | AM14: 0.0277498 | AN14: 0.0277204 | AO14: 0.0277601 | AP14: 0.0277264 | AQ14: 0.0277448 | AR14: 0.0277365 | AS14: 0.0277044 | AT14: 0.0277452 | AU14: 0.027711 | AV14: 0.0277322 | AW14: 0.0277083 | AX14: 0.0276724 | AY14: 0.027715 | AZ14: 0.0276791 | BA14: 0.0277086 | BB14: 0.0276348 | BC14: 0.0275934 | BD14: 0.0276394 | BE14: 0.0275938 | BF14: 0.0276398 | BG14: 0.0273039 | BH14: 0.0272507 | BI14: 0.0272881 | BJ14: 0.0271847 | BK14: 0.0273252 | BL14: 0.022249 | BM14: 0.0220935 | BN14: 0.0217859 | BO14: 0.0216308 | BP14: 0.023015 | BQ14: 0.022249 | BR14: 0.0220935 | BS14: 0.0217859 | BT14: 0.0216308 | BU14: 0.023015 | CA14: 0.0233366 | CB14: 0.0231639 | CC14: 0.0229332 | CD14: 0.0226958 | CE14: 0.0238497 | CF14: 0.0203653 | CG14: 0.0202534 | CH14: 0.0198988 | CI14: 0.0199012 | CJ14: 0.021663 | CK14: 0.0169777 | CL14: 0.0169822 | CM14: 0.0164064 | CN14: 0.0166632 | CO14: 0.0187291 | CP14: 0.0131342 | CQ14: 0.0133294 | CR14: 0.0128617 | CS14: 0.0126556 | CT14: 0.014222 | CU14: 0.00899102 | CV14: 0.00893323 | CW14: 0.00964408 | CX14: 0.00865214 | CY14: 0.00994981 | CZ14: 0.00584093 | DA14: 0.00565326 | DB14: 0.00629482 | DC14: 0.00573197 | DD14: 0.00645887 | DE14: 0.00474696 | DF14: 0.00469394 | DG14: 0.00476161 | DH14: 0.00467948 | DI14: 0.00484816
A15: =range!F21 -> 0.0276945 | B15: =AVERAGE(X15:AB15) -> 0.02774088 | C15: =AVERAGE(AC15:AG15) -> 0.02773706 | D15: =AVERAGE(AH15:AL15) -> 0.02773106 | E15: =AVERAGE(AM15:AQ15) -> 0.02772152 | F15: =AVERAGE(AR15:AV15) -> 0.02770436 | G15: =A15 -> 0.0276945 | H15: =AVERAGE(AW15:BA15) -> 0.02766786 | I15: =AVERAGE(BB15:BF15) -> 0.02756844 | J15: =AVERAGE(BG15:BK15) -> 0.02708474 | K15: =AVERAGE(BL15:BP15) -> 0.02140308 | L15: =AVERAGE(BQ15:BU15) -> 0.02140308 | M15: =L15 -> 0.02140308 | N15: =AVERAGE(CA15:CE15) -> 0.02243736 | O15: =AVERAGE(CF15:CJ15) -> 0.01969444 | P15: =AVERAGE(CK15:CO15) -> 0.01654198 | Q15: =AVERAGE(CP15:CT15) -> 0.01275018 | R15: =AVERAGE(CU15:CY15) -> 0.009032228 | S15: =AVERAGE(CZ15:DD15) -> 0.00604285 | T15: =AVERAGE(DE15:DI15) -> 0.004742834 | U15: =ROUND(G15,4)&"," -> 0.0277, | X15: 0.0277479 | Y15: 0.0277231 | Z15: 0.027766 | AA15: 0.0277272 | AB15: 0.0277402 | AC15: 0.027744 | AD15: 0.0277169 | AE15: 0.0277627 | AF15: 0.027723 | AG15: 0.0277387 | AH15: 0.0277378 | AI15: 0.0277105 | AJ15: 0.027757 | AK15: 0.0277164 | AL15: 0.0277336 | AM15: 0.0277277 | AN15: 0.0277002 | AO15: 0.0277483 | AP15: 0.0277067 | AQ15: 0.0277247 | AR15: 0.0277109 | AS15: 0.0276814 | AT15: 0.0277327 | AU15: 0.0276887 | AV15: 0.0277081 | AW15: 0.0276756 | AX15: 0.0276427 | AY15: 0.0276989 | AZ15: 0.0276491 | BA15: 0.027673 | BB15: 0.0275776 | BC15: 0.0275421 | BD15: 0.0276076 | BE15: 0.0275407 | BF15: 0.0275742 | BG15: 0.0270805 | BH15: 0.0270729 | BI15: 0.0271597 | BJ15: 0.0269706 | BK15: 0.02714 | BL15: 0.0210096 | BM15: 0.0209699 | BN15: 0.0213986 | BO15: 0.0212565 | BP15: 0.0223808 | BQ15: 0.0210096 | BR15: 0.0209699 | BS15: 0.0213986 | BT15: 0.0212565 | BU15: 0.0223808 | CA15: 0.0222309 | CB15: 0.022061 | CC15: 0.0223608 | CD15: 0.0222164 | CE15: 0.0233177 | CF15: 0.0191016 | CG15: 0.0192715 | CH15: 0.0198035 | CI15: 0.0195689 | CJ15: 0.0207267 | CK15: 0.0160728 | CL15: 0.016477 | CM15: 0.016797 | CN15: 0.0160646 | CO15: 0.0172985 | CP15: 0.0124904 | CQ15: 0.0130908 | CR15: 0.012875 | CS15: 0.0119659 | CT15: 0.0133288 | CU15: 0.00886868 | CV15: 0.00886293 | CW15: 0.00937779 | CX15: 0.00851013 | CY15: 0.00954161 | CZ15: 0.00587408 | DA15: 0.00570274 | DB15: 0.00628653 | DC15: 0.00593993 | DD15: 0.00641097 | DE15: 0.00473467 | DF15: 0.00468048 | DG15: 0.00480214 | DH15: 0.0047607 | DI15: 0.00473618
A16: =range!F22 -> 0.0276657 | B16: =AVERAGE(X16:AB16) -> 0.0277169 | C16: =AVERAGE(AC16:AG16) -> 0.02771374 | D16: =AVERAGE(AH16:AL16) -> 0.02770784 | E16: =AVERAGE(AM16:AQ16) -> 0.027697 | F16: =AVERAGE(AR16:AV16) -> 0.02767708 | G16: =A16 -> 0.0276657 | H16: =AVERAGE(AW16:BA16) -> 0.02763354 | I16: =AVERAGE(BB16:BF16) -> 0.02750584 | J16: =AVERAGE(BG16:BK16) -> 0.02685312 | K16: =AVERAGE(BL16:BP16) -> 0.02071956 | L16: =AVERAGE(BQ16:BU16) -> 0.02071956 | M16: =L16 -> 0.02071956 | N16: =AVERAGE(CA16:CE16) -> 0.02171874 | O16: =AVERAGE(CF16:CJ16) -> 0.01908606 | P16: =AVERAGE(CK16:CO16) -> 0.01605602 | Q16: =AVERAGE(CP16:CT16) -> 0.0126034 | R16: =AVERAGE(CU16:CY16) -> 0.00907466 | S16: =AVERAGE(CZ16:DD16) -> 0.006063488 | T16: =AVERAGE(DE16:DI16) -> 0.004745396 | U16: =ROUND(G16,4)&"," -> 0.0277, | X16: 0.0277259 | Y16: 0.0277051 | Z16: 0.0277501 | AA16: 0.027702 | AB16: 0.0277014 | AC16: 0.0277207 | AD16: 0.0277005 | AE16: 0.0277464 | AF16: 0.027698 | AG16: 0.0277031 | AH16: 0.0277123 | AI16: 0.0276942 | AJ16: 0.0277409 | AK16: 0.0276912 | AL16: 0.0277006 | AM16: 0.0276978 | AN16: 0.0276836 | AO16: 0.0277322 | AP16: 0.0276795 | AQ16: 0.0276919 | AR16: 0.0276732 | AS16: 0.0276658 | AT16: 0.0277148 | AU16: 0.0276576 | AV16: 0.027674 | AW16: 0.0276237 | AX16: 0.0276265 | AY16: 0.0276771 | AZ16: 0.0276104 | BA16: 0.02763 | BB16: 0.0274797 | BC16: 0.0275107 | BD16: 0.0275695 | BE16: 0.0274791 | BF16: 0.0274902 | BG16: 0.0267 | BH16: 0.0269114 | BI16: 0.02703 | BJ16: 0.0268459 | BK16: 0.0267783 | BL16: 0.0204823 | BM16: 0.0205308 | BN16: 0.0210105 | BO16: 0.0204746 | BP16: 0.0210996 | BQ16: 0.0204823 | BR16: 0.0205308 | BS16: 0.0210105 | BT16: 0.0204746 | BU16: 0.0210996 | CA16: 0.0213883 | CB16: 0.0214408 | CC16: 0.0220682 | CD16: 0.0214953 | CE16: 0.0222011 | CF16: 0.0190428 | CG16: 0.0190078 | CH16: 0.0191857 | CI16: 0.0187622 | CJ16: 0.0194318 | CK16: 0.016279 | CL16: 0.0155565 | CM16: 0.015985 | CN16: 0.0156262 | CO16: 0.0168334 | CP16: 0.0128071 | CQ16: 0.012338 | CR16: 0.0127077 | CS16: 0.0118367 | CT16: 0.0133275 | CU16: 0.00897752 | CV16: 0.00908938 | CW16: 0.00921965 | CX16: 0.00838922 | CY16: 0.00969753 | CZ16: 0.00583084 | DA16: 0.00595921 | DB16: 0.00634465 | DC16: 0.00575207 | DD16: 0.00643067 | DE16: 0.00476499 | DF16: 0.00466645 | DG16: 0.0048143 | DH16: 0.00467586 | DI16: 0.00480538
A17: =range!F23 -> 0.02761574 | B17: =AVERAGE(X17:AB17) -> 0.02766332 | C17: =AVERAGE(AC17:AG17) -> 0.02766648 | D17: =AVERAGE(AH17:AL17) -> 0.02766278 | E17: =AVERAGE(AM17:AQ17) -> 0.02765468 | F17: =AVERAGE(AR17:AV17) -> 0.02763142 | G17: =A17 -> 0.02761574 | H17: =AVERAGE(AW17:BA17) -> 0.02756994 | I17: =AVERAGE(BB17:BF17) -> 0.02738096 | J17: =AVERAGE(BG17:BK17) -> 0.0264131 | K17: =AVERAGE(BL17:BP17) -> 0.01985896 | L17: =AVERAGE(BQ17:BU17) -> 0.01985896 | M17: =L17 -> 0.01985896 | N17: =AVERAGE(CA17:CE17) -> 0.02085694 | O17: =AVERAGE(CF17:CJ17) -> 0.01825398 | P17: =AVERAGE(CK17:CO17) -> 0.01532362 | Q17: =AVERAGE(CP17:CT17) -> 0.01207154 | R17: =AVERAGE(CU17:CY17) -> 0.008888436 | S17: =AVERAGE(CZ17:DD17) -> 0.00605826 | T17: =AVERAGE(DE17:DI17) -> 0.004743386 | U17: =ROUND(G17,4)&"," -> 0.0276, | X17: 0.027703 | Y17: 0.0276632 | Z17: 0.0276538 | AA17: 0.027639 | AB17: 0.0276576 | AC17: 0.0276991 | AD17: 0.0276592 | AE17: 0.0276847 | AF17: 0.0276399 | AG17: 0.0276495 | AH17: 0.0276909 | AI17: 0.0276565 | AJ17: 0.0276924 | AK17: 0.0276355 | AL17: 0.0276386 | AM17: 0.027678 | AN17: 0.0276458 | AO17: 0.0276923 | AP17: 0.0276261 | AQ17: 0.0276312 | AR17: 0.0276534 | AS17: 0.0276214 | AT17: 0.0276721 | AU17: 0.0276001 | AV17: 0.0276101 | AW17: 0.0275988 | AX17: 0.0275606 | AY17: 0.0276141 | AZ17: 0.0275331 | BA17: 0.0275431 | BB17: 0.0274344 | BC17: 0.0273816 | BD17: 0.0274433 | BE17: 0.0273223 | BF17: 0.0273232 | BG17: 0.0264479 | BH17: 0.0264606 | BI17: 0.0266575 | BJ17: 0.0262485 | BK17: 0.026251 | BL17: 0.0198551 | BM17: 0.0196376 | BN17: 0.0195509 | BO17: 0.01991 | BP17: 0.0203412 | BQ17: 0.0198551 | BR17: 0.0196376 | BS17: 0.0195509 | BT17: 0.01991 | BU17: 0.0203412 | CA17: 0.0207558 | CB17: 0.0206491 | CC17: 0.0206386 | CD17: 0.0209878 | CE17: 0.0212534 | CF17: 0.0182187 | CG17: 0.0181282 | CH17: 0.0178434 | CI17: 0.018119 | CJ17: 0.0189606 | CK17: 0.0149156 | CL17: 0.0156107 | CM17: 0.0148754 | CN17: 0.0150153 | CO17: 0.0162011 | CP17: 0.0116902 | CQ17: 0.0124147 | CR17: 0.011806 | CS17: 0.0118248 | CT17: 0.012622 | CU17: 0.00849398 | CV17: 0.00900164 | CW17: 0.00892049 | CX17: 0.00868699 | CY17: 0.00933908 | CZ17: 0.00581494 | DA17: 0.00580317 | DB17: 0.00632386 | DC17: 0.00581498 | DD17: 0.00653435 | DE17: 0.00474232 | DF17: 0.00463747 | DG17: 0.004809 | DH17: 0.00468783 | DI17: 0.00484031
A18: =range!F24 -> 0.0275478 | B18: =AVERAGE(X18:AB18) -> 0.02739942 | C18: =AVERAGE(AC18:AG18) -> 0.027495 | D18: =AVERAGE(AH18:AL18) -> 0.0275556 | E18: =AVERAGE(AM18:AQ18) -> 0.02758618 | F18: =AVERAGE(AR18:AV18) -> 0.02756656 | G18: =A18 -> 0.0275478 | H18: =AVERAGE(AW18:BA18) -> 0.02749146 | I18: =AVERAGE(BB18:BF18) -> 0.02724688 | J18: =AVERAGE(BG18:BK18) -> 0.02604862 | K18: =AVERAGE(BL18:BP18) -> 0.01934396 | L18: =AVERAGE(BQ18:BU18) -> 0.01934396 | M18: =L18 -> 0.01934396 | N18: =AVERAGE(CA18:CE18) -> 0.02036544 | O18: =AVERAGE(CF18:CJ18) -> 0.01768194 | P18: =AVERAGE(CK18:CO18) -> 0.01473826 | Q18: =AVERAGE(CP18:CT18) -> 0.01167636 | R18: =AVERAGE(CU18:CY18) -> 0.00875876 | S18: =AVERAGE(CZ18:DD18) -> 0.005836952 | T18: =AVERAGE(DE18:DI18) -> 0.004706854 | U18: =ROUND(G18,4)&"," -> 0.0275, | X18: 0.027639 | Y18: 0.0276247 | Z18: 0.0265606 | AA18: 0.0275869 | AB18: 0.0275859 | AC18: 0.027645 | AD18: 0.0276209 | AE18: 0.0270277 | AF18: 0.0275907 | AG18: 0.0275907 | AH18: 0.0276425 | AI18: 0.0276147 | AJ18: 0.0273359 | AK18: 0.0275913 | AL18: 0.0275936 | AM18: 0.0276241 | AN18: 0.0275942 | AO18: 0.0275396 | AP18: 0.0275853 | AQ18: 0.0275877 | AR18: 0.0275868 | AS18: 0.0275601 | AT18: 0.0275572 | AU18: 0.0275598 | AV18: 0.0275689 | AW18: 0.0275014 | AX18: 0.0274847 | AY18: 0.0274807 | AZ18: 0.0274801 | BA18: 0.0275104 | BB18: 0.0272356 | BC18: 0.027263 | BD18: 0.0272363 | BE18: 0.0271936 | BF18: 0.0273059 | BG18: 0.0258593 | BH18: 0.0261141 | BI18: 0.0261946 | BJ18: 0.0257941 | BK18: 0.026281 | BL18: 0.0195997 | BM18: 0.0192363 | BN18: 0.0189602 | BO18: 0.0193529 | BP18: 0.0195707 | BQ18: 0.0195997 | BR18: 0.0192363 | BS18: 0.0189602 | BT18: 0.0193529 | BU18: 0.0195707 | CA18: 0.0205401 | CB18: 0.0202931 | CC18: 0.0199325 | CD18: 0.0206183 | CE18: 0.0204432 | CF18: 0.0177073 | CG18: 0.0176568 | CH18: 0.0175428 | CI18: 0.0172926 | CJ18: 0.0182102 | CK18: 0.014018 | CL18: 0.0150316 | CM18: 0.0149763 | CN18: 0.0143147 | CO18: 0.0153507 | CP18: 0.0111307 | CQ18: 0.012001 | CR18: 0.0115751 | CS18: 0.0113593 | CT18: 0.0123157 | CU18: 0.00837978 | CV18: 0.008886 | CW18: 0.00862893 | CX18: 0.00878466 | CY18: 0.00911443 | CZ18: 0.0058061 | DA18: 0.00557493 | DB18: 0.00594932 | DC18: 0.0060836 | DD18: 0.00577081 | DE18: 0.00472306 | DF18: 0.00467026 | DG18: 0.00469286 | DH18: 0.00471296 | DI18: 0.00473513
A19: =range!F25 -> 0.0274928 | B19: =AVERAGE(X19:AB19) -> 0.02754816 | C19: =AVERAGE(AC19:AG19) -> 0.02756022 | D19: =AVERAGE(AH19:AL19) -> 0.0275625 | E19: =AVERAGE(AM19:AQ19) -> 0.02755382 | F19: =AVERAGE(AR19:AV19) -> 0.027518 | G19: =A19 -> 0.0274928 | H19: =AVERAGE(AW19:BA19) -> 0.02741814 | I19: =AVERAGE(BB19:BF19) -> 0.02707156 | J19: =AVERAGE(BG19:BK19) -> 0.02549896 | K19: =AVERAGE(BL19:BP19) -> 0.01904488 | L19: =AVERAGE(BQ19:BU19) -> 0.01904488 | M19: =L19 -> 0.01904488 | N19: =AVERAGE(CA19:CE19) -> 0.01994074 | O19: =AVERAGE(CF19:CJ19) -> 0.01756546 | P19: =AVERAGE(CK19:CO19) -> 0.01474148 | Q19: =AVERAGE(CP19:CT19) -> 0.01161804 | R19: =AVERAGE(CU19:CY19) -> 0.008661708 | S19: =AVERAGE(CZ19:DD19) -> 0.00606139 | T19: =AVERAGE(DE19:DI19) -> 0.00473335 | U19: =ROUND(G19,4)&"," -> 0.0275, | X19: 0.0275931 | Y19: 0.0274747 | Z19: 0.0276467 | AA19: 0.027553 | AB19: 0.0274733 | AC19: 0.0276029 | AD19: 0.0275019 | AE19: 0.0276591 | AF19: 0.0275426 | AG19: 0.0274946 | AH19: 0.0276042 | AI19: 0.0275086 | AJ19: 0.0276486 | AK19: 0.027541 | AL19: 0.0275101 | AM19: 0.0275917 | AN19: 0.0275042 | AO19: 0.0276292 | AP19: 0.0275358 | AQ19: 0.0275082 | AR19: 0.0275593 | AS19: 0.0274737 | AT19: 0.0275895 | AU19: 0.0274909 | AV19: 0.0274766 | AW19: 0.0274728 | AX19: 0.0273735 | AY19: 0.0274895 | AZ19: 0.0273835 | BA19: 0.0273714 | BB19: 0.0271969 | BC19: 0.0270066 | BD19: 0.0271795 | BE19: 0.027009 | BF19: 0.0269658 | BG19: 0.0256518 | BH19: 0.0253139 | BI19: 0.0255794 | BJ19: 0.025357 | BK19: 0.0255927 | BL19: 0.0188107 | BM19: 0.0192284 | BN19: 0.0193228 | BO19: 0.0187294 | BP19: 0.0191331 | BQ19: 0.0188107 | BR19: 0.0192284 | BS19: 0.0193228 | BT19: 0.0187294 | BU19: 0.0191331 | CA19: 0.0197457 | CB19: 0.02025 | CC19: 0.0201648 | CD19: 0.019598 | CE19: 0.0199452 | CF19: 0.0172495 | CG19: 0.0173825 | CH19: 0.0179717 | CI19: 0.0174417 | CJ19: 0.0177819 | CK19: 0.0139556 | CL19: 0.0143022 | CM19: 0.0152862 | CN19: 0.014996 | CO19: 0.0151674 | CP19: 0.0108663 | CQ19: 0.0116021 | CR19: 0.0117593 | CS19: 0.0116008 | CT19: 0.0122617 | CU19: 0.00832089 | CV19: 0.00888458 | CW19: 0.00869705 | CX19: 0.0084116 | CY19: 0.00899442 | CZ19: 0.00585082 | DA19: 0.00592149 | DB19: 0.00640818 | DC19: 0.00592949 | DD19: 0.00619697 | DE19: 0.00471438 | DF19: 0.00465474 | DG19: 0.00483475 | DH19: 0.00471554 | DI19: 0.00474734
... A67: =range!F73 -> 0.004208692 | B67: =AVERAGE(X67:AB67) -> 0.00420816 | C67: =AVERAGE(AC67:AG67) -> 0.004208938 | D67: =AVERAGE(AH67:AL67) -> 0.004208922 | E67: =AVERAGE(AM67:AQ67) -> 0.004208638 | F67: =AVERAGE(AR67:AV67) -> 0.004208694 | G67: =A67 -> 0.004208692 | H67: =AVERAGE(AW67:BA67) -> 0.004208686 | I67: =AVERAGE(BB67:BF67) -> 0.004208648 | J67: =AVERAGE(BG67:BK67) -> 0.004208598 | K67: =AVERAGE(BL67:BP67) -> 0.004208672 | L67: =AVERAGE(BQ67:BU67) -> 0.004208672 | M67: =L67 -> 0.004208672 | N67: =AVERAGE(CA67:CE67) -> 0.004208674 | O67: =AVERAGE(CF67:CJ67) -> 0.004208618 | P67: =AVERAGE(CK67:CO67) -> 0.004208606 | Q67: =AVERAGE(CP67:CT67) -> 0.004208614 | R67: =AVERAGE(CU67:CY67) -> 0.004208636 | S67: =AVERAGE(CZ67:DD67) -> 0.004208602 | T67: =AVERAGE(DE67:DI67) -> 0.00420856 | U67: =ROUND(G67,4)&"," -> 0.0042, | X67: 0.00421854 | Y67: 0.00419717 | Z67: 0.00421294 | AA67: 0.00420518 | AB67: 0.00420697 | AC67: 0.00421852 | AD67: 0.00419717 | AE67: 0.00421672 | AF67: 0.00420525 | AG67: 0.00420703 | AH67: 0.0042185 | AI67: 0.00419716 | AJ67: 0.00421665 | AK67: 0.00420527 | AL67: 0.00420703 | AM67: 0.00421845 | AN67: 0.00419714 | AO67: 0.0042155 | AP67: 0.00420514 | AQ67: 0.00420696 | AR67: 0.00421845 | AS67: 0.00419712 | AT67: 0.00421599 | AU67: 0.00420507 | AV67: 0.00420684 | AW67: 0.00421846 | AX67: 0.00419711 | AY67: 0.00421601 | AZ67: 0.00420513 | BA67: 0.00420672 | BB67: 0.00421842 | BC67: 0.00419709 | BD67: 0.00421592 | BE67: 0.00420517 | BF67: 0.00420664 | BG67: 0.00421837 | BH67: 0.00419709 | BI67: 0.0042157 | BJ67: 0.0042052 | BK67: 0.00420663 | BL67: 0.00421844 | BM67: 0.00419708 | BN67: 0.00421591 | BO67: 0.0042053 | BP67: 0.00420663 | BQ67: 0.00421844 | BR67: 0.00419708 | BS67: 0.00421591 | BT67: 0.0042053 | BU67: 0.00420663 | CA67: 0.00421845 | CB67: 0.00419708 | CC67: 0.00421592 | CD67: 0.00420529 | CE67: 0.00420663 | CF67: 0.00421836 | CG67: 0.00419708 | CH67: 0.00421571 | CI67: 0.00420531 | CJ67: 0.00420663 | CK67: 0.00421834 | CL67: 0.00419708 | CM67: 0.00421565 | CN67: 0.00420533 | CO67: 0.00420663 | CP67: 0.00421833 | CQ67: 0.00419708 | CR67: 0.00421569 | CS67: 0.00420534 | CT67: 0.00420663 | CU67: 0.00421832 | CV67: 0.00419708 | CW67: 0.0042158 | CX67: 0.00420535 | CY67: 0.00420663 | CZ67: 0.00421832 | DA67: 0.00419708 | DB67: 0.00421564 | DC67: 0.00420535 | DD67: 0.00420662 | DE67: 0.00421831 | DF67: 0.00419708 | DG67: 0.00421544 | DH67: 0.00420535 | DI67: 0.00420662

Sheet beta
B1: beta3*0.1 (optimal) | C1: beta3*0.5 (optimal) | D1: beta3*1 (optimal) | E1: beta3*1.5 (optimal) | F1: beta3*2 | K1: beta3*0.1 | Q1: beta3*0.5 | V1: beta3*1 (base) | AA1: beta3*1.5 | AE1: beta3*2 | AK1: beta3*0.5 | AL1: beta3*1 (base) | AM1: beta3*1.5 | AO1: beta3*0.5 | AP1: beta3*1 (base) | AQ1: beta3*1.5 | AS1: beta3*0.5 | AT1: beta3*1 (base) | AU1: beta3*1.5 | AW1: beta3*0.5 | AX1: beta3*1 (base) | AY1: beta3*1.5
A2: Hosp Cost | B2: 2.968863 | C2: =T3 -> 3.793776 | D2: =Y3 -> 5.610668 | E2: =AD3 -> 9.18523 | F2: 16.166089 | K2: Type no vacc constant vacc actual vacc opt vacc | Q2: no vacc | R2: constant vacc | S2: actual vacc | T2: opt vacc | V2: no vacc | W2: constant vacc | X2: actual vacc | Y2: opt vacc | AA2: no vacc | AB2: constant vacc | AC2: actual vacc | AD2: opt vacc | AE2: Type no vacc constant vacc actual vacc opt vacc | AK2: no vacc | AO2: constant vacc | AS2: actual vacc | AW2: opt vacc
A3: Policy Cost | B3: 3.524076 | C3: =T4 -> 3.823068 | D3: =Y4 -> 4.513925 | E3: =AD4 -> 5.881727 | F3: 8.529911 | K3: 0 Hosp Cost 4.374999 4.315521 2.970420 2.968863 | P3: Hosp Cost | Q3: 6.033669 | R3: 5.694578 | S3: 4.112028 | T3: 3.793776 | V3: 11.616842 | W3: 9.249465 | X3: 6.374409 | Y3: 5.610668 | AA3: 31.330069 | AB3: 18.025888 | AC3: 11.300558 | AD3: 9.18523 | AE3: 0 Hosp Cost 83.887047 38.632483 16.372676 16.166089 | AK3: =Q3 -> 6.033669 | AL3: =V3 -> 11.616842 | AM3: =AA3 -> 31.330069 | AO3: =R3 -> 5.694578 | AP3: =W3 -> 9.249465 | AQ3: =AB3 -> 18.025888 | AS3: =S3 -> 4.112028 | AT3: =OFFSET(S3,0,5) -> 6.374409 | AU3: =OFFSET(S3,0,10) -> 11.300558 | AW3: =T3 -> 3.793776 | AX3: =OFFSET(T3,0,5) -> 5.610668 | AY3: =OFFSET(T3,0,10) -> 9.18523
A4: Econ Cost | B4: 14.439836 | C4: =T5 -> 18.953884 | D4: =Y5 -> 28.924867 | E4: =AD5 -> 48.485532 | F4: 86.571386 | K4: 1 Policy Cost 0.851847 1.797727 3.475704 3.524076 | P4: Policy Cost | Q4: 1.274791 | R4: 2.149876 | S4: 3.150092 | T4: 3.823068 | V4: 2.757488 | W4: 3.077856 | X4: 3.979546 | Y4: 4.513925 | AA4: 8.329062 | AB4: 5.414036 | AC4: 5.794695 | AD4: 5.881727 | AE4: 1 Policy Cost 23.414948 11.005590 8.457483 8.529911 | AK4: =Q4 -> 1.274791 | AL4: =V4 -> 2.757488 | AM4: =AA4 -> 8.329062 | AO4: =R4 -> 2.149876 | AP4: =W4 -> 3.077856 | AQ4: =AB4 -> 5.414036 | AS4: =S4 -> 3.150092 | AT4: =OFFSET(S4,0,5) -> 3.979546 | AU4: =OFFSET(S4,0,10) -> 5.794695 | AW4: =T4 -> 3.823068 | AX4: =OFFSET(T4,0,5) -> 4.513925 | AY4: =OFFSET(T4,0,10) -> 5.881727
A5: Total Cost | B5: 20.932775 | C5: =T6 -> 26.570729 | D5: =Y6 -> 39.049459 | E5: =AD6 -> 63.552489 | F5: 111.26739 | K5: 2 Econ Cost 14.818045 14.671319 14.440365 14.439836 | P5: Econ Cost | Q5: 21.124831 | R5: 19.923195 | S5: 19.638589 | T5: 18.953884 | V5: 42.917935 | W5: 33.642296 | X5: 31.83938 | Y5: 28.924867 | AA5: 123.1473 | AB5: 67.936784 | AC5: 58.409633 | AD5: 48.485532 | AE5: 2 Econ Cost 339.516377 149.512015 87.387802 86.571386 | AK5: =Q5 -> 21.124831 | AL5: =V5 -> 42.917935 | AM5: =AA5 -> 123.1473 | AO5: =R5 -> 19.923195 | AP5: =W5 -> 33.642296 | AQ5: =AB5 -> 67.936784 | AS5: =S5 -> 19.638589 | AT5: =OFFSET(S5,0,5) -> 31.83938 | AU5: =OFFSET(S5,0,10) -> 58.409633 | AW5: =T5 -> 18.953884 | AX5: =OFFSET(T5,0,5) -> 28.924867 | AY5: =OFFSET(T5,0,10) -> 48.485532
K6: 3 Total Cost 20.044891 20.784567 20.886489 20.932775 | P6: Total Cost | Q6: 28.43329 | R6: 27.767648 | S6: 26.900709 | T6: 26.570729 | V6: 57.292265 | W6: 45.969617 | X6: 42.193335 | Y6: 39.049459 | AA6: 162.80643 | AB6: 91.376707 | AC6: 75.504886 | AD6: 63.552489 | AE6: 3 Total Cost 446.818372 199.150088 112.217961 111.267387 | AK6: =Q6 -> 28.43329 | AL6: =V6 -> 57.292265 | AM6: =AA6 -> 162.80643 | AO6: =R6 -> 27.767648 | AP6: =W6 -> 45.969617 | AQ6: =AB6 -> 91.376707 | AS6: =S6 -> 26.900709 | AT6: =OFFSET(S6,0,5) -> 42.193335 | AU6: =OFFSET(S6,0,10) -> 75.504886 | AW6: =T6 -> 26.570729 | AX6: =OFFSET(T6,0,5) -> 39.049459 | AY6: =OFFSET(T6,0,10) -> 63.552489
AK7: No Vacc beta3*0.5 | AL7: No vacc beta3*1 (base) | AM7: No vacc beta3*1.5 | AO7: Const Vacc beta3*0.5 | AP7: Const Vacc beta3*1 (base) | AQ7: Const Vacc beta3*1.5 | AS7: Actual Vacc beta3*0.5 | AT7: Actual Vacc beta3*1 (base) | AU7: Actual Vacc beta3*1.5 | AW7: beta3*0.5 | AX7: beta3*1 (base) | AY7: beta3*1.5
P8: Hosp Cost Savings | Q8: =1-$T3/Q3 -> 0.37123233 | R8: =1-$T3/R3 -> 0.33379155 | S8: =1-$T3/S3 -> 0.077395387 | V8: =1-$Y3/V3 -> 0.51702296 | W8: =1-$Y3/W3 -> 0.39340621 | X8: =1-$Y3/X3 -> 0.11981362 | AA8: =1-$AD3/AA3 -> 0.70682382 | AB8: =1-$AD3/AB3 -> 0.4904423 | AC8: =1-$AD3/AC3 -> 0.18718792 | AJ8: Hosp Cost Savings | AK8: =Q8 -> 0.37123233 | AL8: =V8 -> 0.51702296 | AM8: =AA8 -> 0.70682382 | AO8: =R8 -> 0.33379155 | AP8: =W8 -> 0.39340621 | AQ8: =AB8 -> 0.4904423 | AS8: =S8 -> 0.077395387 | AT8: =OFFSET(S8,0,5) -> 0.11981362 | AU8: =OFFSET(S8,0,10) -> 0.18718792 | AW8: =T8 -> 0 | AX8: =OFFSET(T8,0,5) -> 0 | AY8: =OFFSET(T8,0,10) -> 0
P9: Policy Cost Savings | Q9: =1-$T4/Q4 -> -1.9989763 | R9: =1-$T4/R4 -> -0.77827372 | S9: =1-$T4/S4 -> -0.21363694 | V9: =1-$Y4/V4 -> -0.63696995 | W9: =1-$Y4/W4 -> -0.46658096 | X9: =1-$Y4/X4 -> -0.1342814 | AA9: =1-$AD4/AA4 -> 0.29383081 | AB9: =1-$AD4/AB4 -> -0.086384908 | AC9: =1-$AD4/AC4 -> -0.015019255 | AJ9: Policy Cost Savings | AK9: =Q9 -> -1.9989763 | AL9: =V9 -> -0.63696995 | AM9: =AA9 -> 0.29383081 | AO9: =R9 -> -0.77827372 | AP9: =W9 -> -0.46658096 | AQ9: =AB9 -> -0.086384908 | AS9: =S9 -> -0.21363694 | AT9: =OFFSET(S9,0,5) -> -0.1342814 | AU9: =OFFSET(S9,0,10) -> -0.015019255 | AW9: =T9 -> 0 | AX9: =OFFSET(T9,0,5) -> 0 | AY9: =OFFSET(T9,0,10) -> 0
P10: Econ Cost Savings | Q10: =1-$T5/Q5 -> 0.10276754 | R10: =1-$T5/R5 -> 0.048652387 | S10: =1-$T5/S5 -> 0.034865285 | V10: =1-$Y5/V5 -> 0.32604243 | W10: =1-$Y5/W5 -> 0.14022316 | X10: =1-$Y5/X5 -> 0.091537995 | AA10: =1-$AD5/AA5 -> 0.60628019 | AB10: =1-$AD5/AB5 -> 0.28631399 | AC10: =1-$AD5/AC5 -> 0.16990521 | AJ10: Econ Cost Savings | AK10: =Q10 -> 0.10276754 | AL10: =V10 -> 0.32604243 | AM10: =AA10 -> 0.60628019 | AO10: =R10 -> 0.048652387 | AP10: =W10 -> 0.14022316 | AQ10: =AB10 -> 0.28631399 | AS10: =S10 -> 0.034865285 | AT10: =OFFSET(S10,0,5) -> 0.091537995 | AU10: =OFFSET(S10,0,10) -> 0.16990521 | AW10: =T10 -> 0 | AX10: =OFFSET(T10,0,5) -> 0 | AY10: =OFFSET(T10,0,10) -> 0
P11: Total Cost Savings | Q11: =1-$T6/Q6 -> 0.065506348 | R11: =1-$T6/R6 -> 0.043104803 | S11: =1-$T6/S6 -> 0.012266591 | V11: =1-$Y6/V6 -> 0.31841656 | W11: =1-$Y6/W6 -> 0.15053765 | X11: =1-$Y6/X6 -> 0.074511199 | AA11: =1-$AD6/AA6 -> 0.60964387 | AB11: =1-$AD6/AB6 -> 0.30450012 | AC11: =1-$AD6/AC6 -> 0.15829965
B13: beta3*0.1 | C13: beta3*0.5 | D13: beta3*1 (base) | E13: beta3*1.5 | F13: beta3*2 | K13: beta3*0.1 | P13: beta3*0.5 | U13: base case | Z13: beta3*1.5 | AE13: beta3*2
B14: =AVERAGE(K14:O14) -> 0.02778454 | C14: =AVERAGE(P14:T14) -> 0.02778464 | D14: =AVERAGE(U14:Y14) -> 0.02778504 | E14: =AVERAGE(Z14:AD14) -> 0.02778596 | F14: =AVERAGE(AE14:AI14) -> 0.02778812 | G14: =ROUND(D14,4)&"," -> 0.0278, | K14: 0.0277941 | L14: 0.027768 | M14: 0.0277918 | N14: 0.0277793 | O14: 0.0277895 | P14: 0.0277942 | Q14: 0.0277681 | R14: 0.0277919 | S14: 0.0277794 | T14: 0.0277896 | U14: 0.0277946 | V14: 0.0277686 | W14: 0.0277924 | X14: 0.0277797 | Y14: 0.0277899 | Z14: 0.0277955 | AA14: 0.0277695 | AB14: 0.0277935 | AC14: 0.0277807 | AD14: 0.0277906 | AE14: 0.0277975 | AF14: 0.027772 | AG14: 0.0277959 | AH14: 0.0277832 | AI14: 0.027792
B15: =AVERAGE(K15:O15) -> 0.02778724 | C15: =AVERAGE(P15:T15) -> 0.0277873 | D15: =AVERAGE(U15:Y15) -> 0.02778774 | E15: =AVERAGE(Z15:AD15) -> 0.02778898 | F15: =AVERAGE(AE15:AI15) -> 0.02779178 | G15: =ROUND(D15,4)&"," -> 0.0278, | K15: 0.0277977 | L15: 0.027766 | M15: 0.0277998 | N15: 0.0277803 | O15: 0.0277924 | P15: 0.0277978 | Q15: 0.027766 | R15: 0.0277999 | S15: 0.0277804 | T15: 0.0277924 | U15: 0.0277982 | V15: 0.0277666 | W15: 0.0278003 | X15: 0.0277808 | Y15: 0.0277928 | Z15: 0.0277995 | AA15: 0.0277677 | AB15: 0.0278017 | AC15: 0.0277822 | AD15: 0.0277938 | AE15: 0.0278022 | AF15: 0.0277709 | AG15: 0.0278046 | AH15: 0.0277854 | AI15: 0.0277958
B16: =AVERAGE(K16:O16) -> 0.02777704 | C16: =AVERAGE(P16:T16) -> 0.02777714 | D16: =AVERAGE(U16:Y16) -> 0.02777764 | E16: =AVERAGE(Z16:AD16) -> 0.02777906 | F16: =AVERAGE(AE16:AI16) -> 0.02778234 | G16: =ROUND(D16,4)&"," -> 0.0278, | K16: 0.0277859 | L16: 0.0277572 | M16: 0.0277903 | N16: 0.0277708 | O16: 0.027781 | P16: 0.027786 | Q16: 0.0277572 | R16: 0.0277905 | S16: 0.0277709 | T16: 0.0277811 | U16: 0.0277864 | V16: 0.0277577 | W16: 0.0277911 | X16: 0.0277714 | Y16: 0.0277816 | Z16: 0.0277875 | AA16: 0.0277591 | AB16: 0.027793 | AC16: 0.0277729 | AD16: 0.0277828 | AE16: 0.0277903 | AF16: 0.0277627 | AG16: 0.0277971 | AH16: 0.0277764 | AI16: 0.0277852
B17: =AVERAGE(K17:O17) -> 0.02776744 | C17: =AVERAGE(P17:T17) -> 0.02776746 | D17: =AVERAGE(U17:Y17) -> 0.02776806 | E17: =AVERAGE(Z17:AD17) -> 0.02776996 | F17: =AVERAGE(AE17:AI17) -> 0.0277742 | G17: =ROUND(D17,4)&"," -> 0.0278, | K17: 0.0277765 | L17: 0.0277453 | M17: 0.0277827 | N17: 0.0277583 | O17: 0.0277744 | P17: 0.0277766 | Q17: 0.0277452 | R17: 0.0277828 | S17: 0.0277583 | T17: 0.0277744 | U17: 0.0277772 | V17: 0.0277457 | W17: 0.0277835 | X17: 0.0277589 | Y17: 0.027775 | Z17: 0.0277789 | AA17: 0.0277474 | AB17: 0.0277858 | AC17: 0.027761 | AD17: 0.0277767 | AE17: 0.0277827 | AF17: 0.0277517 | AG17: 0.027791 | AH17: 0.0277656 | AI17: 0.02778
B18: =AVERAGE(K18:O18) -> 0.02775416 | C18: =AVERAGE(P18:T18) -> 0.0277542 | D18: =AVERAGE(U18:Y18) -> 0.02775492 | E18: =AVERAGE(Z18:AD18) -> 0.027757 | F18: =AVERAGE(AE18:AI18) -> 0.02776186 | G18: =ROUND(D18,4)&"," -> 0.0278, | K18: 0.0277634 | L18: 0.0277347 | M18: 0.0277707 | N18: 0.0277418 | O18: 0.0277602 | P18: 0.0277633 | Q18: 0.0277346 | R18: 0.0277708 | S18: 0.0277418 | T18: 0.0277605 | U18: 0.0277638 | V18: 0.0277353 | W18: 0.0277716 | X18: 0.0277424 | Y18: 0.0277615 | Z18: 0.0277655 | AA18: 0.0277372 | AB18: 0.0277742 | AC18: 0.0277444 | AD18: 0.0277637 | AE18: 0.0277697 | AF18: 0.0277423 | AG18: 0.02778 | AH18: 0.0277494 | AI18: 0.0277679
B19: =AVERAGE(K19:O19) -> 0.0277375 | C19: =AVERAGE(P19:T19) -> 0.02773754 | D19: =AVERAGE(U19:Y19) -> 0.02773842 | E19: =AVERAGE(Z19:AD19) -> 0.02774102 | F19: =AVERAGE(AE19:AI19) -> 0.0277468 | G19: =ROUND(D19,4)&"," -> 0.0277, | K19: 0.027751 | L19: 0.0277116 | M19: 0.0277595 | N19: 0.0277232 | O19: 0.0277422 | P19: 0.027751 | Q19: 0.0277115 | R19: 0.0277592 | S19: 0.0277234 | T19: 0.0277426 | U19: 0.0277518 | V19: 0.0277123 | W19: 0.0277599 | X19: 0.0277247 | Y19: 0.0277434 | Z19: 0.0277542 | AA19: 0.0277152 | AB19: 0.0277627 | AC19: 0.0277275 | AD19: 0.0277455 | AE19: 0.0277596 | AF19: 0.0277219 | AG19: 0.0277686 | AH19: 0.0277341 | AI19: 0.0277498
B20: =AVERAGE(K20:O20) -> 0.02771642 | C20: =AVERAGE(P20:T20) -> 0.02771676 | D20: =AVERAGE(U20:Y20) -> 0.02771784 | E20: =AVERAGE(Z20:AD20) -> 0.02772066 | F20: =AVERAGE(AE20:AI20) -> 0.02772786 | G20: =ROUND(D20,4)&"," -> 0.0277, | K20: 0.0277277 | L20: 0.027693 | M20: 0.0277355 | N20: 0.0277005 | O20: 0.0277254 | P20: 0.0277276 | Q20: 0.0276937 | R20: 0.0277357 | S20: 0.0277006 | T20: 0.0277262 | U20: 0.0277288 | V20: 0.0276953 | W20: 0.0277367 | X20: 0.027702 | Y20: 0.0277264 | Z20: 0.0277319 | AA20: 0.0276988 | AB20: 0.0277406 | AC20: 0.0277057 | AD20: 0.0277263 | AE20: 0.0277385 | AF20: 0.0277059 | AG20: 0.0277486 | AH20: 0.027714 | AI20: 0.0277323
B21: =AVERAGE(K21:O21) -> 0.027693 | C21: =AVERAGE(P21:T21) -> 0.0276933 | D21: =AVERAGE(U21:Y21) -> 0.0276945 | E21: =AVERAGE(Z21:AD21) -> 0.02769838 | F21: =AVERAGE(AE21:AI21) -> 0.02770722 | G21: =ROUND(D21,4)&"," -> 0.0277, | K21: 0.0277003 | L21: 0.0276694 | M21: 0.027722 | N21: 0.027676 | O21: 0.0276973 | P21: 0.0277006 | Q21: 0.0276693 | R21: 0.0277222 | S21: 0.0276762 | T21: 0.0276982 | U21: 0.0277015 | V21: 0.0276707 | W21: 0.0277235 | X21: 0.0276778 | Y21: 0.027699 | Z21: 0.0277049 | AA21: 0.0276751 | AB21: 0.0277278 | AC21: 0.0276819 | AD21: 0.0277022 | AE21: 0.0277138 | AF21: 0.0276843 | AG21: 0.0277366 | AH21: 0.0276918 | AI21: 0.0277096
B22: =AVERAGE(K22:O22) -> 0.02766124 | C22: =AVERAGE(P22:T22) -> 0.02766256 | D22: =AVERAGE(U22:Y22) -> 0.0276657 | E22: =AVERAGE(Z22:AD22) -> 0.02767164 | F22: =AVERAGE(AE22:AI22) -> 0.02768246 | G22: =ROUND(D22,4)&"," -> 0.0277, | K22: 0.0276527 | L22: 0.0276545 | M22: 0.0277033 | N22: 0.0276415 | O22: 0.0276542 | P22: 0.0276562 | Q22: 0.0276549 | R22: 0.0277029 | S22: 0.0276421 | T22: 0.0276567 | U22: 0.0276604 | V22: 0.0276556 | W22: 0.0277047 | X22: 0.0276448 | Y22: 0.027663 | Z22: 0.0276661 | AA22: 0.0276592 | AB22: 0.0277099 | AC22: 0.0276518 | AD22: 0.0276712 | AE22: 0.0276766 | AF22: 0.027668 | AG22: 0.0277198 | AH22: 0.0276647 | AI22: 0.0276832
B23: =AVERAGE(K23:O23) -> 0.0276113 | C23: =AVERAGE(P23:T23) -> 0.02761252 | D23: =AVERAGE(U23:Y23) -> 0.02761574 | E23: =AVERAGE(Z23:AD23) -> 0.02762238 | F23: =AVERAGE(AE23:AI23) -> 0.02763474 | G23: =ROUND(D23,4)&"," -> 0.0276, | K23: 0.0276279 | L23: 0.0276045 | M23: 0.027654 | N23: 0.027581 | O23: 0.0275891 | P23: 0.0276355 | Q23: 0.0276042 | R23: 0.0276554 | S23: 0.0275797 | T23: 0.0275878 | U23: 0.0276388 | V23: 0.0276058 | W23: 0.0276569 | X23: 0.0275826 | Y23: 0.0275946 | Z23: 0.0276442 | AA23: 0.0276125 | AB23: 0.027663 | AC23: 0.0275908 | AD23: 0.0276014 | AE23: 0.0276566 | AF23: 0.0276252 | AG23: 0.0276729 | AH23: 0.0276048 | AI23: 0.0276142
B24: =AVERAGE(K24:O24) -> 0.02754682 | C24: =AVERAGE(P24:T24) -> 0.02754498 | D24: =AVERAGE(U24:Y24) -> 0.0275478 | E24: =AVERAGE(Z24:AD24) -> 0.02755468 | F24: =AVERAGE(AE24:AI24) -> 0.02755984 | G24: =ROUND(D24,4)&"," -> 0.0275, | K24: 0.0275414 | L24: 0.0275412 | M24: 0.0275576 | N24: 0.0275367 | O24: 0.0275572 | P24: 0.0275529 | Q24: 0.027539 | R24: 0.0275339 | S24: 0.0275362 | T24: 0.0275629 | U24: 0.0275643 | V24: 0.0275391 | W24: 0.02754 | X24: 0.02754 | Y24: 0.0275556 | Z24: 0.0275785 | AA24: 0.0275451 | AB24: 0.0275444 | AC24: 0.0275444 | AD24: 0.027561 | AE24: 0.0275934 | AF24: 0.0275508 | AG24: 0.0275284 | AH24: 0.0275543 | AI24: 0.0275723
B25: =AVERAGE(K25:O25) -> 0.02748582 | C25: =AVERAGE(P25:T25) -> 0.0274905 | D25: =AVERAGE(U25:Y25) -> 0.0274928 | E25: =AVERAGE(Z25:AD25) -> 0.0275014 | F25: =AVERAGE(AE25:AI25) -> 0.02751548 | G25: =ROUND(D25,4)&"," -> 0.0275, | K25: 0.027536 | L25: 0.0274512 | M25: 0.0275601 | N25: 0.0274582 | O25: 0.0274236 | P25: 0.0275364 | Q25: 0.0274507 | R25: 0.0275593 | S25: 0.0274589 | T25: 0.0274472 | U25: 0.0275381 | V25: 0.0274522 | W25: 0.0275633 | X25: 0.0274556 | Y25: 0.0274548 | Z25: 0.0275465 | AA25: 0.0274532 | AB25: 0.0275747 | AC25: 0.0274752 | AD25: 0.0274574 | AE25: 0.0275679 | AF25: 0.0274436 | AG25: 0.0275959 | AH25: 0.0274941 | AI25: 0.0274759
... B73: =AVERAGE(K73:O73) -> 0.004208606 | C73: =AVERAGE(P73:T73) -> 0.004208618 | D73: =AVERAGE(U73:Y73) -> 0.004208692 | E73: =AVERAGE(Z73:AD73) -> 0.004208878 | F73: =AVERAGE(AE73:AI73) -> 0.00420891 | G73: =ROUND(D73,4)&"," -> 0.0042, | K73: 0.00421832 | L73: 0.00419708 | M73: 0.00421592 | N73: 0.00420515 | O73: 0.00420656 | P73: 0.00421834 | Q73: 0.00419709 | R73: 0.00421598 | S73: 0.0042051 | T73: 0.00420658 | U73: 0.00421842 | V73: 0.00419712 | W73: 0.00421605 | X73: 0.00420508 | Y73: 0.00420679 | Z73: 0.00421846 | AA73: 0.00419713 | AB73: 0.00421648 | AC73: 0.00420526 | AD73: 0.00420706 | AE73: 0.00421844 | AF73: 0.00419709 | AG73: 0.00421667 | AH73: 0.00420514 | AI73: 0.00420721

Sheet beta (2)
B1: beta3*0.1 (optimal) | C1: beta3*0.5 (optimal) | D1: beta3*1 (optimal) | E1: beta3*1.5 (optimal) | F1: beta3*2 | K1: beta3*0.1 | Q1: beta3*0.5 | V1: beta3*1 (base) | AA1: beta3*1.5 | AE1: beta3*2 | AK1: beta3*0.5 | AL1: beta3*1 (base) | AM1: beta3*1.5 | AO1: beta3*0.5 | AP1: beta3*1 (base) | AQ1: beta3*1.5 | AS1: beta3*0.5 | AT1: beta3*1 (base) | AU1: beta3*1.5 | AW1: beta3*0.5 | AX1: beta3*1 (base) | AY1: beta3*1.5
A2: Vaccination costs | B2: =O3 -> 2.65 | C2: =T3 -> 2.65 | D2: =Y3 -> 2.45 | E2: =AD3 -> 2.69 | F2: =AI3 -> 2.73 | K2: Type no vacc constant vacc actual vacc opt vacc | Q2: no vacc | R2: constant vacc | S2: actual vacc | T2: opt vacc | V2: no vacc | W2: constant vacc | X2: actual vacc | Y2: opt vacc | AA2: no vacc | AB2: constant vacc | AC2: actual vacc | AD2: opt vacc | AE2: Type no vacc constant vacc actual vacc opt vacc | AK2: no vacc | AO2: constant vacc | AS2: actual vacc | AW2: opt vacc
A3: Quarantine costs | B3: =O4 -> 0.66 | C3: =T4 -> 0.87 | D3: =Y4 -> 1.3 | E3: =AD4 -> 2.15 | F3: =AI4 -> 1.31 | K3: Vaccination costs | L3: 0 | M3: 1.71 | N3: 1.96 | O3: 2.65 | P3: Vaccination costs | Q3: 0 | R3: 1.71 | S3: 1.96 | T3: 2.65 | U3: Vaccination costs | V3: 0 | W3: 1.71 | X3: 1.96 | Y3: 2.45 | Z3: Vaccination costs | AA3: 0 | AB3: 1.71 | AC3: 1.96 | AD3: 2.69 | AE3: Vaccination costs | AF3: 0 | AG3: 1.71 | AH3: 1.96 | AI3: 2.73 | AK3: =Q3 -> 0 | AL3: =V3 -> 0 | AM3: =AA3 -> 0 | AO3: =R3 -> 1.71 | AP3: =W3 -> 1.71 | AQ3: =AB3 -> 1.71 | AS3: =S3 -> 1.96 | AT3: =OFFSET(S3,0,5) -> 1.96 | AU3: =OFFSET(S3,0,10) -> 1.96 | AW3: =T3 -> 2.65 | AX3: =OFFSET(T3,0,5) -> 2.45 | AY3: =OFFSET(T3,0,10) -> 2.69
A4: Healthcare costs | B4: =O5 -> 2.77 | C4: =T5 -> 3.4 | D4: =Y5 -> 4.72 | E4: =AD5 -> 7.3 | F4: =AI5 -> 4.75 | K4: Quarantine costs | L4: 0.67 | M4: 0.66 | N4: 0.66 | O4: 0.66 | P4: Quarantine costs | Q4: 0.92 | R4: 0.88 | S4: 0.89 | T4: 0.87 | U4: Quarantine costs | V4: 1.66 | W4: 1.37 | X4: 1.39 | Y4: 1.3 | Z4: Quarantine costs | AA4: 4.5 | AB4: 2.54 | AC4: 2.52 | AD4: 2.15 | AE4: Quarantine costs | AF4: 1.51 | AG4: 1.36 | AH4: 1.38 | AI4: 1.31 | AK4: =Q4 -> 0.92 | AL4: =V4 -> 1.66 | AM4: =AA4 -> 4.5 | AO4: =R4 -> 0.88 | AP4: =W4 -> 1.37 | AQ4: =AB4 -> 2.54 | AS4: =S4 -> 0.89 | AT4: =OFFSET(S4,0,5) -> 1.39 | AU4: =OFFSET(S4,0,10) -> 2.52 | AW4: =T4 -> 0.87 | AX4: =OFFSET(T4,0,5) -> 1.3 | AY4: =OFFSET(T4,0,10) -> 2.15
A5: Economic productivity loss | B5: =O6 -> 11.67 | C5: =T6 -> 14.91 | D5: =Y6 -> 21.62 | E5: =AD6 -> 34.85 | F5: =AI6 -> 21.82 | K5: Healthcare costs | L5: 4.53 | M5: 4.51 | N5: 2.93 | O5: 2.77 | P5: Healthcare costs | Q5: 5.85 | R5: 5.64 | S5: 3.64 | T5: 3.4 | U5: Healthcare costs | V5: 9.5 | W5: 8.13 | X5: 5.21 | Y5: 4.72 | Z5: Healthcare costs | AA5: 21.96 | AB5: 13.78 | AC5: 8.67 | AD5: 7.3 | AE5: Healthcare costs | AF5: 8.83 | AG5: 8.06 | AH5: 5.17 | AI5: 4.75 | AK5: =Q5 -> 5.85 | AL5: =V5 -> 9.5 | AM5: =AA5 -> 21.96 | AO5: =R5 -> 5.64 | AP5: =W5 -> 8.13 | AQ5: =AB5 -> 13.78 | AS5: =S5 -> 3.64 | AT5: =OFFSET(S5,0,5) -> 5.21 | AU5: =OFFSET(S5,0,10) -> 8.67 | AW5: =T5 -> 3.4 | AX5: =OFFSET(T5,0,5) -> 4.72 | AY5: =OFFSET(T5,0,10) -> 7.3
A6: Total cost | B6: =O7 -> 17.75 | C6: =T7 -> 21.82 | D6: =Y7 -> 30.08 | E6: =AD7 -> 46.98 | F6: =AI7 -> 30.61 | K6: Economic productivity loss | L6: 11.91 | M6: 11.84 | N6: 11.72 | O6: 11.67 | P6: Economic productivity loss | Q6: 15.98 | R6: 15.31 | S6: 15.26 | T6: 14.91 | U6: Economic productivity loss | V6: 27.56 | W6: 23.07 | X6: 23.09 | Y6: 21.62 | Z6: Economic productivity loss | AA6: 70.66 | AB6: 41.27 | AC6: 40.61 | AD6: 34.85 | AE6: Economic productivity loss | AF6: 25.28 | AG6: 22.83 | AH6: 22.93 | AI6: 21.82 | AK6: =Q6 -> 15.98 | AL6: =V6 -> 27.56 | AM6: =AA6 -> 70.66 | AO6: =R6 -> 15.31 | AP6: =W6 -> 23.07 | AQ6: =AB6 -> 41.27 | AS6: =S6 -> 15.26 | AT6: =OFFSET(S6,0,5) -> 23.09 | AU6: =OFFSET(S6,0,10) -> 40.61 | AW6: =T6 -> 14.91 | AX6: =OFFSET(T6,0,5) -> 21.62 | AY6: =OFFSET(T6,0,10) -> 34.85
K7: Total cost | L7: 17.11 | M7: 18.73 | N7: 17.27 | O7: 17.75 | P7: Total cost | Q7: 22.76 | R7: 23.54 | S7: 21.74 | T7: 21.82 | U7: Total cost | V7: 38.72 | W7: 34.28 | X7: 31.65 | Y7: 30.08 | Z7: Total cost | AA7: 97.11 | AB7: 59.3 | AC7: 53.75 | AD7: 46.98 | AE7: Total cost | AF7: 35.62 | AG7: 33.96 | AH7: 31.43 | AI7: 30.61 | AK7: No Vacc beta3*0.5 | AL7: No vacc beta3*1 (base) | AM7: No vacc beta3*1.5 | AO7: Const Vacc beta3*0.5 | AP7: Const Vacc beta3*1 (base) | AQ7: Const Vacc beta3*1.5 | AS7: Actual Vacc beta3*0.5 | AT7: Actual Vacc beta3*1 (base) | AU7: Actual Vacc beta3*1.5 | AW7: beta3*0.5 | AX7: beta3*1 (base) | AY7: beta3*1.5
K9: Vaccination costs | L9: =1-$T3/L3 -> #DIV/0! | M9: =1-$T3/M3 -> -0.5497076 | N9: =1-$T3/N3 -> -0.35204082 | P9: Hosp Cost Savings | Q9: =1-$T3/Q3 -> #DIV/0! | R9: =1-$T3/R3 -> -0.5497076 | S9: =1-$T3/S3 -> -0.35204082 | V9: =1-$Y3/V3 -> #DIV/0! | W9: =1-$Y3/W3 -> -0.43274854 | X9: =1-$Y3/X3 -> -0.25 | AA9: =1-$AD3/AA3 -> #DIV/0! | AB9: =1-$AD3/AB3 -> -0.57309942 | AC9: =1-$AD3/AC3 -> -0.37244898 | AJ9: Vaccination costs | AK9: =Q9 -> #DIV/0! | AL9: =V9 -> #DIV/0! | AM9: =AA9 -> #DIV/0! | AO9: =R9 -> -0.5497076 | AP9: =W9 -> -0.43274854 | AQ9: =AB9 -> -0.57309942 | AS9: =S9 -> -0.35204082 | AT9: =OFFSET(S9,0,5) -> -0.25 | AU9: =OFFSET(S9,0,10) -> -0.37244898 | AW9: =T9 -> 0 | AX9: =OFFSET(T9,0,5) -> 0 | AY9: =OFFSET(T9,0,10) -> 0
K10: Quarantine costs | L10: =1-$T4/L4 -> -0.29850746 | M10: =1-$T4/M4 -> -0.31818182 | N10: =1-$T4/N4 -> -0.31818182 | P10: Policy Cost Savings | Q10: =1-$T4/Q4 -> 0.054347826 | R10: =1-$T4/R4 -> 0.011363636 | S10: =1-$T4/S4 -> 0.02247191 | V10: =1-$Y4/V4 -> 0.21686747 | W10: =1-$Y4/W4 -> 0.051094891 | X10: =1-$Y4/X4 -> 0.064748201 | AA10: =1-$AD4/AA4 -> 0.52222222 | AB10: =1-$AD4/AB4 -> 0.15354331 | AC10: =1-$AD4/AC4 -> 0.1468254 | AJ10: Quarantine costs | AK10: =Q10 -> 0.054347826 | AL10: =V10 -> 0.21686747 | AM10: =AA10 -> 0.52222222 | AO10: =R10 -> 0.011363636 | AP10: =W10 -> 0.051094891 | AQ10: =AB10 -> 0.15354331 | AS10: =S10 -> 0.02247191 | AT10: =OFFSET(S10,0,5) -> 0.064748201 | AU10: =OFFSET(S10,0,10) -> 0.1468254 | AW10: =T10 -> 0 | AX10: =OFFSET(T10,0,5) -> 0 | AY10: =OFFSET(T10,0,10) -> 0
K11: Healthcare costs | L11: =1-$T5/L5 -> 0.24944812 | M11: =1-$T5/M5 -> 0.24611973 | N11: =1-$T5/N5 -> -0.16040956 | P11: Econ Cost Savings | Q11: =1-$T5/Q5 -> 0.41880342 | R11: =1-$T5/R5 -> 0.39716312 | S11: =1-$T5/S5 -> 0.065934066 | V11: =1-$Y5/V5 -> 0.50315789 | W11: =1-$Y5/W5 -> 0.41943419 | X11: =1-$Y5/X5 -> 0.094049904 | AA11: =1-$AD5/AA5 -> 0.66757741 | AB11: =1-$AD5/AB5 -> 0.47024673 | AC11: =1-$AD5/AC5 -> 0.15801615 | AJ11: Healthcare costs | AK11: =Q11 -> 0.41880342 | AL11: =V11 -> 0.50315789 | AM11: =AA11 -> 0.66757741 | AO11: =R11 -> 0.39716312 | AP11: =W11 -> 0.41943419 | AQ11: =AB11 -> 0.47024673 | AS11: =S11 -> 0.065934066 | AT11: =OFFSET(S11,0,5) -> 0.094049904 | AU11: =OFFSET(S11,0,10) -> 0.15801615 | AW11: =T11 -> 0 | AX11: =OFFSET(T11,0,5) -> 0 | AY11: =OFFSET(T11,0,10) -> 0
K12: Economic productivity loss | L12: =1-$T6/L6 -> -0.25188917 | M12: =1-$T6/M6 -> -0.25929054 | N12: =1-$T6/N6 -> -0.2721843 | P12: Total Cost Savings | Q12: =1-$T6/Q6 -> 0.066958698 | R12: =1-$T6/R6 -> 0.026126715 | S12: =1-$T6/S6 -> 0.02293578 | V12: =1-$Y6/V6 -> 0.21552975 | W12: =1-$Y6/W6 -> 0.062852189 | X12: =1-$Y6/X6 -> 0.063663924 | AA12: =1-$AD6/AA6 -> 0.50679309 | AB12: =1-$AD6/AB6 -> 0.15556094 | AC12: =1-$AD6/AC6 -> 0.14183699 | AJ12: Economic productivity loss
K13: Total cost | L13: =1-$T7/L7 -> -0.27527762 | M13: =1-$T7/M7 -> -0.16497597 | N13: =1-$T7/N7 -> -0.26346265 | P13: Total Cost Savings | Q13: =1-$T7/Q7 -> 0.041300527 | R13: =1-$T7/R7 -> 0.07306712 | S13: =1-$T7/S7 -> -0.0036798528 | V13: =1-$Y7/V7 -> 0.2231405 | W13: =1-$Y7/W7 -> 0.12252042 | X13: =1-$Y7/X7 -> 0.049605055 | AA13: =1-$AD7/AA7 -> 0.51621872 | AB13: =1-$AD7/AB7 -> 0.20775717 | AC13: =1-$AD7/AC7 -> 0.12595349
K15: Vaccination Savings | L15: =L3-$O3 -> -2.65 | M15: =M3-$O3 -> -0.94 | N15: =N3-$O3 -> -0.69 | O15: =SUM(M15:M16) -> -0.94 | P15: Vaccination Savings | Q15: =Q3-$T3 -> -2.65 | R15: =R3-$T3 -> -0.94 | S15: =S3-$T3 -> -0.69 | T15: =SUM(R15:R16) -> -0.93 | V15: =V3-$Y3 -> -2.45 | W15: =W3-$Y3 -> -0.74 | X15: =X3-$Y3 -> -0.49 | Y15: =SUM(W15:W16) -> -0.67 | AA15: =AA3-$AD3 -> -2.69 | AB15: =AB3-$AD3 -> -0.98 | AC15: =AC3-$AD3 -> -0.73 | AD15: =SUM(AB15:AB16) -> -0.59
K16: Quarantine Savings | L16: =L4-$O4 -> 0.01 | M16: =M4-$O4 -> 0 | N16: =N4-$O4 -> 0 | P16: Quarantine Savings | Q16: =Q4-$T4 -> 0.05 | R16: =R4-$T4 -> 0.01 | S16: =S4-$T4 -> 0.02 | V16: =V4-$Y4 -> 0.36 | W16: =W4-$Y4 -> 0.07 | X16: =X4-$Y4 -> 0.09 | AA16: =AA4-$AD4 -> 2.35 | AB16: =AB4-$AD4 -> 0.39 | AC16: =AC4-$AD4 -> 0.37
K17: Healthcare Savings | L17: =L5-$O5 -> 1.76 | M17: =M5-$O5 -> 1.74 | N17: =N5-$O5 -> 0.16 | P17: Healthcare Savings | Q17: =Q5-$T5 -> 2.45 | R17: =R5-$T5 -> 2.24 | S17: =S5-$T5 -> 0.24 | V17: =V5-$Y5 -> 4.78 | W17: =W5-$Y5 -> 3.41 | X17: =X5-$Y5 -> 0.49 | AA17: =AA5-$AD5 -> 14.66 | AB17: =AB5-$AD5 -> 6.48 | AC17: =AC5-$AD5 -> 1.37
K18: Economic Savings | L18: =L6-$O6 -> 0.24 | M18: =M6-$O6 -> 0.17 | N18: =N6-$O6 -> 0.05 | P18: Economic Savings | Q18: =Q6-$T6 -> 1.07 | R18: =R6-$T6 -> 0.4 | S18: =S6-$T6 -> 0.35 | V18: =V6-$Y6 -> 5.94 | W18: =W6-$Y6 -> 1.45 | X18: =X6-$Y6 -> 1.47 | AA18: =AA6-$AD6 -> 35.81 | AB18: =AB6-$AD6 -> 6.42 | AC18: =AC6-$AD6 -> 5.76
K19: total | L19: =L7-$O7 -> -0.64 | M19: =M7-$O7 -> 0.98 | N19: =N7-$O7 -> -0.48 | Q19: =Q7-$T7 -> 0.94 | R19: =R7-$T7 -> 1.72 | S19: =S7-$T7 -> -0.08 | V19: =V7-$Y7 -> 8.64 | W19: =W7-$Y7 -> 4.2 | X19: =X7-$Y7 -> 1.57 | AA19: =AA7-$AD7 -> 50.13 | AB19: =AB7-$AD7 -> 12.32 | AC19: =AC7-$AD7 -> 6.77
B20: beta3*0.1 | C20: beta3*0.5 | D20: beta3*1 (base) | E20: beta3*1.5 | F20: beta3*2 | K20: beta3*0.1 | P20: beta3*0.5 | U20: base case | Z20: beta3*1.5 | AE20: beta3*2
B21: =AVERAGE(K21:O21) -> 0.02778454 | C21: =AVERAGE(P21:T21) -> 0.02778464 | D21: =AVERAGE(U21:Y21) -> 0.02778504 | E21: =AVERAGE(Z21:AD21) -> 0.02778596 | F21: =AVERAGE(AE21:AI21) -> 0.02778812 | G21: =ROUND(D21,4)&"," -> 0.0278, | K21: 0.0277941 | L21: 0.027768 | M21: 0.0277918 | N21: 0.0277793 | O21: 0.0277895 | P21: 0.0277942 | Q21: 0.0277681 | R21: 0.0277919 | S21: 0.0277794 | T21: 0.0277896 | U21: 0.0277946 | V21: 0.0277686 | W21: 0.0277924 | X21: 0.0277797 | Y21: 0.0277899 | Z21: 0.0277955 | AA21: 0.0277695 | AB21: 0.0277935 | AC21: 0.0277807 | AD21: 0.0277906 | AE21: 0.0277975 | AF21: 0.027772 | AG21: 0.0277959 | AH21: 0.0277832 | AI21: 0.027792
B22: =AVERAGE(K22:O22) -> 0.02778724 | C22: =AVERAGE(P22:T22) -> 0.0277873 | D22: =AVERAGE(U22:Y22) -> 0.02778774 | E22: =AVERAGE(Z22:AD22) -> 0.02778898 | F22: =AVERAGE(AE22:AI22) -> 0.02779178 | G22: =ROUND(D22,4)&"," -> 0.0278, | K22: 0.0277977 | L22: 0.027766 | M22: 0.0277998 | N22: 0.0277803 | O22: 0.0277924 | P22: 0.0277978 | Q22: 0.027766 | R22: 0.0277999 | S22: 0.0277804 | T22: 0.0277924 | U22: 0.0277982 | V22: 0.0277666 | W22: 0.0278003 | X22: 0.0277808 | Y22: 0.0277928 | Z22: 0.0277995 | AA22: 0.0277677 | AB22: 0.0278017 | AC22: 0.0277822 | AD22: 0.0277938 | AE22: 0.0278022 | AF22: 0.0277709 | AG22: 0.0278046 | AH22: 0.0277854 | AI22: 0.0277958
B23: =AVERAGE(K23:O23) -> 0.02777704 | C23: =AVERAGE(P23:T23) -> 0.02777714 | D23: =AVERAGE(U23:Y23) -> 0.02777764 | E23: =AVERAGE(Z23:AD23) -> 0.02777906 | F23: =AVERAGE(AE23:AI23) -> 0.02778234 | G23: =ROUND(D23,4)&"," -> 0.0278, | K23: 0.0277859 | L23: 0.0277572 | M23: 0.0277903 | N23: 0.0277708 | O23: 0.027781 | P23: 0.027786 | Q23: 0.0277572 | R23: 0.0277905 | S23: 0.0277709 | T23: 0.0277811 | U23: 0.0277864 | V23: 0.0277577 | W23: 0.0277911 | X23: 0.0277714 | Y23: 0.0277816 | Z23: 0.0277875 | AA23: 0.0277591 | AB23: 0.027793 | AC23: 0.0277729 | AD23: 0.0277828 | AE23: 0.0277903 | AF23: 0.0277627 | AG23: 0.0277971 | AH23: 0.0277764 | AI23: 0.0277852
B24: =AVERAGE(K24:O24) -> 0.02776744 | C24: =AVERAGE(P24:T24) -> 0.02776746 | D24: =AVERAGE(U24:Y24) -> 0.02776806 | E24: =AVERAGE(Z24:AD24) -> 0.02776996 | F24: =AVERAGE(AE24:AI24) -> 0.0277742 | G24: =ROUND(D24,4)&"," -> 0.0278, | K24: 0.0277765 | L24: 0.0277453 | M24: 0.0277827 | N24: 0.0277583 | O24: 0.0277744 | P24: 0.0277766 | Q24: 0.0277452 | R24: 0.0277828 | S24: 0.0277583 | T24: 0.0277744 | U24: 0.0277772 | V24: 0.0277457 | W24: 0.0277835 | X24: 0.0277589 | Y24: 0.027775 | Z24: 0.0277789 | AA24: 0.0277474 | AB24: 0.0277858 | AC24: 0.027761 | AD24: 0.0277767 | AE24: 0.0277827 | AF24: 0.0277517 | AG24: 0.027791 | AH24: 0.0277656 | AI24: 0.02778
B25: =AVERAGE(K25:O25) -> 0.02775416 | C25: =AVERAGE(P25:T25) -> 0.0277542 | D25: =AVERAGE(U25:Y25) -> 0.02775492 | E25: =AVERAGE(Z25:AD25) -> 0.027757 | F25: =AVERAGE(AE25:AI25) -> 0.02776186 | G25: =ROUND(D25,4)&"," -> 0.0278, | K25: 0.0277634 | L25: 0.0277347 | M25: 0.0277707 | N25: 0.0277418 | O25: 0.0277602 | P25: 0.0277633 | Q25: 0.0277346 | R25: 0.0277708 | S25: 0.0277418 | T25: 0.0277605 | U25: 0.0277638 | V25: 0.0277353 | W25: 0.0277716 | X25: 0.0277424 | Y25: 0.0277615 | Z25: 0.0277655 | AA25: 0.0277372 | AB25: 0.0277742 | AC25: 0.0277444 | AD25: 0.0277637 | AE25: 0.0277697 | AF25: 0.0277423 | AG25: 0.02778 | AH25: 0.0277494 | AI25: 0.0277679
B26: =AVERAGE(K26:O26) -> 0.0277375 | C26: =AVERAGE(P26:T26) -> 0.02773754 | D26: =AVERAGE(U26:Y26) -> 0.02773842 | E26: =AVERAGE(Z26:AD26) -> 0.02774102 | F26: =AVERAGE(AE26:AI26) -> 0.0277468 | G26: =ROUND(D26,4)&"," -> 0.0277, | K26: 0.027751 | L26: 0.0277116 | M26: 0.0277595 | N26: 0.0277232 | O26: 0.0277422 | P26: 0.027751 | Q26: 0.0277115 | R26: 0.0277592 | S26: 0.0277234 | T26: 0.0277426 | U26: 0.0277518 | V26: 0.0277123 | W26: 0.0277599 | X26: 0.0277247 | Y26: 0.0277434 | Z26: 0.0277542 | AA26: 0.0277152 | AB26: 0.0277627 | AC26: 0.0277275 | AD26: 0.0277455 | AE26: 0.0277596 | AF26: 0.0277219 | AG26: 0.0277686 | AH26: 0.0277341 | AI26: 0.0277498
B27: =AVERAGE(K27:O27) -> 0.02771642 | C27: =AVERAGE(P27:T27) -> 0.02771676 | D27: =AVERAGE(U27:Y27) -> 0.02771784 | E27: =AVERAGE(Z27:AD27) -> 0.02772066 | F27: =AVERAGE(AE27:AI27) -> 0.02772786 | G27: =ROUND(D27,4)&"," -> 0.0277, | K27: 0.0277277 | L27: 0.027693 | M27: 0.0277355 | N27: 0.0277005 | O27: 0.0277254 | P27: 0.0277276 | Q27: 0.0276937 | R27: 0.0277357 | S27: 0.0277006 | T27: 0.0277262 | U27: 0.0277288 | V27: 0.0276953 | W27: 0.0277367 | X27: 0.027702 | Y27: 0.0277264 | Z27: 0.0277319 | AA27: 0.0276988 | AB27: 0.0277406 | AC27: 0.0277057 | AD27: 0.0277263 | AE27: 0.0277385 | AF27: 0.0277059 | AG27: 0.0277486 | AH27: 0.027714 | AI27: 0.0277323
B28: =AVERAGE(K28:O28) -> 0.027693 | C28: =AVERAGE(P28:T28) -> 0.0276933 | D28: =AVERAGE(U28:Y28) -> 0.0276945 | E28: =AVERAGE(Z28:AD28) -> 0.02769838 | F28: =AVERAGE(AE28:AI28) -> 0.02770722 | G28: =ROUND(D28,4)&"," -> 0.0277, | K28: 0.0277003 | L28: 0.0276694 | M28: 0.027722 | N28: 0.027676 | O28: 0.0276973 | P28: 0.0277006 | Q28: 0.0276693 | R28: 0.0277222 | S28: 0.0276762 | T28: 0.0276982 | U28: 0.0277015 | V28: 0.0276707 | W28: 0.0277235 | X28: 0.0276778 | Y28: 0.027699 | Z28: 0.0277049 | AA28: 0.0276751 | AB28: 0.0277278 | AC28: 0.0276819 | AD28: 0.0277022 | AE28: 0.0277138 | AF28: 0.0276843 | AG28: 0.0277366 | AH28: 0.0276918 | AI28: 0.0277096
B29: =AVERAGE(K29:O29) -> 0.02766124 | C29: =AVERAGE(P29:T29) -> 0.02766256 | D29: =AVERAGE(U29:Y29) -> 0.0276657 | E29: =AVERAGE(Z29:AD29) -> 0.02767164 | F29: =AVERAGE(AE29:AI29) -> 0.02768246 | G29: =ROUND(D29,4)&"," -> 0.0277, | K29: 0.0276527 | L29: 0.0276545 | M29: 0.0277033 | N29: 0.0276415 | O29: 0.0276542 | P29: 0.0276562 | Q29: 0.0276549 | R29: 0.0277029 | S29: 0.0276421 | T29: 0.0276567 | U29: 0.0276604 | V29: 0.0276556 | W29: 0.0277047 | X29: 0.0276448 | Y29: 0.027663 | Z29: 0.0276661 | AA29: 0.0276592 | AB29: 0.0277099 | AC29: 0.0276518 | AD29: 0.0276712 | AE29: 0.0276766 | AF29: 0.027668 | AG29: 0.0277198 | AH29: 0.0276647 | AI29: 0.0276832
B30: =AVERAGE(K30:O30) -> 0.0276113 | C30: =AVERAGE(P30:T30) -> 0.02761252 | D30: =AVERAGE(U30:Y30) -> 0.02761574 | E30: =AVERAGE(Z30:AD30) -> 0.02762238 | F30: =AVERAGE(AE30:AI30) -> 0.02763474 | G30: =ROUND(D30,4)&"," -> 0.0276, | K30: 0.0276279 | L30: 0.0276045 | M30: 0.027654 | N30: 0.027581 | O30: 0.0275891 | P30: 0.0276355 | Q30: 0.0276042 | R30: 0.0276554 | S30: 0.0275797 | T30: 0.0275878 | U30: 0.0276388 | V30: 0.0276058 | W30: 0.0276569 | X30: 0.0275826 | Y30: 0.0275946 | Z30: 0.0276442 | AA30: 0.0276125 | AB30: 0.027663 | AC30: 0.0275908 | AD30: 0.0276014 | AE30: 0.0276566 | AF30: 0.0276252 | AG30: 0.0276729 | AH30: 0.0276048 | AI30: 0.0276142
B31: =AVERAGE(K31:O31) -> 0.02754682 | C31: =AVERAGE(P31:T31) -> 0.02754498 | D31: =AVERAGE(U31:Y31) -> 0.0275478 | E31: =AVERAGE(Z31:AD31) -> 0.02755468 | F31: =AVERAGE(AE31:AI31) -> 0.02755984 | G31: =ROUND(D31,4)&"," -> 0.0275, | K31: 0.0275414 | L31: 0.0275412 | M31: 0.0275576 | N31: 0.0275367 | O31: 0.0275572 | P31: 0.0275529 | Q31: 0.027539 | R31: 0.0275339 | S31: 0.0275362 | T31: 0.0275629 | U31: 0.0275643 | V31: 0.0275391 | W31: 0.02754 | X31: 0.02754 | Y31: 0.0275556 | Z31: 0.0275785 | AA31: 0.0275451 | AB31: 0.0275444 | AC31: 0.0275444 | AD31: 0.027561 | AE31: 0.0275934 | AF31: 0.0275508 | AG31: 0.0275284 | AH31: 0.0275543 | AI31: 0.0275723
B32: =AVERAGE(K32:O32) -> 0.02748582 | C32: =AVERAGE(P32:T32) -> 0.0274905 | D32: =AVERAGE(U32:Y32) -> 0.0274928 | E32: =AVERAGE(Z32:AD32) -> 0.0275014 | F32: =AVERAGE(AE32:AI32) -> 0.02751548 | G32: =ROUND(D32,4)&"," -> 0.0275, | K32: 0.027536 | L32: 0.0274512 | M32: 0.0275601 | N32: 0.0274582 | O32: 0.0274236 | P32: 0.0275364 | Q32: 0.0274507 | R32: 0.0275593 | S32: 0.0274589 | T32: 0.0274472 | U32: 0.0275381 | V32: 0.0274522 | W32: 0.0275633 | X32: 0.0274556 | Y32: 0.0274548 | Z32: 0.0275465 | AA32: 0.0274532 | AB32: 0.0275747 | AC32: 0.0274752 | AD32: 0.0274574 | AE32: 0.0275679 | AF32: 0.0274436 | AG32: 0.0275959 | AH32: 0.0274941 | AI32: 0.0274759
... B80: =AVERAGE(K80:O80) -> 0.004208606 | C80: =AVERAGE(P80:T80) -> 0.004208618 | D80: =AVERAGE(U80:Y80) -> 0.004208692 | E80: =AVERAGE(Z80:AD80) -> 0.004208878 | F80: =AVERAGE(AE80:AI80) -> 0.00420891 | G80: =ROUND(D80,4)&"," -> 0.0042, | K80: 0.00421832 | L80: 0.00419708 | M80: 0.00421592 | N80: 0.00420515 | O80: 0.00420656 | P80: 0.00421834 | Q80: 0.00419709 | R80: 0.00421598 | S80: 0.0042051 | T80: 0.00420658 | U80: 0.00421842 | V80: 0.00419712 | W80: 0.00421605 | X80: 0.00420508 | Y80: 0.00420679 | Z80: 0.00421846 | AA80: 0.00419713 | AB80: 0.00421648 | AC80: 0.00420526 | AD80: 0.00420706 | AE80: 0.00421844 | AF80: 0.00419709 | AG80: 0.00421667 | AH80: 0.00420514 | AI80: 0.00420721

Sheet noise
B1: noise*0.01 | C1: noise*0.1 | D1: noise*0.5 | E1: noise*1 (base) | F1: noise*1.5 | G1: noise*2 | L1: noise*0.01 | R1: noise*0.1 | X1: noise*0.5 | AD1: noise*1 | AJ1: noise*1.5 | AP1: noise*2 | AV1: noise*0.01 | AW1: noise*0.1 | AX1: noise*0.5 | AY1: noise*1 (base) | AZ1: noise*1.5 | BB1: noise*0.01 | BC1: noise*0.1 | BD1: noise*0.5 | BE1: noise*1 (base) | BF1: noise*1.5 | BH1: noise*0.01 | BI1: noise*0.1 | BJ1: noise*0.5 | BK1: noise*1 (base) | BL1: noise*1.5 | BN1: noise*0.01 | BO1: noise*0.1 | BP1: noise*0.5 | BQ1: noise*1 (base) | BR1: noise*1.5
A2: Hosp Cost | B2: =P3 -> 4.828255 | C2: =V3 -> 4.787181 | D2: =AB3 -> 5.205544 | E2: =AH3 -> 5.610668 | F2: =AN3 -> 5.693924 | G2: 5.489056 | L2: Type | M2: no vacc | N2: constant vacc | O2: actual vacc | P2: opt vacc | S2: no vacc | T2: constant vacc | U2: actual vacc | V2: opt vacc | Y2: no vacc | Z2: constant vacc | AA2: actual vacc | AB2: opt vacc | AE2: no vacc | AF2: constant vacc | AG2: actual vacc | AH2: opt vacc | AK2: no vacc | AL2: constant vacc | AM2: actual vacc | AN2: opt vacc | AP2: Type no vacc constant vacc actual vacc opt vacc | AV2: no vacc | BB2: opt vacc | BH2: constant vacc | BN2: actual vacc
A3: Policy Cost | B3: =P4 -> 2.694067 | C3: =V4 -> 3.492417 | D3: =AB4 -> 4.24506 | E3: =AH4 -> 4.513925 | F3: =AN4 -> 4.489997 | G3: 4.291327 | L3: Hosp Cost | M3: 8.210663 | N3: 7.317346 | O3: 5.121327 | P3: 4.828255 | S3: 8.54364 | T3: 7.526641 | U3: 5.256065 | V3: 4.787181 | Y3: 10.076467 | Z3: 8.426349 | AA3: 5.83347 | AB3: 5.205544 | AE3: 11.616842 | AF3: 9.249465 | AG3: 6.374409 | AH3: 5.610668 | AK3: 11.903364 | AL3: 9.373498 | AM3: 5.712317 | AN3: 5.693924 | AP3: 0 Hosp Cost 10.726177 8.679196 5.419329 5.489056 | AV3: =M3 -> 8.210663 | AW3: =S3 -> 8.54364 | AX3: =Y3 -> 10.076467 | AY3: =AE3 -> 11.616842 | AZ3: =AK3 -> 11.903364 | BB3: =P3 -> 4.828255 | BC3: =V3 -> 4.787181 | BD3: =AB3 -> 5.205544 | BE3: =AH3 -> 5.610668 | BF3: =AN3 -> 5.693924 | BH3: =N3 -> 7.317346 | BI3: =T3 -> 7.526641 | BJ3: =Z3 -> 8.426349 | BK3: =AF3 -> 9.249465 | BL3: =AL3 -> 9.373498 | BN3: =O3 -> 5.121327 | BO3: =U3 -> 5.256065 | BP3: =AA3 -> 5.83347 | BQ3: =AG3 -> 6.374409 | BR3: =AM3 -> 5.712317
A4: Econ Cost | B4: =P5 -> 24.047899 | C4: =V5 -> 24.338728 | D4: =AB5 -> 26.669896 | E4: =AH5 -> 28.924867 | F4: =AN5 -> 29.585191 | G4: 28.571574 | L4: Policy Cost | M4: 1.802941 | N4: 2.52677 | O4: 3.501929 | P4: 2.694067 | S4: 1.887222 | T4: 2.579181 | U4: 3.548543 | V4: 3.492417 | Y4: 2.295589 | Z4: 2.818902 | AA4: 3.757776 | AB4: 4.24506 | AE4: 2.757488 | AF4: 3.077856 | AG4: 3.979546 | AH4: 4.513925 | AK4: 2.933683 | AL4: 3.190716 | AM4: 4.535116 | AN4: 4.489997 | AP4: 1 Policy Cost 2.733211 3.103286 4.480941 4.291327 | AV4: =M4 -> 1.802941 | AW4: =S4 -> 1.887222 | AX4: =Y4 -> 2.295589 | AY4: =AE4 -> 2.757488 | AZ4: =AK4 -> 2.933683 | BB4: =P4 -> 2.694067 | BC4: =V4 -> 3.492417 | BD4: =AB4 -> 4.24506 | BE4: =AH4 -> 4.513925 | BF4: =AN4 -> 4.489997 | BH4: =N4 -> 2.52677 | BI4: =T4 -> 2.579181 | BJ4: =Z4 -> 2.818902 | BK4: =AF4 -> 3.077856 | BL4: =AL4 -> 3.190716 | BN4: =O4 -> 3.501929 | BO4: =U4 -> 3.548543 | BP4: =AA4 -> 3.757776 | BQ4: =AG4 -> 3.979546 | BR4: =AM4 -> 4.535116
A5: Total Cost | B5: =P6 -> 31.57022 | C5: =V6 -> 32.618326 | D5: =AB6 -> 36.1205 | E5: =AH6 -> 39.049459 | F5: =AN6 -> 39.769112 | G5: =SUM(G2:G4) -> 38.351957 | L5: Econ Cost | M5: 29.206505 | N5: 25.819239 | O5: 25.133499 | P5: 24.047899 | S5: 30.463582 | T5: 26.60113 | U5: 25.823865 | V5: 24.338728 | Y5: 36.439637 | Z5: 30.092476 | AA5: 28.844291 | AB5: 26.669896 | AE5: 42.917935 | AF5: 33.642296 | AG5: 31.83938 | AH5: 28.924867 | AK5: 44.944349 | AL5: 34.827247 | AM5: 29.638188 | AN5: 29.585191 | AP5: 2 Econ Cost 41.358341 32.962939 28.344601 28.571574 | AV5: =M5 -> 29.206505 | AW5: =S5 -> 30.463582 | AX5: =Y5 -> 36.439637 | AY5: =AE5 -> 42.917935 | AZ5: =AK5 -> 44.944349 | BB5: =P5 -> 24.047899 | BC5: =V5 -> 24.338728 | BD5: =AB5 -> 26.669896 | BE5: =AH5 -> 28.924867 | BF5: =AN5 -> 29.585191 | BH5: =N5 -> 25.819239 | BI5: =T5 -> 26.60113 | BJ5: =Z5 -> 30.092476 | BK5: =AF5 -> 33.642296 | BL5: =AL5 -> 34.827247 | BN5: =O5 -> 25.133499 | BO5: =U5 -> 25.823865 | BP5: =AA5 -> 28.844291 | BQ5: =AG5 -> 31.83938 | BR5: =AM5 -> 29.638188
L6: Total Cost | M6: 39.220109 | N6: 35.663355 | O6: 33.756755 | P6: 31.57022 | S6: 40.894444 | T6: 36.706953 | U6: 34.628473 | V6: 32.618326 | Y6: 48.811693 | Z6: 41.337727 | AA6: 38.435538 | AB6: 36.1205 | AE6: 57.292265 | AF6: 45.969617 | AG6: 42.193335 | AH6: 39.049459 | AK6: 59.781397 | AL6: 47.391462 | AM6: 39.885621 | AN6: 39.769112 | AP6: 3 Total Cost 54.817729 44.745420 38.244872 38.351957 | AV6: =M6 -> 39.220109 | AW6: =S6 -> 40.894444 | AX6: =Y6 -> 48.811693 | AY6: =AE6 -> 57.292265 | AZ6: =AK6 -> 59.781397 | BB6: =P6 -> 31.57022 | BC6: =V6 -> 32.618326 | BD6: =AB6 -> 36.1205 | BE6: =AH6 -> 39.049459 | BF6: =AN6 -> 39.769112 | BH6: =N6 -> 35.663355 | BI6: =T6 -> 36.706953 | BJ6: =Z6 -> 41.337727 | BK6: =AF6 -> 45.969617 | BL6: =AL6 -> 47.391462 | BN6: =O6 -> 33.756755 | BO6: =U6 -> 34.628473 | BP6: =AA6 -> 38.435538 | BQ6: =AG6 -> 42.193335 | BR6: =AM6 -> 39.885621
L8: Hosp Cost Savings | M8: =1-$P3/M3 -> 0.41195309 | N8: =1-$P3/N3 -> 0.34016309 | O8: =1-$P3/O3 -> 0.057225793 | S8: =1-$V3/S3 -> 0.43967899 | T8: =1-$V3/T3 -> 0.36396847 | U8: =1-$V3/U3 -> 0.089208181 | Y8: =1-$V3/Y3 -> 0.52491473 | Z8: =1-$V3/Z3 -> 0.43187957 | AA8: =1-$V3/AA3 -> 0.17935963 | AE8: =1-$AH3/AE3 -> 0.51702296 | AF8: =1-$AH3/AF3 -> 0.39340621 | AG8: =1-$AH3/AG3 -> 0.11981362 | AK8: =1-$V3/AK3 -> 0.59782957 | AL8: =1-$V3/AL3 -> 0.48928554 | AM8: =1-$V3/AM3 -> 0.1619546
L9: Policy Cost Savings | M9: =1-$P4/M4 -> -0.49426243 | N9: =1-$P4/N4 -> -0.066209825 | O9: =1-$P4/O4 -> 0.23069057 | S9: =1-$V4/S4 -> -0.85055971 | T9: =1-$V4/T4 -> -0.35407984 | U9: =1-$V4/U4 -> 0.015816632 | Y9: =1-$V4/Y4 -> -0.52135988 | Z9: =1-$V4/Z4 -> -0.23892814 | AA9: =1-$V4/AA4 -> 0.070615971 | AE9: =1-$AH4/AE4 -> -0.63696995 | AF9: =1-$AH4/AF4 -> -0.46658096 | AG9: =1-$AH4/AG4 -> -0.1342814 | AK9: =1-$V4/AK4 -> -0.1904548 | AL9: =1-$V4/AL4 -> -0.094555893 | AM9: =1-$V4/AM4 -> 0.22991672
L10: Econ Cost Savings | M10: =1-$P5/M5 -> 0.17662524 | N10: =1-$P5/N5 -> 0.06860543 | O10: =1-$P5/O5 -> 0.043193349 | S10: =1-$V5/S5 -> 0.20105495 | T10: =1-$V5/T5 -> 0.085049094 | U10: =1-$V5/U5 -> 0.057510253 | Y10: =1-$V5/Y5 -> 0.33208094 | Z10: =1-$V5/Z5 -> 0.19120221 | AA10: =1-$V5/AA5 -> 0.15620294 | AE10: =1-$AH5/AE5 -> 0.32604243 | AF10: =1-$AH5/AF5 -> 0.14022316 | AG10: =1-$AH5/AG5 -> 0.091537995 | AK10: =1-$V5/AK5 -> 0.45846967 | AL10: =1-$V5/AL5 -> 0.30115843 | AM10: =1-$V5/AM5 -> 0.17880513
L11: Total Cost Savings | M11: =1-$P6/M6 -> 0.19505017 | N11: =1-$P6/N6 -> 0.11477145 | O11: =1-$P6/O6 -> 0.064773258 | S11: =1-$V6/S6 -> 0.20237757 | T11: =1-$V6/T6 -> 0.11138563 | U11: =1-$V6/U6 -> 0.058048965 | Y11: =1-$V6/Y6 -> 0.3317518 | Z11: =1-$V6/Z6 -> 0.21093083 | AA11: =1-$V6/AA6 -> 0.15134983 | AE11: =1-$AH6/AE6 -> 0.31841656 | AF11: =1-$AH6/AF6 -> 0.15053765 | AG11: =1-$AH6/AG6 -> 0.074511199 | AK11: =1-$V6/AK6 -> 0.45437331 | AL11: =1-$V6/AL6 -> 0.31172569 | AM11: =1-$V6/AM6 -> 0.18220338
B13: noise*0.01 | C13: noise*0.1 | D13: noise*0.5 | E13: noise*1 (base) | F13: noise*1.5 | G13: noise*2 | L13: noise*0.01 | R13: noise*0.1 | X13: noise*0.5 | AD13: noise*1 | AJ13: noise*1.5 | AP13: noise*2
B14: =AVERAGE(L14:P14) -> 0.02779742 | C14: =AVERAGE(R14:V14) -> 0.02777486 | D14: =AVERAGE(X14:AB14) -> 0.02777834 | E14: =AVERAGE(AD14:AH14) -> 0.02778504 | F14: =AVERAGE(AJ14:AN14) -> 0.0278049 | G14: =AVERAGE(AP14:AT14) -> 0.02749448 | H14: =ROUND(G14,4)&"," -> 0.0275, | L14: 0.0278055 | M14: 0.0277852 | N14: 0.0278048 | O14: 0.0277932 | P14: 0.0277984 | R14: 0.0277846 | S14: 0.0277575 | T14: 0.0277829 | U14: 0.0277683 | V14: 0.027781 | X14: 0.027788 | Y14: 0.0277611 | Z14: 0.027786 | AA14: 0.0277722 | AB14: 0.0277844 | AD14: 0.0277946 | AE14: 0.0277686 | AF14: 0.0277924 | AG14: 0.0277797 | AH14: 0.0277899 | AJ14: 0.0278028 | AK14: 0.0278217 | AL14: 0.0277861 | AM14: 0.0277889 | AN14: 0.027825 | AP14: 0.0262309 | AQ14: 0.0278266 | AR14: 0.027791 | AS14: 0.0277946 | AT14: 0.0278293
B15: =AVERAGE(L15:P15) -> 0.0278027 | C15: =AVERAGE(R15:V15) -> 0.02777754 | D15: =AVERAGE(X15:AB15) -> 0.02778068 | E15: =AVERAGE(AD15:AH15) -> 0.02778774 | F15: =AVERAGE(AJ15:AN15) -> 0.02780764 | G15: =AVERAGE(AP15:AT15) -> 0.02736572 | H15: =ROUND(G15,4)&"," -> 0.0274, | L15: 0.0278108 | M15: 0.027788 | N15: 0.0278138 | O15: 0.0277979 | P15: 0.027803 | R15: 0.0277875 | S15: 0.0277569 | T15: 0.0277888 | U15: 0.0277712 | V15: 0.0277833 | X15: 0.0277905 | Y15: 0.0277591 | Z15: 0.0277932 | AA15: 0.027774 | AB15: 0.0277866 | AD15: 0.0277982 | AE15: 0.0277666 | AF15: 0.0278003 | AG15: 0.0277808 | AH15: 0.0277928 | AJ15: 0.0278196 | AK15: 0.0278193 | AL15: 0.0277903 | AM15: 0.0277858 | AN15: 0.0278232 | AP15: 0.025598 | AQ15: 0.027822 | AR15: 0.0277932 | AS15: 0.027789 | AT15: 0.0278264
B16: =AVERAGE(L16:P16) -> 0.02779854 | C16: =AVERAGE(R16:V16) -> 0.02777098 | D16: =AVERAGE(X16:AB16) -> 0.02777138 | E16: =AVERAGE(AD16:AH16) -> 0.02777764 | F16: =AVERAGE(AJ16:AN16) -> 0.02779812 | G16: =AVERAGE(AP16:AT16) -> 0.02719176 | H16: =ROUND(G16,4)&"," -> 0.0272, | L16: 0.0278054 | M16: 0.0277839 | N16: 0.0278102 | O16: 0.0277954 | P16: 0.0277978 | R16: 0.0277779 | S16: 0.0277493 | T16: 0.0277872 | U16: 0.027765 | V16: 0.0277755 | X16: 0.0277792 | Y16: 0.027751 | Z16: 0.0277847 | AA16: 0.0277651 | AB16: 0.0277769 | AD16: 0.0277864 | AE16: 0.0277577 | AF16: 0.0277911 | AG16: 0.0277714 | AH16: 0.0277816 | AJ16: 0.027811 | AK16: 0.0278092 | AL16: 0.0277796 | AM16: 0.0277757 | AN16: 0.0278151 | AP16: 0.0247827 | AQ16: 0.0278074 | AR16: 0.0277781 | AS16: 0.027776 | AT16: 0.0278146
B17: =AVERAGE(L17:P17) -> 0.0277912 | C17: =AVERAGE(R17:V17) -> 0.0277612 | D17: =AVERAGE(X17:AB17) -> 0.02776214 | E17: =AVERAGE(AD17:AH17) -> 0.02776806 | F17: =AVERAGE(AJ17:AN17) -> 0.0277846 | G17: =AVERAGE(AP17:AT17) -> 0.02707814 | H17: =ROUND(G17,4)&"," -> 0.0271, | L17: 0.0277984 | M17: 0.0277759 | N17: 0.0278035 | O17: 0.0277864 | P17: 0.0277918 | R17: 0.0277679 | S17: 0.0277378 | T17: 0.0277774 | U17: 0.0277564 | V17: 0.0277665 | X17: 0.0277705 | Y17: 0.0277401 | Z17: 0.027776 | AA17: 0.0277534 | AB17: 0.0277707 | AD17: 0.0277772 | AE17: 0.0277457 | AF17: 0.0277835 | AG17: 0.0277589 | AH17: 0.027775 | AJ17: 0.027794 | AK17: 0.0277971 | AL17: 0.0277661 | AM17: 0.0277615 | AN17: 0.0278043 | AP17: 0.0243074 | AQ17: 0.02779 | AR17: 0.0277399 | AS17: 0.0277548 | AT17: 0.0277986
B18: =AVERAGE(L18:P18) -> 0.02778274 | C18: =AVERAGE(R18:V18) -> 0.02775168 | D18: =AVERAGE(X18:AB18) -> 0.02775104 | E18: =AVERAGE(AD18:AH18) -> 0.02775492 | F18: =AVERAGE(AJ18:AN18) -> 0.02776728 | G18: =AVERAGE(AP18:AT18) -> 0.0269496 | H18: =ROUND(G18,4)&"," -> 0.0269, | L18: 0.0277897 | M18: 0.0277637 | N18: 0.0277941 | O18: 0.0277832 | P18: 0.027783 | R18: 0.0277592 | S18: 0.0277287 | T18: 0.0277694 | U18: 0.0277406 | V18: 0.0277605 | X18: 0.0277589 | Y18: 0.0277317 | Z18: 0.0277663 | AA18: 0.0277386 | AB18: 0.0277597 | AD18: 0.0277638 | AE18: 0.0277353 | AF18: 0.0277716 | AG18: 0.0277424 | AH18: 0.0277615 | AJ18: 0.0277731 | AK18: 0.0277822 | AL18: 0.0277476 | AM18: 0.0277422 | AN18: 0.0277913 | AP18: 0.0237851 | AQ18: 0.0277657 | AR18: 0.0276997 | AS18: 0.0277243 | AT18: 0.0277732
B19: =AVERAGE(L19:P19) -> 0.02776766 | C19: =AVERAGE(R19:V19) -> 0.02773786 | D19: =AVERAGE(X19:AB19) -> 0.02773702 | E19: =AVERAGE(AD19:AH19) -> 0.02773842 | F19: =AVERAGE(AJ19:AN19) -> 0.0277484 | G19: =AVERAGE(AP19:AT19) -> 0.02705604 | H19: =ROUND(G19,4)&"," -> 0.0271, | L19: 0.0277767 | M19: 0.0277482 | N19: 0.0277816 | O19: 0.0277607 | P19: 0.0277711 | R19: 0.027749 | S19: 0.0277099 | T19: 0.0277603 | U19: 0.0277227 | V19: 0.0277474 | X19: 0.0277478 | Y19: 0.027711 | Z19: 0.0277573 | AA19: 0.0277243 | AB19: 0.0277447 | AD19: 0.0277518 | AE19: 0.0277123 | AF19: 0.0277599 | AG19: 0.0277247 | AH19: 0.0277434 | AJ19: 0.0277594 | AK19: 0.0277667 | AL19: 0.0277244 | AM19: 0.0277195 | AN19: 0.027772 | AP19: 0.0244529 | AQ19: 0.0277372 | AR19: 0.0276592 | AS19: 0.0276859 | AT19: 0.027745
B20: =AVERAGE(L20:P20) -> 0.02774682 | C20: =AVERAGE(R20:V20) -> 0.02772182 | D20: =AVERAGE(X20:AB20) -> 0.02771974 | E20: =AVERAGE(AD20:AH20) -> 0.02771784 | F20: =AVERAGE(AJ20:AN20) -> 0.0277212 | G20: =AVERAGE(AP20:AT20) -> 0.0269301 | H20: =ROUND(G20,4)&"," -> 0.0269, | L20: 0.0277559 | M20: 0.0277264 | N20: 0.0277605 | O20: 0.0277386 | P20: 0.0277527 | R20: 0.0277295 | S20: 0.0276987 | T20: 0.0277358 | U20: 0.0277072 | V20: 0.0277379 | X20: 0.0277297 | Y20: 0.0276968 | Z20: 0.0277343 | AA20: 0.027707 | AB20: 0.0277309 | AD20: 0.0277288 | AE20: 0.0276953 | AF20: 0.0277367 | AG20: 0.027702 | AH20: 0.0277264 | AJ20: 0.02771 | AK20: 0.0277499 | AL20: 0.0276993 | AM20: 0.0276863 | AN20: 0.0277605 | AP20: 0.0239655 | AQ20: 0.0277076 | AR20: 0.0276259 | AS20: 0.0276256 | AT20: 0.0277259
B21: =AVERAGE(L21:P21) -> 0.02771546 | C21: =AVERAGE(R21:V21) -> 0.02769806 | D21: =AVERAGE(X21:AB21) -> 0.02769994 | E21: =AVERAGE(AD21:AH21) -> 0.0276945 | F21: =AVERAGE(AJ21:AN21) -> 0.02766752 | G21: =AVERAGE(AP21:AT21) -> 0.0265423 | H21: =ROUND(G21,4)&"," -> 0.0265, | L21: 0.0277248 | M21: 0.0276914 | N21: 0.0277365 | O21: 0.0277047 | P21: 0.0277199 | R21: 0.02771 | S21: 0.0276725 | T21: 0.0277173 | U21: 0.0276854 | V21: 0.0277051 | X21: 0.0277074 | Y21: 0.0276767 | Z21: 0.0277211 | AA21: 0.0276861 | AB21: 0.0277084 | AD21: 0.0277015 | AE21: 0.0276707 | AF21: 0.0277235 | AG21: 0.0276778 | AH21: 0.027699 | AJ21: 0.0276763 | AK21: 0.0277223 | AL21: 0.0276449 | AM21: 0.0275684 | AN21: 0.0277257 | AP21: 0.0235044 | AQ21: 0.0276377 | AR21: 0.0272514 | AS21: 0.0266655 | AT21: 0.0276525
B22: =AVERAGE(L22:P22) -> 0.02765188 | C22: =AVERAGE(R22:V22) -> 0.02767666 | D22: =AVERAGE(X22:AB22) -> 0.02767904 | E22: =AVERAGE(AD22:AH22) -> 0.0276657 | F22: =AVERAGE(AJ22:AN22) -> 0.02760382 | G22: =AVERAGE(AP22:AT22) -> 0.02645062 | H22: =ROUND(G22,4)&"," -> 0.0265, | L22: 0.0276604 | M22: 0.0276192 | N22: 0.0276798 | O22: 0.0276407 | P22: 0.0276593 | R22: 0.0276745 | S22: 0.0276672 | T22: 0.0277039 | U22: 0.0276577 | V22: 0.02768 | X22: 0.0276812 | Y22: 0.0276718 | Z22: 0.0277085 | AA22: 0.0276535 | AB22: 0.0276802 | AD22: 0.0276604 | AE22: 0.0276556 | AF22: 0.0277047 | AG22: 0.0276448 | AH22: 0.027663 | AJ22: 0.0275354 | AK22: 0.0276776 | AL22: 0.0275701 | AM22: 0.0275485 | AN22: 0.0276875 | AP22: 0.0239947 | AQ22: 0.027529 | AR22: 0.0266807 | AS22: 0.0265633 | AT22: 0.0274854
B23: =AVERAGE(L23:P23) -> 0.02748342 | C23: =AVERAGE(R23:V23) -> 0.02763202 | D23: =AVERAGE(X23:AB23) -> 0.02764424 | E23: =AVERAGE(AD23:AH23) -> 0.02761574 | F23: =AVERAGE(AJ23:AN23) -> 0.02754664 | G23: =AVERAGE(AP23:AT23) -> 0.0263821 | H23: =ROUND(G23,4)&"," -> 0.0264, | L23: 0.0275012 | M23: 0.0274501 | N23: 0.0275236 | O23: 0.0274533 | P23: 0.0274889 | R23: 0.0276406 | S23: 0.0276099 | T23: 0.0276566 | U23: 0.0276186 | V23: 0.0276344 | X23: 0.0276632 | Y23: 0.0276216 | Z23: 0.0276666 | AA23: 0.0276227 | AB23: 0.0276471 | AD23: 0.0276388 | AE23: 0.0276058 | AF23: 0.0276569 | AG23: 0.0275826 | AH23: 0.0275946 | AJ23: 0.027487 | AK23: 0.0276515 | AL23: 0.0273377 | AM23: 0.0276022 | AN23: 0.0276548 | AP23: 0.0231858 | AQ23: 0.0274912 | AR23: 0.026284 | AS23: 0.0274629 | AT23: 0.0274866
B24: =AVERAGE(L24:P24) -> 0.02699594 | C24: =AVERAGE(R24:V24) -> 0.02759528 | D24: =AVERAGE(X24:AB24) -> 0.02760982 | E24: =AVERAGE(AD24:AH24) -> 0.0275478 | F24: =AVERAGE(AJ24:AN24) -> 0.0272807 | G24: =AVERAGE(AP24:AT24) -> 0.02616934 | H24: =ROUND(G24,4)&"," -> 0.0262, | L24: 0.0270407 | M24: 0.0268678 | N24: 0.0270348 | O24: 0.0269947 | P24: 0.0270417 | R24: 0.0276004 | S24: 0.0275764 | T24: 0.0275989 | U24: 0.0275932 | V24: 0.0276075 | X24: 0.0276088 | Y24: 0.027601 | Z24: 0.0276137 | AA24: 0.0276096 | AB24: 0.027616 | AD24: 0.0275643 | AE24: 0.0275391 | AF24: 0.02754 | AG24: 0.02754 | AH24: 0.0275556 | AJ24: 0.0263789 | AK24: 0.0275796 | AL24: 0.0273193 | AM24: 0.0275606 | AN24: 0.0275651 | AP24: 0.0228106 | AQ24: 0.0272799 | AR24: 0.0262203 | AS24: 0.0273246 | AT24: 0.0272113
B25: =AVERAGE(L25:P25) -> 0.02605632 | C25: =AVERAGE(R25:V25) -> 0.02753336 | D25: =AVERAGE(X25:AB25) -> 0.02756486 | E25: =AVERAGE(AD25:AH25) -> 0.0274928 | F25: =AVERAGE(AJ25:AN25) -> 0.02725782 | G25: =AVERAGE(AP25:AT25) -> 0.0259874 | H25: =ROUND(G25,4)&"," -> 0.026, | L25: 0.0260217 | M25: 0.0260184 | N25: 0.0260522 | O25: 0.0260135 | P25: 0.0261758 | R25: 0.0275377 | S25: 0.0275085 | T25: 0.0275549 | U25: 0.0275298 | V25: 0.0275359 | X25: 0.027584 | Y25: 0.0275404 | Z25: 0.0275944 | AA25: 0.0275512 | AB25: 0.0275543 | AD25: 0.0275381 | AE25: 0.0274522 | AF25: 0.0275633 | AG25: 0.0274556 | AH25: 0.0274548 | AJ25: 0.0267134 | AK25: 0.0274632 | AL25: 0.0272151 | AM25: 0.0274525 | AN25: 0.0274449 | AP25: 0.0232918 | AQ25: 0.0269049 | AR25: 0.0260374 | AS25: 0.0268746 | AT25: 0.0268283
... B73: =AVERAGE(L73:P73) -> 0.004208292 | C73: =AVERAGE(R73:V73) -> 0.00420859 | D73: =AVERAGE(X73:AB73) -> 0.004208486 | E73: =AVERAGE(AD73:AH73) -> 0.004208692 | F73: =AVERAGE(AJ73:AN73) -> 0.00423214 | G73: =AVERAGE(AP73:AT73) -> 0.004232386 | H73: =ROUND(G73,4)&"," -> 0.0042, | L73: 0.00421757 | M73: 0.00419712 | N73: 0.00421437 | O73: 0.00420541 | P73: 0.00420699 | R73: 0.0042186 | S73: 0.00419704 | T73: 0.004215 | U73: 0.00420536 | V73: 0.00420695 | X73: 0.00421833 | Y73: 0.00419709 | Z73: 0.00421516 | AA73: 0.00420511 | AB73: 0.00420674 | AD73: 0.00421842 | AE73: 0.00419712 | AF73: 0.00421605 | AG73: 0.00420508 | AH73: 0.00420679 | AJ73: 0.00421939 | AK73: 0.00426465 | AL73: 0.00420581 | AM73: 0.0042078 | AN73: 0.00426305 | AP73: 0.00422092 | AQ73: 0.0042647 | AR73: 0.00420586 | AS73: 0.00420775 | AT73: 0.0042627

Sheet delta
B1: delta1*0.5 | C1: delta1*2 | D1: delta23*0.5 | E1: delta23*2 | F1: delta3*0.5 | G1: delta3*1 (base) | H1: delta3*2 | M1: delta1*0.5 | R1: delta1*2 | W1: delta23*0.5 | AB1: delta23*2 | AH1: beta3*0.5 | AM1: beta3*1 (base) | AR1: beta3*1.5 | AW1: beta3*0.5 | AX1: beta3*1 (base) | AY1: beta3*1.5 | BA1: beta3*0.5 | BB1: beta3*1 (base) | BC1: beta3*1.5 | BE1: beta3*0.5 | BF1: beta3*1 (base) | BG1: beta3*1.5 | BI1: beta3*0.5 | BJ1: beta3*1 (base) | BK1: beta3*1.5
A2: Hosp Cost | B2: 22.005607 | C2: 2.087207 | D2: 6.88492 | E2: 5.024936 | F2: =AK3 -> 3.793776 | G2: =AP3 -> 5.610668 | H2: =AU3 -> 9.18523 | M2: Type no vacc constant vacc actual vacc opt vacc | R2: Type no vacc constant vacc actual vacc opt vacc | W2: Type | X2: no vacc | Y2: constant vacc | Z2: actual vacc | AA2: opt vacc | AB2: Type no vacc constant vacc actual vacc opt vacc | AH2: no vacc | AI2: constant vacc | AJ2: actual vacc | AK2: opt vacc | AM2: no vacc | AN2: constant vacc | AO2: actual vacc | AP2: opt vacc | AR2: no vacc | AS2: constant vacc | AT2: actual vacc | AU2: opt vacc | AW2: no vacc | BA2: constant vacc | BE2: actual vacc | BI2: opt vacc
A3: Policy Cost | B3: 6.911104 | C3: 3.832974 | D3: 4.523725 | E3: 4.500132 | F3: =AK4 -> 3.823068 | G3: =AP4 -> 4.513925 | H3: =AU4 -> 5.881727 | M3: 0 Hosp Cost 78.688535 43.336387 22.304407 22.005607 | R3: 0 Hosp Cost 3.262190 3.120357 2.088547 2.087207 | W3: Hosp Cost | X3: 18.693275 | Y3: 14.986807 | Z3: 6.918028 | AA3: 6.88492 | AB3: 0 Hosp Cost 8.362534 6.646297 5.034210 5.024936 | AG3: Hosp Cost | AH3: 6.033669 | AI3: 5.694578 | AJ3: 4.112028 | AK3: 3.793776 | AM3: 11.616842 | AN3: 9.249465 | AO3: 6.374409 | AP3: 5.610668 | AR3: 31.330069 | AS3: 18.025888 | AT3: 11.300558 | AU3: 9.18523 | AW3: =AH3 -> 6.033669 | AX3: =AM3 -> 11.616842 | AY3: =AR3 -> 31.330069 | BA3: =AI3 -> 5.694578 | BB3: =AN3 -> 9.249465 | BC3: =AS3 -> 18.025888 | BE3: =AJ3 -> 4.112028 | BF3: =OFFSET(AJ3,0,5) -> 6.374409 | BG3: =OFFSET(AJ3,0,10) -> 11.300558 | BI3: =AK3 -> 3.793776 | BJ3: =OFFSET(AK3,0,5) -> 5.610668 | BK3: =OFFSET(AK3,0,10) -> 9.18523
A4: Econ Cost | B4: 89.543587 | C4: 14.429683 | D4: 29.24976 | E4: 28.738098 | F4: =AK5 -> 18.953884 | G4: =AP5 -> 28.924867 | H4: =AU5 -> 48.485532 | M4: 1 Policy Cost 12.576429 7.111998 6.776722 6.911104 | R4: 1 Policy Cost 1.268650 2.159269 3.791742 3.832974 | W4: Policy Cost | X4: 2.830537 | Y4: 3.115067 | Z4: 4.466645 | AA4: 4.523725 | AB4: 1 Policy Cost 2.707257 3.051506 4.456236 4.500132 | AG4: Policy Cost | AH4: 1.274791 | AI4: 2.149876 | AJ4: 3.150092 | AK4: 3.823068 | AM4: 2.757488 | AN4: 3.077856 | AO4: 3.979546 | AP4: 4.513925 | AR4: 8.329062 | AS4: 5.414036 | AT4: 5.794695 | AU4: 5.881727 | AW4: =AH4 -> 1.274791 | AX4: =AM4 -> 2.757488 | AY4: =AR4 -> 8.329062 | BA4: =AI4 -> 2.149876 | BB4: =AN4 -> 3.077856 | BC4: =AS4 -> 5.414036 | BE4: =AJ4 -> 3.150092 | BF4: =OFFSET(AJ4,0,5) -> 3.979546 | BG4: =OFFSET(AJ4,0,10) -> 5.794695 | BI4: =AK4 -> 3.823068 | BJ4: =OFFSET(AK4,0,5) -> 4.513925 | BK4: =OFFSET(AK4,0,10) -> 5.881727
A5: Total Cost | B5: =SUM(B2:B4) -> 118.4603 | C5: =SUM(C2:C4) -> 20.349864 | D5: =SUM(D2:D4) -> 40.658405 | E5: =SUM(E2:E4) -> 38.263166 | F5: =AK6 -> 26.570729 | G5: =AP6 -> 39.049459 | H5: =AU6 -> 63.552489 | M5: 2 Econ Cost 249.387855 129.723415 90.411723 89.543587 | R5: 2 Econ Cost 15.929165 15.199578 14.431924 14.429683 | W5: Econ Cost | X5: 45.292741 | Y5: 35.268043 | Z5: 29.297053 | AA5: 29.24976 | AB5: 2 Econ Cost 41.503130 32.697386 28.774814 28.738098 | AG5: Econ Cost | AH5: 21.124831 | AI5: 19.923195 | AJ5: 19.638589 | AK5: 18.953884 | AM5: 42.917935 | AN5: 33.642296 | AO5: 31.83938 | AP5: 28.924867 | AR5: 123.1473 | AS5: 67.936784 | AT5: 58.409633 | AU5: 48.485532 | AW5: =AH5 -> 21.124831 | AX5: =AM5 -> 42.917935 | AY5: =AR5 -> 123.1473 | BA5: =AI5 -> 19.923195 | BB5: =AN5 -> 33.642296 | BC5: =AS5 -> 67.936784 | BE5: =AJ5 -> 19.638589 | BF5: =OFFSET(AJ5,0,5) -> 31.83938 | BG5: =OFFSET(AJ5,0,10) -> 58.409633 | BI5: =AK5 -> 18.953884 | BJ5: =OFFSET(AK5,0,5) -> 28.924867 | BK5: =OFFSET(AK5,0,10) -> 48.485532
M6: 3 Total Cost 340.652820 180.171800 119.492852 118.460298 | R6: 3 Total Cost 20.460005 20.479205 20.312213 20.349864 | W6: Total Cost | X6: 66.816553 | Y6: 53.369917 | Z6: 40.681726 | AA6: 40.658406 | AB6: 3 Total Cost 52.572921 42.395189 38.265259 38.263165 | AG6: Total Cost | AH6: 28.43329 | AI6: 27.767648 | AJ6: 26.900709 | AK6: 26.570729 | AM6: 57.292265 | AN6: 45.969617 | AO6: 42.193335 | AP6: 39.049459 | AR6: 162.80643 | AS6: 91.376707 | AT6: 75.504886 | AU6: 63.552489 | AW6: =AH6 -> 28.43329 | AX6: =AM6 -> 57.292265 | AY6: =AR6 -> 162.80643 | BA6: =AI6 -> 27.767648 | BB6: =AN6 -> 45.969617 | BC6: =AS6 -> 91.376707 | BE6: =AJ6 -> 26.900709 | BF6: =OFFSET(AJ6,0,5) -> 42.193335 | BG6: =OFFSET(AJ6,0,10) -> 75.504886 | BI6: =AK6 -> 26.570729 | BJ6: =OFFSET(AK6,0,5) -> 39.049459 | BK6: =OFFSET(AK6,0,10) -> 63.552489
AW7: No Vacc beta3*0.5 | AX7: No vacc beta3*1 (base) | AY7: No vacc beta3*1.5 | BA7: Const Vacc beta3*0.5 | BB7: Const Vacc beta3*1 (base) | BC7: Const Vacc beta3*1.5 | BE7: Actual Vacc beta3*0.5 | BF7: Actual Vacc beta3*1 (base) | BG7: Actual Vacc beta3*1.5 | BI7: beta3*0.5 | BJ7: beta3*1 (base) | BK7: beta3*1.5
AG8: Hosp Cost Savings | AH8: =1-$AK3/AH3 -> 0.37123233 | AI8: =1-$AK3/AI3 -> 0.33379155 | AJ8: =1-$AK3/AJ3 -> 0.077395387 | AM8: =1-$AP3/AM3 -> 0.51702296 | AN8: =1-$AP3/AN3 -> 0.39340621 | AO8: =1-$AP3/AO3 -> 0.11981362 | AR8: =1-$AU3/AR3 -> 0.70682382 | AS8: =1-$AU3/AS3 -> 0.4904423 | AT8: =1-$AU3/AT3 -> 0.18718792 | AV8: Hosp Cost Savings | AW8: =AH8 -> 0.37123233 | AX8: =AM8 -> 0.51702296 | AY8: =AR8 -> 0.70682382 | BA8: =AI8 -> 0.33379155 | BB8: =AN8 -> 0.39340621 | BC8: =AS8 -> 0.4904423 | BE8: =AJ8 -> 0.077395387 | BF8: =OFFSET(AJ8,0,5) -> 0.11981362 | BG8: =OFFSET(AJ8,0,10) -> 0.18718792 | BI8: =AK8 -> 0 | BJ8: =OFFSET(AK8,0,5) -> 0 | BK8: =OFFSET(AK8,0,10) -> 0
AG9: Policy Cost Savings | AH9: =1-$AK4/AH4 -> -1.9989763 | AI9: =1-$AK4/AI4 -> -0.77827372 | AJ9: =1-$AK4/AJ4 -> -0.21363694 | AM9: =1-$AP4/AM4 -> -0.63696995 | AN9: =1-$AP4/AN4 -> -0.46658096 | AO9: =1-$AP4/AO4 -> -0.1342814 | AR9: =1-$AU4/AR4 -> 0.29383081 | AS9: =1-$AU4/AS4 -> -0.086384908 | AT9: =1-$AU4/AT4 -> -0.015019255 | AV9: Policy Cost Savings | AW9: =AH9 -> -1.9989763 | AX9: =AM9 -> -0.63696995 | AY9: =AR9 -> 0.29383081 | BA9: =AI9 -> -0.77827372 | BB9: =AN9 -> -0.46658096 | BC9: =AS9 -> -0.086384908 | BE9: =AJ9 -> -0.21363694 | BF9: =OFFSET(AJ9,0,5) -> -0.1342814 | BG9: =OFFSET(AJ9,0,10) -> -0.015019255 | BI9: =AK9 -> 0 | BJ9: =OFFSET(AK9,0,5) -> 0 | BK9: =OFFSET(AK9,0,10) -> 0
AG10: Econ Cost Savings | AH10: =1-$AK5/AH5 -> 0.10276754 | AI10: =1-$AK5/AI5 -> 0.048652387 | AJ10: =1-$AK5/AJ5 -> 0.034865285 | AM10: =1-$AP5/AM5 -> 0.32604243 | AN10: =1-$AP5/AN5 -> 0.14022316 | AO10: =1-$AP5/AO5 -> 0.091537995 | AR10: =1-$AU5/AR5 -> 0.60628019 | AS10: =1-$AU5/AS5 -> 0.28631399 | AT10: =1-$AU5/AT5 -> 0.16990521 | AV10: Econ Cost Savings | AW10: =AH10 -> 0.10276754 | AX10: =AM10 -> 0.32604243 | AY10: =AR10 -> 0.60628019 | BA10: =AI10 -> 0.048652387 | BB10: =AN10 -> 0.14022316 | BC10: =AS10 -> 0.28631399 | BE10: =AJ10 -> 0.034865285 | BF10: =OFFSET(AJ10,0,5) -> 0.091537995 | BG10: =OFFSET(AJ10,0,10) -> 0.16990521 | BI10: =AK10 -> 0 | BJ10: =OFFSET(AK10,0,5) -> 0 | BK10: =OFFSET(AK10,0,10) -> 0
AG11: Total Cost Savings | AH11: =1-$AK6/AH6 -> 0.065506348 | AI11: =1-$AK6/AI6 -> 0.043104803 | AJ11: =1-$AK6/AJ6 -> 0.012266591 | AM11: =1-$AP6/AM6 -> 0.31841656 | AN11: =1-$AP6/AN6 -> 0.15053765 | AO11: =1-$AP6/AO6 -> 0.074511199 | AR11: =1-$AU6/AR6 -> 0.60964387 | AS11: =1-$AU6/AS6 -> 0.30450012 | AT11: =1-$AU6/AT6 -> 0.15829965
B13: delta1*0.5 | C13: delta1*2 | D13: delta23*0.5 | E13: delta23*2 | F13: delta3*0.5 | G13: delta3*1 (base) | H13: delta3*2 | M13: delta1*0.5 | R13: delta1*2 | W13: delta23*0.5 | AB13: delta23*2 | AG13: beta3*0.5 | AL13: base case | AQ13: beta3*1.5
B14: =AVERAGE(M14:Q14) -> 0.02778778 | C14: =AVERAGE(R14:V14) -> 0.02778448 | D14: =AVERAGE(W14:AA14) -> 0.02778522 | E14: =AVERAGE(AB14:AF14) -> 0.0277849 | F14: =AVERAGE(AG14:AK14) -> 0.02778464 | G14: =AVERAGE(AL14:AP14) -> 0.02778504 | H14: =AVERAGE(AQ14:AU14) -> 0.02778596 | I14: =ROUND(E14,4)&"," -> 0.0278, | M14: 0.0277973 | N14: 0.0277716 | O14: 0.0277954 | P14: 0.0277827 | Q14: 0.0277919 | R14: 0.027794 | S14: 0.0277679 | T14: 0.0277918 | U14: 0.0277792 | V14: 0.0277895 | W14: 0.0277947 | X14: 0.0277688 | Y14: 0.0277926 | Z14: 0.0277799 | AA14: 0.0277901 | AB14: 0.0277944 | AC14: 0.0277684 | AD14: 0.0277923 | AE14: 0.0277796 | AF14: 0.0277898 | AG14: 0.0277942 | AH14: 0.0277681 | AI14: 0.0277919 | AJ14: 0.0277794 | AK14: 0.0277896 | AL14: 0.0277946 | AM14: 0.0277686 | AN14: 0.0277924 | AO14: 0.0277797 | AP14: 0.0277899 | AQ14: 0.0277955 | AR14: 0.0277695 | AS14: 0.0277935 | AT14: 0.0277807 | AU14: 0.0277906
B15: =AVERAGE(M15:Q15) -> 0.02779158 | C15: =AVERAGE(R15:V15) -> 0.0277871 | D15: =AVERAGE(W15:AA15) -> 0.02778838 | E15: =AVERAGE(AB15:AF15) -> 0.02778742 | F15: =AVERAGE(AG15:AK15) -> 0.0277873 | G15: =AVERAGE(AL15:AP15) -> 0.02778774 | H15: =AVERAGE(AQ15:AU15) -> 0.02778898 | I15: =ROUND(E15,4)&"," -> 0.0278, | M15: 0.0278021 | N15: 0.0277704 | O15: 0.0278045 | P15: 0.0277849 | Q15: 0.027796 | R15: 0.0277976 | S15: 0.0277658 | T15: 0.0277997 | U15: 0.0277802 | V15: 0.0277922 | W15: 0.0277988 | X15: 0.0277673 | Y15: 0.0278009 | Z15: 0.0277815 | AA15: 0.0277934 | AB15: 0.0277979 | AC15: 0.0277662 | AD15: 0.0278 | AE15: 0.0277805 | AF15: 0.0277925 | AG15: 0.0277978 | AH15: 0.027766 | AI15: 0.0277999 | AJ15: 0.0277804 | AK15: 0.0277924 | AL15: 0.0277982 | AM15: 0.0277666 | AN15: 0.0278003 | AO15: 0.0277808 | AP15: 0.0277928 | AQ15: 0.0277995 | AR15: 0.0277677 | AS15: 0.0278017 | AT15: 0.0277822 | AU15: 0.0277938
B16: =AVERAGE(M16:Q16) -> 0.02778228 | C16: =AVERAGE(R16:V16) -> 0.02777684 | D16: =AVERAGE(W16:AA16) -> 0.0277787 | E16: =AVERAGE(AB16:AF16) -> 0.02777712 | F16: =AVERAGE(AG16:AK16) -> 0.02777714 | G16: =AVERAGE(AL16:AP16) -> 0.02777764 | H16: =AVERAGE(AQ16:AU16) -> 0.02777906 | I16: =ROUND(E16,4)&"," -> 0.0278, | M16: 0.0277904 | N16: 0.0277627 | O16: 0.027797 | P16: 0.0277761 | Q16: 0.0277852 | R16: 0.0277857 | S16: 0.0277568 | T16: 0.0277901 | U16: 0.0277706 | V16: 0.027781 | W16: 0.0277874 | X16: 0.0277589 | Y16: 0.0277921 | Z16: 0.0277725 | AA16: 0.0277826 | AB16: 0.0277859 | AC16: 0.0277571 | AD16: 0.0277906 | AE16: 0.0277709 | AF16: 0.0277811 | AG16: 0.027786 | AH16: 0.0277572 | AI16: 0.0277905 | AJ16: 0.0277709 | AK16: 0.0277811 | AL16: 0.0277864 | AM16: 0.0277577 | AN16: 0.0277911 | AO16: 0.0277714 | AP16: 0.0277816 | AQ16: 0.0277875 | AR16: 0.0277591 | AS16: 0.027793 | AT16: 0.0277729 | AU16: 0.0277828
B17: =AVERAGE(M17:Q17) -> 0.0277745 | C17: =AVERAGE(R17:V17) -> 0.02776692 | D17: =AVERAGE(W17:AA17) -> 0.02776962 | E17: =AVERAGE(AB17:AF17) -> 0.02776732 | F17: =AVERAGE(AG17:AK17) -> 0.02776746 | G17: =AVERAGE(AL17:AP17) -> 0.02776806 | H17: =AVERAGE(AQ17:AU17) -> 0.02776996 | I17: =ROUND(E17,4)&"," -> 0.0278, | M17: 0.027783 | N17: 0.027752 | O17: 0.0277913 | P17: 0.0277658 | Q17: 0.0277804 | R17: 0.0277762 | S17: 0.0277443 | T17: 0.0277823 | U17: 0.0277578 | V17: 0.027774 | W17: 0.0277786 | X17: 0.0277474 | Y17: 0.0277851 | Z17: 0.0277606 | AA17: 0.0277764 | AB17: 0.0277765 | AC17: 0.0277449 | AD17: 0.0277827 | AE17: 0.0277582 | AF17: 0.0277743 | AG17: 0.0277766 | AH17: 0.0277452 | AI17: 0.0277828 | AJ17: 0.0277583 | AK17: 0.0277744 | AL17: 0.0277772 | AM17: 0.0277457 | AN17: 0.0277835 | AO17: 0.0277589 | AP17: 0.027775 | AQ17: 0.0277789 | AR17: 0.0277474 | AS17: 0.0277858 | AT17: 0.027761 | AU17: 0.0277767
B18: =AVERAGE(M18:Q18) -> 0.02776242 | C18: =AVERAGE(R18:V18) -> 0.02775352 | D18: =AVERAGE(W18:AA18) -> 0.02775706 | E18: =AVERAGE(AB18:AF18) -> 0.0277539 | F18: =AVERAGE(AG18:AK18) -> 0.0277542 | G18: =AVERAGE(AL18:AP18) -> 0.02775492 | H18: =AVERAGE(AQ18:AU18) -> 0.027757 | I18: =ROUND(E18,4)&"," -> 0.0278, | M18: 0.0277704 | N18: 0.0277428 | O18: 0.0277806 | P18: 0.0277497 | Q18: 0.0277686 | R18: 0.027763 | S18: 0.0277337 | T18: 0.0277701 | U18: 0.0277408 | V18: 0.02776 | W18: 0.0277657 | X18: 0.0277374 | Y18: 0.0277738 | Z18: 0.0277448 | AA18: 0.0277636 | AB18: 0.0277629 | AC18: 0.0277342 | AD18: 0.0277706 | AE18: 0.0277413 | AF18: 0.0277605 | AG18: 0.0277633 | AH18: 0.0277346 | AI18: 0.0277708 | AJ18: 0.0277418 | AK18: 0.0277605 | AL18: 0.0277638 | AM18: 0.0277353 | AN18: 0.0277716 | AO18: 0.0277424 | AP18: 0.0277615 | AQ18: 0.0277655 | AR18: 0.0277372 | AS18: 0.0277742 | AT18: 0.0277444 | AU18: 0.0277637
B19: =AVERAGE(M19:Q19) -> 0.02774786 | C19: =AVERAGE(R19:V19) -> 0.02773698 | D19: =AVERAGE(W19:AA19) -> 0.02774126 | E19: =AVERAGE(AB19:AF19) -> 0.0277371 | F19: =AVERAGE(AG19:AK19) -> 0.02773754 | G19: =AVERAGE(AL19:AP19) -> 0.02773842 | H19: =AVERAGE(AQ19:AU19) -> 0.02774102 | I19: =ROUND(E19,4)&"," -> 0.0277, | M19: 0.0277606 | N19: 0.0277225 | O19: 0.0277698 | P19: 0.0277348 | Q19: 0.0277516 | R19: 0.0277515 | S19: 0.0277108 | T19: 0.0277582 | U19: 0.0277228 | V19: 0.0277416 | W19: 0.0277543 | X19: 0.0277153 | Y19: 0.0277625 | Z19: 0.0277279 | AA19: 0.0277463 | AB19: 0.0277506 | AC19: 0.0277108 | AD19: 0.0277587 | AE19: 0.0277232 | AF19: 0.0277422 | AG19: 0.027751 | AH19: 0.0277115 | AI19: 0.0277592 | AJ19: 0.0277234 | AK19: 0.0277426 | AL19: 0.0277518 | AM19: 0.0277123 | AN19: 0.0277599 | AO19: 0.0277247 | AP19: 0.0277434 | AQ19: 0.0277542 | AR19: 0.0277152 | AS19: 0.0277627 | AT19: 0.0277275 | AU19: 0.0277455
B20: =AVERAGE(M20:Q20) -> 0.02772984 | C20: =AVERAGE(R20:V20) -> 0.0277153 | D20: =AVERAGE(W20:AA20) -> 0.0277217 | E20: =AVERAGE(AB20:AF20) -> 0.02771604 | F20: =AVERAGE(AG20:AK20) -> 0.02771676 | G20: =AVERAGE(AL20:AP20) -> 0.02771784 | H20: =AVERAGE(AQ20:AU20) -> 0.02772066 | I20: =ROUND(E20,4)&"," -> 0.0277, | M20: 0.0277401 | N20: 0.0277076 | O20: 0.0277506 | P20: 0.027716 | Q20: 0.0277349 | R20: 0.0277266 | S20: 0.0276912 | T20: 0.0277342 | U20: 0.0276992 | V20: 0.0277253 | W20: 0.0277323 | X20: 0.0276991 | Y20: 0.0277405 | Z20: 0.0277063 | AA20: 0.0277303 | AB20: 0.0277271 | AC20: 0.0276935 | AD20: 0.0277349 | AE20: 0.0276999 | AF20: 0.0277248 | AG20: 0.0277276 | AH20: 0.0276937 | AI20: 0.0277357 | AJ20: 0.0277006 | AK20: 0.0277262 | AL20: 0.0277288 | AM20: 0.0276953 | AN20: 0.0277367 | AO20: 0.027702 | AP20: 0.0277264 | AQ20: 0.0277319 | AR20: 0.0276988 | AS20: 0.0277406 | AT20: 0.0277057 | AU20: 0.0277263
B21: =AVERAGE(M21:Q21) -> 0.02771016 | C21: =AVERAGE(R21:V21) -> 0.02769174 | D21: =AVERAGE(W21:AA21) -> 0.02769928 | E21: =AVERAGE(AB21:AF21) -> 0.02769224 | F21: =AVERAGE(AG21:AK21) -> 0.0276933 | G21: =AVERAGE(AL21:AP21) -> 0.0276945 | H21: =AVERAGE(AQ21:AU21) -> 0.02769838 | I21: =ROUND(E21,4)&"," -> 0.0277, | M21: 0.0277177 | N21: 0.0276862 | O21: 0.0277389 | P21: 0.0276947 | Q21: 0.0277133 | R21: 0.0276994 | S21: 0.0276691 | T21: 0.0277207 | U21: 0.0276743 | V21: 0.0276952 | W21: 0.0277063 | X21: 0.0276754 | Y21: 0.0277276 | Z21: 0.0276831 | AA21: 0.027704 | AB21: 0.0276993 | AC21: 0.0276684 | AD21: 0.0277215 | AE21: 0.0276752 | AF21: 0.0276968 | AG21: 0.0277006 | AH21: 0.0276693 | AI21: 0.0277222 | AJ21: 0.0276762 | AK21: 0.0276982 | AL21: 0.0277015 | AM21: 0.0276707 | AN21: 0.0277235 | AO21: 0.0276778 | AP21: 0.027699 | AQ21: 0.0277049 | AR21: 0.0276751 | AS21: 0.0277278 | AT21: 0.0276819 | AU21: 0.0277022
