Workbook
Name Full: #REF!
Name Glossary: #REF!
Name scope: #REF!
Name TopOfTable_Table_2: #REF!
Name TopOfTable_Table_2: death_vic!$A$2
Name Y2015_BIRTHS_LG: birth_vic!$A$6:$B$88

Sheet reg control (2)
K1: top | L1: bottom
C2: top | K2: k0 = 0.0067 | L2: k0 = 0.0053 | N2: k0 low 0.0053 | O2: k0 high 0.0067 | S2: Strategy 1 | T2: Strategy 2 | U2: Optimal Control
C3: k0 = 0.0067 | F3: vaccination_rate | I3: bottom | K3: k1 = -0.1006 | L3: k1 = -0.1676 | M3: avg | N3: k1 high -0.1006 | O3: k1 low -0.1676 | S3: Constant Vaccination | T3: Actual alpha | U3: control_1 | V3: control_2 | W3: control_3 | X3: control_4 | Y3: control_5 | AB3: avg over rounds
C4: k1 = -0.1006 | F4: 0.02779241 | I4: k0 = 0.0053 | J4: 1 | K4: =F4 -> 0.02779241 | L4: 0.02779236 | M4: =AB4 -> 0.02447724 | N4: 0.02779235 | O4: 0.02779241 | S4: =$F$3 -> vaccination_rate | T4: =Reg_30days!AJ32 -> 0 | U4: 0.0245031 | V4: 0.0244278 | W4: 0.0244835 | X4: 0.0244886 | Y4: 0.0244832 | AB4: =AVERAGE(U4:Y4) -> 0.02447724
F5: 0.02779357 | I5: k1 = -0.1676 | J5: 2 | K5: =F5 -> 0.02779357 | L5: 0.02779371 | M5: =AB5 -> 0.02438572 | N5: 0.02779351 | O5: 0.02779376 | S5: =$F$3 -> vaccination_rate | T5: =Reg_30days!AJ33 -> 0 | U5: 0.0244224 | V5: 0.0243765 | W5: 0.0243693 | X5: 0.0243777 | Y5: 0.0243827 | AB5: =AVERAGE(U5:Y5) -> 0.02438572
F6: 0.02777892 | J6: 3 | K6: =F6 -> 0.02777892 | L6: 0.02777925 | M6: =AB6 -> 0.0242678 | N6: 0.02777886 | O6: 0.0277793 | S6: =$F$3 -> vaccination_rate | T6: =Reg_30days!AJ34 -> 0 | U6: 0.0243032 | V6: 0.0242313 | W6: 0.0242684 | X6: 0.0242707 | Y6: 0.0242654 | AB6: =AVERAGE(U6:Y6) -> 0.0242678
F7: 0.02776494 | J7: 4 | K7: =F7 -> 0.02776494 | L7: 0.02776547 | M7: =AB7 -> 0.02410956 | N7: 0.02776487 | O7: 0.02776553 | S7: =$F$3 -> vaccination_rate | T7: =Reg_30days!AJ35 -> 0 | U7: 0.0241285 | V7: 0.0241053 | W7: 0.0240692 | X7: 0.024107 | Y7: 0.0241378 | AB7: =AVERAGE(U7:Y7) -> 0.02410956
F8: 0.02774444 | J8: 5 | K8: =F8 -> 0.02774444 | L8: 0.02774524 | M8: =AB8 -> 0.02387136 | N8: 0.02774436 | O8: 0.0277453 | S8: =$F$3 -> vaccination_rate | T8: =Reg_30days!AJ36 -> 0 | U8: 0.02399 | V8: 0.0237615 | W8: 0.0239481 | X8: 0.0239716 | Y8: 0.0236856 | AB8: =AVERAGE(U8:Y8) -> 0.02387136
F9: 0.02771779 | J9: 6 | K9: =F9 -> 0.02771779 | L9: 0.02771905 | M9: =AB9 -> 0.02355274 | N9: 0.02771771 | O9: 0.02771912 | S9: =$F$3 -> vaccination_rate | T9: =Reg_30days!AJ37 -> 0 | U9: 0.0239124 | V9: 0.023483 | W9: 0.0234279 | X9: 0.0233801 | Y9: 0.0235603 | AB9: =AVERAGE(U9:Y9) -> 0.02355274
F10: 0.02769106 | J10: 7 | K10: =F10 -> 0.02769106 | L10: 0.02769274 | M10: =AB10 -> 0.02338316 | N10: 0.02769097 | O10: 0.0276928 | S10: =$F$3 -> vaccination_rate | T10: =Reg_30days!AJ38 -> 0 | U10: 0.0235616 | V10: 0.0234558 | W10: 0.0234109 | X10: 0.0231867 | Y10: 0.0233008 | AB10: =AVERAGE(U10:Y10) -> 0.02338316
F11: 0.02765664 | J11: 8 | K11: =F11 -> 0.02765664 | L11: 0.02765901 | M11: =AB11 -> 0.02316708 | N11: 0.02765656 | O11: 0.02765907 | S11: =$F$3 -> vaccination_rate | T11: =Reg_30days!AJ39 -> 0 | U11: 0.0231953 | V11: 0.0231481 | W11: 0.02331 | X11: 0.0231032 | Y11: 0.0230788 | AB11: =AVERAGE(U11:Y11) -> 0.02316708
F12: 0.02761797 | J12: 9 | K12: =F12 -> 0.02761797 | L12: 0.02762101 | M12: =AB12 -> 0.02305654 | N12: 0.02761784 | O12: 0.0276211 | S12: =$F$3 -> vaccination_rate | T12: =Reg_30days!AJ40 -> 0 | U12: 0.0230804 | V12: 0.0229861 | W12: 0.0233851 | X12: 0.0229123 | Y12: 0.0229188 | AB12: =AVERAGE(U12:Y12) -> 0.02305654
F13: 0.02759025 | J13: 10 | K13: =F13 -> 0.02759025 | L13: 0.02759398 | M13: =AB13 -> 0.02285692 | N13: 0.02759015 | O13: 0.02759403 | S13: =$F$3 -> vaccination_rate | T13: =Reg_30days!AJ41 -> 0 | U13: 0.022797 | V13: 0.0226103 | W13: 0.0232388 | X13: 0.0229475 | Y13: 0.022691 | AB13: =AVERAGE(U13:Y13) -> 0.02285692
F14: 0.02758413 | J14: 11 | K14: =F14 -> 0.02758413 | L14: 0.02758989 | M14: =AB14 -> 0.02267136 | N14: 0.02758616 | O14: 0.02758931 | S14: =$F$3 -> vaccination_rate | T14: =Reg_30days!AJ42 -> 0 | U14: 0.0225398 | V14: 0.0225778 | W14: 0.0229953 | X14: 0.0226186 | Y14: 0.0226253 | AB14: =AVERAGE(U14:Y14) -> 0.02267136
F15: 0.02747588 | J15: 12 | K15: =F15 -> 0.02747588 | L15: 0.02748173 | M15: =AB15 -> 0.02247434 | N15: 0.02747582 | O15: 0.02748176 | S15: =$F$3 -> vaccination_rate | T15: =Reg_30days!AJ43 -> 0 | U15: 0.0223361 | V15: 0.0225738 | W15: 0.022726 | X15: 0.0224946 | Y15: 0.0222412 | AB15: =AVERAGE(U15:Y15) -> 0.02247434
F16: 0.02734684 | J16: 13 | K16: =F16 -> 0.02734684 | L16: 0.02735633 | M16: =AB16 -> 0.02239424 | N16: 0.02734733 | O16: 0.027356 | S16: =$F$3 -> vaccination_rate | T16: =Reg_30days!AJ44 -> 0 | U16: 0.0221573 | V16: 0.0222858 | W16: 0.0225789 | X16: 0.0226736 | Y16: 0.0222756 | AB16: =AVERAGE(U16:Y16) -> 0.02239424
F17: 0.02724283 | J17: 14 | K17: =F17 -> 0.02724283 | L17: 0.0272533 | M17: =AB17 -> 0.02230826 | N17: 0.02724293 | O17: 0.02725343 | S17: =$F$3 -> vaccination_rate | T17: =Reg_30days!AJ45 -> 0 | U17: 0.0226141 | V17: 0.0222929 | W17: 0.0225579 | X17: 0.0223482 | Y17: 0.0217282 | AB17: =AVERAGE(U17:Y17) -> 0.02230826
... F63: 0.00424856 | J63: 60 | K63: =F63 -> 0.00424856 | L63: 0.00424851 | M63: =AB63 -> 0.005159404 | N63: 0.00424854 | O63: 0.00424854 | S63: =$F$3 -> vaccination_rate | T63: =Reg_30days!AJ91 -> 0 | U63: 0.00516643 | V63: 0.00515081 | W63: 0.00516471 | X63: 0.00515668 | Y63: 0.00515839 | AB63: =AVERAGE(U63:Y63) -> 0.005159404
S70: upper
E71: lower | AE71: base | AQ71: k1low | BC71: k0 low
AQ72: k0 high | BC72: k1 high
G84: Strategy | H84: Total Cost | I84: Healthcare | J84: Policy | K84: Economic | L84: Cost reduction
G85: No Vaccination | H85: 38.72 | I85: 9.5 | J85: 1.66 | K85: 27.56 | L85: =1-H88/H85 -> 0.17742769
G86: Constant Vaccination | H86: 34.28 | I86: 8.13 | J86: 3.08 | K86: 23.07 | L86: =1-H88/H86 -> 0.070886814
G87: Actual (Government) | H87: 31.4 | I87: 4.93 | J87: 3.35 | K87: 23.12
G88: Optimal | H88: 31.85 | I88: 4.42 | J88: 5.89 | K88: 21.54
E101: standard
E111: peak infected | F111: hosp | G111: icu
D112: no | AQ112: Strategy | AR112: Peak Infected | AS112: Peak Mild | AT112: Peak Hosp | AU112: Peak ICU | AV112: Peak Infected | AW112: Peak Mild | AX112: Peak Hosp | AY112: Peak ICU | BC112: Strategy | BD112: Peak Infected | BE112: Peak Mild | BF112: Peak Hosp | BG112: Peak ICU | BH112: Peak Infected | BI112: Peak Mild | BJ112: Peak Hosp | BK112: Peak ICU
D113: constant | AQ113: No Vaccination | AR113: 0.5662 | AS113: 0.5421 | AT113: 0.02185 | AU113: 0.01598 | AV113: =1-AR116/AR113 -> 0.0060049452 | AW113: =1-AS116/AS113 -> -0.027116768 | AX113: =1-AT116/AT113 -> 0.65629291 | AY113: =1-AU116/AU113 -> 0.8097622 | BC113: No Vaccination | BD113: 0.5662 | BE113: 0.5421 | BF113: 0.02185 | BG113: 0.01598 | BH113: =1-BD116/BD113 -> 0.0060049452 | BI113: =1-BE116/BE113 -> -0.026194429 | BJ113: =1-BF116/BF113 -> 0.65629291 | BK113: =1-BG116/BG113 -> 0.79411765
D114: optimal | S114: Strategy | T114: Peak Infected | U114: Peak Mild | V114: Peak Hosp | W114: Peak ICU | X114: Peak Infected | Y114: Peak Mild | Z114: Peak Hosp | AA114: Peak ICU | AQ114: Constant Vaccination | AR114: 0.5632 | AS114: 0.5395 | AT114: 0.02161 | AU114: 0.01551 | AV114: =1-AR116/AR114 -> 0.00071022727 | AW114: =1-AS116/AS114 -> -0.032066728 | AX114: =1-AT116/AT114 -> 0.65247571 | AY114: =1-AU116/AU114 -> 0.80399742 | BC114: Constant Vaccination | BD114: 0.5632 | BE114: 0.5395 | BF114: 0.02161 | BG114: 0.01551 | BH114: =1-BD116/BD114 -> 0.00071022727 | BI114: =1-BE116/BE114 -> -0.031139944 | BJ114: =1-BF116/BF114 -> 0.65247571 | BK114: =1-BG116/BG114 -> 0.78787879
F115: Strategy | G115: Peak Infected | H115: Peak Mild | I115: Peak Hosp | J115: Peak ICU | K115: Peak Infected | L115: Peak Mild | M115: Peak Hosp | N115: Peak ICU | S115: No Vaccination | T115: 0.5662 | U115: 0.5421 | V115: 0.02185 | W115: 0.01598 | X115: =1-T118/T115 -> 0.0061815613 | Y115: =1-U118/U115 -> -0.023058476 | Z115: =1-V118/V115 -> 0.65583524 | AA115: =1-W118/W115 -> 0.73404255 | AE115: Strategy | AF115: Peak Infected | AG115: Peak Mild | AH115: Peak Hosp | AI115: Peak ICU | AJ115: Peak Infected | AK115: Peak Mild | AL115: Peak Hosp | AM115: Peak ICU | AQ115: Actual (Government) | AR115: 0.5649 | AS115: 0.5564 | AT115: 0.00752 | AU115: 0.0043 | BC115: Actual (Government) | BD115: 0.5649 | BE115: 0.5569 | BF115: 0.00752 | BG115: 0.00408
F116: No Vaccination | G116: 0.5662 | H116: 0.5421 | I116: 0.02185 | J116: 0.01598 | K116: =1-G119/G116 -> 0.0058283292 | L116: =1-H119/H116 -> -0.02951485 | M116: =1-I119/I116 -> 0.65629291 | N116: =1-J119/J116 -> 0.83291615 | S116: Constant Vaccination | T116: 0.5632 | U116: 0.5395 | V116: 0.02161 | W116: 0.01551 | X116: =1-T118/T116 -> 0.00088778409 | Y116: =1-U118/U116 -> -0.027988879 | Z116: =1-V118/V116 -> 0.65201296 | AA116: =1-W118/W116 -> 0.72598324 | AE116: No Vaccination | AF116: 0.5662 | AG116: 0.5421 | AH116: 0.02185 | AI116: 0.01598 | AJ116: =1-AF119/AF116 -> 0.0060049452 | AK116: =1-AG119/AG116 -> -0.026563365 | AL116: =1-AH119/AH116 -> 0.65629291 | AM116: =1-AI119/AI116 -> 0.80162703 | AQ116: Optimal | AR116: 0.5628 | AS116: 0.5568 | AT116: 0.00751 | AU116: 0.00304 | BC116: Optimal | BD116: 0.5628 | BE116: 0.5563 | BF116: 0.00751 | BG116: 0.00329
F117: Constant Vaccination | G117: 0.5632 | H117: 0.5395 | I117: 0.02161 | J117: 0.01551 | K117: =1-G119/G117 -> 0.00053267045 | L117: =1-H119/H117 -> -0.034476367 | M117: =1-I119/I117 -> 0.65247571 | N117: =1-J119/J117 -> 0.827853 | S117: Actual (Government) | T117: 0.5648 | U117: 0.5552 | V117: 0.00757 | W117: 0.00512 | AE117: Constant Vaccination | AF117: 0.5632 | AG117: 0.5395 | AH117: 0.02161 | AI117: 0.01551 | AJ117: =1-AF119/AF117 -> 0.00071022727 | AK117: =1-AG119/AG117 -> -0.031510658 | AL117: =1-AH119/AH117 -> 0.65247571 | AM117: =1-AI119/AI117 -> 0.79561573
F118: Actual (Government) | G118: 0.565 | H118: 0.5581 | I118: 0.00751 | J118: 0.0034 | S118: Optimal | T118: 0.5627 | U118: 0.5546 | V118: 0.00752 | W118: 0.00425 | AE118: Actual (Government) | AF118: 0.5649 | AG118: 0.5567 | AH118: 0.00752 | AI118: 0.00419
F119: Optimal | G119: 0.5629 | H119: 0.5581 | I119: 0.00751 | J119: 0.00267 | AE119: Optimal | AF119: 0.5628 | AG119: 0.5565 | AH119: 0.00751 | AI119: 0.00317 | AQ119: Table 3: Peak Infection (Mean, absolute numbers) | BC119: Table 3: Peak Infection (Mean, absolute numbers)
F121: Strategy | G121: Peak Infected | H121: Peak Mild | I121: Peak Hosp | J121: Peak ICU | K121: Peak Infected | L121: Peak Mild | M121: Peak Hosp | N121: Peak ICU | AQ121: Strategy | AR121: Peak Infected | AS121: Peak Mild | AT121: Peak Hosp | AU121: Peak ICU | BC121: Strategy | BD121: Peak Infected | BE121: Peak Mild | BF121: Peak Hosp | BG121: Peak ICU
F122: No Vaccination | G122: 37539 | H122: 35941 | I122: 1448 | J122: 1059 | K122: =1-G125/G122 -> 0.0058072937 | L122: =1-H125/H122 -> -0.029437133 | M122: =1-I125/I122 -> 0.65607735 | N122: =1-J125/J122 -> 0.83286119 | AE122: Table 3: Peak Infection (Mean, absolute numbers) | AQ122: No Vaccination | AR122: 37539 | AS122: 35941 | AT122: 1448 | AU122: 1059 | BC122: No Vaccination | BD122: 37539 | BE122: 35941 | BF122: 1448 | BG122: 1059
F123: Constant Vaccination | G123: 37338 | H123: 35769 | I123: 1433 | J123: 1028 | K123: =1-G125/G123 -> 0.00045530023 | L123: =1-H125/H123 -> -0.034387319 | M123: =1-I125/I123 -> 0.65247732 | N123: =1-J125/J123 -> 0.82782101 | S123: Strategy | T123: Peak Infected | U123: Peak Mild | V123: Peak Hosp | W123: Peak ICU | AQ123: Constant Vaccination | AR123: 37338 | AS123: 35769 | AT123: 1433 | AU123: 1028 | BC123: Constant Vaccination | BD123: 37338 | BE123: 35769 | BF123: 1433 | BG123: 1028
F124: Actual (Government) | G124: 37460 | H124: 37002 | I124: 498 | J124: 225 | S124: No Vaccination | T124: 37539 | U124: 35941 | V124: 1448 | W124: 1059 | AE124: Strategy | AF124: Peak Infected | AG124: Peak Mild | AH124: Peak Hosp | AI124: Peak ICU | AQ124: Actual (Government) | AR124: 37452 | AS124: 36889 | AT124: 498 | AU124: 285 | BC124: Actual (Government) | BD124: 37454 | BE124: 36923 | BF124: 498 | BG124: 271
F125: Optimal | G125: 37321 | H125: 36999 | I125: 498 | J125: 177 | S125: Constant Vaccination | T125: 37338 | U125: 35769 | V125: 1433 | W125: 1028 | AE125: No Vaccination | AF125: 37539 | AG125: 35941 | AH125: 1448 | AI125: 1059 | AQ125: Optimal | AR125: 37315 | AS125: 36916 | AT125: 498 | AU125: 202 | BC125: Optimal | BD125: 37313 | BE125: 36879 | BF125: 498 | BG125: 218
S126: Actual (Government) | T126: 37446 | U126: 36811 | V126: 502 | W126: 339 | AE126: Constant Vaccination | AF126: 37338 | AG126: 35769 | AH126: 1433 | AI126: 1028
S127: Optimal | T127: 37305 | U127: 36769 | V127: 498 | W127: 282 | AE127: Actual (Government) | AF127: 37453 | AG127: 36906 | AH127: 498 | AI127: 278
AE128: Optimal | AF128: 37314 | AG128: 36898 | AH128: 498 | AI128: 210
F138: Strategy | G138: Hospital | H138: Vaccination | I138: Quarantine | J138: Economic | K138: Total | L138: Cost reduction
F139: No Vaccination | G139: 9.5 | H139: 0 | I139: 1.66 | J139: 27.56 | K139: 38.72 | L139: =1-K142/K139 -> 0.17665289 | S139: Strategy | T139: Hospital | U139: Vaccination | V139: Quarantine | W139: Economic | X139: Total | Y139: Cost reduction
F140: Constant Vaccination | G140: 8.13 | H140: 1.71 | I140: 1.37 | J140: 23.07 | K140: 34.28 | L140: =1-K142/K140 -> 0.070011669 | S140: No Vaccination | T140: 9.5 | U140: 0 | V140: 1.66 | W140: 27.56 | X140: 38.72 | Y140: =1-X143/X140 -> 0.16296488
F141: Actual (Government) | G141: 4.93 | H141: 1.96 | I141: 1.39 | J141: 23.12 | K141: 31.4 | S141: Constant Vaccination | T141: 8.13 | U141: 1.71 | V141: 1.37 | W141: 23.07 | X141: 34.28 | Y141: =1-X143/X141 -> 0.054550758
F142: Optimal | G142: 4.42 | H142: 4.63 | I142: 1.29 | J142: 21.54 | K142: 31.88 | S142: Actual (Government) | T142: 5.48 | U142: 1.96 | V142: 1.39 | W142: 23.07 | X142: 31.89 | AE142: Strategy | AF142: Hospital | AG142: Vaccination | AH142: Quarantine | AI142: Economic | AJ142: Total | AK142: Cost reduction | BC142: Strategy | BD142: Hospital | BE142: Vaccination | BF142: Quarantine | BG142: Economic | BH142: Total | BI142: Cost reduction
S143: Optimal | T143: 4.99 | U143: 4.64 | V143: 1.29 | W143: 21.5 | X143: 32.41 | AE143: No Vaccination | AF143: 9.5 | AG143: 0 | AH143: 1.66 | AI143: 27.56 | AJ143: 38.72 | AK143: =1-AJ146/AJ143 -> 0.2231405 | AQ143: Strategy | AR143: Hospital | AS143: Vaccination | AT143: Quarantine | AU143: Economic | AV143: Total | AW143: Cost reduction | BC143: No Vaccination | BD143: 9.5 | BE143: 0 | BF143: 1.66 | BG143: 27.56 | BH143: 38.72 | BI143: =1-BH146/BH143 -> 0.16942149
AE144: Constant Vaccination | AF144: 8.13 | AG144: 1.71 | AH144: 1.37 | AI144: 23.07 | AJ144: 34.28 | AK144: =1-AJ146/AJ144 -> 0.12252042 | AQ144: No Vaccination | AR144: 9.5 | AS144: 0 | AT144: 1.66 | AU144: 27.56 | AV144: 38.72 | AW144: =1-AV147/AV144 -> 0.17174587 | BC144: Constant Vaccination | BD144: 8.13 | BE144: 1.71 | BF144: 1.37 | BG144: 23.07 | BH144: 34.28 | BI144: =1-BH146/BH144 -> 0.061843641
AE145: Actual (Government) | AF145: 5.21 | AG145: 1.96 | AH145: 1.39 | AI145: 23.09 | AJ145: 31.65 | AQ145: Constant Vaccination | AR145: 8.13 | AS145: 1.71 | AT145: 1.37 | AU145: 23.07 | AV145: 34.28 | AW145: =1-AV147/AV145 -> 0.064469078 | BC145: Actual (Government) | BD145: 5.2 | BE145: 1.96 | BF145: 1.39 | BG145: 23.1 | BH145: 31.64
AE146: Optimal | AF146: 4.72 | AG146: 2.45 | AH146: 1.3 | AI146: 21.62 | AJ146: 30.08 | AQ146: Actual (Government) | AR146: 5.21 | AS146: 1.96 | AT146: 1.39 | AU146: 23.09 | AV146: 31.65 | BC146: Optimal | BD146: 4.72 | BE146: 4.63 | BF146: 1.29 | BG146: 21.52 | BH146: 32.16
F147: k0 low 0.0053 | G147: k0 high 0.0067 | AQ147: Optimal | AR147: 4.63 | AS147: 4.63 | AT147: 1.29 | AU147: 21.52 | AV147: 32.07
B148: optimal compare to | C148: top | D148: bottom | E148: avg | F148: k1 high -0.1006 | G148: k1 low -0.1676
A149: Cost reduction | B149: No Vaccination | C149: =L139 -> 0.17665289 | D149: =Y140 -> 0.16296488 | E149: =AK143 -> 0.2231405 | F149: =AW144 -> 0.17174587 | G149: =BI143 -> 0.16942149
B150: Constant Vaccination | C150: =L140 -> 0.070011669 | D150: =Y141 -> 0.054550758 | E150: =AK144 -> 0.12252042 | F150: =AW145 -> 0.064469078 | G150: =BI144 -> 0.061843641
A151: Peak Hosp reduction | B151: No Vaccination | C151: =M116 -> 0.65629291 | D151: =Z115 -> 0.65583524 | E151: =AL116 -> 0.65629291 | F151: =AX113 -> 0.65629291 | G151: =BJ113 -> 0.65629291
B152: Constant Vaccination | C152: =M117 -> 0.65247571 | D152: =Z116 -> 0.65201296 | E152: =AL117 -> 0.65247571 | F152: =AX114 -> 0.65247571 | G152: =BJ114 -> 0.65247571
A153: Peak ICU reduction | B153: No Vaccination | C153: =N116 -> 0.83291615 | D153: =AA115 -> 0.73404255 | E153: =AM116 -> 0.80162703 | F153: =AY113 -> 0.8097622 | G153: =BK113 -> 0.79411765
B154: Constant Vaccination | C154: =N117 -> 0.827853 | D154: =AA116 -> 0.72598324 | E154: =AM117 -> 0.79561573 | F154: =AY114 -> 0.80399742 | G154: =BK114 -> 0.78787879

Sheet net_migration
B1: Overseas migrant arrivals and departures by visa group by state, quarterly and financial years, from September quarter 2006 onwards
B2: Frequency: Quarterly
B4: Time Period | C4: Time Period | D4: 2020-Q1 | E4: 2020-Q2 | F4: 2020-Q3 | G4: 2020-Q4 | H4: 2021-Q1 | I4: 2021-Q2 | J4: 2021-Q3 | K4: 2021-Q4 | L4: 2022-Q1 | M4: 2022-Q2 | N4: 2022-Q3 | O4: 2022-Q4 | P4: 2023-Q1 | Q4: 2023-Q2 | R4: 2023-Q3 | S4: 2023-Q4
B5: Visa and Citizenship Groups
B6: Migration Type: Migrant arrivals
B7: Region: Victoria
B8: Unit of measure: Persons
B9: Total | D9: 48160 | E9: 3080 | F9: 2500 | G9: 6010 | H9: 8850 | I9: 9790 | J9: 9330 | K9: 30680 | L9: 50970 | M9: 38330 | N9: 51700 | O9: 49780 | P9: 63040 | Q9: 48530 | R9: 56890 | S9: 46880
B10: · Permanent visa - Total | D10: 6250 | E10: 1060 | F10: 650 | G10: 1720 | H10: 2910 | I10: 3720 | J10: 3260 | K10: 7310 | L10: 6520 | M10: 6020 | N10: 5670 | O10: 6380 | P10: 6530 | Q10: 6900 | R10: 6310 | S10: 7660
B11: · · Permanent visa - Family | D11: 2000 | E11: 400 | F11: 260 | G11: 750 | H11: 1190 | I11: 1720 | J11: 1250 | K11: 2820 | L11: 2200 | M11: 1770 | N11: 1600 | O11: 1890 | P11: 1600 | Q11: 1790 | R11: 1710 | S11: 2600
B12: · · Permanent visa - Skill | D12: 2470 | E12: 500 | F12: 250 | G12: 700 | H12: 1250 | I12: 1430 | J12: 1310 | K12: 2850 | L12: 2800 | M12: 2300 | N12: 2340 | O12: 2250 | P12: 3000 | Q12: 3000 | R12: 2670 | S12: 2800
B13: · · Permanent visa - Special eligibility and humanitarian | D13: 980 | E13: 0 | F13: 0 | G13: 30 | H13: 40 | I13: 80 | J13: 330 | K13: 790 | L13: 610 | M13: 1020 | N13: 880 | O13: 1320 | P13: 930 | Q13: 1290 | R13: 1180 | S13: 1440
B14: · · Permanent visa - Other permanent visas | D14: 790 | E14: 160 | F14: 130 | G14: 240 | H14: 430 | I14: 500 | J14: 370 | K14: 850 | L14: 920 | M14: 930 | N14: 850 | O14: 920 | P14: 990 | Q14: 820 | R14: 750 | S14: 820
B15: · Temporary visa - Total | D15: 33360 | E15: 320 | F15: 370 | G15: 910 | H15: 1390 | I15: 1720 | J15: 2430 | K15: 16660 | L15: 37120 | M15: 26190 | N15: 39390 | O15: 35570 | P15: 48710 | Q15: 35670 | R15: 43780 | S15: 30930
B16: · · Temporary visa - Student | D16: 14050 | E16: 0 | F16: 0 | G16: 40 | H16: 110 | I16: 150 | J16: 200 | K16: 10500 | L16: 25590 | M16: 10460 | N16: 21850 | O16: 14210 | P16: 28760 | Q16: 15560 | R16: 23730 | S16: 9400
B17: · · · Temporary visa - Student -Vocational education and training sector | D17: 730 | E17: 0 | F17: 0 | G17: 0 | H17: 10 | I17: 10 | J17: 10 | K17: 1350 | L17: 2090 | M17: 1650 | N17: 2320 | O17: 2380 | P17: 2400 | Q17: 2920 | R17: 2670 | S17: 1270
B18: · · · Temporary visa -Student - Higher education sector | D18: 10690 | E18: 0 | F18: 0 | G18: 20 | H18: 70 | I18: 70 | J18: 80 | K18: 8200 | L18: 20610 | M18: 6120 | N18: 14900 | O18: 7280 | P18: 21320 | Q18: 8130 | R18: 16690 | S18: 5630
B19: · · · Temporary visa - student - Other temporary student visas | D19: 2630 | E19: 0 | F19: 0 | G19: 10 | H19: 40 | I19: 80 | J19: 110 | K19: 950 | L19: 2880 | M19: 2690 | N19: 4630 | O19: 4540 | P19: 5040 | Q19: 4510 | R19: 4370 | S19: 2500
B20: · · Temporary visa - Temporary work (skilled) | D20: 1760 | E20: 40 | F20: 100 | G20: 290 | H20: 510 | I20: 490 | J20: 560 | K20: 1430 | L20: 2010 | M20: 2320 | N20: 2960 | O20: 3630 | P20: 3870 | Q20: 3320 | R20: 3530 | S20: 2850
... B26: · Other Visas | D26: 140 | E26: 10 | F26: 10 | G26: 20 | H26: 30 | I26: 30 | J26: 360 | K26: 110 | L26: 60 | M26: 60 | N26: 100 | O26: 0 | P26: 0 | Q26: 0 | R26: 0 | S26: 0
B27: Migration Type: Migrant departures
B28: Region: Victoria
B29: Unit of measure: Persons
B30: Total | D30: 26750 | E30: 5590 | F30: 23100 | G30: 24690 | H30: 18730 | I30: 13620 | J30: 14270 | K30: 17580 | L30: 15590 | M30: 15820 | N30: 14130 | O30: 12190 | P30: 13260 | Q30: 13250 | R30: 13730 | S30: 14920
B31: · Permanent visa - Total | D31: 2470 | E31: 240 | F31: 1510 | G31: 2280 | H31: 1710 | I31: 1530 | J31: 1620 | K31: 2360 | L31: 1720 | M31: 1670 | N31: 1340 | O31: 1390 | P31: 1620 | Q31: 1540 | R31: 1440 | S31: 1590
B32: · · Permanent visa - Family | D32: 660 | E32: 60 | F32: 320 | G32: 420 | H32: 360 | I32: 400 | J32: 380 | K32: 560 | L32: 440 | M32: 480 | N32: 370 | O32: 340 | P32: 460 | Q32: 430 | R32: 380 | S32: 370
B33: · · Permanent visa - Skill | D33: 920 | E33: 90 | F33: 660 | G33: 1030 | H33: 650 | I33: 540 | J33: 620 | K33: 740 | L33: 430 | M33: 460 | N33: 330 | O33: 400 | P33: 340 | Q33: 330 | R33: 310 | S33: 440
B34: · · Permanent visa - Special eligibility and humanitarian | D34: 10 | E34: 0 | F34: 0 | G34: 10 | H34: 10 | I34: 0 | J34: 10 | K34: 10 | L34: 10 | M34: 10 | N34: 10 | O34: 10 | P34: 10 | Q34: 10 | R34: 20 | S34: 10
B35: · · Permanent visa - Other permanent visas | D35: 880 | E35: 90 | F35: 520 | G35: 830 | H35: 700 | I35: 590 | J35: 630 | K35: 1050 | L35: 830 | M35: 730 | N35: 630 | O35: 640 | P35: 810 | Q35: 770 | R35: 730 | S35: 760
B36: · Temporary visa - Total | D36: 17860 | E36: 4440 | F36: 16520 | G36: 16800 | H36: 13290 | I36: 7980 | J36: 7860 | K36: 9170 | L36: 7410 | M36: 5960 | N36: 5360 | O36: 4860 | P36: 5610 | Q36: 5020 | R36: 5540 | S36: 7220
B37: · · Temporary visa - Student | D37: 8100 | E37: 1740 | F37: 9180 | G37: 9120 | H37: 4490 | I37: 1880 | J37: 2680 | K37: 2880 | L37: 1840 | M37: 870 | N37: 970 | O37: 1030 | P37: 1280 | Q37: 1060 | R37: 1880 | S37: 2760
B38: · · · Temporary visa - Student -Vocational education and training sector | D38: 2140 | E38: 810 | F38: 1510 | G38: 970 | H38: 710 | I38: 480 | J38: 510 | K38: 540 | L38: 460 | M38: 400 | N38: 310 | O38: 260 | P38: 350 | Q38: 260 | R38: 350 | S38: 410
B39: · · · Temporary visa -Student - Higher education sector | D39: 5190 | E39: 670 | F39: 6930 | G39: 7060 | H39: 3240 | I39: 1160 | J39: 1790 | K39: 1870 | L39: 1170 | M39: 320 | N39: 520 | O39: 600 | P39: 710 | Q39: 580 | R39: 1110 | S39: 1840
B40: · · · Temporary visa - student - Other temporary student visas | D40: 780 | E40: 260 | F40: 750 | G40: 1100 | H40: 540 | I40: 240 | J40: 380 | K40: 470 | L40: 210 | M40: 150 | N40: 140 | O40: 170 | P40: 220 | Q40: 220 | R40: 420 | S40: 500
B41: · · Temporary visa - Temporary work (skilled) | D41: 1100 | E41: 370 | F41: 990 | G41: 880 | H41: 750 | I41: 710 | J41: 590 | K41: 690 | L41: 420 | M41: 540 | N41: 360 | O41: 280 | P41: 270 | Q41: 340 | R41: 290 | S41: 370
... B47: · Other Visas | D47: 230 | E47: 60 | F47: 160 | G47: 440 | H47: 100 | I47: 110 | J47: 300 | K47: 370 | L47: 240 | M47: 330 | N47: 540 | O47: 0 | P47: 0 | Q47: 0 | R47: 0 | S47: 0
D48: =D9-D30 -> 21410 | E48: =E9-E30 -> -2510 | F48: =F9-F30 -> -20600 | G48: =G9-G30 -> -18680 | H48: =H9-H30 -> -9880 | I48: =I9-I30 -> -3830 | J48: =J9-J30 -> -4940 | K48: =K9-K30 -> 13100 | ... S48: =S9-S30 -> 31960 | V48: https://explore.data.abs.gov.au/vis?fs[0]=People%2C1%7CPopulation%23POPULATION%23%7COverseas%20Migration%23OVERSEAS_MIGRATION%23&pg=0&fc=People&df[ds]=PEOPLE_TOPICS&df[id]=OMAD_VISA&df[ag]=ABS&df[vs]=&pd=2020-Q1%2C&dq=..2%2BAUS.Q&ly[cl]=TIME_PERIOD&ly[rw]=VISA&ly[rs]=MEASURE
K50: N | L50: annual data | M50: annual rate | N50: daily data | O50: daily rate | P50: daily rate | S50: [S4] Spain | T50: fertilty rate of spain = 1.2, au=1.6
I51: 2021 | J51: migration | N51: =K48/(31+30+31) -> 142.3913 | O51: =N51/K52 -> 2.1745638e-05 | V51: https://www.abs.gov.au/statistics/people/population/births-australia/2022
J52: birth | K52: 6548040 | L52: 75363 | M52: =L52/K52 -> 0.011509246 | N52: =L52/365 -> 206.47397 | O52: =N52/K52 -> 3.1532179e-05 | P52: =(N52+N51)/K52 -> 5.3277817e-05 | S52: =1165/47431256 -> 2.4561863e-05 | T52: =S52/1.2*1.6 -> 3.274915e-05 | V52: https://www.abs.gov.au/statistics/people/population/deaths-australia/2022
J53: death | K53: 6547822 | L53: 42486 | M53: =L53/K53 -> 0.0064885698 | N53: =L53/4 -> 10621.5 | O53: =N53-N54 -> 10621.5 | P53: =D73 -> 3.2724015e-05 | S53: 3.3e-05
C57: sex ratio
C58: Age | D58: Age | E58: All ages
C59: Sex
C60: Time Period: 2021
C61: Persons | E61: 6547822
C62: · Males | E62: 3237594
C63: · Females | E63: 3310228
C67: Life expectancy at birth by state and territory of usual residence
D68: 2019-2021
D69: Males | E69: Females
C70: Vic. | D70: 81.7 | E70: 85.7
C71: prop% | D71: =E62/E61 -> 0.49445358 | E71: =E63/E61 -> 0.50554642
C72: e_x | D72: =D70*D71+E70*E71 -> 83.722186
C73: 1/e_0 | D73: =1/(D72*365) -> 3.2724015e-05 | E73: force of mortality

Sheet Sheet1
B3: Monte Carlo Simulation Results
B5: Outcome Metric | C5: No Vacc | D5: Constant | E5: Actual | F5: Optimal | G5: Actual vs No | H5: Optimal vs No | I5: Actual vs No | J5: Optimal vs No
B6: Epidemiological outcomes
B7: Peak infection prevalence (%) | C7: 0.566 | D7: 0.563 | E7: 0.565 | F7: 0.563 | G7: -0.2% | H7: -0.6% | I7: =E7/C7-1 -> -0.0017667845 | J7: =F7/C7-1 -> -0.0053003534 | K7: =J7-I7 -> -0.0035335689
B8: Peak hospitalised (persons) | C8: 1448 | D8: 1433 | E8: 498 | F8: 498 | G8: -65.6% | H8: -65.6% | I8: =E8/C8-1 -> -0.65607735 | J8: =F8/C8-1 -> -0.65607735 | K8: =J8-I8 -> 0
B9: Peak ICU (persons) | C9: 1059 | D9: 1028 | E9: 278 | F9: 210 | G9: -73.8% | H9: -80.2% | I9: =E9/C9-1 -> -0.7374882 | J9: =F9/C9-1 -> -0.80169972 | K9: =J9-I9 -> -0.06421152
B10: Cumulative hospital-days | C10: 27456 | D10: 23439 | E10: 5450 | F10: 4042 | G10: -80.2% | H10: -85.3% | I10: =E10/C10-1 -> -0.80150058 | J10: =F10/C10-1 -> -0.85278263 | K10: =J10-I10 -> -0.051282051
B11: Cumulative ICU-days | C11: 27063 | D11: 23496 | E11: 6031 | F11: 4663 | G11: -77.7% | H11: -82.8% | I11: =E11/C11-1 -> -0.77714961 | J11: =F11/C11-1 -> -0.82769833 | K11: =J11-I11 -> -0.05054872
B12: Cumulative deaths | C12: 110.9 | D12: 96 | E12: 23 | F12: 17.3 | G12: -79.3% | H12: -84.4% | I12: =E12/C12-1 -> -0.79260595 | J12: =F12/C12-1 -> -0.84400361 | K12: =J12-I12 -> -0.051397656
B13: Cost outcomes (units)
B14: Vaccination costs | C14: 0 | D14: 1.71 | E14: 1.96 | F14: 2.45 | G14: – | H14: –
B15: Quarantine costs | C15: 1.66 | D15: 1.37 | E15: 1.39 | F15: 1.3 | G15: -16.3% | H15: -21.9% | I15: =E15/C15-1 -> -0.1626506 | J15: =F15/C15-1 -> -0.21686747 | K15: =J15-I15 -> -0.054216867
B16: Healthcare costs | C16: 9.5 | D16: 8.13 | E16: 5.21 | F16: 4.72 | G16: -45.2% | H16: -50.3% | I16: =E16/C16-1 -> -0.45157895 | J16: =F16/C16-1 -> -0.50315789 | K16: =J16-I16 -> -0.051578947
B17: Economic productivity loss | C17: 27.56 | D17: 23.07 | E17: 23.09 | F17: 21.62 | G17: -16.2% | H17: -21.6% | I17: =E17/C17-1 -> -0.16219158 | J17: =F17/C17-1 -> -0.21552975 | K17: =J17-I17 -> -0.053338171
B18: Total cost | C18: 38.72 | D18: 34.28 | E18: 31.65 | F18: 30.08 | G18: -18.3% | H18: -22.3% | I18: =E18/C18-1 -> -0.18259298 | J18: =F18/C18-1 -> -0.2231405 | K18: =J18-I18 -> -0.040547521

Sheet birth_vic
A1: Australian Bureau of Statistics
A2: =[1]Contents!A2 -> 33010DO003 Births, Australia, 2021
A3: =[1]Contents!A3 -> Released at 11.30am (Canberra time) Tuesday 25 October 2022
A4: Table 3.2 Births, Summary, Local Government Areas, Victoria–2011 to 2021
C6: 2011 | G6: 2012 | K6: 2013 | O6: 2014 | S6: 2015 | W6: 2016 | AA6: 2017 | AE6: 2018 | AI6: 2019 | AM6: 2020 | AQ6: 2021
A7: Local government area of usual address | C7: Estimated resident population | D7: Births | E7: Total fertility rate | G7: Estimated resident population | H7: Births | I7: Total fertility rate | K7: Estimated resident population | L7: Births | M7: Total fertility rate | O7: Estimated resident population | P7: Births | Q7: Total fertility rate | S7: Estimated resident population | T7: Births | U7: Total fertility rate | W7: Estimated resident population | X7: Births | Y7: Total fertility rate | AA7: Estimated resident population | AB7: Births | AC7: Total fertility rate | AE7: Estimated resident population | AF7: Births | AG7: Total fertility rate | AI7: Estimated resident population | AJ7: Births | AK7: Total fertility rate | AM7: Estimated resident population | AN7: Births | AO7: Total fertility rate | AQ7: Estimated resident population | AR7: Births | AS7: Total fertility rate
A8: LGA Code 2021 | B8: LGA Name 2021 | C8: persons | D8: no. | E8: rate | G8: persons | H8: no. | I8: rate | K8: persons | L8: no. | M8: rate | O8: persons | P8: no. | Q8: rate | S8: persons | T8: no. | U8: rate | W8: persons | X8: no. | Y8: rate | AA8: persons | AB8: no. | AC8: rate | AE8: persons | AF8: no. | AG8: rate | AI8: persons | AJ8: no. | AK8: rate | AM8: persons | AN8: no. | AO8: rate | AQ8: persons | AR8: no. | AS8: rate
A9: 20110 | B9: Alpine | C9: 12068 | D9: 89 | E9: np | G9: 12183 | H9: 108 | I9: np | K9: 12283 | L9: 86 | M9: 1.8 | O9: 12355 | P9: 87 | Q9: 1.78 | S9: 12429 | T9: 99 | U9: 1.72 | W9: 12578 | X9: 97 | Y9: 1.77 | AA9: 12679 | AB9: 118 | AC9: 1.91 | AE9: 12807 | AF9: 93 | AG9: 1.79 | AI9: 12884 | AJ9: 95 | AK9: 1.71 | AM9: 13028 | AN9: 92 | AO9: 1.51 | AQ9: 13156 | AR9: 109 | AS9: 1.58
A10: 20260 | B10: Ararat | C10: 11326 | D10: 111 | E10: np | G10: 11400 | H10: 126 | I10: np | K10: 11490 | L10: 116 | M10: 2.24 | O10: 11560 | P10: 113 | Q10: 2.25 | S10: 11644 | T10: 108 | U10: 2.1 | W10: 11745 | X10: 112 | Y10: 2.06 | AA10: 11790 | AB10: 124 | AC10: 2.1 | AE10: 11792 | AF10: 101 | AG10: 2.03 | AI10: 11822 | AJ10: 125 | AK10: 2.03 | AM10: 11896 | AN10: 105 | AO10: 1.86 | AQ10: 11821 | AR10: 103 | AS10: 1.84
A11: 20570 | B11: Ballarat | C11: 95185 | D11: 1209 | E11: np | G11: 96728 | H11: 1323 | I11: np | K11: 98344 | L11: 1357 | M11: 1.99 | O11: 99914 | P11: 1258 | Q11: 1.98 | S11: 101479 | T11: 1288 | U11: 1.93 | W11: 103500 | X11: 1367 | Y11: 1.91 | AA11: 105498 | AB11: 1409 | AC11: 1.94 | AE11: 107518 | AF11: 1264 | AG11: 1.89 | AI11: 109650 | AJ11: 1297 | AK11: 1.81 | AM11: 111476 | AN11: 1225 | AO11: 1.69 | AQ11: 113482 | AR11: 1358 | AS11: 1.7
A12: 20660 | B12: Banyule | C12: 122983 | D12: 1726 | E12: np | G12: 123584 | H12: 1645 | I12: np | K12: 124314 | L12: 1635 | M12: 1.91 | O12: 125107 | P12: 1594 | Q12: 1.85 | S12: 126088 | T12: 1532 | U12: 1.79 | W12: 127447 | X12: 1757 | Y12: 1.83 | AA12: 128601 | AB12: 1628 | AC12: 1.82 | AE12: 129548 | AF12: 1572 | AG12: 1.82 | AI12: 130478 | AJ12: 1513 | AK12: 1.7 | AM12: 130121 | AN12: 1369 | AO12: 1.6 | AQ12: 127376 | AR12: 1413 | AS12: 1.55
A13: 20740 | B13: Bass Coast | C13: 30233 | D13: 365 | E13: np | G13: 30811 | H13: 344 | I13: np | K13: 31331 | L13: 302 | M13: 2.29 | O13: 31917 | P13: 362 | Q13: 2.26 | S13: 32576 | T13: 285 | U13: 2.11 | W13: 33464 | X13: 341 | Y13: 2.16 | AA13: 34726 | AB13: 367 | AC13: 2.1 | AE13: 36041 | AF13: 353 | AG13: 2.14 | AI13: 37382 | AJ13: 297 | AK13: 1.95 | AM13: 38869 | AN13: 295 | AO13: 1.73 | AQ13: 40641 | AR13: 370 | AS13: 1.7
A14: 20830 | B14: Baw Baw | C14: 43389 | D14: 515 | E14: np | G14: 44506 | H14: 529 | I14: np | K14: 45627 | L14: 524 | M14: 2.09 | O14: 46644 | P14: 552 | Q14: 2.09 | S14: 47837 | T14: 544 | U14: 2.05 | W14: 49296 | X14: 653 | Y14: 2.14 | AA14: 50852 | AB14: 625 | AC14: 2.14 | AE14: 52392 | AF14: 623 | AG14: 2.12 | AI14: 53970 | AJ14: 653 | AK14: 2.01 | AM14: 55647 | AN14: 619 | AO14: 1.91 | AQ14: 57580 | AR14: 726 | AS14: 1.92
A15: 20910 | B15: Bayside (Vic.) | C15: 96119 | D15: 948 | E15: np | G15: 96971 | H15: 927 | I15: np | K15: 98252 | L15: 935 | M15: 1.75 | O15: 99797 | P15: 979 | Q15: 1.77 | S15: 101268 | T15: 907 | U15: 1.73 | W15: 102912 | X15: 962 | Y15: 1.72 | AA15: 103621 | AB15: 956 | AC15: 1.69 | AE15: 104545 | AF15: 892 | AG15: 1.67 | AI15: 105029 | AJ15: 846 | AK15: 1.6 | AM15: 104881 | AN15: 791 | AO15: 1.51 | AQ15: 102337 | AR15: 851 | AS15: 1.54
A16: 21010 | B16: Benalla | C16: 13818 | D16: 105 | E16: np | G16: 13849 | H16: 143 | I16: np | K16: 13878 | L16: 134 | M16: 1.98 | O16: 13898 | P16: 140 | Q16: 2.13 | S16: 13923 | T16: 120 | U16: 1.99 | W16: 13982 | X16: 123 | Y16: 1.92 | AA16: 14041 | AB16: 136 | AC16: 1.88 | AE16: 14145 | AF16: 164 | AG16: 2.06 | AI16: 14219 | AJ16: 125 | AK16: 2.04 | AM16: 14358 | AN16: 129 | AO16: 1.98 | AQ16: 14431 | AR16: 136 | AS16: 1.86
A17: 21110 | B17: Boroondara | C17: 167062 | D17: 1561 | E17: np | G17: 168483 | H17: 1576 | I17: np | K17: 170485 | L17: 1511 | M17: 1.41 | O17: 172660 | P17: 1455 | Q17: 1.36 | S17: 174753 | T17: 1522 | U17: 1.32 | W17: 177276 | X17: 1635 | Y17: 1.34 | AA17: 178591 | AB17: 1520 | AC17: 1.34 | AE17: 179295 | AF17: 1392 | AG17: 1.29 | AI17: 179547 | AJ17: 1413 | AK17: 1.23 | AM17: 177722 | AN17: 1236 | AO17: 1.16 | AQ17: 169901 | AR17: 1228 | AS17: 1.15
A18: 21180 | B18: Brimbank | C18: 191496 | D18: 2812 | E18: np | G18: 193774 | H18: 3036 | I18: np | K18: 196169 | L18: 2822 | M18: 1.95 | O18: 198468 | P18: 2806 | Q18: 1.93 | S18: 200860 | T18: 2818 | U18: 1.87 | W18: 204190 | X18: 3065 | Y18: 1.9 | AA18: 206036 | AB18: 2964 | AC18: 1.91 | AE18: 206849 | AF18: 2812 | AG18: 1.9 | AI18: 206611 | AJ18: 2584 | AK18: 1.8 | AM18: 203999 | AN18: 2399 | AO18: 1.69 | AQ18: 196712 | AR18: 2180 | AS18: 1.6
A19: 21270 | B19: Buloke | C19: 6465 | D19: 42 | E19: np | G19: 6434 | H19: 52 | I19: np | K19: 6388 | L19: 55 | M19: 1.97 | O19: 6335 | P19: 52 | Q19: 2.14 | S19: 6306 | T19: 60 | U19: 2.24 | W19: 6284 | X19: 49 | Y19: 2.22 | AA19: 6218 | AB19: 51 | AC19: 2.2 | AE19: 6208 | AF19: 51 | AG19: 2.12 | AI19: 6159 | AJ19: 58 | AK19: 2.2 | AM19: 6146 | AN19: 64 | AO19: 2.35 | AQ19: 6130 | AR19: 62 | AS19: 2.43
A20: 21370 | B20: Campaspe | C20: 36855 | D20: 408 | E20: np | G20: 37041 | H20: 431 | I20: np | K20: 37213 | L20: 447 | M20: 2.3 | O20: 37338 | P20: 428 | Q20: 2.32 | S20: 37429 | T20: 408 | U20: 2.26 | W20: 37595 | X20: 430 | Y20: 2.21 | AA20: 37780 | AB20: 397 | AC20: 2.14 | AE20: 37913 | AF20: 395 | AG20: 2.08 | AI20: 38084 | AJ20: 391 | AK20: 1.97 | AM20: 38317 | AN20: 384 | AO20: 1.92 | AQ20: 38545 | AR20: 396 | AS20: 1.93
... A68: 25990 | B68: Pyrenees | C68: 6759 | D68: 72 | E68: np | G68: 6860 | H68: 58 | I68: np | K68: 6938 | L68: 60 | M68: 2.26 | O68: 7047 | P68: 69 | Q68: 2.22 | S68: 7179 | T68: 58 | U68: 2.19 | W68: 7316 | X68: 58 | Y68: 2.1 | AA68: 7320 | AB68: 56 | AC68: 1.93 | AE68: 7320 | AF68: 57 | AG68: 1.88 | AI68: 7438 | AJ68: 59 | AK68: 1.85 | AM68: 7530 | AN68: 68 | AO68: 1.94 | AQ68: 7613 | AR68: 54 | AS68: 1.89
A69: 26080 | B69: Queenscliffe | C69: 3061 | D69: 18 | E69: np | G69: 3057 | H69: 21 | I69: np | K69: 3002 | L69: 13 | M69: 1.55 | O69: 2970 | P69: 16 | Q69: 1.67 | S69: 2933 | T69: 6 | U69: np | W69: 2929 | X69: 16 | Y69: 1.43 | AA69: 2921 | AB69: 17 | AC69: 1.47 | AE69: 2951 | AF69: 18 | AG69: 1.9 | AI69: 2968 | AJ69: 16 | AK69: 1.93 | AM69: 3089 | AN69: 12 | AO69: 1.76 | AQ69: 3235 | AR69: 21 | AS69: np
A70: 26170 | B70: South Gippsland | C70: 27512 | D70: 286 | E70: np | G70: 27926 | H70: 306 | I70: np | K70: 28273 | L70: 311 | M70: 2.26 | O70: 28521 | P70: 309 | Q70: 2.31 | S70: 28781 | T70: 286 | U70: 2.26 | W70: 29122 | X70: 310 | Y70: 2.23 | AA70: 29346 | AB70: 282 | AC70: 2.13 | AE70: 29577 | AF70: 289 | AG70: 2.08 | AI70: 29887 | AJ70: 267 | AK70: 1.92 | AM70: 30222 | AN70: 247 | AO70: 1.82 | AQ70: 30378 | AR70: 257 | AS70: 1.8
A71: 26260 | B71: Southern Grampians | C71: 16571 | D71: 169 | E71: np | G71: 16461 | H71: 186 | I71: np | K71: 16355 | L71: 181 | M71: 2.19 | O71: 16255 | P71: 159 | Q71: 2.16 | S71: 16162 | T71: 168 | U71: 2.11 | W71: 16123 | X71: 197 | Y71: 2.19 | AA71: 16199 | AB71: 193 | AC71: 2.32 | AE71: 16276 | AF71: 177 | AG71: 2.34 | AI71: 16360 | AJ71: 164 | AK71: 2.16 | AM71: 16479 | AN71: 169 | AO71: 2.03 | AQ71: 16488 | AR71: 178 | AS71: 2.04
A72: 26350 | B72: Stonnington | C72: 98853 | D72: 979 | E72: np | G72: 101410 | H72: 1085 | I72: np | K72: 103487 | L72: 1049 | M72: 1.16 | O72: 105894 | P72: 1047 | Q72: 1.15 | S72: 108028 | T72: 1017 | U72: 1.1 | W72: 111003 | X72: 1135 | Y72: 1.09 | AA72: 112102 | AB72: 1187 | AC72: 1.11 | AE72: 113287 | AF72: 1035 | AG72: 1.1 | AI72: 113739 | AJ72: 1033 | AK72: 1.06 | AM72: 112524 | AN72: 898 | AO72: 0.97 | AQ72: 106278 | AR72: 998 | AS72: 0.97
A73: 26430 | B73: Strathbogie | C73: 9598 | D73: 80 | E73: np | G73: 9744 | H73: 87 | I73: np | K73: 9867 | L73: 86 | M73: 2.08 | O73: 10018 | P73: 78 | Q73: 2.02 | S73: 10175 | T73: 91 | U73: 1.98 | W73: 10357 | X73: 88 | Y73: 1.94 | AA73: 10527 | AB73: 93 | AC73: 1.99 | AE73: 10724 | AF73: 95 | AG73: 1.98 | AI73: 10894 | AJ73: 92 | AK73: 1.95 | AM73: 11139 | AN73: 82 | AO73: 1.82 | AQ73: 11364 | AR73: 115 | AS73: 1.97
A74: 26490 | B74: Surf Coast | C74: 26666 | D74: 321 | E74: np | G74: 27530 | H74: 359 | I74: np | K74: 28228 | L74: 322 | M74: 2.01 | O74: 28874 | P74: 299 | Q74: 1.9 | S74: 29625 | T74: 326 | U74: 1.81 | W74: 30465 | X74: 360 | Y74: 1.84 | AA74: 31535 | AB74: 344 | AC74: 1.86 | AE74: 32715 | AF74: 391 | AG74: 1.9 | AI74: 34164 | AJ74: 372 | AK74: 1.82 | AM74: 35758 | AN74: 360 | AO74: 1.76 | AQ74: 37623 | AR74: 450 | AS74: 1.79
A75: 26610 | B75: Swan Hill | C75: 20865 | D75: 297 | E75: np | G75: 20971 | H75: 346 | I75: np | K75: 21003 | L75: 318 | M75: 2.6 | O75: 20940 | P75: 254 | Q75: 2.47 | S75: 20893 | T75: 293 | U75: 2.32 | W75: 20896 | X75: 326 | Y75: 2.34 | AA75: 21059 | AB75: 324 | AC75: 2.48 | AE75: 21224 | AF75: 307 | AG75: 2.44 | AI75: 21387 | AJ75: 273 | AK75: 2.2 | AM75: 21472 | AN75: 304 | AO75: 2.08 | AQ75: 21383 | AR75: 288 | AS75: 1.99
A76: 26670 | B76: Towong | C76: 5918 | D76: 52 | E76: np | G76: 5940 | H76: 47 | I76: np | K76: 5961 | L76: 44 | M76: 2.04 | O76: 5982 | P76: 54 | Q76: 2 | S76: 6005 | T76: 53 | U76: 2.08 | W76: 6046 | X76: 67 | Y76: 2.38 | AA76: 6060 | AB76: 60 | AC76: 2.45 | AE76: 6094 | AF76: 42 | AG76: 2.29 | AI76: 6134 | AJ76: 42 | AK76: 1.94 | AM76: 6160 | AN76: 44 | AO76: 1.71 | AQ76: 6183 | AR76: 55 | AS76: 1.87
A77: 26700 | B77: Wangaratta | C77: 27212 | D77: 314 | E77: np | G77: 27438 | H77: 322 | I77: np | K77: 27650 | L77: 282 | M77: 2.18 | O77: 27862 | P77: 267 | Q77: 2.05 | S77: 28143 | T77: 300 | U77: 1.97 | W77: 28592 | X77: 299 | Y77: 1.98 | AA77: 28936 | AB77: 333 | AC77: 2.09 | AE77: 29241 | AF77: 292 | AG77: 2.03 | AI77: 29403 | AJ77: 293 | AK77: 1.97 | AM77: 29468 | AN77: 285 | AO77: 1.83 | AQ77: 29740 | AR77: 300 | AS77: 1.85
A78: 26730 | B78: Warrnambool | C78: 32667 | D78: 396 | E78: np | G78: 33059 | H78: 416 | I78: np | K78: 33423 | L78: 363 | M78: 1.9 | O78: 33729 | P78: 398 | Q78: 1.89 | S78: 34005 | T78: 359 | U78: 1.78 | W78: 34242 | X78: 440 | Y78: 1.89 | AA78: 34501 | AB78: 346 | AC78: 1.78 | AE78: 34791 | AF78: 399 | AG78: 1.81 | AI78: 35060 | AJ78: 359 | AK78: 1.66 | AM78: 35358 | AN78: 366 | AO78: 1.68 | AQ78: 35419 | AR78: 357 | AS78: 1.61
A79: 26810 | B79: Wellington | C79: 42068 | D79: 458 | E79: np | G79: 42445 | H79: 519 | I79: np | K79: 42721 | L79: 461 | M79: 2.12 | O79: 42948 | P79: 438 | Q79: 2.08 | S79: 43172 | T79: 474 | U79: 1.99 | W79: 43530 | X79: 510 | Y79: 2.04 | AA79: 43849 | AB79: 511 | AC79: 2.12 | AE79: 44191 | AF79: 475 | AG79: 2.1 | AI79: 44620 | AJ79: 479 | AK79: 2.03 | AM79: 45029 | AN79: 440 | AO79: 1.91 | AQ79: 45452 | AR79: 459 | AS79: 1.89
A80: 26890 | B80: West Wimmera | C80: 4287 | D80: 40 | E80: np | G80: 4214 | H80: 40 | I80: np | K80: 4124 | L80: 43 | M80: 2.24 | O80: 4038 | P80: 39 | Q80: 2.21 | S80: 3974 | T80: 42 | U80: 2.24 | W80: 3937 | X80: 40 | Y80: 2.21 | AA80: 3951 | AB80: 46 | AC80: 2.38 | AE80: 3962 | AF80: 53 | AG80: 2.59 | AI80: 3974 | AJ80: 40 | AK80: 2.62 | AM80: 3988 | AN80: 55 | AO80: 2.82 | AQ80: 3977 | AR80: 42 | AS80: 2.65
A81: 26980 | B81: Whitehorse | C81: 157538 | D81: 1874 | E81: np | G81: 159661 | H81: 1915 | I81: np | K81: 162081 | L81: 1752 | M81: 1.69 | O81: 164320 | P81: 1891 | Q81: 1.67 | S81: 166679 | T81: 1735 | U81: 1.58 | W81: 169641 | X81: 1845 | Y81: 1.57 | AA81: 172315 | AB81: 1858 | AC81: 1.52 | AE81: 174332 | AF81: 1647 | AG81: 1.46 | AI81: 175738 | AJ81: 1600 | AK81: 1.37 | AM81: 176622 | AN81: 1471 | AO81: 1.26 | AQ81: 171167 | AR81: 1381 | AS81: 1.19
... A87: 27630 | B87: Yarriambiack | C87: 7183 | D87: 73 | E87: np | G87: 7095 | H87: 57 | I87: np | K87: 7032 | L87: 60 | M87: 2.45 | O87: 6924 | P87: 50 | Q87: 2.09 | S87: 6826 | T87: 59 | U87: 2.09 | W87: 6743 | X87: 63 | Y87: 2.07 | AA87: 6705 | AB87: 64 | AC87: 2.21 | AE87: 6693 | AF87: 63 | AG87: 2.25 | AI87: 6669 | AJ87: 47 | AK87: 2.06 | AM87: 6633 | AN87: 69 | AO87: 2.1 | AQ87: 6511 | AR87: 57 | AS87: 2.06
A88: 29399 | B88: Unincorporated Vic | C88: 769 | D88: 3 | E88: np | G88: 797 | H88: 5 | I88: np | K88: 808 | L88: 0 | M88: np | O88: 835 | P88: 3 | Q88: np | S88: 862 | T88: 3 | U88: np | W88: 892 | X88: 5 | Y88: np | AA88: 901 | AB88: 4 | AC88: np | AE88: 911 | AF88: 3 | AG88: np | AI88: 918 | AJ88: 6 | AK88: np | AM88: 932 | AN88: 0 | AO88: np | AQ88: 946 | AR88: 3 | AS88: np
A89: 2 | B89: Total Victoria | C89: 5537817 | D89: 71444 | E89: np | G89: 5651091 | H89: 77405 | I89: np | K89: 5772669 | L89: 73969 | M89: 1.81 | O89: 5894917 | P89: 74224 | Q89: 1.79 | S89: 6022322 | T89: 73568 | U89: 1.71 | W89: 6173172 | X89: 82892 | Y89: 1.73 | AA89: 6299798 | AB89: 82094 | AC89: 1.74 | AE89: 6418168 | AF89: 78488 | AG89: 1.72 | AI89: 6530852 | AJ89: 77220 | AK89: 1.64 | AM89: 6606149 | AN89: 73543 | AO89: 1.55 | AQ89: 6548040 | AR89: 75363 | AS89: 1.52
A91: 0 nil or rounded to zero (including null cells)
A92: np not available for publication but included in totals where applicable, unless otherwise indicated
A95: © Commonwealth of Australia 2022

Sheet death_vic
A1: Australian Bureau of Statistics
A2: 33020DO005_2022 Deaths, Australia, 2022
A3: Released at 11:30 am (Canberra time) Thurs 28 Sep 2023
A4: Table 5.2 Deaths, Summary, Local Government Area, Victoria–2012 to 2022
C5: 2012 | G5: 2013 | K5: 2014 | O5: 2015 | S5: 2016 | W5: 2017 | AA5: 2018 | AE5: 2019 | AI5: 2020 | AM5: 2021 | AQ5: 2022
C6: Estimated resident population | D6: Deaths | E6: Standardised death rate | G6: Estimated resident population | H6: Deaths | I6: Standardised death rate | K6: Estimated resident population | L6: Deaths | M6: Standardised death rate | O6: Estimated resident population | P6: Deaths | Q6: Standardised death rate | S6: Estimated resident population | T6: Deaths | U6: Standardised death rate | W6: Estimated resident population | X6: Deaths | Y6: Standardised death rate | AA6: Estimated resident population | AB6: Deaths | AC6: Standardised death rate | AE6: Estimated resident population | AF6: Deaths | AG6: Standardised death rate | AI6: Estimated resident population | AJ6: Deaths | AK6: Standardised death rate | AM6: Estimated resident population | AN6: Deaths | AO6: Standardised death rate | AQ6: Estimated resident population | AR6: Deaths | AS6: Standardised death rate
A7: LGA Code 2023 | B7: 2023 LGA Name | C7: persons | D7: no. | E7: rate | G7: persons | H7: no. | I7: rate | K7: persons | L7: no. | M7: rate | O7: persons | P7: no. | Q7: rate | S7: persons | T7: no. | U7: rate | W7: persons | X7: no. | Y7: rate | AA7: persons | AB7: no. | AC7: rate | AE7: persons | AF7: no. | AG7: rate | AI7: persons | AJ7: no. | AK7: rate | AM7: persons | AN7: no. | AO7: rate | AQ7: persons | AR7: no. | AS7: rate
A8: 20110 | B8: Alpine | C8: 12183 | D8: 109 | E8: np | G8: 12283 | H8: 126 | I8: 5.5 | K8: 12355 | L8: 109 | M8: 5.6 | O8: 12429 | P8: 120 | Q8: 5.6 | S8: 12578 | T8: 128 | U8: 5.6 | W8: 12687 | X8: 139 | Y8: 5.7 | AA8: 12822 | AB8: 131 | AC8: 5.8 | AE8: 12904 | AF8: 152 | AG8: 6.1 | AI8: 13054 | AJ8: 104 | AK8: 5.6 | AM8: 13166 | AN8: 134 | AO8: 5.6 | AQ8: 13187 | AR8: 122 | AS8: 5.1
A9: 20260 | B9: Ararat | C9: 11400 | D9: 117 | E9: np | G9: 11490 | H9: 124 | I9: 6.8 | K9: 11560 | L9: 119 | M9: 6.2 | O9: 11644 | P9: 107 | Q9: 5.9 | S9: 11745 | T9: 119 | U9: 5.8 | W9: 11796 | X9: 134 | Y9: 5.9 | AA9: 11805 | AB9: 108 | AC9: 6 | AE9: 11838 | AF9: 128 | AG9: 6.2 | AI9: 11918 | AJ9: 104 | AK9: 5.6 | AM9: 11827 | AN9: 128 | AO9: 5.8 | AQ9: 11754 | AR9: 128 | AS9: 5.7
A10: 20570 | B10: Ballarat | C10: 96728 | D10: 699 | E10: np | G10: 98344 | H10: 751 | I10: 6.2 | K10: 99914 | L10: 797 | M10: 6 | O10: 101479 | P10: 833 | Q10: 6.2 | S10: 103500 | T10: 808 | U10: 6.2 | W10: 105551 | X10: 827 | Y10: 6.1 | AA10: 107608 | AB10: 821 | AC10: 5.9 | AE10: 109773 | AF10: 947 | AG10: 6 | AI10: 111645 | AJ10: 835 | AK10: 5.9 | AM10: 113504 | AN10: 928 | AO10: 5.9 | AQ10: 115951 | AR10: 1085 | AS10: 5.9
A11: 20660 | B11: Banyule | C11: 123584 | D11: 841 | E11: np | G11: 124314 | H11: 826 | I11: 5.1 | K11: 125107 | L11: 852 | M11: 4.8 | O11: 126088 | P11: 885 | Q11: 4.8 | S11: 127447 | T11: 799 | U11: 4.8 | W11: 128660 | X11: 885 | Y11: 4.7 | AA11: 129645 | AB11: 855 | AC11: 4.6 | AE11: 130607 | AF11: 1002 | AG11: 4.9 | AI11: 130294 | AJ11: 884 | AK11: 4.8 | AM11: 127370 | AN11: 878 | AO11: 4.8 | AQ11: 127348 | AR11: 1057 | AS11: 4.9
A12: 20740 | B12: Bass Coast | C12: 30811 | D12: 313 | E12: np | G12: 31331 | H12: 317 | I12: 5.7 | K12: 31917 | L12: 314 | M12: 5.5 | O12: 32576 | P12: 355 | Q12: 5.6 | S12: 33464 | T12: 325 | U12: 5.5 | W12: 34748 | X12: 384 | Y12: 5.6 | AA12: 36083 | AB12: 367 | AC12: 5.5 | AE12: 37440 | AF12: 375 | AG12: 5.5 | AI12: 38950 | AJ12: 376 | AK12: 5.3 | AM12: 40675 | AN12: 401 | AO12: 5.2 | AQ12: 41798 | AR12: 444 | AS12: 5.2
A13: 20830 | B13: Baw Baw | C13: 44506 | D13: 301 | E13: np | G13: 45627 | H13: 295 | I13: 5.2 | K13: 46644 | L13: 326 | M13: 5.2 | O13: 47837 | P13: 368 | Q13: 5.4 | S13: 49296 | T13: 376 | U13: 5.5 | W13: 50883 | X13: 369 | Y13: 5.4 | AA13: 52447 | AB13: 390 | AC13: 5.2 | AE13: 54047 | AF13: 414 | AG13: 5.2 | AI13: 55753 | AJ13: 437 | AK13: 5.3 | AM13: 57618 | AN13: 453 | AO13: 5.3 | AQ13: 59248 | AR13: 482 | AS13: 5.3
A14: 20910 | B14: Bayside (Vic.) | C14: 96971 | D14: 828 | E14: np | G14: 98252 | H14: 764 | I14: 4.7 | K14: 99797 | L14: 761 | M14: 4.6 | O14: 101268 | P14: 828 | Q14: 4.5 | S14: 102912 | T14: 801 | U14: 4.4 | W14: 103665 | X14: 794 | Y14: 4.4 | AA14: 104623 | AB14: 724 | AC14: 4.2 | AE14: 105128 | AF14: 849 | AG14: 4.3 | AI14: 105018 | AJ14: 817 | AK14: 4.3 | AM14: 102328 | AN14: 798 | AO14: 4.3 | AQ14: 102177 | AR14: 875 | AS14: 4.3
A15: 21010 | B15: Benalla | C15: 13849 | D15: 157 | E15: np | G15: 13878 | H15: 138 | I15: 6.2 | K15: 13898 | L15: 148 | M15: 5.9 | O15: 13923 | P15: 168 | Q15: 6.1 | S15: 13982 | T15: 160 | U15: 6.1 | W15: 14049 | X15: 181 | Y15: 6.4 | AA15: 14158 | AB15: 149 | AC15: 6 | AE15: 14237 | AF15: 168 | AG15: 6.1 | AI15: 14382 | AJ15: 171 | AK15: 5.8 | AM15: 14436 | AN15: 175 | AO15: 5.8 | AQ15: 14457 | AR15: 220 | AS15: 6.2
A16: 21110 | B16: Boroondara | C16: 168483 | D16: 1084 | E16: np | G16: 170485 | H16: 1138 | I16: 4.5 | K16: 172660 | L16: 1122 | M16: 4.4 | O16: 174753 | P16: 1138 | Q16: 4.5 | S16: 177276 | T16: 1146 | U16: 4.4 | W16: 178650 | X16: 1128 | Y16: 4.3 | AA16: 179386 | AB16: 1049 | AC16: 4.2 | AE16: 179663 | AF16: 1156 | AG16: 4.1 | AI16: 177875 | AJ16: 999 | AK16: 3.9 | AM16: 169789 | AN16: 1055 | AO16: 3.9 | AQ16: 169500 | AR16: 1248 | AS16: 4
A17: 21180 | B17: Brimbank | C17: 193774 | D17: 950 | E17: np | G17: 196169 | H17: 953 | I17: 5.5 | K17: 198468 | L17: 1026 | M17: 5.4 | O17: 200860 | P17: 1097 | Q17: 5.4 | S17: 204190 | T17: 1122 | U17: 5.5 | W17: 206116 | X17: 1136 | Y17: 5.5 | AA17: 206977 | AB17: 1104 | AC17: 5.3 | AE17: 206771 | AF17: 1287 | AG17: 5.4 | AI17: 204213 | AJ17: 1202 | AK17: 5.3 | AM17: 196631 | AN17: 1164 | AO17: 5.3 | AQ17: 193256 | AR17: 1365 | AS17: 5.2
A18: 21270 | B18: Buloke | C18: 6434 | D18: 89 | E18: np | G18: 6388 | H18: 60 | I18: 5.9 | K18: 6335 | L18: 79 | M18: 5.9 | O18: 6306 | P18: 91 | Q18: 5.7 | S18: 6284 | T18: 109 | U18: 6.6 | W18: 6221 | X18: 91 | Y18: 6.8 | AA18: 6214 | AB18: 81 | AC18: 6.5 | AE18: 6166 | AF18: 76 | AG18: 5.9 | AI18: 6156 | AJ18: 81 | AK18: 5.6 | AM18: 6132 | AN18: 83 | AO18: 5.9 | AQ18: 6118 | AR18: 88 | AS18: 6.2
A19: 21370 | B19: Campaspe | C19: 37041 | D19: 310 | E19: np | G19: 37213 | H19: 319 | I19: 5.9 | K19: 37338 | L19: 373 | M19: 5.7 | O19: 37429 | P19: 376 | Q19: 6 | S19: 37595 | T19: 350 | U19: 6 | W19: 37799 | X19: 414 | Y19: 5.9 | AA19: 37948 | AB19: 418 | AC19: 5.9 | AE19: 38128 | AF19: 396 | AG19: 6 | AI19: 38379 | AJ19: 427 | AK19: 6 | AM19: 38556 | AN19: 360 | AO19: 5.6 | AQ19: 38541 | AR19: 492 | AS19: 6
... A67: 25990 | B67: Pyrenees | C67: 6860 | D67: 56 | E67: np | G67: 6938 | H67: 52 | I67: 5.6 | K67: 7047 | L67: 68 | M67: 5.8 | O67: 7179 | P67: 69 | Q67: 6 | S67: 7316 | T67: 82 | U67: 6.6 | W67: 7325 | X67: 57 | Y67: 6.1 | AA67: 7327 | AB67: 66 | AC67: 5.8 | AE67: 7449 | AF67: 72 | AG67: 5.3 | AI67: 7544 | AJ67: 73 | AK67: 5.4 | AM67: 7619 | AN67: 72 | AO67: 5.5 | AQ67: 7651 | AR67: 73 | AS67: 5.4
A68: 26080 | B68: Queenscliffe | C68: 3057 | D68: 34 | E68: np | G68: 3002 | H68: 33 | I68: np | K68: 2970 | L68: 43 | M68: np | O68: 2933 | P68: 28 | Q68: np | S68: 2929 | T68: 31 | U68: np | W68: 2923 | X68: 27 | Y68: np | AA68: 2954 | AB68: 39 | AC68: np | AE68: 2973 | AF68: 33 | AG68: np | AI68: 3095 | AJ68: 34 | AK68: np | AM68: 3236 | AN68: 32 | AO68: np | AQ68: 3220 | AR68: 33 | AS68: np
A69: 26170 | B69: South Gippsland | C69: 27926 | D69: 218 | E69: np | G69: 28273 | H69: 222 | I69: 5.1 | K69: 28521 | L69: 254 | M69: 5.2 | O69: 28781 | P69: 246 | Q69: 5.3 | S69: 29122 | T69: 255 | U69: 5.5 | W69: 29361 | X69: 252 | Y69: 5.2 | AA69: 29604 | AB69: 257 | AC69: 5.2 | AE69: 29923 | AF69: 300 | AG69: 5.4 | AI69: 30272 | AJ69: 308 | AK69: 5.7 | AM69: 30388 | AN69: 277 | AO69: 5.6 | AQ69: 30697 | AR69: 336 | AS69: 5.5
A70: 26260 | B70: Southern Grampians | C70: 16461 | D70: 194 | E70: np | G70: 16355 | H70: 196 | I70: 6.7 | K70: 16255 | L70: 164 | M70: 6.4 | O70: 16162 | P70: 211 | Q70: 6.3 | S70: 16123 | T70: 168 | U70: 6.1 | W70: 16207 | X70: 165 | Y70: 6.1 | AA70: 16291 | AB70: 160 | AC70: 5.4 | AE70: 16378 | AF70: 202 | AG70: 5.7 | AI70: 16506 | AJ70: 160 | AK70: 5.6 | AM70: 16492 | AN70: 209 | AO70: 6 | AQ70: 16393 | AR70: 203 | AS70: 6
A71: 26350 | B71: Stonnington | C71: 101410 | D71: 541 | E71: np | G71: 103487 | H71: 609 | I71: 4.4 | K71: 105894 | L71: 604 | M71: 4.4 | O71: 108028 | P71: 600 | Q71: 4.5 | S71: 111003 | T71: 633 | U71: 4.4 | W71: 112134 | X71: 647 | Y71: 4.4 | AA71: 113340 | AB71: 575 | AC71: 4.3 | AE71: 113800 | AF71: 723 | AG71: 4.4 | AI71: 112610 | AJ71: 614 | AK71: 4.2 | AM71: 106190 | AN71: 651 | AO71: 4.4 | AQ71: 106418 | AR71: 750 | AS71: 4.4
A72: 26430 | B72: Strathbogie | C72: 9744 | D72: 125 | E72: np | G72: 9867 | H72: 111 | I72: 6.2 | K72: 10018 | L72: 110 | M72: 5.9 | O72: 10175 | P72: 138 | Q72: 6 | S72: 10357 | T72: 108 | U72: 5.8 | W72: 10532 | X72: 120 | Y72: 5.7 | AA72: 10734 | AB72: 125 | AC72: 5.5 | AE72: 10907 | AF72: 116 | AG72: 5.2 | AI72: 11158 | AJ72: 118 | AK72: 5.1 | AM72: 11368 | AN72: 137 | AO72: 5.2 | AQ72: 11510 | AR72: 139 | AS72: 5.4
A73: 26490 | B73: Surf Coast | C73: 27530 | D73: 160 | E73: np | G73: 28228 | H73: 167 | I73: 4.9 | K73: 28874 | L73: 155 | M73: 4.8 | O73: 29625 | P73: 191 | Q73: 5 | S73: 30465 | T73: 185 | U73: 5 | W73: 31555 | X73: 151 | Y73: 4.7 | AA73: 32750 | AB73: 197 | AC73: 4.6 | AE73: 34213 | AF73: 213 | AG73: 4.6 | AI73: 35827 | AJ73: 202 | AK73: 4.8 | AM73: 37648 | AN73: 199 | AO73: 4.4 | AQ73: 38652 | AR73: 253 | AS73: 4.4
A74: 26610 | B74: Swan Hill | C74: 20971 | D74: 161 | E74: np | G74: 21003 | H74: 160 | I74: 5.9 | K74: 20940 | L74: 164 | M74: 5.6 | O74: 20893 | P74: 183 | Q74: 5.8 | S74: 20896 | T74: 192 | U74: 6.1 | W74: 21069 | X74: 196 | Y74: 6.4 | AA74: 21240 | AB74: 180 | AC74: 6.2 | AE74: 21407 | AF74: 195 | AG74: 6.2 | AI74: 21499 | AJ74: 157 | AK74: 5.8 | AM74: 21381 | AN74: 192 | AO74: 5.8 | AQ74: 21225 | AR74: 224 | AS74: 6
A75: 26670 | B75: Towong | C75: 5940 | D75: 55 | E75: np | G75: 5961 | H75: 69 | I75: 6.2 | K75: 5982 | L75: 64 | M75: 5.9 | O75: 6005 | P75: 64 | Q75: 5.9 | S75: 6046 | T75: 74 | U75: 5.8 | W75: 6064 | X75: 48 | Y75: 5.2 | AA75: 6100 | AB75: 64 | AC75: 5.3 | AE75: 6142 | AF75: 79 | AG75: 5.5 | AI75: 6170 | AJ75: 56 | AK75: 5.8 | AM75: 6186 | AN75: 67 | AO75: 5.8 | AQ75: 6196 | AR75: 57 | AS75: 5
A76: 26700 | B76: Wangaratta | C76: 27438 | D76: 242 | E76: np | G76: 27650 | H76: 268 | I76: 5.8 | K76: 27862 | L76: 276 | M76: 5.7 | O76: 28143 | P76: 265 | Q76: 5.8 | S76: 28592 | T76: 280 | U76: 5.8 | W76: 28951 | X76: 267 | Y76: 5.6 | AA76: 29269 | AB76: 292 | AC76: 5.6 | AE76: 29439 | AF76: 285 | AG76: 5.5 | AI76: 29517 | AJ76: 271 | AK76: 5.5 | AM76: 29751 | AN76: 260 | AO76: 5.2 | AQ76: 29903 | AR76: 329 | AS76: 5.3
A77: 26730 | B77: Warrnambool | C77: 33059 | D77: 240 | E77: np | G77: 33423 | H77: 290 | I77: 5.7 | K77: 33729 | L77: 288 | M77: 5.9 | O77: 34005 | P77: 283 | Q77: 6 | S77: 34242 | T77: 293 | U77: 5.9 | W77: 34520 | X77: 301 | Y77: 5.8 | AA77: 34823 | AB77: 278 | AC77: 5.6 | AE77: 35104 | AF77: 316 | AG77: 5.7 | AI77: 35418 | AJ77: 289 | AK77: 5.5 | AM77: 35433 | AN77: 316 | AO77: 5.6 | AQ77: 35559 | AR77: 372 | AS77: 5.7
A78: 26810 | B78: Wellington | C78: 42445 | D78: 377 | E78: np | G78: 42721 | H78: 368 | I78: 6.6 | K78: 42948 | L78: 364 | M78: 6.3 | O78: 43172 | P78: 424 | Q78: 6.4 | S78: 43530 | T78: 384 | U78: 6.4 | W78: 43872 | X78: 425 | Y78: 6.6 | AA78: 44233 | AB78: 383 | AC78: 6.3 | AE78: 44676 | AF78: 415 | AG78: 6.3 | AI78: 45105 | AJ78: 404 | AK78: 6.1 | AM78: 45469 | AN78: 432 | AO78: 6.1 | AQ78: 45799 | AR78: 487 | AS78: 6.3
A79: 26890 | B79: West Wimmera | C79: 4214 | D79: 35 | E79: np | G79: 4124 | H79: 43 | I79: 6.3 | K79: 4038 | L79: 48 | M79: 6.2 | O79: 3974 | P79: 58 | Q79: 7.4 | S79: 3937 | T79: 47 | U79: 7.7 | W79: 3952 | X79: 40 | Y79: 7.4 | AA79: 3964 | AB79: 46 | AC79: 6.3 | AE79: 3979 | AF79: 37 | AG79: 5.5 | AI79: 3994 | AJ79: 41 | AK79: 5.2 | AM79: 3978 | AN79: 36 | AO79: 4.8 | AQ79: 3942 | AR79: 51 | AS79: 5.5
A80: 26980 | B80: Whitehorse | C80: 159661 | D80: 1156 | E80: np | G80: 162081 | H80: 1116 | I80: 4.7 | K80: 164320 | L80: 1179 | M80: 4.7 | O80: 166679 | P80: 1119 | Q80: 4.6 | S80: 169641 | T80: 1171 | U80: 4.5 | W80: 172376 | X80: 1066 | Y80: 4.3 | AA80: 174431 | AB80: 1007 | AC80: 4.1 | AE80: 175862 | AF80: 1247 | AG80: 4.1 | AI80: 176794 | AJ80: 1108 | AK80: 4.1 | AM80: 171077 | AN80: 1202 | AO80: 4.3 | AQ80: 172466 | AR80: 1300 | AS80: 4.2
... A86: 27630 | B86: Yarriambiack | C86: 7095 | D86: 89 | E86: np | G86: 7032 | H86: 89 | I86: 6.2 | K86: 6924 | L86: 90 | M86: 5.9 | O86: 6826 | P86: 82 | Q86: 5.6 | S86: 6743 | T86: 92 | U86: 5.7 | W86: 6708 | X86: 89 | Y86: 5.6 | AA86: 6698 | AB86: 116 | AC86: 6.4 | AE86: 6675 | AF86: 110 | AG86: 6.9 | AI86: 6641 | AJ86: 86 | AK86: 7 | AM86: 6510 | AN86: 83 | AO86: 6.6 | AQ86: 6435 | AR86: 112 | AS86: 6.7
A87: 29399 | B87: Unincorporated Vic | C87: 797 | D87: 3 | E87: np | G87: 808 | H87: 0 | I87: np | K87: 835 | L87: 0 | M87: np | O87: 862 | P87: 0 | Q87: np | S87: 892 | T87: 0 | U87: np | W87: 901 | X87: 5 | Y87: np | AA87: 911 | AB87: 0 | AC87: np | AE87: 918 | AF87: 0 | AG87: np | AI87: 934 | AJ87: 0 | AK87: np | AM87: 946 | AN87: 0 | AO87: np | AQ87: 961 | AR87: 0 | AS87: np
B88: Total Victoria | C88: 5651091 | D88: 35760 | E88: np | G88: 5772669 | H88: 35916 | I88: 5.4 | K88: 5894917 | L88: 38042 | M88: 5.3 | O88: 6022322 | P88: 39904 | Q88: 5.3 | S88: 6173172 | T88: 39450 | U88: 5.3 | W88: 6302608 | X88: 39791 | Y88: 5.3 | AA88: 6423038 | AB88: 38231 | AC88: 5 | AE88: 6537305 | AF88: 43944 | AG88: 5.1 | AI88: 6615046 | AJ88: 41093 | AK88: 5 | AM88: 6547822 | AN88: 42486 | AO88: 5.1 | AQ88: 6625964 | AR88: 47978 | AS88: 5.1
A90: 0 nil or rounded to zero (including null cells)
A91: np not available for publication but included in totals where applicable, unless otherwise indicated
A94: © Commonwealth of Australia 2023

Sheet key dates
B1: Real Life | F1: Code Analysis | H1: Vaccine Period
B3: 43916 | C3: 第一次死人
B5: 43921 | D5: lockdown1 (43 days)
B6: 43963
B8: 44021 | D8: lockdown2 (111 days) | F8: 44021
F11: =F8+28 -> 44049 | G11: 4 week
F12: =F8+56 -> 44077 | G12: 8 week
B14: 44131
B18: 44250 | C18: 疫苗开始 | H18: 44250
B20: 44240 | C20: UK | D20: lockdown3 (5 days)
B21: 44244
B23: 44344 | C23: delta
B25: 44344 | D25: lockdown4 (14 days)
B26: 44357
B28: 44393 | D28: lockdown5 (12 days)
B29: 44404
B31: 44413 | D31: lockdown6 (77 days)
B32: 44429 | C32: 封州
H33: 44437 | I33: 44437
B34: 44456 | C34: 第一针70%，解封 | F34: 44456
B36: 44468 | C36: 补贴降低，解封
B38: 44471 | C38: 第一针80%
I39: 44473
B40: 44477 | C40: delta plus
B41: 44480 | C41: 加强针开始
H42: 44480 | I42: 44480
F43: =F34+28 -> 44484 | G43: 4 week
B46: 44490
B50: 44498 | C50: 疫苗两针80%，解封
B52: 44501 | C52: 边境开放 | D52: test kit $15 超市售卖 | F52: =F43+28 -> 44512 | G52: 8 week | I52: 44501
B54: 44519 | C54: 解封第一天
B56: 44537 | C56: omicron | F56: 44537
B58: 44545 | C58: vaccine data miss
F60: =F56+28 -> 44565 | G60: 4 week
B61: 44574 | C61: recovers data miss
B63: 44579 | C63: 补贴降低 | D63: not report 导致数据不准
B65: 44585 | C65: free RAT test kit | D65: 测试数据变多
F66: 44593 | G66: 8 week
B67: 44606 | C67: 加强针50% | H67: 44606

Sheet regression sens->

Sheet reg control
K1: top | L1: bottom
C2: top | K2: k0 = 0.0067 | L2: k0 = 0.0053 | N2: k0 low 0.0053 | O2: k0 high 0.0067 | S2: Strategy 1 | T2: Strategy 2 | U2: Optimal Control
C3: k0 = 0.0067 | F3: vaccination_rate | I3: bottom | K3: k1 = -0.1006 | L3: k1 = -0.1676 | M3: avg | N3: k1 high -0.1006 | O3: k1 low -0.1676 | S3: Constant Vaccination | T3: Actual alpha | U3: control_1 | V3: control_2 | W3: control_3 | X3: control_4 | Y3: control_5 | AB3: avg over rounds
C4: k1 = -0.1006 | F4: 0.02779241 | I4: k0 = 0.0053 | J4: 1 | K4: =F4 -> 0.02779241 | L4: 0.02779236 | M4: =AB4 -> 0.02447724 | N4: 0.02779235 | O4: 0.02779241 | S4: =$F$3 -> vaccination_rate | T4: =Reg_30days!AJ32 -> 0 | U4: 0.0245031 | V4: 0.0244278 | W4: 0.0244835 | X4: 0.0244886 | Y4: 0.0244832 | AB4: =AVERAGE(U4:Y4) -> 0.02447724
F5: 0.02779357 | I5: k1 = -0.1676 | J5: 2 | K5: =F5 -> 0.02779357 | L5: 0.02779371 | M5: =AB5 -> 0.02438572 | N5: 0.02779351 | O5: 0.02779376 | S5: =$F$3 -> vaccination_rate | T5: =Reg_30days!AJ33 -> 0 | U5: 0.0244224 | V5: 0.0243765 | W5: 0.0243693 | X5: 0.0243777 | Y5: 0.0243827 | AB5: =AVERAGE(U5:Y5) -> 0.02438572
F6: 0.02777892 | J6: 3 | K6: =F6 -> 0.02777892 | L6: 0.02777925 | M6: =AB6 -> 0.0242678 | N6: 0.02777886 | O6: 0.0277793 | S6: =$F$3 -> vaccination_rate | T6: =Reg_30days!AJ34 -> 0 | U6: 0.0243032 | V6: 0.0242313 | W6: 0.0242684 | X6: 0.0242707 | Y6: 0.0242654 | AB6: =AVERAGE(U6:Y6) -> 0.0242678
F7: 0.02776494 | J7: 4 | K7: =F7 -> 0.02776494 | L7: 0.02776547 | M7: =AB7 -> 0.02410956 | N7: 0.02776487 | O7: 0.02776553 | S7: =$F$3 -> vaccination_rate | T7: =Reg_30days!AJ35 -> 0 | U7: 0.0241285 | V7: 0.0241053 | W7: 0.0240692 | X7: 0.024107 | Y7: 0.0241378 | AB7: =AVERAGE(U7:Y7) -> 0.02410956
F8: 0.02774444 | J8: 5 | K8: =F8 -> 0.02774444 | L8: 0.02774524 | M8: =AB8 -> 0.02387136 | N8: 0.02774436 | O8: 0.0277453 | S8: =$F$3 -> vaccination_rate | T8: =Reg_30days!AJ36 -> 0 | U8: 0.02399 | V8: 0.0237615 | W8: 0.0239481 | X8: 0.0239716 | Y8: 0.0236856 | AB8: =AVERAGE(U8:Y8) -> 0.02387136
F9: 0.02771779 | J9: 6 | K9: =F9 -> 0.02771779 | L9: 0.02771905 | M9: =AB9 -> 0.02355274 | N9: 0.02771771 | O9: 0.02771912 | S9: =$F$3 -> vaccination_rate | T9: =Reg_30days!AJ37 -> 0 | U9: 0.0239124 | V9: 0.023483 | W9: 0.0234279 | X9: 0.0233801 | Y9: 0.0235603 | AB9: =AVERAGE(U9:Y9) -> 0.02355274
F10: 0.02769106 | J10: 7 | K10: =F10 -> 0.02769106 | L10: 0.02769274 | M10: =AB10 -> 0.02338316 | N10: 0.02769097 | O10: 0.0276928 | S10: =$F$3 -> vaccination_rate | T10: =Reg_30days!AJ38 -> 0 | U10: 0.0235616 | V10: 0.0234558 | W10: 0.0234109 | X10: 0.0231867 | Y10: 0.0233008 | AB10: =AVERAGE(U10:Y10) -> 0.02338316
F11: 0.02765664 | J11: 8 | K11: =F11 -> 0.02765664 | L11: 0.02765901 | M11: =AB11 -> 0.02316708 | N11: 0.02765656 | O11: 0.02765907 | S11: =$F$3 -> vaccination_rate | T11: =Reg_30days!AJ39 -> 0 | U11: 0.0231953 | V11: 0.0231481 | W11: 0.02331 | X11: 0.0231032 | Y11: 0.0230788 | AB11: =AVERAGE(U11:Y11) -> 0.02316708
F12: 0.02761797 | J12: 9 | K12: =F12 -> 0.02761797 | L12: 0.02762101 | M12: =AB12 -> 0.02305654 | N12: 0.02761784 | O12: 0.0276211 | S12: =$F$3 -> vaccination_rate | T12: =Reg_30days!AJ40 -> 0 | U12: 0.0230804 | V12: 0.0229861 | W12: 0.0233851 | X12: 0.0229123 | Y12: 0.0229188 | AB12: =AVERAGE(U12:Y12) -> 0.02305654
F13: 0.02759025 | J13: 10 | K13: =F13 -> 0.02759025 | L13: 0.02759398 | M13: =AB13 -> 0.02285692 | N13: 0.02759015 | O13: 0.02759403 | S13: =$F$3 -> vaccination_rate | T13: =Reg_30days!AJ41 -> 0 | U13: 0.022797 | V13: 0.0226103 | W13: 0.0232388 | X13: 0.0229475 | Y13: 0.022691 | AB13: =AVERAGE(U13:Y13) -> 0.02285692
F14: 0.02758413 | J14: 11 | K14: =F14 -> 0.02758413 | L14: 0.02758989 | M14: =AB14 -> 0.02267136 | N14: 0.02758616 | O14: 0.02758931 | S14: =$F$3 -> vaccination_rate | T14: =Reg_30days!AJ42 -> 0 | U14: 0.0225398 | V14: 0.0225778 | W14: 0.0229953 | X14: 0.0226186 | Y14: 0.0226253 | AB14: =AVERAGE(U14:Y14) -> 0.02267136
F15: 0.02747588 | J15: 12 | K15: =F15 -> 0.02747588 | L15: 0.02748173 | M15: =AB15 -> 0.02247434 | N15: 0.02747582 | O15: 0.02748176 | S15: =$F$3 -> vaccination_rate | T15: =Reg_30days!AJ43 -> 0 | U15: 0.0223361 | V15: 0.0225738 | W15: 0.022726 | X15: 0.0224946 | Y15: 0.0222412 | AB15: =AVERAGE(U15:Y15) -> 0.02247434
F16: 0.02734684 | J16: 13 | K16: =F16 -> 0.02734684 | L16: 0.02735633 | M16: =AB16 -> 0.02239424 | N16: 0.02734733 | O16: 0.027356 | S16: =$F$3 -> vaccination_rate | T16: =Reg_30days!AJ44 -> 0 | U16: 0.0221573 | V16: 0.0222858 | W16: 0.0225789 | X16: 0.0226736 | Y16: 0.0222756 | AB16: =AVERAGE(U16:Y16) -> 0.02239424
F17: 0.02724283 | J17: 14 | K17: =F17 -> 0.02724283 | L17: 0.0272533 | M17: =AB17 -> 0.02230826 | N17: 0.02724293 | O17: 0.02725343 | S17: =$F$3 -> vaccination_rate | T17: =Reg_30days!AJ45 -> 0 | U17: 0.0226141 | V17: 0.0222929 | W17: 0.0225579 | X17: 0.0223482 | Y17: 0.0217282 | AB17: =AVERAGE(U17:Y17) -> 0.02230826
... F63: 0.00424856 | J63: 60 | K63: =F63 -> 0.00424856 | L63: 0.00424851 | M63: =AB63 -> 0.005159404 | N63: 0.00424854 | O63: 0.00424854 | S63: =$F$3 -> vaccination_rate | T63: =Reg_30days!AJ91 -> 0 | U63: 0.00516643 | V63: 0.00515081 | W63: 0.00516471 | X63: 0.00515668 | Y63: 0.00515839 | AB63: =AVERAGE(U63:Y63) -> 0.005159404
S70: upper
E71: lower | AE71: base | AQ71: k1low | BC71: k0 low
AQ72: k0 high | BC72: k1 high
G84: Strategy | H84: Total Cost | I84: Healthcare | J84: Policy | K84: Economic | L84: Cost reduction
G85: No Vaccination | H85: 38.72 | I85: 9.5 | J85: 1.66 | K85: 27.56 | L85: =1-H88/H85 -> 0.17742769
G86: Constant Vaccination | H86: 34.28 | I86: 8.13 | J86: 3.08 | K86: 23.07 | L86: =1-H88/H86 -> 0.070886814
G87: Actual (Government) | H87: 31.4 | I87: 4.93 | J87: 3.35 | K87: 23.12
G88: Optimal | H88: 31.85 | I88: 4.42 | J88: 5.89 | K88: 21.54
E101: standard
E111: peak infected | F111: hosp | G111: icu
D112: no | AQ112: Strategy | AR112: Peak Infected | AS112: Peak Mild | AT112: Peak Hosp | AU112: Peak ICU | AV112: Peak Infected | AW112: Peak Mild | AX112: Peak Hosp | AY112: Peak ICU | BC112: Strategy | BD112: Peak Infected | BE112: Peak Mild | BF112: Peak Hosp | BG112: Peak ICU | BH112: Peak Infected | BI112: Peak Mild | BJ112: Peak Hosp | BK112: Peak ICU
D113: constant | AQ113: No Vaccination | AR113: 0.5662 | AS113: 0.5421 | AT113: 0.02185 | AU113: 0.01598 | AV113: =1-AR116/AR113 -> 0.0060049452 | AW113: =1-AS116/AS113 -> -0.027116768 | AX113: =1-AT116/AT113 -> 0.65629291 | AY113: =1-AU116/AU113 -> 0.8097622 | BC113: No Vaccination | BD113: 0.5662 | BE113: 0.5421 | BF113: 0.02185 | BG113: 0.01598 | BH113: =1-BD116/BD113 -> 0.0060049452 | BI113: =1-BE116/BE113 -> -0.026194429 | BJ113: =1-BF116/BF113 -> 0.65629291 | BK113: =1-BG116/BG113 -> 0.79411765
D114: optimal | S114: Strategy | T114: Peak Infected | U114: Peak Mild | V114: Peak Hosp | W114: Peak ICU | X114: Peak Infected | Y114: Peak Mild | Z114: Peak Hosp | AA114: Peak ICU | AQ114: Constant Vaccination | AR114: 0.5632 | AS114: 0.5395 | AT114: 0.02161 | AU114: 0.01551 | AV114: =1-AR116/AR114 -> 0.00071022727 | AW114: =1-AS116/AS114 -> -0.032066728 | AX114: =1-AT116/AT114 -> 0.65247571 | AY114: =1-AU116/AU114 -> 0.80399742 | BC114: Constant Vaccination | BD114: 0.5632 | BE114: 0.5395 | BF114: 0.02161 | BG114: 0.01551 | BH114: =1-BD116/BD114 -> 0.00071022727 | BI114: =1-BE116/BE114 -> -0.031139944 | BJ114: =1-BF116/BF114 -> 0.65247571 | BK114: =1-BG116/BG114 -> 0.78787879
F115: Strategy | G115: Peak Infected | H115: Peak Mild | I115: Peak Hosp | J115: Peak ICU | K115: Peak Infected | L115: Peak Mild | M115: Peak Hosp | N115: Peak ICU | S115: No Vaccination | T115: 0.5662 | U115: 0.5421 | V115: 0.02185 | W115: 0.01598 | X115: =1-T118/T115 -> 0.0061815613 | Y115: =1-U118/U115 -> -0.023058476 | Z115: =1-V118/V115 -> 0.65583524 | AA115: =1-W118/W115 -> 0.73404255 | AE115: Strategy | AF115: Peak Infected | AG115: Peak Mild | AH115: Peak Hosp | AI115: Peak ICU | AJ115: Peak Infected | AK115: Peak Mild | AL115: Peak Hosp | AM115: Peak ICU | AQ115: Actual (Government) | AR115: 0.5649 | AS115: 0.5564 | AT115: 0.00752 | AU115: 0.0043 | BC115: Actual (Government) | BD115: 0.5649 | BE115: 0.5569 | BF115: 0.00752 | BG115: 0.00408
F116: No Vaccination | G116: 0.5662 | H116: 0.5421 | I116: 0.02185 | J116: 0.01598 | K116: =1-G119/G116 -> 0.0058283292 | L116: =1-H119/H116 -> -0.02951485 | M116: =1-I119/I116 -> 0.65629291 | N116: =1-J119/J116 -> 0.83291615 | S116: Constant Vaccination | T116: 0.5632 | U116: 0.5395 | V116: 0.02161 | W116: 0.01551 | X116: =1-T118/T116 -> 0.00088778409 | Y116: =1-U118/U116 -> -0.027988879 | Z116: =1-V118/V116 -> 0.65201296 | AA116: =1-W118/W116 -> 0.72598324 | AE116: No Vaccination | AF116: 0.5662 | AG116: 0.5421 | AH116: 0.02185 | AI116: 0.01598 | AJ116: =1-AF119/AF116 -> 0.0060049452 | AK116: =1-AG119/AG116 -> -0.026563365 | AL116: =1-AH119/AH116 -> 0.65629291 | AM116: =1-AI119/AI116 -> 0.80162703 | AQ116: Optimal | AR116: 0.5628 | AS116: 0.5568 | AT116: 0.00751 | AU116: 0.00304 | BC116: Optimal | BD116: 0.5628 | BE116: 0.5563 | BF116: 0.00751 | BG116: 0.00329
F117: Constant Vaccination | G117: 0.5632 | H117: 0.5395 | I117: 0.02161 | J117: 0.01551 | K117: =1-G119/G117 -> 0.00053267045 | L117: =1-H119/H117 -> -0.034476367 | M117: =1-I119/I117 -> 0.65247571 | N117: =1-J119/J117 -> 0.827853 | S117: Actual (Government) | T117: 0.5648 | U117: 0.5552 | V117: 0.00757 | W117: 0.00512 | AE117: Constant Vaccination | AF117: 0.5632 | AG117: 0.5395 | AH117: 0.02161 | AI117: 0.01551 | AJ117: =1-AF119/AF117 -> 0.00071022727 | AK117: =1-AG119/AG117 -> -0.031510658 | AL117: =1-AH119/AH117 -> 0.65247571 | AM117: =1-AI119/AI117 -> 0.79561573
F118: Actual (Government) | G118: 0.565 | H118: 0.5581 | I118: 0.00751 | J118: 0.0034 | S118: Optimal | T118: 0.5627 | U118: 0.5546 | V118: 0.00752 | W118: 0.00425 | AE118: Actual (Government) | AF118: 0.5649 | AG118: 0.5567 | AH118: 0.00752 | AI118: 0.00419
F119: Optimal | G119: 0.5629 | H119: 0.5581 | I119: 0.00751 | J119: 0.00267 | AE119: Optimal | AF119: 0.5628 | AG119: 0.5565 | AH119: 0.00751 | AI119: 0.00317 | AQ119: Table 3: Peak Infection (Mean, absolute numbers) | BC119: Table 3: Peak Infection (Mean, absolute numbers)
F121: Strategy | G121: Peak Infected | H121: Peak Mild | I121: Peak Hosp | J121: Peak ICU | K121: Peak Infected | L121: Peak Mild | M121: Peak Hosp | N121: Peak ICU | AQ121: Strategy | AR121: Peak Infected | AS121: Peak Mild | AT121: Peak Hosp | AU121: Peak ICU | BC121: Strategy | BD121: Peak Infected | BE121: Peak Mild | BF121: Peak Hosp | BG121: Peak ICU
F122: No Vaccination | G122: 37539 | H122: 35941 | I122: 1448 | J122: 1059 | K122: =1-G125/G122 -> 0.0058072937 | L122: =1-H125/H122 -> -0.029437133 | M122: =1-I125/I122 -> 0.65607735 | N122: =1-J125/J122 -> 0.83286119 | AE122: Table 3: Peak Infection (Mean, absolute numbers) | AQ122: No Vaccination | AR122: 37539 | AS122: 35941 | AT122: 1448 | AU122: 1059 | BC122: No Vaccination | BD122: 37539 | BE122: 35941 | BF122: 1448 | BG122: 1059
F123: Constant Vaccination | G123: 37338 | H123: 35769 | I123: 1433 | J123: 1028 | K123: =1-G125/G123 -> 0.00045530023 | L123: =1-H125/H123 -> -0.034387319 | M123: =1-I125/I123 -> 0.65247732 | N123: =1-J125/J123 -> 0.82782101 | S123: Strategy | T123: Peak Infected | U123: Peak Mild | V123: Peak Hosp | W123: Peak ICU | AQ123: Constant Vaccination | AR123: 37338 | AS123: 35769 | AT123: 1433 | AU123: 1028 | BC123: Constant Vaccination | BD123: 37338 | BE123: 35769 | BF123: 1433 | BG123: 1028
F124: Actual (Government) | G124: 37460 | H124: 37002 | I124: 498 | J124: 225 | S124: No Vaccination | T124: 37539 | U124: 35941 | V124: 1448 | W124: 1059 | AE124: Strategy | AF124: Peak Infected | AG124: Peak Mild | AH124: Peak Hosp | AI124: Peak ICU | AQ124: Actual (Government) | AR124: 37452 | AS124: 36889 | AT124: 498 | AU124: 285 | BC124: Actual (Government) | BD124: 37454 | BE124: 36923 | BF124: 498 | BG124: 271
F125: Optimal | G125: 37321 | H125: 36999 | I125: 498 | J125: 177 | S125: Constant Vaccination | T125: 37338 | U125: 35769 | V125: 1433 | W125: 1028 | AE125: No Vaccination | AF125: 37539 | AG125: 35941 | AH125: 1448 | AI125: 1059 | AQ125: Optimal | AR125: 37315 | AS125: 36916 | AT125: 498 | AU125: 202 | BC125: Optimal | BD125: 37313 | BE125: 36879 | BF125: 498 | BG125: 218
S126: Actual (Government) | T126: 37446 | U126: 36811 | V126: 502 | W126: 339 | AE126: Constant Vaccination | AF126: 37338 | AG126: 35769 | AH126: 1433 | AI126: 1028
S127: Optimal | T127: 37305 | U127: 36769 | V127: 498 | W127: 282 | AE127: Actual (Government) | AF127: 37453 | AG127: 36906 | AH127: 498 | AI127: 278
AE128: Optimal | AF128: 37314 | AG128: 36898 | AH128: 498 | AI128: 210
F138: Strategy | G138: Hospital | H138: Vaccination | I138: Quarantine | J138: Economic | K138: Total | L138: Cost reduction
F139: No Vaccination | G139: 9.5 | H139: 0 | I139: 1.66 | J139: 27.56 | K139: 38.72 | L139: =1-K142/K139 -> 0.17665289 | S139: Strategy | T139: Hospital | U139: Vaccination | V139: Quarantine | W139: Economic | X139: Total | Y139: Cost reduction
F140: Constant Vaccination | G140: 8.13 | H140: 1.71 | I140: 1.37 | J140: 23.07 | K140: 34.28 | L140: =1-K142/K140 -> 0.070011669 | S140: No Vaccination | T140: 9.5 | U140: 0 | V140: 1.66 | W140: 27.56 | X140: 38.72 | Y140: =1-X143/X140 -> 0.16296488
F141: Actual (Government) | G141: 4.93 | H141: 1.96 | I141: 1.39 | J141: 23.12 | K141: 31.4 | S141: Constant Vaccination | T141: 8.13 | U141: 1.71 | V141: 1.37 | W141: 23.07 | X141: 34.28 | Y141: =1-X143/X141 -> 0.054550758
F142: Optimal | G142: 4.42 | H142: 4.63 | I142: 1.29 | J142: 21.54 | K142: 31.88 | S142: Actual (Government) | T142: 5.48 | U142: 1.96 | V142: 1.39 | W142: 23.07 | X142: 31.89 | AE142: Strategy | AF142: Hospital | AG142: Vaccination | AH142: Quarantine | AI142: Economic | AJ142: Total | AK142: Cost reduction | BC142: Strategy | BD142: Hospital | BE142: Vaccination | BF142: Quarantine | BG142: Economic | BH142: Total | BI142: Cost reduction
S143: Optimal | T143: 4.99 | U143: 4.64 | V143: 1.29 | W143: 21.5 | X143: 32.41 | AE143: No Vaccination | AF143: 9.5 | AG143: 0 | AH143: 1.66 | AI143: 27.56 | AJ143: 38.72 | AK143: =1-AJ146/AJ143 -> 0.2231405 | AQ143: Strategy | AR143: Hospital | AS143: Vaccination | AT143: Quarantine | AU143: Economic | AV143: Total | AW143: Cost reduction | BC143: No Vaccination | BD143: 9.5 | BE143: 0 | BF143: 1.66 | BG143: 27.56 | BH143: 38.72 | BI143: =1-BH146/BH143 -> 0.16942149
AE144: Constant Vaccination | AF144: 8.13 | AG144: 1.71 | AH144: 1.37 | AI144: 23.07 | AJ144: 34.28 | AK144: =1-AJ146/AJ144 -> 0.12252042 | AQ144: No Vaccination | AR144: 9.5 | AS144: 0 | AT144: 1.66 | AU144: 27.56 | AV144: 38.72 | AW144: =1-AV147/AV144 -> 0.17174587 | BC144: Constant Vaccination | BD144: 8.13 | BE144: 1.71 | BF144: 1.37 | BG144: 23.07 | BH144: 34.28 | BI144: =1-BH146/BH144 -> 0.061843641
AE145: Actual (Government) | AF145: 5.21 | AG145: 1.96 | AH145: 1.39 | AI145: 23.09 | AJ145: 31.65 | AQ145: Constant Vaccination | AR145: 8.13 | AS145: 1.71 | AT145: 1.37 | AU145: 23.07 | AV145: 34.28 | AW145: =1-AV147/AV145 -> 0.064469078 | BC145: Actual (Government) | BD145: 5.2 | BE145: 1.96 | BF145: 1.39 | BG145: 23.1 | BH145: 31.64
AE146: Optimal | AF146: 4.72 | AG146: 2.45 | AH146: 1.3 | AI146: 21.62 | AJ146: 30.08 | AQ146: Actual (Government) | AR146: 5.21 | AS146: 1.96 | AT146: 1.39 | AU146: 23.09 | AV146: 31.65 | BC146: Optimal | BD146: 4.72 | BE146: 4.63 | BF146: 1.29 | BG146: 21.52 | BH146: 32.16
F147: k0 low 0.0053 | G147: k0 high 0.0067 | AQ147: Optimal | AR147: 4.63 | AS147: 4.63 | AT147: 1.29 | AU147: 21.52 | AV147: 32.07
B148: optimal compare to | C148: top | D148: bottom | E148: avg | F148: k1 high -0.1006 | G148: k1 low -0.1676
A149: Cost reduction | B149: No Vaccination | C149: =L139 -> 0.17665289 | D149: =Y140 -> 0.16296488 | E149: =AK143 -> 0.2231405 | F149: =AW144 -> 0.17174587 | G149: =BI143 -> 0.16942149
B150: Constant Vaccination | C150: =L140 -> 0.070011669 | D150: =Y141 -> 0.054550758 | E150: =AK144 -> 0.12252042 | F150: =AW145 -> 0.064469078 | G150: =BI144 -> 0.061843641
A151: Peak Hosp reduction | B151: No Vaccination | C151: =M116 -> 0.65629291 | D151: =Z115 -> 0.65583524 | E151: =AL116 -> 0.65629291 | F151: =AX113 -> 0.65629291 | G151: =BJ113 -> 0.65629291
B152: Constant Vaccination | C152: =M117 -> 0.65247571 | D152: =Z116 -> 0.65201296 | E152: =AL117 -> 0.65247571 | F152: =AX114 -> 0.65247571 | G152: =BJ114 -> 0.65247571
A153: Peak ICU reduction | B153: No Vaccination | C153: =N116 -> 0.83291615 | D153: =AA115 -> 0.73404255 | E153: =AM116 -> 0.80162703 | F153: =AY113 -> 0.8097622 | G153: =BK113 -> 0.79411765
B154: Constant Vaccination | C154: =N117 -> 0.827853 | D154: =AA116 -> 0.72598324 | E154: =AM117 -> 0.79561573 | F154: =AY114 -> 0.80399742 | G154: =BK114 -> 0.78787879

Sheet reg cost
C1: high, high | D1: low,low | F1: low, high
C2: k0 = 0.0067 | D2: k0 = 0.0053 | F2: k0 low 0.0053 | G2: k0 high 0.0067
C3: k1 = -0.1006 | D3: k1 = -0.1676 | E3: avg | F3: k1 high -0.1006 | G3: k1 low -0.1676
C9: high, high | K9: low,low | S9: low, high | AA9: high, low | AI9: baseline
B10: high, high | C10: Outcome Metric | D10: No Vacc | E10: Constant | F10: Actual | G10: Optimal | H10: Actual vs No | I10: Optimal vs No | K10: Outcome Metric | L10: No Vacc | M10: Constant | N10: Actual | O10: Optimal | P10: Actual vs No | Q10: Optimal vs No | S10: Outcome Metric | T10: No Vacc | U10: Constant | V10: Actual | W10: Optimal | X10: Actual vs No | Y10: Optimal vs No | AA10: Outcome Metric | AB10: No Vacc | AC10: Constant | AD10: Actual | AE10: Optimal | AF10: Actual vs No | AG10: Optimal vs No | AI10: Outcome Metric | AJ10: No Vacc | AK10: Constant | AL10: Actual | AM10: Optimal | AN10: Actual vs No | AO10: Optimal vs No
C12: Epidemiological outcomes | K12: Epidemiological outcomes | S12: Epidemiological outcomes | AA12: Epidemiological outcomes | AI12: Epidemiological outcomes
C13: Peak infection prevalence (%) | D13: 0.566 | E13: 0.563 | F13: 0.565 | G13: 0.563 | H13: -0.002 | I13: -0.006 | K13: Peak infection prevalence (%) | L13: 0.566 | M13: 0.563 | N13: 0.565 | O13: 0.563 | P13: -0.002 | Q13: -0.006 | S13: Peak infection prevalence (%) | T13: 0.566 | U13: 0.563 | V13: 0.565 | W13: 0.563 | X13: -0.002 | Y13: -0.006 | AA13: Peak infection prevalence (%) | AB13: 0.566 | AC13: 0.563 | AD13: 0.565 | AE13: 0.563 | AF13: -0.002 | AG13: -0.006 | AI13: Peak infection prevalence (%) | AJ13: 0.566 | AK13: 0.563 | AL13: 0.565 | AM13: 0.563 | AN13: -0.002 | AO13: -0.006
C14: Peak hospitalised (persons) | D14: 1448 | E14: 1433 | F14: 502 | G14: 498 | H14: -0.653 | I14: -0.656 | K14: Peak hospitalised (persons) | L14: 1448 | M14: 1433 | N14: 498 | O14: 498 | P14: -0.656 | Q14: -0.656 | S14: Peak hospitalised (persons) | T14: 1448 | U14: 1433 | V14: 498 | W14: 498 | X14: -0.656 | Y14: -0.656 | AA14: Peak hospitalised (persons) | AB14: 1448 | AC14: 1433 | AD14: 498 | AE14: 498 | AF14: -0.656 | AG14: -0.656 | AI14: Peak hospitalised (persons) | AJ14: 1448 | AK14: 1433 | AL14: 498 | AM14: 498 | AN14: -0.656 | AO14: -0.656
C15: Peak ICU (persons) | D15: 1059 | E15: 1028 | F15: 339 | G15: 282 | H15: -0.68 | I15: -0.734 | K15: Peak ICU (persons) | L15: 1059 | M15: 1028 | N15: 225 | O15: 177 | P15: -0.787 | Q15: -0.833 | S15: Peak ICU (persons) | T15: 1059 | U15: 1028 | V15: 271 | W15: 219 | X15: -0.744 | Y15: -0.794 | AA15: Peak ICU (persons) | AB15: 1059 | AC15: 1028 | AD15: 285 | AE15: 202 | AF15: -0.731 | AG15: -0.809 | AI15: Peak ICU (persons) | AJ15: 1059 | AK15: 1028 | AL15: 278 | AM15: 210 | AN15: -0.738 | AO15: -0.802 | AP15: =AO15-AN15 -> -0.064
C16: Cumulative hospital-days | D16: 27456 | E16: 23439 | F16: 7155 | G16: 5944 | H16: -0.739 | I16: -0.784 | K16: Cumulative hospital-days | L16: 27456 | M16: 23439 | N16: 3750 | O16: 2432 | P16: -0.863 | Q16: -0.911 | S16: Cumulative hospital-days | T16: 27456 | U16: 23439 | V16: 5388 | W16: 4274 | X16: -0.804 | Y16: -0.844 | AA16: Cumulative hospital-days | AB16: 27456 | AC16: 23439 | AD16: 5511 | AE16: 3819 | AF16: -0.799 | AG16: -0.861 | AI16: Cumulative hospital-days | AJ16: 27456 | AK16: 23439 | AL16: 5450 | AM16: 4042 | AN16: -0.802 | AO16: -0.853 | AP16: =AO16-AN16 -> -0.051
C17: Cumulative ICU-days | D17: 27063 | E17: 23496 | F17: 7689 | G17: 6517 | H17: -0.716 | I17: -0.759 | K17: Cumulative ICU-days | L17: 27063 | M17: 23496 | N17: 4379 | O17: 3095 | P17: -0.838 | Q17: -0.886 | S17: Cumulative ICU-days | T17: 27063 | U17: 23496 | V17: 5973 | W17: 4892 | X17: -0.779 | Y17: -0.819 | AA17: Cumulative ICU-days | AB17: 27063 | AC17: 23496 | AD17: 6089 | AE17: 4444 | AF17: -0.775 | AG17: -0.836 | AI17: Cumulative ICU-days | AJ17: 27063 | AK17: 23496 | AL17: 6031 | AM17: 4663 | AN17: -0.777 | AO17: -0.828
C18: Cumulative deaths | D18: 110.9 | E18: 96 | F18: 29.9 | G18: 25 | H18: -0.73 | I18: -0.774 | K18: Cumulative deaths | L18: 110.9 | M18: 96 | N18: 16.1 | O18: 10.7 | P18: -0.855 | Q18: -0.903 | S18: Cumulative deaths | T18: 110.9 | U18: 96 | V18: 22.8 | W18: 18.2 | X18: -0.795 | Y18: -0.836 | AA18: Cumulative deaths | AB18: 110.9 | AC18: 96 | AD18: 23.2 | AE18: 16.4 | AF18: -0.79 | AG18: -0.852 | AI18: Cumulative deaths | AJ18: 110.9 | AK18: 96 | AL18: 23 | AM18: 17.3 | AN18: -0.793 | AO18: -0.844
C20: Cost outcomes (units) | K20: Cost outcomes (units) | S20: Cost outcomes (units) | AA20: Cost outcomes (units) | AI20: Cost outcomes (units)
C21: Vaccination costs | D21: 0 | E21: 1.71 | F21: 1.96 | G21: 2.42 | H21: – | I21: – | K21: Vaccination costs | L21: 0 | M21: 1.71 | N21: 1.96 | O21: 2.43 | P21: – | Q21: – | S21: Vaccination costs | T21: 0 | U21: 1.71 | V21: 1.96 | W21: 2.42 | X21: – | Y21: – | AA21: Vaccination costs | AB21: 0 | AC21: 1.71 | AD21: 1.96 | AE21: 2.43 | AF21: – | AG21: – | AI21: Vaccination costs | AJ21: 0 | AK21: 1.71 | AL21: 1.96 | AM21: 2.45 | AN21: – | AO21: –
C22: Quarantine costs | D22: 1.66 | E22: 1.37 | F22: 1.39 | G22: 1.29 | H22: -0.165 | I22: -0.221 | K22: Quarantine costs | L22: 1.66 | M22: 1.37 | N22: 1.39 | O22: 1.3 | P22: -0.161 | Q22: -0.218 | S22: Quarantine costs | T22: 1.66 | U22: 1.37 | V22: 1.39 | W22: 1.3 | X22: -0.163 | Y22: -0.219 | AA22: Quarantine costs | AB22: 1.66 | AC22: 1.37 | AD22: 1.39 | AE22: 1.3 | AF22: -0.163 | AG22: -0.219 | AI22: Quarantine costs | AJ22: 1.66 | AK22: 1.37 | AL22: 1.39 | AM22: 1.3 | AN22: -0.163 | AO22: -0.219
C23: Healthcare costs | D23: 9.5 | E23: 8.13 | F23: 5.48 | G23: 5.03 | H23: -0.424 | I23: -0.471 | K23: Healthcare costs | L23: 9.5 | M23: 8.13 | N23: 4.93 | O23: 4.46 | P23: -0.481 | Q23: -0.531 | S23: Healthcare costs | T23: 9.5 | U23: 8.13 | V23: 5.2 | W23: 4.76 | X23: -0.453 | Y23: -0.499 | AA23: Healthcare costs | AB23: 9.5 | AC23: 8.13 | AD23: 5.21 | AE23: 4.68 | AF23: -0.451 | AG23: -0.507 | AI23: Healthcare costs | AJ23: 9.5 | AK23: 8.13 | AL23: 5.21 | AM23: 4.72 | AN23: -0.452 | AO23: -0.503
C24: Economic productivity loss | D24: 27.56 | E24: 23.07 | F24: 23.07 | G24: 21.6 | H24: -0.163 | I24: -0.216 | K24: Economic productivity loss | L24: 27.56 | M24: 23.07 | N24: 23.12 | O24: 21.64 | P24: -0.161 | Q24: -0.215 | S24: Economic productivity loss | T24: 27.56 | U24: 23.07 | V24: 23.1 | W24: 21.62 | X24: -0.162 | Y24: -0.215 | AA24: Economic productivity loss | AB24: 27.56 | AC24: 23.07 | AD24: 23.09 | AE24: 21.62 | AF24: -0.162 | AG24: -0.215 | AI24: Economic productivity loss | AJ24: 27.56 | AK24: 23.07 | AL24: 23.09 | AM24: 21.62 | AN24: -0.162 | AO24: -0.216
C25: Total cost | D25: 38.72 | E25: 34.28 | F25: 31.89 | G25: 30.35 | H25: -0.176 | I25: -0.216 | K25: Total cost | L25: 38.72 | M25: 34.28 | N25: 31.4 | O25: 29.82 | P25: -0.189 | Q25: -0.23 | S25: Total cost | T25: 38.72 | U25: 34.28 | V25: 31.64 | W25: 30.1 | X25: -0.183 | Y25: -0.223 | AA25: Total cost | AB25: 38.72 | AC25: 34.28 | AD25: 31.65 | AE25: 30.03 | AF25: -0.182 | AG25: -0.224 | AI25: Total cost | AJ25: 38.72 | AK25: 34.28 | AL25: 31.65 | AM25: 30.08 | AN25: -0.183 | AO25: -0.223

Sheet Regression>>

Sheet Reg_30days
C1: V | Y1: Actual Vacc=second dose/S | AA1: Total dose/S | AC1: Cumulative booster num | AE1: booster rate | AF1: Second+booster | AG1: opt+booster
B2: date | C2: Number of people fully vaccinated | D2: N | E2: S | F2: E | G2: I1 | H2: I2 | I2: I3 | J2: R | K2: D | L2: I1 change | M2: I2 change | N2: I3 change | O2: Delta R = total decrease in I | P2: I1 increase | Q2: I2 increase | R2: I3 increase | S2: gamma | T2: p1 | U2: p2 | V2: gamma_avg | W2: p1_avg | X2: p2_avg | Y2: alpha | Z2: alpha_avg | AA2: alpha_all | AB2: alpha_all_avg | AC2: Actual | AD2: Fitted
B3: 44444 | D3: 6629870 | E3: =D3-C3-SUM(F3:K3) -> 6558441 | F3: 48487 | G3: 1301 | H3: 89 | I3: 24 | J3: 20702 | K3: 826
B4: 44445 | D4: 6629870 | E4: =D4-C4-SUM(F4:K4) -> 6564425 | F4: 42258 | G4: 1498 | H4: 92 | I4: 26 | J4: 20745 | K4: 826
B5: 44446 | D5: 6629870 | E5: =D5-C5-SUM(F5:K5) -> 6562583 | F5: 43858 | G5: 1643 | H5: 110 | I5: 30 | J5: 20820 | K5: 826
B6: 44447 | D6: 6629870 | E6: =D6-C6-SUM(F6:K6) -> 6563800 | F6: 42429 | G6: 1764 | H6: 120 | I6: 33 | J6: 20898 | K6: 826 | L6: =G6-G5 -> 121 | M6: =H6-H5 -> 10 | N6: =I6-I5 -> 3 | O6: =J6-J5 -> 78 | P6: =MAX(0,MIN(G6,L6+$O6*G6/SUM($G6:$I6))) -> 192.77465 | Q6: =MAX(0,MIN(H6,M6+$O6*H6/SUM($G6:$I6))) -> 14.882629 | R6: =MAX(0,MIN(I6,N6+$O6*I6/SUM($G6:$I6))) -> 4.342723 | S6: =MIN(1,P6/F5) -> 0.0043954272 | T6: =MIN(1,Q6/G5) -> 0.009058204 | U6: =MIN(1,R6/H5) -> 0.0394793
B7: 44448 | D7: 6629870 | E7: =D7-C7-SUM(F7:K7) -> 6551664 | F7: 54242 | G7: 2020 | H7: 111 | I7: 32 | J7: 20975 | K7: 826 | L7: =G7-G6 -> 256 | M7: =H7-H6 -> -9 | N7: =I7-I6 -> -1 | O7: =J7-J6 -> 77 | P7: =MAX(0,MIN(G7,L7+$O7*G7/SUM($G7:$I7))) -> 327.90939 | Q7: =MAX(0,MIN(H7,M7+$O7*H7/SUM($G7:$I7))) -> 0 | R7: =MAX(0,MIN(I7,N7+$O7*I7/SUM($G7:$I7))) -> 0.13915858 | S7: =MIN(1,P7/F6) -> 0.007728426 | T7: =MIN(1,Q7/G6) -> 0 | U7: =MIN(1,R7/H6) -> 0.0011596548
B8: 44449 | D8: 6629870 | E8: =D8-C8-SUM(F8:K8) -> 6562575 | F8: 42998 | G8: 2263 | H8: 127 | I8: 33 | J8: 21047 | K8: 827 | L8: =G8-G7 -> 243 | M8: =H8-H7 -> 16 | N8: =I8-I7 -> 1 | O8: =J8-J7 -> 72 | P8: =MAX(0,MIN(G8,L8+$O8*G8/SUM($G8:$I8))) -> 310.24556 | Q8: =MAX(0,MIN(H8,M8+$O8*H8/SUM($G8:$I8))) -> 19.773834 | R8: =MAX(0,MIN(I8,N8+$O8*I8/SUM($G8:$I8))) -> 1.9806026 | S8: =MIN(1,P8/F7) -> 0.0057196557 | T8: =MIN(1,Q8/G7) -> 0.0097890268 | U8: =MIN(1,R8/H7) -> 0.017843266
B9: 44450 | D9: 6629870 | E9: =D9-C9-SUM(F9:K9) -> 6562361 | F9: 42765 | G9: 2613 | H9: 143 | I9: 34 | J9: 21127 | K9: 827 | L9: =G9-G8 -> 350 | M9: =H9-H8 -> 16 | N9: =I9-I8 -> 1 | O9: =J9-J8 -> 80 | P9: =MAX(0,MIN(G9,L9+$O9*G9/SUM($G9:$I9))) -> 424.92473 | Q9: =MAX(0,MIN(H9,M9+$O9*H9/SUM($G9:$I9))) -> 20.100358 | R9: =MAX(0,MIN(I9,N9+$O9*I9/SUM($G9:$I9))) -> 1.9749104 | S9: =MIN(1,P9/F8) -> 0.0098824301 | T9: =MIN(1,Q9/G8) -> 0.0088821734 | U9: =MIN(1,R9/H8) -> 0.015550476 | V9: =AVERAGE(S6:S12) -> 0.007765351 | W9: =AVERAGE(T6:T12) -> 0.0052865415 | X9: =AVERAGE(U6:U12) -> 0.023812869
B10: 44451 | D10: 6629870 | E10: =D10-C10-SUM(F10:K10) -> 6556679 | F10: 48063 | G10: 2928 | H10: 147 | I10: 34 | J10: 21192 | K10: 827 | L10: =G10-G9 -> 315 | M10: =H10-H9 -> 4 | N10: =I10-I9 -> 0 | O10: =J10-J9 -> 65 | P10: =MAX(0,MIN(G10,L10+$O10*G10/SUM($G10:$I10))) -> 376.21583 | Q10: =MAX(0,MIN(H10,M10+$O10*H10/SUM($G10:$I10))) -> 7.0733355 | R10: =MAX(0,MIN(I10,N10+$O10*I10/SUM($G10:$I10))) -> 0.7108395 | S10: =MIN(1,P10/F9) -> 0.0087972834 | T10: =MIN(1,Q10/G9) -> 0.0027069788 | U10: =MIN(1,R10/H9) -> 0.0049709056 | V10: =AVERAGE(S7:S13) -> 0.0084253731 | W10: =AVERAGE(T7:T13) -> 0.004877004 | X10: =AVERAGE(U7:U13) -> 0.018935062
B11: 44452 | D11: 6629870 | E11: =D11-C11-SUM(F11:K11) -> 6555242 | F11: 49037 | G11: 3309 | H11: 157 | I11: 38 | J11: 21260 | K11: 827 | L11: =G11-G10 -> 381 | M11: =H11-H10 -> 10 | N11: =I11-I10 -> 4 | O11: =J11-J10 -> 68 | P11: =MAX(0,MIN(G11,L11+$O11*G11/SUM($G11:$I11))) -> 445.21575 | Q11: =MAX(0,MIN(H11,M11+$O11*H11/SUM($G11:$I11))) -> 13.046804 | R11: =MAX(0,MIN(I11,N11+$O11*I11/SUM($G11:$I11))) -> 4.7374429 | S11: =MIN(1,P11/F10) -> 0.0092631703 | T11: =MIN(1,Q11/G10) -> 0.0044558756 | U11: =MIN(1,R11/H10) -> 0.032227503 | V11: =AVERAGE(S8:S14) -> 0.0085705218 | W11: =AVERAGE(T8:T14) -> 0.0054804101 | X11: =AVERAGE(U8:U14) -> 0.026198814
B12: 44453 | D12: 6629870 | E12: =D12-C12-SUM(F12:K12) -> 6561147 | F12: 42694 | G12: 3593 | H12: 158 | I12: 45 | J12: 21404 | K12: 829 | L12: =G12-G11 -> 284 | M12: =H12-H11 -> 1 | N12: =I12-I11 -> 7 | O12: =J12-J11 -> 144 | P12: =MAX(0,MIN(G12,L12+$O12*G12/SUM($G12:$I12))) -> 420.29926 | Q12: =MAX(0,MIN(H12,M12+$O12*H12/SUM($G12:$I12))) -> 6.9936776 | R12: =MAX(0,MIN(I12,N12+$O12*I12/SUM($G12:$I12))) -> 8.7070601 | S12: =MIN(1,P12/F11) -> 0.0085710639 | T12: =MIN(1,Q12/G11) -> 0.0021135321 | U12: =MIN(1,R12/H11) -> 0.055458981 | V12: =AVERAGE(S9:S15) -> 0.0088203368 | W12: =AVERAGE(T9:T15) -> 0.0052392349 | X12: =AVERAGE(U9:U15) -> 0.023649776
B13: 44454 | D13: 6629870 | E13: =D13-C13-SUM(F13:K13) -> 6548782 | F13: 54649 | G13: 3818 | H13: 173 | I13: 44 | J13: 21573 | K13: 831 | L13: =G13-G12 -> 225 | M13: =H13-H12 -> 15 | N13: =I13-I12 -> -1 | O13: =J13-J12 -> 169 | P13: =MAX(0,MIN(G13,L13+$O13*G13/SUM($G13:$I13))) -> 384.91128 | Q13: =MAX(0,MIN(H13,M13+$O13*H13/SUM($G13:$I13))) -> 22.245849 | R13: =MAX(0,MIN(I13,N13+$O13*I13/SUM($G13:$I13))) -> 0.84287485 | S13: =MIN(1,P13/F12) -> 0.0090155824 | T13: =MIN(1,Q13/G12) -> 0.0061914414 | U13: =MIN(1,R13/H12) -> 0.0053346509 | V13: =AVERAGE(S10:S16) -> 0.0087185751 | W13: =AVERAGE(T10:T16) -> 0.0042746777 | X13: =AVERAGE(U10:U16) -> 0.028178005
B14: 44455 | D14: 6629870 | E14: =D14-C14-SUM(F14:K14) -> 6540967 | F14: 61961 | G14: 4134 | H14: 182 | I14: 51 | J14: 21744 | K14: 831 | L14: =G14-G13 -> 316 | M14: =H14-H13 -> 9 | N14: =I14-I13 -> 7 | O14: =J14-J13 -> 171 | P14: =MAX(0,MIN(G14,L14+$O14*G14/SUM($G14:$I14))) -> 477.87635 | Q14: =MAX(0,MIN(H14,M14+$O14*H14/SUM($G14:$I14))) -> 16.126632 | R14: =MAX(0,MIN(I14,N14+$O14*I14/SUM($G14:$I14))) -> 8.9970231 | S14: =MIN(1,P14/F13) -> 0.0087444664 | T14: =MIN(1,Q14/G13) -> 0.0042238427 | U14: =MIN(1,R14/H13) -> 0.052005914 | V14: =AVERAGE(S11:S17) -> 0.0085773762 | W14: =AVERAGE(T11:T17) -> 0.0040311676 | X14: =AVERAGE(U11:U17) -> 0.028214041
B15: 44456 | D15: 6629870 | E15: =D15-C15-SUM(F15:K15) -> 6546955 | F15: 55476 | G15: 4437 | H15: 208 | I15: 49 | J15: 21913 | K15: 832 | L15: =G15-G14 -> 303 | M15: =H15-H14 -> 26 | N15: =I15-I14 -> -2 | O15: =J15-J14 -> 169 | P15: =MAX(0,MIN(G15,L15+$O15*G15/SUM($G15:$I15))) -> 462.74712 | Q15: =MAX(0,MIN(H15,M15+$O15*H15/SUM($G15:$I15))) -> 33.488709 | R15: =MAX(0,MIN(I15,N15+$O15*I15/SUM($G15:$I15))) -> 0 | S15: =MIN(1,P15/F14) -> 0.0074683611 | T15: =MIN(1,Q15/G14) -> 0.0081008004 | U15: =MIN(1,R15/H14) -> 0 | V15: =AVERAGE(S12:S18) -> 0.0085590539 | W15: =AVERAGE(T12:T18) -> 0.0036827562 | X15: =AVERAGE(U12:U18) -> 0.027416465
B16: 44457 | D16: 6629870 | E16: =D16-C16-SUM(F16:K16) -> 6540280 | F16: 61622 | G16: 4708 | H16: 207 | I16: 56 | J16: 22164 | K16: 833 | L16: =G16-G15 -> 271 | M16: =H16-H15 -> -1 | N16: =I16-I15 -> 7 | O16: =J16-J15 -> 251 | P16: =MAX(0,MIN(G16,L16+$O16*G16/SUM($G16:$I16))) -> 508.72038 | Q16: =MAX(0,MIN(H16,M16+$O16*H16/SUM($G16:$I16))) -> 9.4520217 | R16: =MAX(0,MIN(I16,N16+$O16*I16/SUM($G16:$I16))) -> 9.8276001 | S16: =MIN(1,P16/F15) -> 0.0091700984 | T16: =MIN(1,Q16/G15) -> 0.0021302731 | U16: =MIN(1,R16/H15) -> 0.047248077 | V16: =AVERAGE(S13:S19) -> 0.0088521307 | W16: =AVERAGE(T13:T19) -> 0.0045050943 | X16: =AVERAGE(U13:U19) -> 0.021969017
B17: 44458 | D17: 6629870 | E17: =D17-C17-SUM(F17:K17) -> 6542795 | F17: 58619 | G17: 5000 | H17: 204 | I17: 55 | J17: 22363 | K17: 834 | L17: =G17-G16 -> 292 | M17: =H17-H16 -> -3 | N17: =I17-I16 -> -1 | O17: =J17-J16 -> 199 | P17: =MAX(0,MIN(G17,L17+$O17*G17/SUM($G17:$I17))) -> 481.19947 | Q17: =MAX(0,MIN(H17,M17+$O17*H17/SUM($G17:$I17))) -> 4.7193383 | R17: =MAX(0,MIN(I17,N17+$O17*I17/SUM($G17:$I17))) -> 1.0811941 | S17: =MIN(1,P17/F16) -> 0.0078088908 | T17: =MIN(1,Q17/G16) -> 0.0010024083 | U17: =MIN(1,R17/H16) -> 0.0052231601 | V17: =AVERAGE(S14:S20) -> 0.0092699877 | W17: =AVERAGE(T14:T20) -> 0.0044301789 | X17: =AVERAGE(U14:U20) -> 0.022199192
B18: 44459 | D18: 6629870 | E18: =D18-C18-SUM(F18:K18) -> 6549947 | F18: 50915 | G18: 5404 | H18: 209 | I18: 59 | J18: 22501 | K18: 835 | L18: =G18-G17 -> 404 | M18: =H18-H17 -> 5 | N18: =I18-I17 -> 4 | O18: =J18-J17 -> 138 | P18: =MAX(0,MIN(G18,L18+$O18*G18/SUM($G18:$I18))) -> 535.47955 | Q18: =MAX(0,MIN(H18,M18+$O18*H18/SUM($G18:$I18))) -> 10.084979 | R18: =MAX(0,MIN(I18,N18+$O18*I18/SUM($G18:$I18))) -> 5.4354725 | S18: =MIN(1,P18/F17) -> 0.0091349144 | T18: =MIN(1,Q18/G17) -> 0.0020169958 | U18: =MIN(1,R18/H17) -> 0.026644473 | V18: =AVERAGE(S15:S21) -> 0.0097230262 | W18: =AVERAGE(T15:T21) -> 0.0041048475 | X18: =AVERAGE(U15:U21) -> 0.017373153
B19: 44460 | D19: 6629870 | E19: =D19-C19-SUM(F19:K19) -> 6551445 | F19: 48829 | G19: 5696 | H19: 241 | I19: 60 | J19: 22763 | K19: 836 | L19: =G19-G18 -> 292 | M19: =H19-H18 -> 32 | N19: =I19-I18 -> 1 | O19: =J19-J18 -> 262 | P19: =MAX(0,MIN(G19,L19+$O19*G19/SUM($G19:$I19))) -> 540.84976 | Q19: =MAX(0,MIN(H19,M19+$O19*H19/SUM($G19:$I19))) -> 42.528931 | R19: =MAX(0,MIN(I19,N19+$O19*I19/SUM($G19:$I19))) -> 3.6213107 | S19: =MIN(1,P19/F18) -> 0.010622602 | T19: =MIN(1,Q19/G18) -> 0.0078698984 | U19: =MIN(1,R19/H18) -> 0.017326845 | V19: =AVERAGE(S16:S22) -> 0.010166202 | W19: =AVERAGE(T16:T22) -> 0.0040563657 | X19: =AVERAGE(U16:U22) -> 0.021851445
B20: 44461 | D20: 6629870 | E20: =D20-C20-SUM(F20:K20) -> 6538825 | F20: 60829 | G20: 5905 | H20: 257 | I20: 58 | J20: 23157 | K20: 839 | L20: =G20-G19 -> 209 | M20: =H20-H19 -> 16 | N20: =I20-I19 -> -2 | O20: =J20-J19 -> 394 | P20: =MAX(0,MIN(G20,L20+$O20*G20/SUM($G20:$I20))) -> 583.04662 | Q20: =MAX(0,MIN(H20,M20+$O20*H20/SUM($G20:$I20))) -> 32.279421 | R20: =MAX(0,MIN(I20,N20+$O20*I20/SUM($G20:$I20))) -> 1.673955 | S20: =MIN(1,P20/F19) -> 0.011940581 | T20: =MIN(1,Q20/G19) -> 0.0056670332 | U20: =MIN(1,R20/H19) -> 0.0069458713 | V20: =AVERAGE(S17:S23) -> 0.010859315 | W20: =AVERAGE(T17:T23) -> 0.0045973644 | X20: =AVERAGE(U17:U23) -> 0.016198765
... B28: 44469 | D28: 6629870 | E28: =D28-C28-SUM(F28:K28) -> 6527040 | F28: 65497 | G28: 10534 | H28: 398 | I28: 83 | J28: 25454 | K28: 864 | L28: =G28-G27 -> 1099 | M28: =H28-H27 -> 27 | N28: =I28-I27 -> 2 | O28: =J28-J27 -> 296 | P28: =MAX(0,MIN(G28,L28+$O28*G28/SUM($G28:$I28))) -> 1382.0744 | Q28: =MAX(0,MIN(H28,M28+$O28*H28/SUM($G28:$I28))) -> 37.695234 | R28: =MAX(0,MIN(I28,N28+$O28*I28/SUM($G28:$I28))) -> 4.2304131 | S28: =MIN(1,P28/F27) -> 0.022537986 | T28: =MIN(1,Q28/G27) -> 0.0039952553 | U28: =MIN(1,R28/H27) -> 0.011402731 | V28: =AVERAGE(S25:S31) -> 0.018206605 | W28: =AVERAGE(T25:T31) -> 0.0045123298 | X28: =AVERAGE(U25:U31) -> 0.021474087
B29: 44470 | C29: 2738168 | D29: 6629870 | E29: =D29-C29-SUM(F29:K29) -> 3790355 | F29: 62883 | G29: 10458 | H29: 395 | I29: 87 | J29: 26657 | K29: 867 | L29: =G29-G28 -> -76 | M29: =H29-H28 -> -3 | N29: =I29-I28 -> 4 | O29: =J29-J28 -> 1203 | P29: =MAX(0,MIN(G29,L29+$O29*G29/SUM($G29:$I29))) -> 1073.9976 | Q29: =MAX(0,MIN(H29,M29+$O29*H29/SUM($G29:$I29))) -> 40.435558 | R29: =MAX(0,MIN(I29,N29+$O29*I29/SUM($G29:$I29))) -> 13.566819 | S29: =MIN(1,P29/F28) -> 0.016397661 | T29: =MIN(1,Q29/G28) -> 0.0038385758 | U29: =MIN(1,R29/H28) -> 0.034087485 | V29: =AVERAGE(S26:S32) -> 0.018459778 | W29: =AVERAGE(T26:T32) -> 0.0040468772 | X29: =AVERAGE(U26:U32) -> 0.019766592
B30: 44471 | C30: 2783434 | D30: 6629870 | E30: =D30-C30-SUM(F30:K30) -> 3735463 | F30: 71224 | G30: 11061 | H30: 429 | I30: 97 | J30: 27293 | K30: 869 | L30: =G30-G29 -> 603 | M30: =H30-H29 -> 34 | N30: =I30-I29 -> 10 | O30: =J30-J29 -> 636 | P30: =MAX(0,MIN(G30,L30+$O30*G30/SUM($G30:$I30))) -> 1210.1283 | Q30: =MAX(0,MIN(H30,M30+$O30*H30/SUM($G30:$I30))) -> 57.547424 | R30: =MAX(0,MIN(I30,N30+$O30*I30/SUM($G30:$I30))) -> 15.324243 | S30: =MIN(1,P30/F29) -> 0.019244125 | T30: =MIN(1,Q30/G29) -> 0.0055027179 | U30: =MIN(1,R30/H29) -> 0.038795551 | V30: =AVERAGE(S27:S33) -> 0.019779845 | W30: =AVERAGE(T27:T33) -> 0.0040056564 | X30: =AVERAGE(U27:U33) -> 0.01857876 | Y30: =(C30-C29)/E29 -> 0.011942417 | Z30: =AVERAGE(Y27:Y33) -> 0.010648776
B31: 44472 | C31: 2819637 | D31: 6629870 | E31: =D31-C31-SUM(F31:K31) -> 3697830 | F31: 71275 | G31: 11207 | H31: 476 | I31: 98 | J31: 28475 | K31: 872 | L31: =G31-G30 -> 146 | M31: =H31-H30 -> 47 | N31: =I31-I30 -> 1 | O31: =J31-J30 -> 1182 | P31: =MAX(0,MIN(G31,L31+$O31*G31/SUM($G31:$I31))) -> 1270.41 | Q31: =MAX(0,MIN(H31,M31+$O31*H31/SUM($G31:$I31))) -> 94.757576 | R31: =MAX(0,MIN(I31,N31+$O31*I31/SUM($G31:$I31))) -> 10.832442 | S31: =MIN(1,P31/F30) -> 0.017836824 | T31: =MIN(1,Q31/G30) -> 0.0085668182 | U31: =MIN(1,R31/H30) -> 0.025250448 | V31: =AVERAGE(S28:S34) -> 0.020227464 | W31: =AVERAGE(T28:T34) -> 0.0044903623 | X31: =AVERAGE(U28:U34) -> 0.018182157 | Y31: =(C31-C30)/E30 -> 0.0096917035 | Z31: =AVERAGE(Y28:Y34) -> 0.011440147
A32: 1 | B32: 44473 | C32: 2845438 | D32: 6629870 | E32: =D32-C32-SUM(F32:K32) -> 3674149 | F32: 67789 | G32: 12113 | H32: 498 | I32: 96 | J32: 28911 | K32: 876 | L32: =G32-G31 -> 906 | M32: =H32-H31 -> 22 | N32: =I32-I31 -> -2 | O32: =J32-J31 -> 436 | P32: =MAX(0,MIN(G32,L32+$O32*G32/SUM($G32:$I32))) -> 1321.6188 | Q32: =MAX(0,MIN(H32,M32+$O32*H32/SUM($G32:$I32))) -> 39.087275 | R32: =MAX(0,MIN(I32,N32+$O32*I32/SUM($G32:$I32))) -> 1.2939325 | S32: =MIN(1,P32/F31) -> 0.01854253 | T32: =MIN(1,Q32/G31) -> 0.0034877554 | U32: =MIN(1,R32/H31) -> 0.0027183455 | V32: =AVERAGE(S29:S35) -> 0.020002466 | W32: =AVERAGE(T29:T35) -> 0.0046866916 | X32: =AVERAGE(U29:U35) -> 0.024211064 | Y32: =(C32-C31)/E31 -> 0.0069773354 | Z32: =AVERAGE(Y29:Y35) -> 0.012596397 | AA32: ='ori data'!AV119 -> 0.01361322 | AB32: ='ori data'!AW119 -> 0.023351457 | AE32: 0 | AF32: =Z32+AE32 -> 0.012596397 | AG32: ='opt vacc_sigma0.1'!L3+AE32 -> 0.02431008
A33: 2 | B33: 44474 | C33: 2896816 | D33: 6629870 | E33: =D33-C33-SUM(F33:K33) -> 3626614 | F33: 62189 | G33: 13746 | H33: 517 | I33: 101 | J33: 29007 | K33: 880 | L33: =G33-G32 -> 1633 | M33: =H33-H32 -> 19 | N33: =I33-I32 -> 5 | O33: =J33-J32 -> 96 | P33: =MAX(0,MIN(G33,L33+$O33*G33/SUM($G33:$I33))) -> 1724.8697 | Q33: =MAX(0,MIN(H33,M33+$O33*H33/SUM($G33:$I33))) -> 22.455305 | R33: =MAX(0,MIN(I33,N33+$O33*I33/SUM($G33:$I33))) -> 5.6750209 | S33: =MIN(1,P33/F32) -> 0.025444684 | T33: =MIN(1,Q33/G32) -> 0.0018538186 | U33: =MIN(1,R33/H32) -> 0.011395624 | V33: =AVERAGE(S30:S36) -> 0.020915166 | W33: =AVERAGE(T30:T36) -> 0.004719476 | X33: =AVERAGE(U30:U36) -> 0.019341423 | Y33: =(C33-C32)/E32 -> 0.013983646 | Z33: =AVERAGE(Y30:Y36) -> 0.013190538 | AA33: ='ori data'!AV120 -> 0.026563897 | AB33: ='ori data'!AW120 -> 0.023768685 | AE33: 0 | AF33: =Z33+AE33 -> 0.013190538 | AG33: ='opt vacc_sigma0.1'!L4+AE33 -> 0.024222336
A34: 3 | B34: 44475 | C34: 2949785 | D34: 6629870 | E34: =D34-C34-SUM(F34:K34) -> 3562970 | F34: 71451 | G34: 13787 | H34: 525 | I34: 94 | J34: 30367 | K34: 891 | L34: =G34-G33 -> 41 | M34: =H34-H33 -> 8 | N34: =I34-I33 -> -7 | O34: =J34-J33 -> 1360 | P34: =MAX(0,MIN(G34,L34+$O34*G34/SUM($G34:$I34))) -> 1342.5632 | Q34: =MAX(0,MIN(H34,M34+$O34*H34/SUM($G34:$I34))) -> 57.562682 | R34: =MAX(0,MIN(I34,N34+$O34*I34/SUM($G34:$I34))) -> 1.8740802 | S34: =MIN(1,P34/F33) -> 0.021588436 | T34: =MIN(1,Q34/G33) -> 0.0041875951 | U34: =MIN(1,R34/H33) -> 0.0036249134 | V34: =AVERAGE(S31:S37) -> 0.021656061 | W34: =AVERAGE(T31:T37) -> 0.0040207081 | X34: =AVERAGE(U31:U37) -> 0.016908012 | Y34: =(C34-C33)/E33 -> 0.014605635 | Z34: =AVERAGE(Y31:Y37) -> 0.014105239 | AA34: ='ori data'!AV121 -> 0.026831548 | AB34: ='ori data'!AW121 -> 0.024416678 | AE34: 0 | AF34: =Z34+AE34 -> 0.014105239 | AG34: ='opt vacc_sigma0.1'!L5+AE34 -> 0.024110737
A35: 4 | B35: 44476 | C35: 3015264 | D35: 6629870 | E35: =D35-C35-SUM(F35:K35) -> 3490102 | F35: 77238 | G35: 14391 | H35: 564 | I35: 115 | J35: 31303 | K35: 893 | L35: =G35-G34 -> 604 | M35: =H35-H34 -> 39 | N35: =I35-I34 -> 21 | O35: =J35-J34 -> 936 | P35: =MAX(0,MIN(G35,L35+$O35*G35/SUM($G35:$I35))) -> 1497.8272 | Q35: =MAX(0,MIN(H35,M35+$O35*H35/SUM($G35:$I35))) -> 74.030126 | R35: =MAX(0,MIN(I35,N35+$O35*I35/SUM($G35:$I35))) -> 28.142668 | S35: =MIN(1,P35/F34) -> 0.020962999 | T35: =MIN(1,Q35/G34) -> 0.0053695602 | U35: =MIN(1,R35/H34) -> 0.053605081 | V35: =AVERAGE(S32:S38) -> 0.022605274 | W35: =AVERAGE(T32:T38) -> 0.003273447 | X35: =AVERAGE(U32:U38) -> 0.016754732 | Y35: =(C35-C34)/E34 -> 0.018377646 | Z35: =AVERAGE(Y32:Y38) -> 0.015091189 | AA35: ='ori data'!AV122 -> 0.027577418 | AB35: ='ori data'!AW122 -> 0.025121909 | AE35: 0 | AF35: =Z35+AE35 -> 0.015091189 | AG35: ='opt vacc_sigma0.1'!L6+AE35 -> 0.024006797
A36: 5 | B36: 44477 | C36: 3073742 | D36: 6629870 | E36: =D36-C36-SUM(F36:K36) -> 3429485 | F36: 77554 | G36: 16085 | H36: 620 | I36: 114 | J36: 31372 | K36: 898 | L36: =G36-G35 -> 1694 | M36: =H36-H35 -> 56 | N36: =I36-I35 -> -1 | O36: =J36-J35 -> 69 | P36: =MAX(0,MIN(G36,L36+$O36*G36/SUM($G36:$I36))) -> 1759.9888 | Q36: =MAX(0,MIN(H36,M36+$O36*H36/SUM($G36:$I36))) -> 58.543552 | R36: =MAX(0,MIN(I36,N36+$O36*I36/SUM($G36:$I36))) -> 0 | S36: =MIN(1,P36/F35) -> 0.022786566 | T36: =MIN(1,Q36/G35) -> 0.004068067 | U36: =MIN(1,R36/H35) -> 0 | V36: =AVERAGE(S33:S39) -> 0.022779183 | W36: =AVERAGE(T33:T39) -> 0.0035895043 | X36: =AVERAGE(U33:U39) -> 0.019498774 | Y36: =(C36-C35)/E35 -> 0.016755384 | Z36: =AVERAGE(Y33:Y39) -> 0.015831503 | AA36: ='ori data'!AV123 -> 0.02778872 | AB36: ='ori data'!AW123 -> 0.025688985 | AE36: 0 | AF36: =Z36+AE36 -> 0.015831503 | AG36: ='opt vacc_sigma0.1'!L7+AE36 -> 0.023819631
A37: 6 | B37: 44478 | C37: 3136657 | D37: 6629870 | E37: =D37-C37-SUM(F37:K37) -> 3368758 | F37: 73443 | G37: 16500 | H37: 578 | I37: 117 | J37: 32914 | K37: 903 | L37: =G37-G36 -> 415 | M37: =H37-H36 -> -42 | N37: =I37-I36 -> 3 | O37: =J37-J36 -> 1542 | P37: =MAX(0,MIN(G37,L37+$O37*G37/SUM($G37:$I37))) -> 1894.6743 | Q37: =MAX(0,MIN(H37,M37+$O37*H37/SUM($G37:$I37))) -> 9.83344 | R37: =MAX(0,MIN(I37,N37+$O37*I37/SUM($G37:$I37))) -> 13.492236 | S37: =MIN(1,P37/F36) -> 0.024430388 | T37: =MIN(1,Q37/G36) -> 0.00061134224 | U37: =MIN(1,R37/H36) -> 0.021761671 | V37: =AVERAGE(S34:S40) -> 0.021834645 | W37: =AVERAGE(T34:T40) -> 0.0035263493 | X37: =AVERAGE(U34:U40) -> 0.021438533 | Y37: =(C37-C36)/E36 -> 0.01834532 | Z37: =AVERAGE(Y34:Y40) -> 0.016559196 | AA37: ='ori data'!AV124 -> 0.029017519 | AB37: ='ori data'!AW124 -> 0.0259455 | AE37: 0 | AF37: =Z37+AE37 -> 0.016559196 | AG37: ='opt vacc_sigma0.1'!L8+AE37 -> 0.023629749
A38: 7 | B38: 44479 | C38: 3192556 | D38: 6629870 | E38: =D38-C38-SUM(F38:K38) -> 3310325 | F38: 74105 | G38: 17603 | H38: 609 | I38: 126 | J38: 33638 | K38: 908 | L38: =G38-G37 -> 1103 | M38: =H38-H37 -> 31 | N38: =I38-I37 -> 9 | O38: =J38-J37 -> 724 | P38: =MAX(0,MIN(G38,L38+$O38*G38/SUM($G38:$I38))) -> 1797.9816 | Q38: =MAX(0,MIN(H38,M38+$O38*H38/SUM($G38:$I38))) -> 55.043843 | R38: =MAX(0,MIN(I38,N38+$O38*I38/SUM($G38:$I38))) -> 13.974588 | S38: =MIN(1,P38/F37) -> 0.02448132 | T38: =MIN(1,Q38/G37) -> 0.0033359905 | U38: =MIN(1,R38/H37) -> 0.024177488 | V38: =AVERAGE(S35:S41) -> 0.021818319 | W38: =AVERAGE(T35:T41) -> 0.0035136967 | X38: =AVERAGE(U35:U41) -> 0.023407357 | Y38: =(C38-C37)/E37 -> 0.016593356 | Z38: =AVERAGE(Y35:Y41) -> 0.017423507 | AA38: ='ori data'!AV125 -> 0.024461042 | AB38: ='ori data'!AW125 -> 0.026551033 | AE38: 0 | AF38: =Z38+AE38 -> 0.017423507 | AG38: ='opt vacc_sigma0.1'!L9+AE38 -> 0.023428194
A39: 8 | B39: 44480 | C39: 3232808 | D39: 6629870 | E39: =D39-C39-SUM(F39:K39) -> 3269454 | F39: 73138 | G39: 18198 | H39: 677 | I39: 133 | J39: 34546 | K39: 916 | L39: =G39-G38 -> 595 | M39: =H39-H38 -> 68 | N39: =I39-I38 -> 7 | O39: =J39-J38 -> 908 | P39: =MAX(0,MIN(G39,L39+$O39*G39/SUM($G39:$I39))) -> 1464.3068 | Q39: =MAX(0,MIN(H39,M39+$O39*H39/SUM($G39:$I39))) -> 100.33986 | R39: =MAX(0,MIN(I39,N39+$O39*I39/SUM($G39:$I39))) -> 13.353325 | S39: =MIN(1,P39/F38) -> 0.019759892 | T39: =MIN(1,Q39/G38) -> 0.0057001566 | U39: =MIN(1,R39/H38) -> 0.021926642 | V39: =AVERAGE(S36:S42) -> 0.022666122 | W39: =AVERAGE(T36:T42) -> 0.003349545 | X39: =AVERAGE(U36:U42) -> 0.019294317 | Y39: =(C39-C38)/E38 -> 0.012159531 | Z39: =AVERAGE(Y36:Y42) -> 0.01791683 | AA39: ='ori data'!AV126 -> 0.017582752 | AB39: ='ori data'!AW126 -> 0.027172354 | AC39: 0 | AD39: 0 | AE39: =(AD39-AD38)/E38 -> 0 | AF39: =Z39+AE39 -> 0.01791683 | AG39: ='opt vacc_sigma0.1'!L10+AE39 -> 0.023222737
A40: 9 | B40: 44481 | C40: 3295181 | D40: 6629870 | E40: =D40-C40-SUM(F40:K40) -> 3210282 | F40: 68509 | G40: 18804 | H40: 675 | I40: 144 | J40: 35351 | K40: 924 | L40: =G40-G39 -> 606 | M40: =H40-H39 -> -2 | N40: =I40-I39 -> 11 | O40: =J40-J39 -> 805 | P40: =MAX(0,MIN(G40,L40+$O40*G40/SUM($G40:$I40))) -> 1377.4019 | Q40: =MAX(0,MIN(H40,M40+$O40*H40/SUM($G40:$I40))) -> 25.69072 | R40: =MAX(0,MIN(I40,N40+$O40*I40/SUM($G40:$I40))) -> 16.907354 | S40: =MIN(1,P40/F39) -> 0.018832918 | T40: =MIN(1,Q40/G39) -> 0.0014117332 | U40: =MIN(1,R40/H39) -> 0.024973934 | V40: =AVERAGE(S37:S43) -> 0.023081364 | W40: =AVERAGE(T37:T43) -> 0.0028547876 | X40: =AVERAGE(U37:U43) -> 0.022345945 | Y40: =(C40-C39)/E39 -> 0.019077497 | Z40: =AVERAGE(Y37:Y43) -> 0.018746479 | AA40: ='ori data'!AV127 -> 0.028359502 | AB40: ='ori data'!AW127 -> 0.027939907 | AD40: =AD39+$AC$49/10 -> 720.5 | AE40: =(AD40-AD39)/E39 -> 0.00022037319 | AF40: =Z40+AE40 -> 0.018966852 | AG40: ='opt vacc_sigma0.1'!L11+AE40 -> 0.023243536
A41: 10 | B41: 44482 | C41: 3361492 | D41: 6629870 | E41: =D41-C41-SUM(F41:K41) -> 3131707 | F41: 79200 | G41: 19006 | H41: 705 | I41: 146 | J41: 36677 | K41: 937 | L41: =G41-G40 -> 202 | M41: =H41-H40 -> 30 | N41: =I41-I40 -> 2 | O41: =J41-J40 -> 1326 | P41: =MAX(0,MIN(G41,L41+$O41*G41/SUM($G41:$I41))) -> 1471.1724 | Q41: =MAX(0,MIN(H41,M41+$O41*H41/SUM($G41:$I41))) -> 77.078108 | R41: =MAX(0,MIN(I41,N41+$O41*I41/SUM($G41:$I41))) -> 11.749509 | S41: =MIN(1,P41/F40) -> 0.021474148 | T41: =MIN(1,Q41/G40) -> 0.0040990273 | U41: =MIN(1,R41/H40) -> 0.01740668 | V41: =AVERAGE(S38:S44) -> 0.023027039 | W41: =AVERAGE(T38:T44) -> 0.0039076154 | X41: =AVERAGE(U38:U44) -> 0.023004605 | Y41: =(C41-C40)/E40 -> 0.020655818 | Z41: =AVERAGE(Y38:Y44) -> 0.019534493 | AA41: ='ori data'!AV128 -> 0.031070276 | AB41: ='ori data'!AW128 -> 0.028653253 | AD41: =AD40+$AC$49/10 -> 1441 | AE41: =(AD41-AD40)/E40 -> 0.00022443511 | AF41: =Z41+AE41 -> 0.019758928 | AG41: ='opt vacc_sigma0.1'!L12+AE41 -> 0.023082098
A42: 11 | B42: 44483 | C42: 3429860 | D42: 6629870 | E42: =D42-C42-SUM(F42:K42) -> 3057538 | F42: 82762 | G42: 19004 | H42: 706 | I42: 147 | J42: 38905 | K42: 948 | L42: =G42-G41 -> -2 | M42: =H42-H41 -> 1 | N42: =I42-I41 -> 1 | O42: =J42-J41 -> 2228 | P42: =MAX(0,MIN(G42,L42+$O42*G42/SUM($G42:$I42))) -> 2130.2915 | Q42: =MAX(0,MIN(H42,M42+$O42*H42/SUM($G42:$I42))) -> 80.214786 | R42: =MAX(0,MIN(I42,N42+$O42*I42/SUM($G42:$I42))) -> 17.49373 | S42: =MIN(1,P42/F41) -> 0.02689762 | T42: =MIN(1,Q42/G41) -> 0.004220498 | U42: =MIN(1,R42/H41) -> 0.024813802 | V42: =AVERAGE(S39:S45) -> 0.022784659 | W42: =AVERAGE(T39:T45) -> 0.0034310453 | X42: =AVERAGE(U39:U45) -> 0.019550678 | Y42: =(C42-C41)/E41 -> 0.021830906 | Z42: =AVERAGE(Y39:Y45) -> 0.020085908 | AA42: ='ori data'!AV129 -> 0.031926668 | AB42: ='ori data'!AW129 -> 0.029015139 | AC42: 1728 | AD42: =AD41+$AC$49/10 -> 2161.5 | AE42: =(AD42-AD41)/E41 -> 0.00023006622 | AF42: =Z42+AE42 -> 0.020315974 | AG42: ='opt vacc_sigma0.1'!L13+AE42 -> 0.022934172
A43: 12 | B43: 44484 | C43: 3498847 | D43: 6629870 | E43: =D43-C43-SUM(F43:K43) -> 2995212 | F43: 73942 | G43: 20468 | H43: 695 | I43: 157 | J43: 39595 | K43: 954 | L43: =G43-G42 -> 1464 | M43: =H43-H42 -> -11 | N43: =I43-I42 -> 10 | O43: =J43-J42 -> 690 | P43: =MAX(0,MIN(G43,L43+$O43*G43/SUM($G43:$I43))) -> 2126.4259 | Q43: =MAX(0,MIN(H43,M43+$O43*H43/SUM($G43:$I43))) -> 11.492964 | R43: =MAX(0,MIN(I43,N43+$O43*I43/SUM($G43:$I43))) -> 15.081144 | S43: =MIN(1,P43/F42) -> 0.025693264 | T43: =MIN(1,Q43/G42) -> 0.00060476554 | U43: =MIN(1,R43/H42) -> 0.021361394 | V43: =AVERAGE(S40:S46) -> 0.023202359 | W43: =AVERAGE(T40:T46) -> 0.0037899773 | X43: =AVERAGE(U40:U46) -> 0.020848255 | Y43: =(C43-C42)/E42 -> 0.022562925 | Z43: =AVERAGE(Y40:Y46) -> 0.020574637 | AA43: ='ori data'!AV130 -> 0.033161593 | AB43: ='ori data'!AW130 -> 0.029334002 | AD43: =AD42+$AC$49/10 -> 2882 | AE43: =(AD43-AD42)/E42 -> 0.00023564711 | AF43: =Z43+AE43 -> 0.020810284 | AG43: ='opt vacc_sigma0.1'!L14+AE43 -> 0.022775113
A44: 13 | B44: 44485 | C44: 3570317 | D44: 6629870 | E44: =D44-C44-SUM(F44:K44) -> 2916503 | F44: 79214 | G44: 20682 | H44: 798 | I44: 163 | J44: 41232 | K44: 961 | L44: =G44-G43 -> 214 | M44: =H44-H43 -> 103 | N44: =I44-I43 -> 6 | O44: =J44-J43 -> 1637 | P44: =MAX(0,MIN(G44,L44+$O44*G44/SUM($G44:$I44))) -> 1778.3134 | Q44: =MAX(0,MIN(H44,M44+$O44*H44/SUM($G44:$I44))) -> 163.3579 | R44: =MAX(0,MIN(I44,N44+$O44*I44/SUM($G44:$I44))) -> 18.328744 | S44: =MIN(1,P44/F43) -> 0.024050112 | T44: =MIN(1,Q44/G43) -> 0.0079811363 | U44: =MIN(1,R44/H43) -> 0.026372293 | V44: =AVERAGE(S41:S47) -> 0.024167008 | W44: =AVERAGE(T41:T47) -> 0.0035883011 | X44: =AVERAGE(U41:U47) -> 0.018011925 | Y44: =(C44-C43)/E43 -> 0.023861416 | Z44: =AVERAGE(Y41:Y47) -> 0.021674524 | AA44: ='ori data'!AV131 -> 0.034010937 | AB44: ='ori data'!AW131 -> 0.030507944 | AD44: =AD43+$AC$49/10 -> 3602.5 | AE44: =(AD44-AD43)/E43 -> 0.00024055059 | AF44: =Z44+AE44 -> 0.021915075 | AG44: ='opt vacc_sigma0.1'!L15+AE44 -> 0.022636008
A45: 14 | B45: 44486 | C45: 3629969 | D45: 6629870 | E45: =D45-C45-SUM(F45:K45) -> 2860795 | F45: 73501 | G45: 22444 | H45: 777 | I45: 151 | J45: 41265 | K45: 968 | L45: =G45-G44 -> 1762 | M45: =H45-H44 -> -21 | N45: =I45-I44 -> -12 | O45: =J45-J44 -> 33 | P45: =MAX(0,MIN(G45,L45+$O45*G45/SUM($G45:$I45))) -> 1793.6897 | Q45: =MAX(0,MIN(H45,M45+$O45*H45/SUM($G45:$I45))) -> 0 | R45: =MAX(0,MIN(I45,N45+$O45*I45/SUM($G45:$I45))) -> 0 | T45: =MIN(1,Q45/G44) -> 0 | U45: =MIN(1,R45/H44) -> 0 | V45: =AVERAGE(S42:S48) -> 0.024802852 | W45: =AVERAGE(T42:T48) -> 0.0034047724 | X45: =AVERAGE(U42:U48) -> 0.017158431 | Y45: =(C45-C44)/E44 -> 0.020453262 | Z45: =AVERAGE(Y42:Y48) -> 0.022735849 | AA45: ='ori data'!AV132 -> 0.026994245 | AB45: ='ori data'!AW132 -> 0.031539824 | AD45: =AD44+$AC$49/10 -> 4323 | AE45: =(AD45-AD44)/E44 -> 0.00024704243 | AF45: =Z45+AE45 -> 0.022982891 | AG45: ='opt vacc_sigma0.1'!L16+AE45 -> 0.02250918
A46: 15 | B46: 44487 | C46: 3674542 | D46: 6629870 | E46: =D46-C46-SUM(F46:K46) -> 2818046 | F46: 69825 | G46: 21317 | H46: 851 | I46: 155 | J46: 44159 | K46: 975 | L46: =G46-G45 -> -1127 | M46: =H46-H45 -> 74 | N46: =I46-I45 -> 4 | O46: =J46-J45 -> 2894 | P46: =MAX(0,MIN(G46,L46+$O46*G46/SUM($G46:$I46))) -> 1636.5801 | Q46: =MAX(0,MIN(H46,M46+$O46*H46/SUM($G46:$I46))) -> 184.3254 | R46: =MAX(0,MIN(I46,N46+$O46*I46/SUM($G46:$I46))) -> 24.094521 | S46: =MIN(1,P46/F45) -> 0.022266093 | T46: =MIN(1,Q46/G45) -> 0.0082126806 | U46: =MIN(1,R46/H45) -> 0.03100968 | V46: =AVERAGE(S43:S49) -> 0.024711319 | W46: =AVERAGE(T43:T49) -> 0.0031709971 | X46: =AVERAGE(U43:U49) -> 0.014594754 | Y46: =(C46-C45)/E45 -> 0.015580634 | Z46: =AVERAGE(Y43:Y49) -> 0.0236201 | AA46: ='ori data'!AV133 -> 0.019814794 | AB46: ='ori data'!AW133 -> 0.032446016 | AD46: =AD45+$AC$49/10 -> 5043.5 | AE46: =(AD46-AD45)/E45 -> 0.00025185307 | AF46: =Z46+AE46 -> 0.023871953 | AG46: ='opt vacc_sigma0.1'!L17+AE46 -> 0.022374439
A47: 16 | B47: 44488 | C47: 3750000 | D47: 6629870 | E47: =D47-C47-SUM(F47:K47) -> 2741989 | F47: 68702 | G47: 21539 | H47: 784 | I47: 149 | J47: 45721 | K47: 986 | L47: =G47-G46 -> 222 | M47: =H47-H46 -> -67 | N47: =I47-I46 -> -6 | O47: =J47-J46 -> 1562 | P47: =MAX(0,MIN(G47,L47+$O47*G47/SUM($G47:$I47))) -> 1719.1484 | Q47: =MAX(0,MIN(H47,M47+$O47*H47/SUM($G47:$I47))) -> 0 | R47: =MAX(0,MIN(I47,N47+$O47*I47/SUM($G47:$I47))) -> 4.3567996 | S47: =MIN(1,P47/F46) -> 0.024620814 | T47: =MIN(1,Q47/G46) -> 0 | U47: =MIN(1,R47/H46) -> 0.0051196235 | V47: =AVERAGE(S44:S50) -> 0.024809751 | W47: =AVERAGE(T44:T50) -> 0.0035193174 | X47: =AVERAGE(U44:U50) -> 0.014374079 | Y47: =(C47-C46)/E46 -> 0.02677671 | Z47: =AVERAGE(Y44:Y50) -> 0.024767235 | AA47: ='ori data'!AV134 -> 0.036577098 | AB47: ='ori data'!AW134 -> 0.033544899 | AD47: =AD46+$AC$49/10 -> 5764 | AE47: =(AD47-AD46)/E46 -> 0.00025567361 | AF47: =Z47+AE47 -> 0.025022908 | AG47: ='opt vacc_sigma0.1'!L18+AE47 -> 0.022240799
A48: 17 | B48: 44489 | C48: 3827009 | D48: 6629870 | E48: =D48-C48-SUM(F48:K48) -> 2652935 | F48: 78928 | G48: 21661 | H48: 786 | I48: 147 | J48: 47406 | K48: 998 | L48: =G48-G47 -> 122 | M48: =H48-H47 -> 2 | N48: =I48-I47 -> -2 | O48: =J48-J47 -> 1685 | P48: =MAX(0,MIN(G48,L48+$O48*G48/SUM($G48:$I48))) -> 1737.4194 | Q48: =MAX(0,MIN(H48,M48+$O48*H48/SUM($G48:$I48))) -> 60.617775 | R48: =MAX(0,MIN(I48,N48+$O48*I48/SUM($G48:$I48))) -> 8.9628662 | S48: =MIN(1,P48/F47) -> 0.025289211 | T48: =MIN(1,Q48/G47) -> 0.0028143263 | U48: =MIN(1,R48/H47) -> 0.011432227 | V48: =AVERAGE(S45:S51) -> 0.024022271 | W48: =AVERAGE(T45:T51) -> 0.002630918 | X48: =AVERAGE(U45:U51) -> 0.012240507 | Y48: =(C48-C47)/E47 -> 0.028085087 | Z48: =AVERAGE(Y45:Y51) -> 0.025850144 | AA48: ='ori data'!AV135 -> 0.038293437 | AB48: ='ori data'!AW135 -> 0.034559753 | AD48: =AD47+$AC$49/10 -> 6484.5 | AE48: =(AD48-AD47)/E47 -> 0.00026276546 | AF48: =Z48+AE48 -> 0.026112909 | AG48: ='opt vacc_sigma0.1'!L19+AE48 -> 0.022102528
A49: 18 | B49: 44490 | C49: 3901346 | D49: 6629870 | E49: =D49-C49-SUM(F49:K49) -> 2575829 | F49: 79544 | G49: 21965 | H49: 779 | I49: 141 | J49: 49256 | K49: 1010 | L49: =G49-G48 -> 304 | M49: =H49-H48 -> -7 | N49: =I49-I48 -> -6 | O49: =J49-J48 -> 1850 | P49: =MAX(0,MIN(G49,L49+$O49*G49/SUM($G49:$I49))) -> 2079.6281 | Q49: =MAX(0,MIN(H49,M49+$O49*H49/SUM($G49:$I49))) -> 55.973563 | R49: =MAX(0,MIN(I49,N49+$O49*I49/SUM($G49:$I49))) -> 5.3982958 | S49: =MIN(1,P49/F48) -> 0.026348421 | T49: =MIN(1,Q49/G48) -> 0.0025840711 | U49: =MIN(1,R49/H48) -> 0.0068680608 | V49: =AVERAGE(S46:S52) -> 0.024209335 | W49: =AVERAGE(T46:T52) -> 0.00274757 | X49: =AVERAGE(U46:U52) -> 0.012651672 | Y49: =(C49-C48)/E48 -> 0.028020664 | Z49: =AVERAGE(Y46:Y52) -> 0.026643545 | AA49: ='ori data'!AV136 -> 0.038270009 | AB49: ='ori data'!AW136 -> 0.035390495 | AC49: 7205 | AD49: =AD48+$AC$49/10 -> 7205 | AE49: =(AD49-AD48)/E48 -> 0.000271586 | AF49: =Z49+AE49 -> 0.026915131 | AG49: ='opt vacc_sigma0.1'!L20+AE49 -> 0.021955912
A50: 19 | B50: 44491 | C50: 3980148 | D50: 6629870 | E50: =D50-C50-SUM(F50:K50) -> 2497346 | F50: 77036 | G50: 22297 | H50: 784 | I50: 145 | J50: 51088 | K50: 1026 | L50: =G50-G49 -> 332 | M50: =H50-H49 -> 5 | N50: =I50-I49 -> 4 | O50: =J50-J49 -> 1832 | P50: =MAX(0,MIN(G50,L50+$O50*G50/SUM($G50:$I50))) -> 2090.7232 | Q50: =MAX(0,MIN(H50,M50+$O50*H50/SUM($G50:$I50))) -> 66.839662 | R50: =MAX(0,MIN(I50,N50+$O50*I50/SUM($G50:$I50))) -> 15.437182 | S50: =MIN(1,P50/F49) -> 0.026283857 | T50: =MIN(1,Q50/G49) -> 0.0030430076 | U50: =MIN(1,R50/H49) -> 0.019816666 | V50: =AVERAGE(S47:S53) -> 0.024533209 | W50: =AVERAGE(T47:T53) -> 0.0019596015 | X50: =AVERAGE(U47:U53) -> 0.011026752 | Y50: =(C50-C49)/E49 -> 0.030592869 | Z50: =AVERAGE(Y47:Y53) -> 0.02681191 | AA50: ='ori data'!AV137 -> 0.04085377 | AB50: ='ori data'!AW137 -> 0.035506688 | AD50: =10289*EXP(0.05828*(A50-17)) -> 11560.977 | AE50: =(AD50-AD49)/E49 -> 0.0016910971 | AF50: =Z50+AE50 -> 0.028503007 | AG50: ='opt vacc_sigma0.1'!L21+AE50 -> 0.023266226
A51: 20 | B51: 44492 | C51: 4058669 | D51: 6629870 | E51: =D51-C51-SUM(F51:K51) -> 2421457 | F51: 72858 | G51: 22246 | H51: 770 | I51: 144 | J51: 52691 | K51: 1035 | L51: =G51-G50 -> -51 | M51: =H51-H50 -> -14 | N51: =I51-I50 -> -1 | O51: =J51-J50 -> 1603 | P51: =MAX(0,MIN(G51,L51+$O51*G51/SUM($G51:$I51))) -> 1488.7383 | Q51: =MAX(0,MIN(H51,M51+$O51*H51/SUM($G51:$I51))) -> 39.294905 | R51: =MAX(0,MIN(I51,N51+$O51*I51/SUM($G51:$I51))) -> 8.9668394 | S51: =MIN(1,P51/F50) -> 0.019325228 | T51: =MIN(1,Q51/G50) -> 0.0017623404 | U51: =MIN(1,R51/H50) -> 0.011437295 | V51: =AVERAGE(S48:S54) -> 0.024595025 | W51: =AVERAGE(T48:T54) -> 0.0023680917 | X51: =AVERAGE(U48:U54) -> 0.011111812 | Y51: =(C51-C50)/E50 -> 0.031441779 | Z51: =AVERAGE(Y48:Y54) -> 0.027254024 | AA51: ='ori data'!AV138 -> 0.041114916 | AB51: ='ori data'!AW138 -> 0.035810484 | AD51: =10289*EXP(0.05828*(A51-17)) -> 12254.771 | AE51: =(AD51-AD50)/E50 -> 0.00027781274 | AF51: =Z51+AE51 -> 0.027531837 | AG51: ='opt vacc_sigma0.1'!L22+AE51 -> 0.021726578
A52: 21 | B52: 44493 | C52: 4121644 | D52: 6629870 | E52: =D52-C52-SUM(F52:K52) -> 2359839 | F52: 69624 | G52: 24056 | H52: 787 | I52: 146 | J52: 52728 | K52: 1046 | L52: =G52-G51 -> 1810 | M52: =H52-H51 -> 17 | N52: =I52-I51 -> 2 | O52: =J52-J51 -> 37 | P52: =MAX(0,MIN(G52,L52+$O52*G52/SUM($G52:$I52))) -> 1845.6186 | Q52: =MAX(0,MIN(H52,M52+$O52*H52/SUM($G52:$I52))) -> 18.165273 | R52: =MAX(0,MIN(I52,N52+$O52*I52/SUM($G52:$I52))) -> 2.2161751 | S52: =MIN(1,P52/F51) -> 0.025331721 | T52: =MIN(1,Q52/G51) -> 0.00081656355 | U52: =MIN(1,R52/H51) -> 0.0028781495 | V52: =AVERAGE(S49:S55) -> 0.024688201 | W52: =AVERAGE(T49:T55) -> 0.0019660451 | X52: =AVERAGE(U49:U55) -> 0.0098874775 | Y52: =(C52-C51)/E51 -> 0.026007069 | Z52: =AVERAGE(Y49:Y55) -> 0.027149173 | AA52: ='ori data'!AV139 -> 0.032809442 | AB52: ='ori data'!AW139 -> 0.035464426 | AD52: =10289*EXP(0.05828*(A52-17)) -> 12990.202 | AE52: =(AD52-AD51)/E51 -> 0.00030371399 | AF52: =Z52+AE52 -> 0.027452887 | AG52: ='opt vacc_sigma0.1'!L23+AE52 -> 0.021582843
A53: 22 | B53: 44494 | C53: 4161193 | D53: 6629870 | E53: =D53-C53-SUM(F53:K53) -> 2331620 | F53: 56905 | G53: 23873 | H53: 802 | I53: 152 | J53: 54272 | K53: 1053 | L53: =G53-G52 -> -183 | M53: =H53-H52 -> 15 | N53: =I53-I52 -> 6 | O53: =J53-J52 -> 1544 | P53: =MAX(0,MIN(G53,L53+$O53*G53/SUM($G53:$I53))) -> 1301.6704 | Q53: =MAX(0,MIN(H53,M53+$O53*H53/SUM($G53:$I53))) -> 64.876667 | R53: =MAX(0,MIN(I53,N53+$O53*I53/SUM($G53:$I53))) -> 15.452934 | T53: =MIN(1,Q53/G52) -> 0.0026969017 | U53: =MIN(1,R53/H52) -> 0.019635241 | V53: =AVERAGE(S50:S56) -> 0.023643736 | W53: =AVERAGE(T50:T56) -> 0.0023676987 | X53: =AVERAGE(U50:U56) -> 0.013189988 | Y53: =(C53-C52)/E52 -> 0.016759194 | Z53: =AVERAGE(Y50:Y56) -> 0.026844426 | AA53: ='ori data'!AV140 -> 0.020628147 | AB53: ='ori data'!AW140 -> 0.034781291 | AD53: =10289*EXP(0.05828*(A53-17)) -> 13769.767 | AE53: =(AD53-AD52)/E52 -> 0.00033034662 | AF53: =Z53+AE53 -> 0.027174773 | AG53: ='opt vacc_sigma0.1'!L24+AE53 -> 0.021451621
A54: 23 | B54: 44495 | C54: 4230842 | D54: 6629870 | E54: =D54-C54-SUM(F54:K54) -> 2261698 | F54: 55679 | G54: 23747 | H54: 817 | I54: 147 | J54: 55883 | K54: 1057 | L54: =G54-G53 -> -126 | M54: =H54-H53 -> 15 | N54: =I54-I53 -> -5 | O54: =J54-J53 -> 1611 | P54: =MAX(0,MIN(G54,L54+$O54*G54/SUM($G54:$I54))) -> 1422.1533 | Q54: =MAX(0,MIN(H54,M54+$O54*H54/SUM($G54:$I54))) -> 68.263203 | R54: =MAX(0,MIN(I54,N54+$O54*I54/SUM($G54:$I54))) -> 4.5834649 | S54: =MIN(1,P54/F53) -> 0.024991711 | T54: =MIN(1,Q54/G53) -> 0.0028594313 | U54: =MIN(1,R54/H53) -> 0.0057150435 | V54: =AVERAGE(S51:S57) -> 0.023115712 | W54: =AVERAGE(T51:T57) -> 0.0019329833 | X54: =AVERAGE(U51:U57) -> 0.010359036 | Y54: =(C54-C53)/E53 -> 0.029871506 | Z54: =AVERAGE(Y51:Y57) -> 0.026352638 | AA54: ='ori data'!AV141 -> 0.038703664 | AB54: ='ori data'!AW141 -> 0.033896747 | AD54: =10289*EXP(0.05828*(A54-17)) -> 14596.115 | AE54: =(AD54-AD53)/E53 -> 0.00035440934 | AF54: =Z54+AE54 -> 0.026707047 | AG54: ='opt vacc_sigma0.1'!L25+AE54 -> 0.021321006
A55: 24 | B55: 44496 | C55: 4292702 | D55: 6629870 | E55: =D55-C55-SUM(F55:K55) -> 2170860 | F55: 83210 | G55: 23274 | H55: 748 | I55: 138 | J55: 57868 | K55: 1070 | L55: =G55-G54 -> -473 | M55: =H55-H54 -> -69 | N55: =I55-I54 -> -9 | O55: =J55-J54 -> 1985 | P55: =MAX(0,MIN(G55,L55+$O55*G55/SUM($G55:$I55))) -> 1439.2057 | Q55: =MAX(0,MIN(H55,M55+$O55*H55/SUM($G55:$I55))) -> 0 | R55: =MAX(0,MIN(I55,N55+$O55*I55/SUM($G55:$I55))) -> 2.3381623 | S55: =MIN(1,P55/F54) -> 0.025848268 | T55: =MIN(1,Q55/G54) -> 0 | U55: =MIN(1,R55/H54) -> 0.0028618877 | V55: =AVERAGE(S52:S58) -> 0.022501184 | W55: =AVERAGE(T52:T58) -> 0.0026129229 | X55: =AVERAGE(U52:U58) -> 0.014593371 | Y55: =(C55-C54)/E54 -> 0.027351132 | Z55: =AVERAGE(Y52:Y58) -> 0.025807821 | AA55: ='ori data'!AV142 -> 0.035871037 | AB55: ='ori data'!AW142 -> 0.032985034 | AD55: =10289*EXP(0.05828*(A55-17)) -> 15472.053 | AE55: =(AD55-AD54)/E54 -> 0.00038729242 | AF55: =Z55+AE55 -> 0.026195113 | AG55: ='opt vacc_sigma0.1'!L26+AE55 -> 0.021197407
A56: 25 | B56: 44497 | C56: 4348900 | D56: 6629870 | E56: =D56-C56-SUM(F56:K56) -> 2113380 | F56: 82648 | G56: 21302 | H56: 746 | I56: 137 | J56: 61662 | K56: 1095 | L56: =G56-G55 -> -1972 | M56: =H56-H55 -> -2 | N56: =I56-I55 -> -1 | O56: =J56-J55 -> 3794 | P56: =MAX(0,MIN(G56,L56+$O56*G56/SUM($G56:$I56))) -> 1670.9925 | Q56: =MAX(0,MIN(H56,M56+$O56*H56/SUM($G56:$I56))) -> 125.57827 | R56: =MAX(0,MIN(I56,N56+$O56*I56/SUM($G56:$I56))) -> 22.429254 | S56: =MIN(1,P56/F55) -> 0.02008163 | T56: =MIN(1,Q56/G55) -> 0.0053956464 | U56: =MIN(1,R56/H55) -> 0.029985634 | V56: =AVERAGE(S53:S59) -> 0.02179355 | W56: =AVERAGE(T53:T59) -> 0.002496271 | X56: =AVERAGE(U53:U59) -> 0.014182207 | Y56: =(C56-C55)/E55 -> 0.025887436 | Z56: =AVERAGE(Y53:Y59) -> 0.025170466 | AA56: ='ori data'!AV143 -> 0.033488062 | AB56: ='ori data'!AW143 -> 0.032045178 | AD56: =10289*EXP(0.05828*(A56-17)) -> 16400.558 | AE56: =(AD56-AD55)/E55 -> 0.00042771302 | AF56: =Z56+AE56 -> 0.025598179 | AG56: ='opt vacc_sigma0.1'!L27+AE56 -> 0.021083767
A57: 26 | B57: 44498 | C57: 4406279 | D57: 6629870 | E57: =D57-C57-SUM(F57:K57) -> 2066848 | F57: 70180 | G57: 22858 | H57: 738 | I57: 130 | J57: 61732 | K57: 1105 | L57: =G57-G56 -> 1556 | M57: =H57-H56 -> -8 | N57: =I57-I56 -> -7 | O57: =J57-J56 -> 70 | P57: =MAX(0,MIN(G57,L57+$O57*G57/SUM($G57:$I57))) -> 1623.4391 | Q57: =MAX(0,MIN(H57,M57+$O57*H57/SUM($G57:$I57))) -> 0 | R57: =MAX(0,MIN(I57,N57+$O57*I57/SUM($G57:$I57))) -> 0 | T57: =MIN(1,Q57/G56) -> 0 | U57: =MIN(1,R57/H56) -> 0 | V57: =AVERAGE(S54:S60) -> 0.022266597 | W57: =AVERAGE(T54:T60) -> 0.0024101021 | X57: =AVERAGE(U54:U60) -> 0.014879656 | Y57: =(C57-C56)/E56 -> 0.027150347 | Z57: =AVERAGE(Y54:Y60) -> 0.024392045 | AA57: ='ori data'!AV144 -> 0.034661959 | AB57: ='ori data'!AW144 -> 0.031047919 | AD57: =10289*EXP(0.05828*(A57-17)) -> 17384.784 | AE57: =(AD57-AD56)/E56 -> 0.00046571195 | AF57: =Z57+AE57 -> 0.024857757 | AG57: ='opt vacc_sigma0.1'!L28+AE57 -> 0.020925732
A58: 27 | B58: 44499 | C58: 4463382 | D58: 6629870 | E58: =D58-C58-SUM(F58:K58) -> 2010110 | F58: 68484 | G58: 20209 | H58: 747 | I58: 135 | J58: 65687 | K58: 1116 | L58: =G58-G57 -> -2649 | M58: =H58-H57 -> 9 | N58: =I58-I57 -> 5 | O58: =J58-J57 -> 3955 | P58: =MAX(0,MIN(G58,L58+$O58*G58/SUM($G58:$I58))) -> 1140.6067 | Q58: =MAX(0,MIN(H58,M58+$O58*H58/SUM($G58:$I58))) -> 149.078 | R58: =MAX(0,MIN(I58,N58+$O58*I58/SUM($G58:$I58))) -> 30.3153 | S58: =MIN(1,P58/F57) -> 0.016252589 | T58: =MIN(1,Q58/G57) -> 0.0065219177 | U58: =MIN(1,R58/H57) -> 0.041077643 | V58: =AVERAGE(S55:S61) -> 0.020936602 | W58: =AVERAGE(T55:T61) -> 0.0025982091 | X58: =AVERAGE(U55:U61) -> 0.016901323 | Y58: =(C58-C57)/E57 -> 0.02762806 | Z58: =AVERAGE(Y55:Y61) -> 0.023980076 | AA58: ='ori data'!AV145 -> 0.034732925 | AB58: ='ori data'!AW145 -> 0.029940371 | AD58: =10289*EXP(0.05828*(A58-17)) -> 18428.076 | AE58: =(AD58-AD57)/E57 -> 0.00050477416 | AF58: =Z58+AE58 -> 0.02448485 | AG58: ='opt vacc_sigma0.1'!L29+AE58 -> 0.020735806
A59: 28 | B59: 44500 | C59: 4506691 | D59: 6629870 | E59: =D59-C59-SUM(F59:K59) -> 1977587 | F59: 56768 | G59: 21179 | H59: 702 | I59: 128 | J59: 65687 | K59: 1128 | L59: =G59-G58 -> 970 | M59: =H59-H58 -> -45 | N59: =I59-I58 -> -7 | O59: =J59-J58 -> 0 | P59: =MAX(0,MIN(G59,L59+$O59*G59/SUM($G59:$I59))) -> 970 | Q59: =MAX(0,MIN(H59,M59+$O59*H59/SUM($G59:$I59))) -> 0 | R59: =MAX(0,MIN(I59,N59+$O59*I59/SUM($G59:$I59))) -> 0 | T59: =MIN(1,Q59/G58) -> 0 | U59: =MIN(1,R59/H58) -> 0 | V59: =AVERAGE(S56:S62) -> 0.019261898 | W59: =AVERAGE(T56:T62) -> 0.0030568858 | X59: =AVERAGE(U56:U62) -> 0.01701125 | Y59: =(C59-C58)/E58 -> 0.021545587 | Z59: =AVERAGE(Y56:Y62) -> 0.021123966 | AA59: ='ori data'!AV146 -> 0.026230452 | AB59: ='ori data'!AW146 -> 0.026110312 | AC59: 15596 | AD59: =10289*EXP(0.05828*(A59-17)) -> 19533.977 | AE59: =(AD59-AD58)/E58 -> 0.0005501695 | AF59: =Z59+AE59 -> 0.021674136 | AG59: ='opt vacc_sigma0.1'!L30+AE59 -> 0.020590741
A60: 29 | B60: 44501 | C60: 4529058 | D60: 6629870 | E60: =D60-C60-SUM(F60:K60) -> 1964486 | F60: 46065 | G60: 21120 | H60: 699 | I60: 136 | J60: 67174 | K60: 1132 | L60: =G60-G59 -> -59 | M60: =H60-H59 -> -3 | N60: =I60-I59 -> 8 | O60: =J60-J59 -> 1487 | P60: =MAX(0,MIN(G60,L60+$O60*G60/SUM($G60:$I60))) -> 1371.4459 | Q60: =MAX(0,MIN(H60,M60+$O60*H60/SUM($G60:$I60))) -> 44.342883 | R60: =MAX(0,MIN(I60,N60+$O60*I60/SUM($G60:$I60))) -> 17.211205 | S60: =MIN(1,P60/F59) -> 0.024158785 | T60: =MIN(1,Q60/G59) -> 0.0020937194 | U60: =MIN(1,R60/H59) -> 0.024517386 | V60: =AVERAGE(S57:S63) -> 0.0187892 | W60: =AVERAGE(T57:T63) -> 0.002884316 | X60: =AVERAGE(U57:U63) -> 0.014728023 | Y60: =(C60-C59)/E59 -> 0.011310248 | Z60: =AVERAGE(Y57:Y63) -> 0.021056157 | AA60: ='ori data'!AV147 -> 0.013647336 | AB60: ='ori data'!AW147 -> 0.025908979 | AD60: =10289*EXP(0.05828*(A60-17)) -> 20706.245 | AE60: =(AD60-AD59)/E59 -> 0.0005927771 | AF60: =Z60+AE60 -> 0.021648934 | AG60: ='opt vacc_sigma0.1'!L31+AE60 -> 0.0204249
A61: 30 | B61: 44502 | C61: 4582075 | D61: 6629870 | E61: =D61-C61-SUM(F61:K61) -> 1908576 | F61: 48002 | G61: 18611 | H61: 667 | I61: 127 | J61: 70671 | K61: 1141 | L61: =G61-G60 -> -2509 | M61: =H61-H60 -> -32 | N61: =I61-I60 -> -9 | O61: =J61-J60 -> 3497 | P61: =MAX(0,MIN(G61,L61+$O61*G61/SUM($G61:$I61))) -> 844.91224 | Q61: =MAX(0,MIN(H61,M61+$O61*H61/SUM($G61:$I61))) -> 88.200928 | R61: =MAX(0,MIN(I61,N61+$O61*I61/SUM($G61:$I61))) -> 13.886833 | S61: =MIN(1,P61/F60) -> 0.01834174 | T61: =MIN(1,Q61/G60) -> 0.0041761803 | U61: =MIN(1,R61/H60) -> 0.019866714 | V61: =AVERAGE(S58:S64) -> 0.020139376 | W61: =AVERAGE(T58:T64) -> 0.002884316 | X61: =AVERAGE(U58:U64) -> 0.014728023 | Y61: =(C61-C60)/E60 -> 0.026987721 | Z61: =AVERAGE(Y58:Y64) -> 0.020739005 | AA61: ='ori data'!AV148 -> 0.030950824 | AB61: ='ori data'!AW148 -> 0.025537187 | AD61: =10289*EXP(0.05828*(A61-17)) -> 21948.864 | AE61: =(AD61-AD60)/E60 -> 0.00063254112 | AF61: =Z61+AE61 -> 0.021371546 | AG61: ='opt vacc_sigma0.1'!L32+AE61 -> 0.020229538
A62: 31 | B62: 44503 | C62: 4596119 | D62: 6629870 | E62: =D62-C62-SUM(F62:K62) -> 1878347 | F62: 63278 | G62: 17583 | H62: 657 | I62: 117 | J62: 72620 | K62: 1149 | L62: =G62-G61 -> -1028 | M62: =H62-H61 -> -10 | N62: =I62-I61 -> -10 | O62: =J62-J61 -> 1949 | P62: =MAX(0,MIN(G62,L62+$O62*G62/SUM($G62:$I62))) -> 838.82285 | Q62: =MAX(0,MIN(H62,M62+$O62*H62/SUM($G62:$I62))) -> 59.755025 | R62: =MAX(0,MIN(I62,N62+$O62*I62/SUM($G62:$I62))) -> 2.4221278 | S62: =MIN(1,P62/F61) -> 0.017474748 | T62: =MIN(1,Q62/G61) -> 0.0032107369 | U62: =MIN(1,R62/H61) -> 0.003631376 | V62: =AVERAGE(S59:S65) -> 0.02011758 | W62: =AVERAGE(T59:T65) -> 0.0031688618 | X62: =AVERAGE(U59:U65) -> 0.013246639 | Y62: =(C62-C61)/E61 -> 0.0073583656 | Z62: =AVERAGE(Y59:Y65) -> 0.020314954 | AA62: ='ori data'!AV149 -> 0.0090606262 | AB62: ='ori data'!AW149 -> 0.025064247 | AD62: =10289*EXP(0.05828*(A62-17)) -> 23266.053 | AE62: =(AD62-AD61)/E61 -> 0.00069014274 | AF62: =Z62+AE62 -> 0.021005097 | AG62: ='opt vacc_sigma0.1'!L33+AE62 -> 0.020074048
A63: 32 | B63: 44504 | C63: 4643853 | D63: 6629870 | E63: =D63-C63-SUM(F63:K63) -> 1842498 | F63: 50180 | G63: 16896 | H63: 660 | I63: 114 | J63: 74511 | K63: 1158 | L63: =G63-G62 -> -687 | M63: =H63-H62 -> 3 | N63: =I63-I62 -> -3 | O63: =J63-J62 -> 1891 | P63: =MAX(0,MIN(G63,L63+$O63*G63/SUM($G63:$I63))) -> 1121.1684 | Q63: =MAX(0,MIN(H63,M63+$O63*H63/SUM($G63:$I63))) -> 73.631579 | R63: =MAX(0,MIN(I63,N63+$O63*I63/SUM($G63:$I63))) -> 9.2 | S63: =MIN(1,P63/F62) -> 0.017718139 | T63: =MIN(1,Q63/G62) -> 0.0041876573 | U63: =MIN(1,R63/H62) -> 0.014003044 | V63: =AVERAGE(S60:S66) -> 0.019765587 | W63: =AVERAGE(T60:T66) -> 0.0031688618 | X63: =AVERAGE(U60:U66) -> 0.013246639 | Y63: =(C63-C62)/E62 -> 0.02541277 | Z63: =AVERAGE(Y60:Y66) -> 0.019498183 | AA63: ='ori data'!AV150 -> 0.032078732 | AB63: ='ori data'!AW150 -> 0.023987008 | AC63: 32316 | AD63: =10289*EXP(0.05828*(A63-17)) -> 24662.29 | AE63: =(AD63-AD62)/E62 -> 0.0007433327 | AF63: =Z63+AE63 -> 0.020241515 | AG63: ='opt vacc_sigma0.1'!L34+AE63 -> 0.019891436
A64: 33 | B64: 44505 | C64: 4689787 | D64: 6629870 | E64: =D64-C64-SUM(F64:K64) -> 1779259 | F64: 66155 | G64: 18205 | H64: 634 | I64: 109 | J64: 74553 | K64: 1168 | L64: =G64-G63 -> 1309 | M64: =H64-H63 -> -26 | N64: =I64-I63 -> -5 | O64: =J64-J63 -> 42 | P64: =MAX(0,MIN(G64,L64+$O64*G64/SUM($G64:$I64))) -> 1349.3531 | Q64: =MAX(0,MIN(H64,M64+$O64*H64/SUM($G64:$I64))) -> 0 | R64: =MAX(0,MIN(I64,N64+$O64*I64/SUM($G64:$I64))) -> 0 | S64: =MIN(1,P64/F63) -> 0.026890257 | T64: =MIN(1,Q64/G63) -> 0 | U64: =MIN(1,R64/H63) -> 0 | V64: =AVERAGE(S61:S67) -> 0.018952928 | W64: =AVERAGE(T61:T67) -> 0.0031716545 | X64: =AVERAGE(U61:U67) -> 0.010350256 | Y64: =(C64-C63)/E63 -> 0.024930285 | Z64: =AVERAGE(Y61:Y67) -> 0.019011593 | AA64: ='ori data'!AV151 -> 0.032059413 | AB64: ='ori data'!AW151 -> 0.023341435 | AD64: =10289*EXP(0.05828*(A64-17)) -> 26142.318 | AE64: =(AD64-AD63)/E63 -> 0.00080327218 | AF64: =Z64+AE64 -> 0.019814865 | AG64: ='opt vacc_sigma0.1'!L35+AE64 -> 0.019730735
A65: 34 | B65: 44506 | C65: 4733663 | D65: 6629870 | E65: =D65-C65-SUM(F65:K65) -> 1734880 | F65: 65410 | G65: 15901 | H65: 651 | I65: 106 | J65: 78084 | K65: 1175 | L65: =G65-G64 -> -2304 | M65: =H65-H64 -> 17 | N65: =I65-I64 -> -3 | O65: =J65-J64 -> 3531 | P65: =MAX(0,MIN(G65,L65+$O65*G65/SUM($G65:$I65))) -> 1066.5385 | Q65: =MAX(0,MIN(H65,M65+$O65*H65/SUM($G65:$I65))) -> 154.99262 | R65: =MAX(0,MIN(I65,N65+$O65*I65/SUM($G65:$I65))) -> 19.468844 | S65: =MIN(1,P65/F64) -> 0.016121813 | T65: =MIN(1,Q65/G64) -> 0.0085137389 | U65: =MIN(1,R65/H64) -> 0.030707956 | V65: =AVERAGE(S62:S68) -> 0.019389652 | W65: =AVERAGE(T62:T68) -> 0.0033377169 | X65: =AVERAGE(U62:U68) -> 0.0096472384 | Y65: =(C65-C64)/E64 -> 0.024659704 | Z65: =AVERAGE(Y62:Y68) -> 0.017947895 | AA65: ='ori data'!AV152 -> 0.031422346 | AB65: ='ori data'!AW152 -> 0.022500899 | AD65: =10289*EXP(0.05828*(A65-17)) -> 27711.164 | AE65: =(AD65-AD64)/E64 -> 0.00088174146 | AF65: =Z65+AE65 -> 0.018829637 | AG65: ='opt vacc_sigma0.1'!L36+AE65 -> 0.019592413
A66: 35 | B66: 44507 | C66: 4761123 | D66: 6629870 | E66: =D66-C66-SUM(F66:K66) -> 1715055 | F66: 56649 | G66: 15745 | H66: 568 | I66: 96 | J66: 79450 | K66: 1184 | L66: =G66-G65 -> -156 | M66: =H66-H65 -> -83 | N66: =I66-I65 -> -10 | O66: =J66-J65 -> 1366 | P66: =MAX(0,MIN(G66,L66+$O66*G66/SUM($G66:$I66))) -> 1154.724 | Q66: =MAX(0,MIN(H66,M66+$O66*H66/SUM($G66:$I66))) -> 0 | R66: =MAX(0,MIN(I66,N66+$O66*I66/SUM($G66:$I66))) -> 0 | S66: =MIN(1,P66/F65) -> 0.017653631 | T66: =MIN(1,Q66/G65) -> 0 | U66: =MIN(1,R66/H65) -> 0 | V66: =AVERAGE(S63:S69) -> 0.019948292 | W66: =AVERAGE(T63:T69) -> 0.0028790402 | X66: =AVERAGE(U63:U69) -> 0.0097734481 | Y66: =(C66-C65)/E65 -> 0.015828184 | Z66: =AVERAGE(Y63:Y69) -> 0.019411451 | AA66: ='ori data'!AV153 -> 0.01868978 | AB66: ='ori data'!AW153 -> 0.02459864 | AD66: =10289*EXP(0.05828*(A66-17)) -> 29374.16 | AE66: =(AD66-AD65)/E65 -> 0.00095856523 | AF66: =Z66+AE66 -> 0.020370016 | AG66: ='opt vacc_sigma0.1'!L37+AE66 -> 0.019453971
A67: 36 | B67: 44508 | C67: 4774679 | D67: 6629870 | E67: =D67-C67-SUM(F67:K67) -> 1712582 | F67: 44479 | G67: 15527 | H67: 556 | I67: 91 | J67: 80767 | K67: 1189 | L67: =G67-G66 -> -218 | M67: =H67-H66 -> -12 | N67: =I67-I66 -> -5 | O67: =J67-J66 -> 1317 | P67: =MAX(0,MIN(G67,L67+$O67*G67/SUM($G67:$I67))) -> 1046.3167 | Q67: =MAX(0,MIN(H67,M67+$O67*H67/SUM($G67:$I67))) -> 33.273402 | R67: =MAX(0,MIN(I67,N67+$O67*I67/SUM($G67:$I67))) -> 2.4098553 | S67: =MIN(1,P67/F66) -> 0.018470171 | T67: =MIN(1,Q67/G66) -> 0.0021132678 | U67: =MIN(1,R67/H66) -> 0.004242703 | V67: =AVERAGE(S64:S70) -> 0.019975106 | W67: =AVERAGE(T64:T70) -> 0.0023271287 | X67: =AVERAGE(U64:U70) -> 0.0077730132 | Y67: =(C67-C66)/E66 -> 0.0079041197 | Z67: =AVERAGE(Y64:Y70) -> 0.018248225 | AA67: ='ori data'!AV154 -> 0.009128322 | AB67: ='ori data'!AW154 -> 0.023346788 | AD67: =10289*EXP(0.05828*(A67-17)) -> 31136.955 | AE67: =(AD67-AD66)/E66 -> 0.0010278358 | AF67: =Z67+AE67 -> 0.019276061 | AG67: ='opt vacc_sigma0.1'!L38+AE67 -> 0.019261633
A68: 37 | B68: 44509 | C68: 4808146 | D68: 6629870 | E68: =D68-C68-SUM(F68:K68) -> 1674747 | F68: 47794 | G68: 14934 | H68: 579 | I68: 90 | J68: 82381 | K68: 1199 | L68: =G68-G67 -> -593 | M68: =H68-H67 -> 23 | N68: =I68-I67 -> -1 | O68: =J68-J67 -> 1614 | P68: =MAX(0,MIN(G68,L68+$O68*G68/SUM($G68:$I68))) -> 951.79754 | Q68: =MAX(0,MIN(H68,M68+$O68*H68/SUM($G68:$I68))) -> 82.892713 | R68: =MAX(0,MIN(I68,N68+$O68*I68/SUM($G68:$I68))) -> 8.3097481 | S68: =MIN(1,P68/F67) -> 0.021398807 | T68: =MIN(1,Q68/G67) -> 0.0053386174 | U68: =MIN(1,R68/H67) -> 0.01494559 | V68: =AVERAGE(S65:S71) -> 0.018473009 | W68: =AVERAGE(T65:T71) -> 0.0023271287 | X68: =AVERAGE(U65:U71) -> 0.0097763266 | Y68: =(C68-C67)/E67 -> 0.019541838 | Z68: =AVERAGE(Y65:Y71) -> 0.017298506 | AA68: ='ori data'!AV155 -> 0.02506707 | AB68: ='ori data'!AW155 -> 0.022177587 | AD68: =10289*EXP(0.05828*(A68-17)) -> 33005.538 | AE68: =(AD68-AD67)/E67 -> 0.0010910913 | AF68: =Z68+AE68 -> 0.018389597 | AG68: ='opt vacc_sigma0.1'!L39+AE68 -> 0.0190478
A69: 38 | B69: 44510 | C69: 4837627 | D69: 6629870 | E69: =D69-C69-SUM(F69:K69) -> 1620480 | F69: 71601 | G69: 14472 | H69: 471 | I69: 84 | J69: 83922 | K69: 1213 | L69: =G69-G68 -> -462 | M69: =H69-H68 -> -108 | N69: =I69-I68 -> -6 | O69: =J69-J68 -> 1541 | P69: =MAX(0,MIN(G69,L69+$O69*G69/SUM($G69:$I69))) -> 1022.0854 | Q69: =MAX(0,MIN(H69,M69+$O69*H69/SUM($G69:$I69))) -> 0 | R69: =MAX(0,MIN(I69,N69+$O69*I69/SUM($G69:$I69))) -> 2.6140946 | S69: =MIN(1,P69/F68) -> 0.021385225 | T69: =MIN(1,Q69/G68) -> 0 | U69: =MIN(1,R69/H68) -> 0.0045148439 | V69: =AVERAGE(S66:S72) -> 0.018718401 | W69: =AVERAGE(T66:T72) -> 0.0011108803 | X69: =AVERAGE(U66:U72) -> 0.0053894758 | Y69: =(C69-C68)/E68 -> 0.017603256 | Z69: =AVERAGE(Y66:Y72) -> 0.016442358 | AA69: ='ori data'!AV156 -> 0.023744816 | AB69: ='ori data'!AW156 -> 0.021245511 | AD69: =10289*EXP(0.05828*(A69-17)) -> 34986.258 | AE69: =(AD69-AD68)/E68 -> 0.0011826982 | AF69: =Z69+AE69 -> 0.017625056 | AG69: ='opt vacc_sigma0.1'!L40+AE69 -> 0.018783507
A70: 39 | B70: 44511 | C70: 4865613 | D70: 6629870 | E70: =D70-C70-SUM(F70:K70) -> 1595701 | F70: 67105 | G70: 15135 | H70: 457 | I70: 79 | J70: 84563 | K70: 1217 | L70: =G70-G69 -> 663 | M70: =H70-H69 -> -14 | N70: =I70-I69 -> -5 | O70: =J70-J69 -> 641 | P70: =MAX(0,MIN(G70,L70+$O70*G70/SUM($G70:$I70))) -> 1282.0757 | Q70: =MAX(0,MIN(H70,M70+$O70*H70/SUM($G70:$I70))) -> 4.692936 | R70: =MAX(0,MIN(I70,N70+$O70*I70/SUM($G70:$I70))) -> 0 | S70: =MIN(1,P70/F69) -> 0.017905835 | T70: =MIN(1,Q70/G69) -> 0.00032427695 | U70: =MIN(1,R70/H69) -> 0 | V70: =AVERAGE(S67:S73) -> 0.018895862 | W70: =AVERAGE(T67:T73) -> 0.0011108803 | X70: =AVERAGE(U68:U72) -> 0.0066967255 | Y70: =(C70-C69)/E69 -> 0.017270192 | Z70: =AVERAGE(Y67:Y73) -> 0.015755833 | AA70: ='ori data'!AV157 -> 0.023315772 | AB70: ='ori data'!AW157 -> 0.020563574 | AC70: 55670 | AD70: =10289*EXP(0.05828*(A70-17)) -> 37085.845 | AE70: =(AD70-AD69)/E69 -> 0.0012956574 | AF70: =Z70+AE70 -> 0.017051491 | AG70: ='opt vacc_sigma0.1'!L41+AE70 -> 0.018560132
A71: 40 | B71: 44512 | C71: 4894786 | D71: 6629870 | E71: =D71-C71-SUM(F71:K71) -> 1564607 | F71: 67925 | G71: 15586 | H71: 426 | I71: 82 | J71: 85232 | K71: 1226 | L71: =G71-G70 -> 451 | M71: =H71-H70 -> -31 | N71: =I71-I70 -> 3 | O71: =J71-J70 -> 669 | P71: =MAX(0,MIN(G71,L71+$O71*G71/SUM($G71:$I71))) -> 1098.8833 | Q71: =MAX(0,MIN(H71,M71+$O71*H71/SUM($G71:$I71))) -> 0 | R71: =MAX(0,MIN(I71,N71+$O71*I71/SUM($G71:$I71))) -> 6.4085995 | S71: =MIN(1,P71/F70) -> 0.01637558 | T71: =MIN(1,Q71/G70) -> 0 | U71: =MIN(1,R71/H70) -> 0.014023194 | V71: =AVERAGE(S68:S74) -> 0.017971454 | W71: =AVERAGE(T68:T74) -> 0.00080898491 | X71: =AVERAGE(U69:U73) -> 0.0037076075 | Y71: =(C71-C70)/E70 -> 0.018282247 | Z71: =AVERAGE(Y68:Y74) -> 0.015390571 | AA71: ='ori data'!AV158 -> 0.023875005 | AB71: ='ori data'!AW158 -> 0.020162316 | AD71: =10289*EXP(0.05828*(A71-17)) -> 39311.432 | AE71: =(AD71-AD70)/E70 -> 0.0013947392 | AF71: =Z71+AE71 -> 0.01678531 | AG71: ='opt vacc_sigma0.1'!L42+AE71 -> 0.018247256
A72: 41 | B72: 44513 | C72: 4923992 | D72: 6629870 | E72: =D72-C72-SUM(F72:K72) -> 1541300 | F72: 60818 | G72: 16185 | H72: 405 | I72: 77 | J72: 85863 | K72: 1230 | L72: =G72-G71 -> 599 | M72: =H72-H71 -> -21 | N72: =I72-I71 -> -5 | O72: =J72-J71 -> 631 | P72: =MAX(0,MIN(G72,L72+$O72*G72/SUM($G72:$I72))) -> 1211.7518 | Q72: =MAX(0,MIN(H72,M72+$O72*H72/SUM($G72:$I72))) -> 0 | R72: =MAX(0,MIN(I72,N72+$O72*I72/SUM($G72:$I72))) -> 0 | S72: =MIN(1,P72/F71) -> 0.017839556 | T72: =MIN(1,Q72/G71) -> 0 | U72: =MIN(1,R72/H71) -> 0 | V72: =AVERAGE(S69:S75) -> 0.016563072 | W72: =AVERAGE(T69:T75) -> 0.0011512792 | X72: =AVERAGE(U70:U74) -> 0.0057223336 | Y72: =(C72-C71)/E71 -> 0.018666668 | Z72: =AVERAGE(Y69:Y75) -> 0.014755058 | AA72: ='ori data'!AV159 -> 0.024897814 | AB72: ='ori data'!AW159 -> 0.019425055 | AD72: =10289*EXP(0.05828*(A72-17)) -> 41670.58 | AE72: =(AD72-AD71)/E71 -> 0.0015078215 | AF72: =Z72+AE72 -> 0.016262879 | AG72: ='opt vacc_sigma0.1'!L43+AE72 -> 0.017940613
A73: 42 | B73: 44514 | C73: 4940981 | D73: 6629870 | E73: =D73-C73-SUM(F73:K73) -> 1520025 | F73: 64218 | G73: 16829 | H73: 394 | I73: 75 | J73: 86114 | K73: 1234 | L73: =G73-G72 -> 644 | M73: =H73-H72 -> -11 | N73: =I73-I72 -> -2 | O73: =J73-J72 -> 251 | P73: =MAX(0,MIN(G73,L73+$O73*G73/SUM($G73:$I73))) -> 888.19465 | Q73: =MAX(0,MIN(H73,M73+$O73*H73/SUM($G73:$I73))) -> 0 | R73: =MAX(0,MIN(I73,N73+$O73*I73/SUM($G73:$I73))) -> 0 | T73: =MIN(1,Q73/G72) -> 0 | U73: =MIN(1,R73/H72) -> 0 | V73: =AVERAGE(S70:S76) -> 0.016113811 | W73: =AVERAGE(T71:T75) -> 0.0015469355 | X73: =AVERAGE(U71:U75) -> 0.013757605 | Y73: =(C73-C72)/E72 -> 0.011022513 | Z73: =AVERAGE(Y70:Y76) -> 0.014131689 | AA73: ='ori data'!AV160 -> 0.013916218 | AB73: ='ori data'!AW160 -> 0.018681815 | AD73: =10289*EXP(0.05828*(A73-17)) -> 44171.305 | AE73: =(AD73-AD72)/E72 -> 0.0016224776 | AF73: =Z73+AE73 -> 0.015754167 | AG73: ='opt vacc_sigma0.1'!L44+AE73 -> 0.017579578
A74: 43 | B74: 44515 | C74: 4949109 | D74: 6629870 | E74: =D74-C74-SUM(F74:K74) -> 1527173 | F74: 48104 | G74: 17058 | H74: 378 | I74: 78 | J74: 86731 | K74: 1239 | L74: =G74-G73 -> 229 | M74: =H74-H73 -> -16 | N74: =I74-I73 -> 3 | O74: =J74-J73 -> 617 | P74: =MAX(0,MIN(G74,L74+$O74*G74/SUM($G74:$I74))) -> 829.93559 | Q74: =MAX(0,MIN(H74,M74+$O74*H74/SUM($G74:$I74))) -> 0 | R74: =MAX(0,MIN(I74,N74+$O74*I74/SUM($G74:$I74))) -> 5.7478589 | S74: =MIN(1,P74/F73) -> 0.012923722 | T74: =MIN(1,Q74/G73) -> 0 | U74: =MIN(1,R74/H73) -> 0.014588474 | V74: =AVERAGE(S71:S77) -> 0.01532784 | W74: =AVERAGE(T72:T76) -> 0.0015469355 | X74: =AVERAGE(U72:U76) -> 0.010952967 | Y74: =(C74-C73)/E73 -> 0.0053472805 | Z74: =AVERAGE(Y71:Y77) -> 0.013460634 | AA74: ='ori data'!AV161 -> 0.0063195198 | AB74: ='ori data'!AW161 -> 0.017894354 | AD74: =10289*EXP(0.05828*(A74-17)) -> 46822.102 | AE74: =(AD74-AD73)/E73 -> 0.0017439171 | AF74: =Z74+AE74 -> 0.015204551 | AG74: ='opt vacc_sigma0.1'!L45+AE74 -> 0.017257249
A75: 44 | B75: 44516 | C75: 4972159 | D75: 6629870 | E75: =D75-C75-SUM(F75:K75) -> 1497922 | F75: 53527 | G75: 13661 | H75: 394 | I75: 72 | J75: 90888 | K75: 1247 | L75: =G75-G74 -> -3397 | M75: =H75-H74 -> 16 | N75: =I75-I74 -> -6 | O75: =J75-J74 -> 4157 | P75: =MAX(0,MIN(G75,L75+$O75*G75/SUM($G75:$I75))) -> 622.8752 | Q75: =MAX(0,MIN(H75,M75+$O75*H75/SUM($G75:$I75))) -> 131.93813 | R75: =MAX(0,MIN(I75,N75+$O75*I75/SUM($G75:$I75))) -> 15.186664 | S75: =MIN(1,P75/F74) -> 0.012948512 | T75: =MIN(1,Q75/G74) -> 0.0077346777 | U75: =MIN(1,R75/H74) -> 0.040176359 | V75: =AVERAGE(S72:S78) -> 0.015443861 | W75: =AVERAGE(T73:T77) -> 0.0017593553 | X75: =AVERAGE(U73:U77) -> 0.017388282 | Y75: =(C75-C74)/E74 -> 0.015093247 | Z75: =AVERAGE(Y72:Y78) -> 0.012693866 | AA75: ='ori data'!AV162 -> 0.019906243 | AB75: ='ori data'!AW162 -> 0.017030905 | AD75: =10289*EXP(0.05828*(A75-17)) -> 49631.979 | AE75: =(AD75-AD74)/E74 -> 0.0018399203 | AF75: =Z75+AE75 -> 0.014533786 | AG75: ='opt vacc_sigma0.1'!L46+AE75 -> 0.016880189
A76: 45 | B76: 44517 | C76: 4991991 | D76: 6629870 | E76: =D76-C76-SUM(F76:K76) -> 1458624 | F76: 72010 | G76: 13841 | H76: 357 | I76: 58 | J76: 91733 | K76: 1256 | L76: =G76-G75 -> 180 | M76: =H76-H75 -> -37 | N76: =I76-I75 -> -14 | O76: =J76-J75 -> 845 | P76: =MAX(0,MIN(G76,L76+$O76*G76/SUM($G76:$I76))) -> 1000.4016 | Q76: =MAX(0,MIN(H76,M76+$O76*H76/SUM($G76:$I76))) -> 0 | R76: =MAX(0,MIN(I76,N76+$O76*I76/SUM($G76:$I76))) -> 0 | S76: =MIN(1,P76/F75) -> 0.018689663 | T76: =MIN(1,Q76/G75) -> 0 | U76: =MIN(1,R76/H75) -> 0 | V76: =AVERAGE(S73:S79) -> 0.014696697 | W76: =AVERAGE(T74:T78) -> 0.0021029661 | X76: =AVERAGE(U74:U78) -> 0.017388282 | Y76: =(C76-C75)/E75 -> 0.013239675 | Z76: =AVERAGE(Y73:Y79) -> 0.011594615 | AA76: ='ori data'!AV163 -> 0.018542133 | AB76: ='ori data'!AW163 -> 0.015510073 | AD76: =10289*EXP(0.05828*(A76-17)) -> 52610.481 | AE76: =(AD76-AD75)/E75 -> 0.0019884228 | AF76: =Z76+AE76 -> 0.013583038 | AG76: ='opt vacc_sigma0.1'!L47+AE76 -> 0.016522843
A77: 46 | B77: 44518 | C77: 5010330 | D77: 6629870 | E77: =D77-C77-SUM(F77:K77) -> 1439039 | F77: 72270 | G77: 13410 | H77: 337 | I77: 63 | J77: 93155 | K77: 1266 | L77: =G77-G76 -> -431 | M77: =H77-H76 -> -20 | N77: =I77-I76 -> 5 | O77: =J77-J76 -> 1422 | P77: =MAX(0,MIN(G77,L77+$O77*G77/SUM($G77:$I77))) -> 949.81245 | Q77: =MAX(0,MIN(H77,M77+$O77*H77/SUM($G77:$I77))) -> 14.700507 | R77: =MAX(0,MIN(I77,N77+$O77*I77/SUM($G77:$I77))) -> 11.487038 | S77: =MIN(1,P77/F76) -> 0.013190008 | T77: =MIN(1,Q77/G76) -> 0.0010620986 | U77: =MIN(1,R77/H76) -> 0.032176578 | V77: =AVERAGE(S74:S80) -> 0.015289623 | W77: =AVERAGE(T75:T79) -> 0.004453227 | X77: =AVERAGE(U75:U79) -> 0.032032613 | Y77: =(C77-C76)/E76 -> 0.012572808 | Z77: =AVERAGE(Y74:Y80) -> 0.011148707 | AA77: ='ori data'!AV164 -> 0.017803548 | AB77: ='ori data'!AW164 -> 0.015172986 | AC77: =(AC70+AC84)/2 -> 73411.5 | AD77: =10289*EXP(0.05828*(A77-17)) -> 55767.729 | AE77: =(AD77-AD76)/E76 -> 0.0021645383 | AF77: =Z77+AE77 -> 0.013313245 | AG77: ='opt vacc_sigma0.1'!L48+AE77 -> 0.016124401
A78: 47 | B78: 44519 | C78: 5028915 | D78: 6629870 | E78: =D78-C78-SUM(F78:K78) -> 1418440 | F78: 73020 | G78: 13422 | H78: 330 | I78: 57 | J78: 94412 | K78: 1274 | L78: =G78-G77 -> 12 | M78: =H78-H77 -> -7 | N78: =I78-I77 -> -6 | O78: =J78-J77 -> 1257 | P78: =MAX(0,MIN(G78,L78+$O78*G78/SUM($G78:$I78))) -> 1233.7723 | Q78: =MAX(0,MIN(H78,M78+$O78*H78/SUM($G78:$I78))) -> 23.039105 | R78: =MAX(0,MIN(I78,N78+$O78*I78/SUM($G78:$I78))) -> 0 | S78: =MIN(1,P78/F77) -> 0.017071708 | T78: =MIN(1,Q78/G77) -> 0.0017180541 | U78: =MIN(1,R78/H77) -> 0 | V78: =AVERAGE(S75:S81) -> 0.015724189 | W78: =AVERAGE(T76:T80) -> 0.0038792792 | X78: =AVERAGE(U76:U80) -> 0.029146052 | Y78: =(C78-C77)/E77 -> 0.012914869 | Z78: =AVERAGE(Y75:Y81) -> 0.010607764 | AA78: ='ori data'!AV165 -> 0.017830856 | AB78: ='ori data'!AW165 -> 0.014537909 | AD78: =10289*EXP(0.05828*(A78-17)) -> 59114.448 | AE78: =(AD78-AD77)/E77 -> 0.0023256628 | AF78: =Z78+AE78 -> 0.012933427 | AG78: ='opt vacc_sigma0.1'!L49+AE78 -> 0.015718177
A79: 48 | B79: 44520 | C79: 5044478 | D79: 6629870 | E79: =D79-C79-SUM(F79:K79) -> 1410680 | F79: 64050 | G79: 9210 | H79: 312 | I79: 55 | J79: 99806 | K79: 1279 | L79: =G79-G78 -> -4212 | M79: =H79-H78 -> -18 | N79: =I79-I78 -> -2 | O79: =J79-J78 -> 5394 | P79: =MAX(0,MIN(G79,L79+$O79*G79/SUM($G79:$I79))) -> 975.29665 | Q79: =MAX(0,MIN(H79,M79+$O79*H79/SUM($G79:$I79))) -> 157.72601 | R79: =MAX(0,MIN(I79,N79+$O79*I79/SUM($G79:$I79))) -> 28.977342 | S79: =MIN(1,P79/F78) -> 0.013356569 | T79: =MIN(1,Q79/G78) -> 0.011751305 | U79: =MIN(1,R79/H78) -> 0.087810126 | V79: =AVERAGE(S76:S82) -> 0.016091603 | W79: =AVERAGE(T77:T81) -> 0.0046489611 | X79: =AVERAGE(U77:U81) -> 0.029146052 | Y79: =(C79-C78)/E78 -> 0.010971913 | Z79: =AVERAGE(Y76:Y82) -> 0.010765196 | AA79: ='ori data'!AV166 -> 0.014251992 | AB79: ='ori data'!AW166 -> 0.015018987 | AD79: =10289*EXP(0.05828*(A79-17)) -> 62662.01 | AE79: =(AD79-AD78)/E78 -> 0.0025010307 | AF79: =Z79+AE79 -> 0.013266227 | AG79: ='opt vacc_sigma0.1'!L50+AE79 -> 0.015227494
A80: 49 | B80: 44521 | C80: 5055624 | D80: 6629870 | E80: =D80-C80-SUM(F80:K80) -> 1400670 | F80: 61650 | G80: 9255 | H80: 317 | I80: 56 | J80: 101015 | K80: 1283 | L80: =G80-G79 -> 45 | M80: =H80-H79 -> 5 | N80: =I80-I79 -> 1 | O80: =J80-J79 -> 1209 | P80: =MAX(0,MIN(G80,L80+$O80*G80/SUM($G80:$I80))) -> 1207.1619 | Q80: =MAX(0,MIN(H80,M80+$O80*H80/SUM($G80:$I80))) -> 44.806086 | R80: =MAX(0,MIN(I80,N80+$O80*I80/SUM($G80:$I80))) -> 8.03199 | S80: =MIN(1,P80/F79) -> 0.018847181 | T80: =MIN(1,Q80/G79) -> 0.0048649388 | U80: =MIN(1,R80/H79) -> 0.025743558 | V80: =AVERAGE(S77:S83) -> 0.016865457 | W80: =AVERAGE(T78:T82) -> 0.0047965631 | X80: =AVERAGE(U78:U82) -> 0.025423656 | Y80: =(C80-C79)/E79 -> 0.0079011541 | Z80: =AVERAGE(Y77:Y83) -> 0.010089855 | AA80: ='ori data'!AV167 -> 0.011556612 | AB80: ='ori data'!AW167 -> 0.01424244 | AD80: =10289*EXP(0.05828*(A80-17)) -> 66422.467 | AE80: =(AD80-AD79)/E79 -> 0.0026657054 | AF80: =Z80+AE80 -> 0.012755561 | AG80: ='opt vacc_sigma0.1'!L51+AE80 -> 0.014731526
A81: 50 | B81: 44522 | C81: 5057810 | D81: 6629870 | E81: =D81-C81-SUM(F81:K81) -> 1409300 | F81: 49818 | G81: 9176 | H81: 316 | I81: 44 | J81: 102120 | K81: 1286 | L81: =G81-G80 -> -79 | M81: =H81-H80 -> -1 | N81: =I81-I80 -> -12 | O81: =J81-J80 -> 1105 | P81: =MAX(0,MIN(G81,L81+$O81*G81/SUM($G81:$I81))) -> 984.2844 | Q81: =MAX(0,MIN(H81,M81+$O81*H81/SUM($G81:$I81))) -> 35.61703 | R81: =MAX(0,MIN(I81,N81+$O81*I81/SUM($G81:$I81))) -> 0 | S81: =MIN(1,P81/F80) -> 0.015965684 | T81: =MIN(1,Q81/G80) -> 0.0038484095 | U81: =MIN(1,R81/H80) -> 0 | V81: =AVERAGE(S78:S84) -> 0.017324167 | W81: =AVERAGE(T79:T83) -> 0.0045668593 | X81: =AVERAGE(U79:U83) -> 0.033624505 | Y81: =(C81-C80)/E80 -> 0.0015606817 | Z81: =AVERAGE(Y78:Y84) -> 0.009677083 | AA81: ='ori data'!AV168 -> 0.00187398 | AB81: ='ori data'!AW168 -> 0.013790771 | AD81: =10289*EXP(0.05828*(A81-17)) -> 70408.596 | AE81: =(AD81-AD80)/E80 -> 0.002845873 | AF81: =Z81+AE81 -> 0.012522956 | AG81: ='opt vacc_sigma0.1'!L52+AE81 -> 0.014195591
A82: 51 | B82: 44523 | C82: 5080634 | D82: 6629870 | E82: =D82-C82-SUM(F82:K82) -> 1387054 | F82: 48427 | G82: 9066 | H82: 303 | I82: 44 | J82: 103037 | K82: 1305 | L82: =G82-G81 -> -110 | M82: =H82-H81 -> -13 | N82: =I82-I81 -> 0 | O82: =J82-J81 -> 917 | P82: =MAX(0,MIN(G82,L82+$O82*G82/SUM($G82:$I82))) -> 773.19579 | Q82: =MAX(0,MIN(H82,M82+$O82*H82/SUM($G82:$I82))) -> 16.517795 | R82: =MAX(0,MIN(I82,N82+$O82*I82/SUM($G82:$I82))) -> 4.2864124 | S82: =MIN(1,P82/F81) -> 0.01552041 | T82: =MIN(1,Q82/G81) -> 0.0018001084 | U82: =MIN(1,R82/H81) -> 0.013564596 | V82: =AVERAGE(S79:S85) -> 0.017403232 | W82: =AVERAGE(T80:T84) -> 0.0032410686 | X82: =AVERAGE(U80:U84) -> 0.01606248 | Y82: =(C82-C81)/E81 -> 0.016195274 | Z82: =AVERAGE(Y79:Y85) -> 0.009275441 | AA82: ='ori data'!AV169 -> 0.023273787 | AB82: ='ori data'!AW169 -> 0.013459857 | AD82: =10289*EXP(0.05828*(A82-17)) -> 74633.94 | AE82: =(AD82-AD81)/E81 -> 0.0029981861 | AF82: =Z82+AE82 -> 0.012273627 | AG82: ='opt vacc_sigma0.1'!L53+AE82 -> 0.013575676
A83: 52 | B83: 44524 | C83: 5092441 | D83: 6629870 | E83: =D83-C83-SUM(F83:K83) -> 1349732 | F83: 72754 | G83: 9431 | H83: 284 | I83: 52 | J83: 103868 | K83: 1308 | L83: =G83-G82 -> 365 | M83: =H83-H82 -> -19 | N83: =I83-I82 -> 8 | O83: =J83-J82 -> 831 | P83: =MAX(0,MIN(G83,L83+$O83*G83/SUM($G83:$I83))) -> 1167.4123 | Q83: =MAX(0,MIN(H83,M83+$O83*H83/SUM($G83:$I83))) -> 5.1634074 | R83: =MAX(0,MIN(I83,N83+$O83*I83/SUM($G83:$I83))) -> 12.424286 | S83: =MIN(1,P83/F82) -> 0.024106641 | T83: =MIN(1,Q83/G82) -> 0.00056953534 | U83: =MIN(1,R83/H82) -> 0.041004244 | V83: =AVERAGE(S80:S86) -> 0.017859258 | W83: =AVERAGE(T81:T85) -> 0.0026487408 | X83: =AVERAGE(U81:U85) -> 0.011633763 | Y83: =(C83-C82)/E82 -> 0.0085122858 | Z83: =AVERAGE(Y80:Y86) -> 0.0091487939 | AA83: ='ori data'!AV170 -> 0.013106306 | AB83: ='ori data'!AW170 -> 0.013617774 | AD83: =10289*EXP(0.05828*(A83-17)) -> 79112.854 | AE83: =(AD83-AD82)/E82 -> 0.003229084 | AF83: =Z83+AE83 -> 0.012377878 | AG83: ='opt vacc_sigma0.1'!L54+AE83 -> 0.013008761
A84: 53 | B84: 44525 | C84: 5105511 | D84: 6629870 | E84: =D84-C84-SUM(F84:K84) -> 1332822 | F84: 75348 | G84: 9911 | H84: 310 | I84: 48 | J84: 104607 | K84: 1313 | L84: =G84-G83 -> 480 | M84: =H84-H83 -> 26 | N84: =I84-I83 -> -4 | O84: =J84-J83 -> 739 | P84: =MAX(0,MIN(G84,L84+$O84*G84/SUM($G84:$I84))) -> 1193.2368 | Q84: =MAX(0,MIN(H84,M84+$O84*H84/SUM($G84:$I84))) -> 48.308891 | R84: =MAX(0,MIN(I84,N84+$O84*I84/SUM($G84:$I84))) -> 0 | S84: =MIN(1,P84/F83) -> 0.016400979 | T84: =MIN(1,Q84/G83) -> 0.0051223508 | U84: =MIN(1,R84/H83) -> 0 | V84: =AVERAGE(S81:S87) -> 0.01771086 | W84: =AVERAGE(T82:T86) -> 0.0021413376 | X84: =AVERAGE(U82:U86) -> 0.011633763 | Y84: =(C84-C83)/E83 -> 0.0096834038 | Z84: =AVERAGE(Y81:Y87) -> 0.0086375322 | AA84: ='ori data'!AV171 -> 0.014641865 | AB84: ='ori data'!AW171 -> 0.012852374 | AC84: 91153 | AD84: =10289*EXP(0.05828*(A84-17)) -> 83860.555 | AE84: =(AD84-AD83)/E83 -> 0.0035175141 | AF84: =Z84+AE84 -> 0.012155046 | AG84: ='opt vacc_sigma0.1'!L55+AE84 -> 0.012431613
A85: 54 | B85: 44526 | C85: 5118977 | D85: 6629870 | E85: =D85-C85-SUM(F85:K85) -> 1319930 | F85: 73419 | G85: 10526 | H85: 308 | I85: 46 | J85: 105344 | K85: 1320 | L85: =G85-G84 -> 615 | M85: =H85-H84 -> -2 | N85: =I85-I84 -> -2 | O85: =J85-J84 -> 737 | P85: =MAX(0,MIN(G85,L85+$O85*G85/SUM($G85:$I85))) -> 1328.0204 | Q85: =MAX(0,MIN(H85,M85+$O85*H85/SUM($G85:$I85))) -> 18.863603 | R85: =MAX(0,MIN(I85,N85+$O85*I85/SUM($G85:$I85))) -> 1.1159926 | S85: =MIN(1,P85/F84) -> 0.017625158 | T85: =MIN(1,Q85/G84) -> 0.0019032997 | U85: =MIN(1,R85/H84) -> 0.0035999763 | V85: =AVERAGE(S82:S88) -> 0.018002737 | W85: =AVERAGE(T83:T87) -> 0.0019278284 | X85: =AVERAGE(U83:U87) -> 0.012753707 | Y85: =(C85-C84)/E84 -> 0.010103375 | Z85: =AVERAGE(Y82:Y88) -> 0.0086731908 | AA85: ='ori data'!AV172 -> 0.015514459 | AB85: ='ori data'!AW172 -> 0.012961858 | AD85: =10289*EXP(0.05828*(A85-17)) -> 88893.175 | AE85: =(AD85-AD84)/E84 -> 0.0037759125 | AF85: =Z85+AE85 -> 0.012449103 | AG85: ='opt vacc_sigma0.1'!L56+AE85 -> 0.011809221
A86: 55 | B86: 44527 | C86: 5132289 | D86: 6629870 | E86: =D86-C86-SUM(F86:K86) -> 1321512 | F86: 57292 | G86: 10909 | H86: 299 | I86: 42 | J86: 106202 | K86: 1325 | L86: =G86-G85 -> 383 | M86: =H86-H85 -> -9 | N86: =I86-I85 -> -4 | O86: =J86-J85 -> 858 | P86: =MAX(0,MIN(G86,L86+$O86*G86/SUM($G86:$I86))) -> 1214.9931 | Q86: =MAX(0,MIN(H86,M86+$O86*H86/SUM($G86:$I86))) -> 13.803733 | R86: =MAX(0,MIN(I86,N86+$O86*I86/SUM($G86:$I86))) -> 0 | S86: =MIN(1,P86/F85) -> 0.016548755 | T86: =MIN(1,Q86/G85) -> 0.001311394 | U86: =MIN(1,R86/H85) -> 0 | V86: =AVERAGE(S83:S89) -> 0.01837114 | W86: =AVERAGE(T84:T88) -> 0.0025151867 | X86: =AVERAGE(U84:U88) -> 0.0075449866 | Y86: =(C86-C85)/E85 -> 0.010085383 | Z86: =AVERAGE(Y83:Y89) -> 0.0074121788 | AA86: ='ori data'!AV173 -> 0.015357409 | AB86: ='ori data'!AW173 -> 0.011438791 | AD86: =10289*EXP(0.05828*(A86-17)) -> 94227.81 | AE86: =(AD86-AD85)/E85 -> 0.004041605 | AF86: =Z86+AE86 -> 0.011453784 | AG86: ='opt vacc_sigma0.1'!L57+AE86 -> 0.011322226
A87: 56 | B87: 44528 | C87: 5138001 | D87: 6629870 | E87: =D87-C87-SUM(F87:K87) -> 1319124 | F87: 52930 | G87: 10997 | H87: 283 | I87: 44 | J87: 107162 | K87: 1329 | L87: =G87-G86 -> 88 | M87: =H87-H86 -> -16 | N87: =I87-I86 -> 2 | O87: =J87-J86 -> 960 | P87: =MAX(0,MIN(G87,L87+$O87*G87/SUM($G87:$I87))) -> 1020.2783 | Q87: =MAX(0,MIN(H87,M87+$O87*H87/SUM($G87:$I87))) -> 7.9915224 | R87: =MAX(0,MIN(I87,N87+$O87*I87/SUM($G87:$I87))) -> 5.7301307 | S87: =MIN(1,P87/F86) -> 0.017808391 | T87: =MIN(1,Q87/G86) -> 0.00073256233 | U87: =MIN(1,R87/H86) -> 0.019164317 | V87: =AVERAGE(S84:S90) -> 0.018504777 | W87: =AVERAGE(T85:T89) -> 0.0020556167 | X87: =AVERAGE(U85:U89) -> 0.0075449866 | Y87: =(C87-C86)/E86 -> 0.0043223217 | Z87: =AVERAGE(Y84:Y90) -> 0.0069675897 | AA87: ='ori data'!AV174 -> 0.0061988107 | AB87: ='ori data'!AW174 -> 0.011128396 | AD87: =10289*EXP(0.05828*(A87-17)) -> 99882.587 | AE87: =(AD87-AD86)/E86 -> 0.0042790202 | AF87: =Z87+AE87 -> 0.01124661 | AG87: ='opt vacc_sigma0.1'!L58+AE87 -> 0.010876223
A88: 57 | B88: 44529 | C88: 5140389 | D88: 6629870 | E88: =D88-C88-SUM(F88:K88) -> 1320270 | F88: 48397 | G88: 11149 | H88: 300 | I88: 45 | J88: 107988 | K88: 1332 | L88: =G88-G87 -> 152 | M88: =H88-H87 -> 17 | N88: =I88-I87 -> 1 | O88: =J88-J87 -> 826 | P88: =MAX(0,MIN(G88,L88+$O88*G88/SUM($G88:$I88))) -> 953.20706 | Q88: =MAX(0,MIN(H88,M88+$O88*H88/SUM($G88:$I88))) -> 38.559074 | R88: =MAX(0,MIN(I88,N88+$O88*I88/SUM($G88:$I88))) -> 4.2338611 | S88: =MIN(1,P88/F87) -> 0.018008824 | T88: =MIN(1,Q88/G87) -> 0.0035063267 | U88: =MIN(1,R88/H87) -> 0.01496064 | V88: =AVERAGE(S85:S91) -> 0.018847047 | W88: =AVERAGE(T86:T90) -> 0.0018450869 | X88: =AVERAGE(U86:U90) -> 0.009589833 | Y88: =(C88-C87)/E87 -> 0.0018102923 | Z88: =AVERAGE(Y85:Y91) -> 0.0063572619 | AA88: ='ori data'!AV175 -> 0.002640369 | AB88: ='ori data'!AW175 -> 0.010702271 | AD88: =10289*EXP(0.05828*(A88-17)) -> 105876.72 | AE88: =(AD88-AD87)/E87 -> 0.0045440228 | AF88: =Z88+AE88 -> 0.010901285 | AG88: ='opt vacc_sigma0.1'!L59+AE88 -> 0.010566851
A89: 58 | B89: 44530 | C89: 5150117 | D89: 6629870 | E89: =D89-C89-SUM(F89:K89) -> 1312368 | F89: 45658 | G89: 11064 | H89: 305 | I89: 41 | J89: 108979 | K89: 1338 | L89: =G89-G88 -> -85 | M89: =H89-H88 -> 5 | N89: =I89-I88 -> -4 | O89: =J89-J88 -> 991 | P89: =MAX(0,MIN(G89,L89+$O89*G89/SUM($G89:$I89))) -> 875.94864 | Q89: =MAX(0,MIN(H89,M89+$O89*H89/SUM($G89:$I89))) -> 31.490359 | R89: =MAX(0,MIN(I89,N89+$O89*I89/SUM($G89:$I89))) -> 0 | S89: =MIN(1,P89/F88) -> 0.018099234 | T89: =MIN(1,Q89/G88) -> 0.0028245008 | U89: =MIN(1,R89/H88) -> 0 | V89: =AVERAGE(S86:S92) -> 0.018635852 | W89: =AVERAGE(T87:T91) -> 0.0016390429 | X89: =AVERAGE(U87:U91) -> 0.0096103417 | Y89: =(C89-C88)/E88 -> 0.0073681898 | Z89: =AVERAGE(Y86:Y92) -> 0.0056843332 | AA89: ='ori data'!AV176 -> 0.012612316 | AB89: ='ori data'!AW176 -> 0.010213966 | AD89: =10289*EXP(0.05828*(A89-17)) -> 112230.56 | AE89: =(AD89-AD88)/E88 -> 0.0048125367 | AF89: =Z89+AE89 -> 0.01049687 | AG89: ='opt vacc_sigma0.1'!L60+AE89 -> 0.010484696
A90: 59 | B90: 44531 | C90: 5157204 | D90: 6629870 | E90: =D90-C90-SUM(F90:K90) -> 1275524 | F90: 74252 | G90: 11609 | H90: 299 | I90: 43 | J90: 109595 | K90: 1344 | L90: =G90-G89 -> 545 | M90: =H90-H89 -> -6 | N90: =I90-I89 -> 2 | O90: =J90-J89 -> 616 | P90: =MAX(0,MIN(G90,L90+$O90*G90/SUM($G90:$I90))) -> 1143.372 | Q90: =MAX(0,MIN(H90,M90+$O90*H90/SUM($G90:$I90))) -> 9.4115974 | R90: =MAX(0,MIN(I90,N90+$O90*I90/SUM($G90:$I90))) -> 4.2163836 | S90: =MIN(1,P90/F89) -> 0.025042096 | T90: =MIN(1,Q90/G89) -> 0.00085065052 | U90: =MIN(1,R90/H89) -> 0.013824208 | V90: =AVERAGE(S87:S93) -> 0.019306791 | W90: =AVERAGE(T88:T92) -> 0.0018625431 | X90: =AVERAGE(U88:U92) -> 0.0094316929 | Y90: =(C90-C89)/E89 -> 0.0054001621 | Z90: =AVERAGE(Y87:Y93) -> 0.0049889912 | AA90: ='ori data'!AV177 -> 0.010933546 | AB90: ='ori data'!AW177 -> 0.0097823799 | AD90: =10289*EXP(0.05828*(A90-17)) -> 118965.72 | AE90: =(AD90-AD89)/E89 -> 0.0051320616 | AF90: =Z90+AE90 -> 0.010121053 | AG90: ='opt vacc_sigma0.1'!L61+AE90 -> 0.010504103
A91: 60 | B91: 44532 | C91: 5164106 | D91: 6629870 | E91: =D91-C91-SUM(F91:K91) -> 1271122 | F91: 70343 | G91: 12391 | H91: 288 | I91: 41 | J91: 110225 | K91: 1354 | L91: =G91-G90 -> 782 | M91: =H91-H90 -> -11 | N91: =I91-I90 -> -2 | O91: =J91-J90 -> 630 | P91: =MAX(0,MIN(G91,L91+$O91*G91/SUM($G91:$I91))) -> 1395.7052 | Q91: =MAX(0,MIN(H91,M91+$O91*H91/SUM($G91:$I91))) -> 3.2641509 | R91: =MAX(0,MIN(I91,N91+$O91*I91/SUM($G91:$I91))) -> 0.030660377 | S91: =MIN(1,P91/F90) -> 0.01879687 | T91: =MIN(1,Q91/G90) -> 0.00028117417 | U91: =MIN(1,R91/H90) -> 0.00010254307 | V91: =AVERAGE(S88:S94) -> 0.019556525 | W91: =AVERAGE(T89:T93) -> 0.0011612778 | X91: =AVERAGE(U89:U93) -> 0.006856234 | Y91: =(C91-C90)/E90 -> 0.0054111095 | Z91: =AVERAGE(Y88:Y94) -> 0.0047616186 | AA91: ='ori data'!AV178 -> 0.011658991 | AB91: ='ori data'!AW178 -> 0.0097104425 | AC91: 115861 | AD91: =10289*EXP(0.05828*(A91-17)) -> 126105.06 | AE91: =(AD91-AD90)/E90 -> 0.0055971834 | AF91: =Z91+AE91 -> 0.010358802 | AG91: ='opt vacc_sigma0.1'!L62+AE91 -> 0.010798266
A92: 61 | B92: 44533 | C92: 5170961 | D92: 6629870 | E92: =D92-C92-SUM(F92:K92) -> 1270221 | F92: 63214 | G92: 12573 | H92: 289 | I92: 43 | J92: 111204 | K92: 1365 | L92: =G92-G91 -> 182 | M92: =H92-H91 -> 1 | N92: =I92-I91 -> 2 | O92: =J92-J91 -> 979 | P92: =MAX(0,MIN(G92,L92+$O92*G92/SUM($G92:$I92))) -> 1135.8138 | Q92: =MAX(0,MIN(H92,M92+$O92*H92/SUM($G92:$I92))) -> 22.924138 | R92: =MAX(0,MIN(I92,N92+$O92*I92/SUM($G92:$I92))) -> 5.262069 | S92: =MIN(1,P92/F91) -> 0.016146792 | T92: =MIN(1,Q92/G91) -> 0.0018500636 | U92: =MIN(1,R92/H91) -> 0.018271073 | V92: =AVERAGE(S89:S95) -> 0.019199156 | W92: =AVERAGE(T90:T94) -> 0.00072791715 | X92: =AVERAGE(U90:U94) -> 0.006856234 | Y92: =(C92-C91)/E91 -> 0.0053928734 | Z92: =AVERAGE(Y89:Y95) -> 0.0046680933 | AD92: =10289*EXP(0.05828*(A92-17)) -> 133672.85 | AE92: =(AD92-AD91)/E91 -> 0.005953627 | AF92: =Z92+AE92 -> 0.01062172
A93: 62 | B93: 44534 | C93: 5177589 | D93: 6629870 | E93: =D93-C93-SUM(F93:K93) -> 1257913 | F93: 67545 | G93: 14043 | H93: 288 | I93: 44 | J93: 111074 | K93: 1374 | L93: =G93-G92 -> 1470 | M93: =H93-H92 -> -1 | N93: =I93-I92 -> 1 | O93: =J93-J92 -> -130 | P93: =MAX(0,MIN(G93,L93+$O93*G93/SUM($G93:$I93))) -> 1343.0024 | Q93: =MAX(0,MIN(H93,M93+$O93*H93/SUM($G93:$I93))) -> 0 | R93: =MAX(0,MIN(I93,N93+$O93*I93/SUM($G93:$I93))) -> 0.60208696 | S93: =MIN(1,P93/F92) -> 0.021245332 | T93: =MIN(1,Q93/G92) -> 0 | U93: =MIN(1,R93/H92) -> 0.0020833459 | V93: =AVERAGE(S90:S96) -> 0.019324346 | W93: =AVERAGE(T91:T95) -> 0.0006998801 | X93: =AVERAGE(U91:U95) -> 0.0074085001 | Y93: =(C93-C92)/E92 -> 0.0052179896 | Z93: =AVERAGE(Y90:Y96) -> 0.0042714876 | AD93: =10289*EXP(0.05828*(A93-17)) -> 141694.79 | AE93: =(AD93-AD92)/E92 -> 0.0063153911 | AF93: =Z93+AE93 -> 0.010586879
A94: 63 | B94: 44535 | C94: 5181024 | D94: 6629870 | E94: =D94-C94-SUM(F94:K94) -> 1255608 | F94: 65449 | G94: 15086 | H94: 299 | I94: 40 | J94: 110983 | K94: 1381 | L94: =G94-G93 -> 1043 | M94: =H94-H93 -> 11 | N94: =I94-I93 -> -4 | O94: =J94-J93 -> -91 | P94: =MAX(0,MIN(G94,L94+$O94*G94/SUM($G94:$I94))) -> 953.99994 | Q94: =MAX(0,MIN(H94,M94+$O94*H94/SUM($G94:$I94))) -> 9.2360454 | R94: =MAX(0,MIN(I94,N94+$O94*I94/SUM($G94:$I94))) -> 0 | T94: =MIN(1,Q94/G93) -> 0.00065769746 | U94: =MIN(1,R94/H93) -> 0 | V94: =AVERAGE(S91:S97) -> 0.018936082 | W94: =AVERAGE(T92:T96) -> 0.001788128 | X94: =AVERAGE(U92:U96) -> 0.019434564 | Y94: =(C94-C93)/E93 -> 0.0027307135 | Z94: =AVERAGE(Y91:Y97) -> 0.0040801708 | AD94: =10289*EXP(0.05828*(A94-17)) -> 150198.14 | AE94: =(AD94-AD93)/E93 -> 0.0067598898 | AF94: =Z94+AE94 -> 0.010840061
A95: 64 | B95: 44536 | C95: 5182475 | D95: 6629870 | E95: =D95-C95-SUM(F95:K95) -> 1262209 | F95: 56337 | G95: 16139 | H95: 310 | I95: 45 | J95: 110968 | K95: 1387 | L95: =G95-G94 -> 1053 | M95: =H95-H94 -> 11 | N95: =I95-I94 -> 5 | O95: =J95-J94 -> -15 | P95: =MAX(0,MIN(G95,L95+$O95*G95/SUM($G95:$I95))) -> 1038.3228 | Q95: =MAX(0,MIN(H95,M95+$O95*H95/SUM($G95:$I95))) -> 10.718079 | R95: =MAX(0,MIN(I95,N95+$O95*I95/SUM($G95:$I95))) -> 4.959076 | S95: =MIN(1,P95/F94) -> 0.01586461 | T95: =MIN(1,Q95/G94) -> 0.00071046529 | U95: =MIN(1,R95/H94) -> 0.016585539 | V95: =AVERAGE(S92:S98) -> 0.018218601 | W95: =AVERAGE(T93:T97) -> 0.0027814892 | X95: =AVERAGE(U93:U97) -> 0.027604295 | Y95: =(C95-C94)/E94 -> 0.0011556154 | Z95: =AVERAGE(Y92:Y98) -> 0.0039103238 | AD95: =10289*EXP(0.05828*(A95-17)) -> 159211.8 | AE95: =(AD95-AD94)/E94 -> 0.0071787169 | AF95: =Z95+AE95 -> 0.011089041
A96: 65 | B96: 44537 | C96: 5188271 | D96: 6629870 | E96: =D96-C96-SUM(F96:K96) -> 1259313 | F96: 52257 | G96: 12697 | H96: 297 | I96: 47 | J96: 115594 | K96: 1394 | L96: =G96-G95 -> -3442 | M96: =H96-H95 -> -13 | N96: =I96-I95 -> 2 | O96: =J96-J95 -> 4626 | P96: =MAX(0,MIN(G96,L96+$O96*G96/SUM($G96:$I96))) -> 1061.9738 | Q96: =MAX(0,MIN(H96,M96+$O96*H96/SUM($G96:$I96))) -> 92.354037 | R96: =MAX(0,MIN(I96,N96+$O96*I96/SUM($G96:$I96))) -> 18.672188 | S96: =MIN(1,P96/F95) -> 0.018850379 | T96: =MIN(1,Q96/G95) -> 0.0057224139 | U96: =MIN(1,R96/H95) -> 0.060232864 | V96: =AVERAGE(S93:S99) -> 0.018197725 | W96: =AVERAGE(T94:T98) -> 0.0036738106 | X96: =AVERAGE(U94:U98) -> 0.03187224 | Y96: =(C96-C95)/E95 -> 0.0045919495 | Z96: =AVERAGE(Y93:Y99) -> 0.0037172349 | AD96: =10289*EXP(0.05828*(A96-17)) -> 168766.38 | AE96: =(AD96-AD95)/E95 -> 0.0075697287 | AF96: =Z96+AE96 -> 0.011286964
A97: 66 | B97: 44538 | C97: 5193385 | D97: 6629870 | E97: =D97-C97-SUM(F97:K97) -> 1225670 | F97: 79490 | G97: 10968 | H97: 303 | I97: 51 | J97: 118604 | K97: 1399 | L97: =G97-G96 -> -1729 | M97: =H97-H96 -> 6 | N97: =I97-I96 -> 4 | O97: =J97-J96 -> 3010 | P97: =MAX(0,MIN(G97,L97+$O97*G97/SUM($G97:$I97))) -> 1186.8877 | Q97: =MAX(0,MIN(H97,M97+$O97*H97/SUM($G97:$I97))) -> 86.553789 | R97: =MAX(0,MIN(I97,N97+$O97*I97/SUM($G97:$I97))) -> 17.558559 | S97: =MIN(1,P97/F96) -> 0.02271251 | T97: =MIN(1,Q97/G96) -> 0.0068168693 | U97: =MIN(1,R97/H96) -> 0.059119726 | V97: =AVERAGE(S94:S100) -> 0.017446678 | W97: =AVERAGE(T95:T99) -> 0.0041629908 | X97: =AVERAGE(U95:U99) -> 0.042000011 | Y97: =(C97-C96)/E96 -> 0.0040609443 | Z97: =AVERAGE(Y94:Y100) -> 0.0036141709 | AD97: =10289*EXP(0.05828*(A97-17)) -> 178894.34 | AE97: =(AD97-AD96)/E96 -> 0.0080424539 | AF97: =Z97+AE97 -> 0.011656625
A98: 67 | B98: 44539 | C98: 5198560 | D98: 6629870 | E98: =D98-C98-SUM(F98:K98) -> 1227590 | F98: 71178 | G98: 10848 | H98: 315 | I98: 52 | J98: 119919 | K98: 1408 | L98: =G98-G97 -> -120 | M98: =H98-H97 -> 12 | N98: =I98-I97 -> 1 | O98: =J98-J97 -> 1315 | P98: =MAX(0,MIN(G98,L98+$O98*G98/SUM($G98:$I98))) -> 1151.9679 | Q98: =MAX(0,MIN(H98,M98+$O98*H98/SUM($G98:$I98))) -> 48.934909 | R98: =MAX(0,MIN(I98,N98+$O98*I98/SUM($G98:$I98))) -> 7.0971913 | S98: =MIN(1,P98/F97) -> 0.014491985 | T98: =MIN(1,Q98/G97) -> 0.0044616073 | U98: =MIN(1,R98/H97) -> 0.023423073 | V98: =AVERAGE(S95:S101) -> 0.016704458 | W98: =AVERAGE(T96:T100) -> 0.0046534713 | X98: =AVERAGE(U96:U100) -> 0.046389483 | Y98: =(C98-C97)/E97 -> 0.0042221805 | Z98: =AVERAGE(Y95:Y101) -> 0.0035159508 | AC98: 152220 | AD98: =10289*EXP(0.05828*(A98-17)) -> 189630.11 | AE98: =(AD98-AD97)/E97 -> 0.0087590982 | AF98: =Z98+AE98 -> 0.012275049
A99: 68 | B99: 44540 | C99: 5203521 | D99: 6629870 | E99: =D99-C99-SUM(F99:K99) -> 1225831 | F99: 66784 | G99: 10762 | H99: 313 | I99: 61 | J99: 121188 | K99: 1410 | L99: =G99-G98 -> -86 | M99: =H99-H98 -> -2 | N99: =I99-I98 -> 9 | O99: =J99-J98 -> 1269 | P99: =MAX(0,MIN(G99,L99+$O99*G99/SUM($G99:$I99))) -> 1140.3809 | Q99: =MAX(0,MIN(H99,M99+$O99*H99/SUM($G99:$I99))) -> 33.667834 | R99: =MAX(0,MIN(I99,N99+$O99*I99/SUM($G99:$I99))) -> 15.951239 | S99: =MIN(1,P99/F98) -> 0.016021537 | T99: =MIN(1,Q99/G98) -> 0.0031035983 | U99: =MIN(1,R99/H98) -> 0.050638855 | V99: =AVERAGE(S96:S102) -> 0.017017315 | W99: =AVERAGE(T97:T101) -> 0.0038205854 | X99: =AVERAGE(U97:U101) -> 0.042525814 | Y99: =(C99-C98)/E98 -> 0.0040412516 | Z99: =AVERAGE(Y96:Y102) -> 0.003455733 | AD99: =10289*EXP(0.05828*(A99-17)) -> 201010.14 | AE99: =(AD99-AD98)/E98 -> 0.0092702253 | AF99: =Z99+AE99 -> 0.012725958
A100: 69 | B100: 44541 | C100: 5209033 | D100: 6629870 | E100: =D100-C100-SUM(F100:K100) -> 1203031 | F100: 82895 | G100: 11057 | H100: 323 | I100: 68 | J100: 122040 | K100: 1423 | L100: =G100-G99 -> 295 | M100: =H100-H99 -> 10 | N100: =I100-I99 -> 7 | O100: =J100-J99 -> 852 | P100: =MAX(0,MIN(G100,L100+$O100*G100/SUM($G100:$I100))) -> 1117.9004 | Q100: =MAX(0,MIN(H100,M100+$O100*H100/SUM($G100:$I100))) -> 34.038784 | R100: =MAX(0,MIN(I100,N100+$O100*I100/SUM($G100:$I100))) -> 12.060797 | S100: =MIN(1,P100/F99) -> 0.016739046 | T100: =MIN(1,Q100/G99) -> 0.0031628679 | U100: =MIN(1,R100/H99) -> 0.038532897 | V100: =AVERAGE(S97:S103) -> 0.017086578 | W100: =AVERAGE(T98:T102) -> 0.0032031503 | X100: =AVERAGE(U98:U102) -> 0.036947851 | Y100: =(C100-C99)/E99 -> 0.0044965415 | Z100: =AVERAGE(Y97:Y103) -> 0.0033762351 | AD100: =10289*EXP(0.05828*(A100-17)) -> 213073.11 | AE100: =(AD100-AD99)/E99 -> 0.0098406484 | AF100: =Z100+AE100 -> 0.013216883
A101: 70 | B101: 44542 | C101: 5211491 | D101: 6629870 | E101: =D101-C101-SUM(F101:K101) -> 1215108 | F101: 67312 | G101: 11000 | H101: 310 | I101: 74 | J101: 123150 | K101: 1425 | L101: =G101-G100 -> -57 | M101: =H101-H100 -> -13 | N101: =I101-I100 -> 6 | O101: =J101-J100 -> 1110 | P101: =MAX(0,MIN(G101,L101+$O101*G101/SUM($G101:$I101))) -> 1015.558 | Q101: =MAX(0,MIN(H101,M101+$O101*H101/SUM($G101:$I101))) -> 17.226634 | R101: =MAX(0,MIN(I101,N101+$O101*I101/SUM($G101:$I101))) -> 13.21539 | S101: =MIN(1,P101/F100) -> 0.012251137 | T101: =MIN(1,Q101/G100) -> 0.0015579844 | U101: =MIN(1,R101/H100) -> 0.04091452 | V101: =AVERAGE(S98:S104) -> 0.017373778 | W101: =AVERAGE(T99:T103) -> 0.0040061182 | X101: =AVERAGE(U99:U103) -> 0.041506969 | Y101: =(C101-C100)/E100 -> 0.0020431726 | Z101: =AVERAGE(Y98:Y104) -> 0.0033169683 | AD101: =10289*EXP(0.05828*(A101-17)) -> 225860.01 | AE101: =(AD101-AD100)/E100 -> 0.010628897 | AF101: =Z101+AE101 -> 0.013945865
A102: 71 | B102: 44543 | C102: 5212383 | D102: 6629870 | E102: =D102-C102-SUM(F102:K102) -> 1225138 | F102: 55122 | G102: 11240 | H102: 323 | I102: 77 | J102: 124160 | K102: 1427 | L102: =G102-G101 -> 240 | M102: =H102-H101 -> 13 | N102: =I102-I101 -> 3 | O102: =J102-J101 -> 1010 | P102: =MAX(0,MIN(G102,L102+$O102*G102/SUM($G102:$I102))) -> 1215.2921 | Q102: =MAX(0,MIN(H102,M102+$O102*H102/SUM($G102:$I102))) -> 41.026632 | R102: =MAX(0,MIN(I102,N102+$O102*I102/SUM($G102:$I102))) -> 9.6812715 | S102: =MIN(1,P102/F101) -> 0.018054613 | T102: =MIN(1,Q102/G101) -> 0.0037296938 | U102: =MIN(1,R102/H101) -> 0.031229908 | V102: =AVERAGE(S99:S105) -> 0.018170438 | W102: =AVERAGE(T100:T104) -> 0.0040176897 | X102: =AVERAGE(U100:U104) -> 0.037731608 | Y102: =(C102-C101)/E101 -> 0.00073409113 | Z102: =AVERAGE(Y99:Y105) -> 0.0032522605 | AD102: =10289*EXP(0.05828*(A102-17)) -> 239414.26 | AE102: =(AD102-AD101)/E101 -> 0.011154775 | AF102: =Z102+AE102 -> 0.014407035
A103: 72 | B103: 44544 | C103: 5217327 | D103: 6629870 | E103: =D103-C103-SUM(F103:K103) -> 1219667 | F103: 54467 | G103: 10709 | H103: 364 | I103: 80 | J103: 125823 | K103: 1433 | L103: =G103-G102 -> -531 | M103: =H103-H102 -> 41 | N103: =I103-I102 -> 3 | O103: =J103-J102 -> 1663 | P103: =MAX(0,MIN(G103,L103+$O103*G103/SUM($G103:$I103))) -> 1065.7961 | Q103: =MAX(0,MIN(H103,M103+$O103*H103/SUM($G103:$I103))) -> 95.275262 | R103: =MAX(0,MIN(I103,N103+$O103*I103/SUM($G103:$I103))) -> 14.928629 | S103: =MIN(1,P103/F102) -> 0.019335222 | T103: =MIN(1,Q103/G102) -> 0.0084764468 | U103: =MIN(1,R103/H102) -> 0.046218666 | V103: =AVERAGE(S100:S106) -> 0.018434887 | W103: =AVERAGE(T101:T105) -> 0.0042210058 | X103: =AVERAGE(U101:U105) -> 0.035048643 | Y103: =(C103-C102)/E102 -> 0.0040354638 | Z103: =AVERAGE(Y100:Y106) -> 0.0031833161 | AD103: =10289*EXP(0.05828*(A103-17)) -> 253781.93 | AE103: =(AD103-AD102)/E102 -> 0.01172739 | AF103: =Z103+AE103 -> 0.014910706
A104: 73 | B104: 44545 | C104: 5221774 | D104: 6629870 | E104: =D104-C104-SUM(F104:K104) -> 1191226 | F104: 77066 | G104: 11060 | H104: 365 | I104: 84 | J104: 126859 | K104: 1436 | L104: =G104-G103 -> 351 | M104: =H104-H103 -> 1 | N104: =I104-I103 -> 4 | O104: =J104-J103 -> 1036 | P104: =MAX(0,MIN(G104,L104+$O104*G104/SUM($G104:$I104))) -> 1346.5826 | Q104: =MAX(0,MIN(H104,M104+$O104*H104/SUM($G104:$I104))) -> 33.856026 | R104: =MAX(0,MIN(I104,N104+$O104*I104/SUM($G104:$I104))) -> 11.561387 | S104: =MIN(1,P104/F103) -> 0.024722907 | T104: =MIN(1,Q104/G103) -> 0.0031614554 | U104: =MIN(1,R104/H103) -> 0.031762051 | V104: =AVERAGE(S101:S107) -> 0.018488257 | W104: =AVERAGE(T102:T106) -> 0.0045481015 | X104: =AVERAGE(U102:U106) -> 0.028199751 | Y104: =(C104-C103)/E103 -> 0.0036460772 | Z104: =AVERAGE(Y101:Y107) -> 0.0030541318 | AD104: =10289*EXP(0.05828*(A104-17)) -> 269011.83 | AE104: =(AD104-AD103)/E103 -> 0.012486933 | AF104: =Z104+AE104 -> 0.015541065
A105: 74 | B105: 44546 | C105: 5226264 | D105: 6629870 | E105: =D105-C105-SUM(F105:K105) -> 1181350 | F105: 80841 | G105: 11772 | H105: 384 | I105: 87 | J105: 127727 | K105: 1445 | L105: =G105-G104 -> 712 | M105: =H105-H104 -> 19 | N105: =I105-I104 -> 3 | O105: =J105-J104 -> 868 | P105: =MAX(0,MIN(G105,L105+$O105*G105/SUM($G105:$I105))) -> 1546.6072 | Q105: =MAX(0,MIN(H105,M105+$O105*H105/SUM($G105:$I105))) -> 46.2247 | R105: =MAX(0,MIN(I105,N105+$O105*I105/SUM($G105:$I105))) -> 9.1680961 | S105: =MIN(1,P105/F104) -> 0.020068606 | T105: =MIN(1,Q105/G104) -> 0.0041794484 | U105: =MIN(1,R105/H104) -> 0.025118071 | V105: =AVERAGE(S102:S108) -> 0.01862284 | W105: =AVERAGE(T103:T107) -> 0.0040350839 | X105: =AVERAGE(U103:U107) -> 0.024814039 | Y105: =(C105-C104)/E104 -> 0.003769226 | Z105: =AVERAGE(Y102:Y108) -> 0.0029775016 | AC105: 251856 | AD105: =10289*EXP(0.05828*(A105-17)) -> 285155.7 | AE105: =(AD105-AD104)/E104 -> 0.013552317 | AF105: =Z105+AE105 -> 0.016529819
A106: 75 | B106: 44547 | C106: 5230468 | D106: 6629870 | E106: =D106-C106-SUM(F106:K106) -> 1174194 | F106: 82301 | G106: 12101 | H106: 386 | I106: 82 | J106: 128886 | K106: 1452 | L106: =G106-G105 -> 329 | M106: =H106-H105 -> 2 | N106: =I106-I105 -> -5 | O106: =J106-J105 -> 1159 | P106: =MAX(0,MIN(G106,L106+$O106*G106/SUM($G106:$I106))) -> 1444.8453 | Q106: =MAX(0,MIN(H106,M106+$O106*H106/SUM($G106:$I106))) -> 37.593444 | R106: =MAX(0,MIN(I106,N106+$O106*I106/SUM($G106:$I106))) -> 2.5613016 | S106: =MIN(1,P106/F105) -> 0.017872679 | T106: =MIN(1,Q106/G105) -> 0.0031934628 | U106: =MIN(1,R106/H105) -> 0.0066700563 | V106: =AVERAGE(S103:S109) -> 0.018355301 | W106: =AVERAGE(T104:T108) -> 0.0031905958 | X106: =AVERAGE(U104:U108) -> 0.019082946 | Y106: =(C106-C105)/E105 -> 0.0035586405 | Z106: =AVERAGE(Y103:Y109) -> 0.0029777174 | AD106: =10289*EXP(0.05828*(A106-17)) -> 302268.4 | AE106: =(AD106-AD105)/E105 -> 0.014485711 | AF106: =Z106+AE106 -> 0.017463429
A107: 76 | B107: 44548 | C107: 5234686 | D107: 6629870 | E107: =D107-C107-SUM(F107:K107) -> 1162759 | F107: 88083 | G107: 12966 | H107: 384 | I107: 84 | J107: 129449 | K107: 1459 | L107: =G107-G106 -> 865 | M107: =H107-H106 -> -2 | N107: =I107-I106 -> 2 | O107: =J107-J106 -> 563 | P107: =MAX(0,MIN(G107,L107+$O107*G107/SUM($G107:$I107))) -> 1408.3868 | Q107: =MAX(0,MIN(H107,M107+$O107*H107/SUM($G107:$I107))) -> 14.092899 | R107: =MAX(0,MIN(I107,N107+$O107*I107/SUM($G107:$I107))) -> 5.5203216 | S107: =MIN(1,P107/F106) -> 0.017112633 | T107: =MIN(1,Q107/G106) -> 0.0011646061 | U107: =MIN(1,R107/H106) -> 0.014301351 | V107: =AVERAGE(S104:S110) -> 0.018018528 | W107: =AVERAGE(T105:T109) -> 0.0033706156 | X107: =AVERAGE(U105:U109) -> 0.016519167 | Y107: =(C107-C106)/E106 -> 0.0035922514 | Z107: =AVERAGE(Y104:Y110) -> 0.0028639006 | AD107: =10289*EXP(0.05828*(A107-17)) -> 320408.06 | AE107: =(AD107-AD106)/E106 -> 0.015448604 | AF107: =Z107+AE107 -> 0.018312504
...

Sheet Reg_30days (2)
C1: V | Y1: Actual Vacc=second dose/S | AA1: Total dose/S | AC1: Cumulative booster num | AE1: booster rate | AF1: Second+booster | AG1: opt+booster
B2: date | C2: Number of people fully vaccinated | D2: N | E2: S | F2: E | G2: I1 | H2: I2 | I2: I3 | J2: R | K2: D | L2: I1 change | M2: I2 change | N2: I3 change | O2: Delta R = total decrease in I | P2: I1 increase | Q2: I2 increase | R2: I3 increase | S2: gamma | T2: p1 | U2: p2 | V2: gamma_avg | W2: p1_avg | X2: p2_avg | Y2: alpha | Z2: alpha_avg | AA2: alpha_all | AB2: alpha_all_avg | AC2: Actual | AD2: Fitted
B3: 44444 | D3: 6629870 | E3: =D3-C3-SUM(F3:K3) -> 6558441 | F3: 48487 | G3: 1301 | H3: 89 | I3: 24 | J3: 20702 | K3: 826
B4: 44445 | D4: 6629870 | E4: =D4-C4-SUM(F4:K4) -> 6564425 | F4: 42258 | G4: 1498 | H4: 92 | I4: 26 | J4: 20745 | K4: 826
B5: 44446 | D5: 6629870 | E5: =D5-C5-SUM(F5:K5) -> 6562583 | F5: 43858 | G5: 1643 | H5: 110 | I5: 30 | J5: 20820 | K5: 826
B6: 44447 | D6: 6629870 | E6: =D6-C6-SUM(F6:K6) -> 6563800 | F6: 42429 | G6: 1764 | H6: 120 | I6: 33 | J6: 20898 | K6: 826 | L6: =G6-G5 -> 121 | M6: =H6-H5 -> 10 | N6: =I6-I5 -> 3 | O6: =J6-J5 -> 78 | P6: =MAX(0,MIN(G6,L6+$O6*G6/SUM($G6:$I6))) -> 192.77465 | Q6: =MAX(0,MIN(H6,M6+$O6*H6/SUM($G6:$I6))) -> 14.882629 | R6: =MAX(0,MIN(I6,N6+$O6*I6/SUM($G6:$I6))) -> 4.342723 | S6: =MIN(1,P6/F5) -> 0.0043954272 | T6: =MIN(1,Q6/G5) -> 0.009058204 | U6: =MIN(1,R6/H5) -> 0.0394793
B7: 44448 | D7: 6629870 | E7: =D7-C7-SUM(F7:K7) -> 6551664 | F7: 54242 | G7: 2020 | H7: 111 | I7: 32 | J7: 20975 | K7: 826 | L7: =G7-G6 -> 256 | M7: =H7-H6 -> -9 | N7: =I7-I6 -> -1 | O7: =J7-J6 -> 77 | P7: =MAX(0,MIN(G7,L7+$O7*G7/SUM($G7:$I7))) -> 327.90939 | Q7: =MAX(0,MIN(H7,M7+$O7*H7/SUM($G7:$I7))) -> 0 | R7: =MAX(0,MIN(I7,N7+$O7*I7/SUM($G7:$I7))) -> 0.13915858 | S7: =MIN(1,P7/F6) -> 0.007728426 | T7: =MIN(1,Q7/G6) -> 0 | U7: =MIN(1,R7/H6) -> 0.0011596548
B8: 44449 | D8: 6629870 | E8: =D8-C8-SUM(F8:K8) -> 6562575 | F8: 42998 | G8: 2263 | H8: 127 | I8: 33 | J8: 21047 | K8: 827 | L8: =G8-G7 -> 243 | M8: =H8-H7 -> 16 | N8: =I8-I7 -> 1 | O8: =J8-J7 -> 72 | P8: =MAX(0,MIN(G8,L8+$O8*G8/SUM($G8:$I8))) -> 310.24556 | Q8: =MAX(0,MIN(H8,M8+$O8*H8/SUM($G8:$I8))) -> 19.773834 | R8: =MAX(0,MIN(I8,N8+$O8*I8/SUM($G8:$I8))) -> 1.9806026 | S8: =MIN(1,P8/F7) -> 0.0057196557 | T8: =MIN(1,Q8/G7) -> 0.0097890268 | U8: =MIN(1,R8/H7) -> 0.017843266
B9: 44450 | D9: 6629870 | E9: =D9-C9-SUM(F9:K9) -> 6562361 | F9: 42765 | G9: 2613 | H9: 143 | I9: 34 | J9: 21127 | K9: 827 | L9: =G9-G8 -> 350 | M9: =H9-H8 -> 16 | N9: =I9-I8 -> 1 | O9: =J9-J8 -> 80 | P9: =MAX(0,MIN(G9,L9+$O9*G9/SUM($G9:$I9))) -> 424.92473 | Q9: =MAX(0,MIN(H9,M9+$O9*H9/SUM($G9:$I9))) -> 20.100358 | R9: =MAX(0,MIN(I9,N9+$O9*I9/SUM($G9:$I9))) -> 1.9749104 | S9: =MIN(1,P9/F8) -> 0.0098824301 | T9: =MIN(1,Q9/G8) -> 0.0088821734 | U9: =MIN(1,R9/H8) -> 0.015550476 | V9: =AVERAGE(S6:S12) -> 0.007765351 | W9: =AVERAGE(T6:T12) -> 0.0052865415 | X9: =AVERAGE(U6:U12) -> 0.023812869
B10: 44451 | D10: 6629870 | E10: =D10-C10-SUM(F10:K10) -> 6556679 | F10: 48063 | G10: 2928 | H10: 147 | I10: 34 | J10: 21192 | K10: 827 | L10: =G10-G9 -> 315 | M10: =H10-H9 -> 4 | N10: =I10-I9 -> 0 | O10: =J10-J9 -> 65 | P10: =MAX(0,MIN(G10,L10+$O10*G10/SUM($G10:$I10))) -> 376.21583 | Q10: =MAX(0,MIN(H10,M10+$O10*H10/SUM($G10:$I10))) -> 7.0733355 | R10: =MAX(0,MIN(I10,N10+$O10*I10/SUM($G10:$I10))) -> 0.7108395 | S10: =MIN(1,P10/F9) -> 0.0087972834 | T10: =MIN(1,Q10/G9) -> 0.0027069788 | U10: =MIN(1,R10/H9) -> 0.0049709056 | V10: =AVERAGE(S7:S13) -> 0.0084253731 | W10: =AVERAGE(T7:T13) -> 0.004877004 | X10: =AVERAGE(U7:U13) -> 0.018935062
B11: 44452 | D11: 6629870 | E11: =D11-C11-SUM(F11:K11) -> 6555242 | F11: 49037 | G11: 3309 | H11: 157 | I11: 38 | J11: 21260 | K11: 827 | L11: =G11-G10 -> 381 | M11: =H11-H10 -> 10 | N11: =I11-I10 -> 4 | O11: =J11-J10 -> 68 | P11: =MAX(0,MIN(G11,L11+$O11*G11/SUM($G11:$I11))) -> 445.21575 | Q11: =MAX(0,MIN(H11,M11+$O11*H11/SUM($G11:$I11))) -> 13.046804 | R11: =MAX(0,MIN(I11,N11+$O11*I11/SUM($G11:$I11))) -> 4.7374429 | S11: =MIN(1,P11/F10) -> 0.0092631703 | T11: =MIN(1,Q11/G10) -> 0.0044558756 | U11: =MIN(1,R11/H10) -> 0.032227503 | V11: =AVERAGE(S8:S14) -> 0.0085705218 | W11: =AVERAGE(T8:T14) -> 0.0054804101 | X11: =AVERAGE(U8:U14) -> 0.026198814
B12: 44453 | D12: 6629870 | E12: =D12-C12-SUM(F12:K12) -> 6561147 | F12: 42694 | G12: 3593 | H12: 158 | I12: 45 | J12: 21404 | K12: 829 | L12: =G12-G11 -> 284 | M12: =H12-H11 -> 1 | N12: =I12-I11 -> 7 | O12: =J12-J11 -> 144 | P12: =MAX(0,MIN(G12,L12+$O12*G12/SUM($G12:$I12))) -> 420.29926 | Q12: =MAX(0,MIN(H12,M12+$O12*H12/SUM($G12:$I12))) -> 6.9936776 | R12: =MAX(0,MIN(I12,N12+$O12*I12/SUM($G12:$I12))) -> 8.7070601 | S12: =MIN(1,P12/F11) -> 0.0085710639 | T12: =MIN(1,Q12/G11) -> 0.0021135321 | U12: =MIN(1,R12/H11) -> 0.055458981 | V12: =AVERAGE(S9:S15) -> 0.0088203368 | W12: =AVERAGE(T9:T15) -> 0.0052392349 | X12: =AVERAGE(U9:U15) -> 0.023649776
B13: 44454 | D13: 6629870 | E13: =D13-C13-SUM(F13:K13) -> 6548782 | F13: 54649 | G13: 3818 | H13: 173 | I13: 44 | J13: 21573 | K13: 831 | L13: =G13-G12 -> 225 | M13: =H13-H12 -> 15 | N13: =I13-I12 -> -1 | O13: =J13-J12 -> 169 | P13: =MAX(0,MIN(G13,L13+$O13*G13/SUM($G13:$I13))) -> 384.91128 | Q13: =MAX(0,MIN(H13,M13+$O13*H13/SUM($G13:$I13))) -> 22.245849 | R13: =MAX(0,MIN(I13,N13+$O13*I13/SUM($G13:$I13))) -> 0.84287485 | S13: =MIN(1,P13/F12) -> 0.0090155824 | T13: =MIN(1,Q13/G12) -> 0.0061914414 | U13: =MIN(1,R13/H12) -> 0.0053346509 | V13: =AVERAGE(S10:S16) -> 0.0087185751 | W13: =AVERAGE(T10:T16) -> 0.0042746777 | X13: =AVERAGE(U10:U16) -> 0.028178005
B14: 44455 | D14: 6629870 | E14: =D14-C14-SUM(F14:K14) -> 6540967 | F14: 61961 | G14: 4134 | H14: 182 | I14: 51 | J14: 21744 | K14: 831 | L14: =G14-G13 -> 316 | M14: =H14-H13 -> 9 | N14: =I14-I13 -> 7 | O14: =J14-J13 -> 171 | P14: =MAX(0,MIN(G14,L14+$O14*G14/SUM($G14:$I14))) -> 477.87635 | Q14: =MAX(0,MIN(H14,M14+$O14*H14/SUM($G14:$I14))) -> 16.126632 | R14: =MAX(0,MIN(I14,N14+$O14*I14/SUM($G14:$I14))) -> 8.9970231 | S14: =MIN(1,P14/F13) -> 0.0087444664 | T14: =MIN(1,Q14/G13) -> 0.0042238427 | U14: =MIN(1,R14/H13) -> 0.052005914 | V14: =AVERAGE(S11:S17) -> 0.0085773762 | W14: =AVERAGE(T11:T17) -> 0.0040311676 | X14: =AVERAGE(U11:U17) -> 0.028214041
B15: 44456 | D15: 6629870 | E15: =D15-C15-SUM(F15:K15) -> 6546955 | F15: 55476 | G15: 4437 | H15: 208 | I15: 49 | J15: 21913 | K15: 832 | L15: =G15-G14 -> 303 | M15: =H15-H14 -> 26 | N15: =I15-I14 -> -2 | O15: =J15-J14 -> 169 | P15: =MAX(0,MIN(G15,L15+$O15*G15/SUM($G15:$I15))) -> 462.74712 | Q15: =MAX(0,MIN(H15,M15+$O15*H15/SUM($G15:$I15))) -> 33.488709 | R15: =MAX(0,MIN(I15,N15+$O15*I15/SUM($G15:$I15))) -> 0 | S15: =MIN(1,P15/F14) -> 0.0074683611 | T15: =MIN(1,Q15/G14) -> 0.0081008004 | U15: =MIN(1,R15/H14) -> 0 | V15: =AVERAGE(S12:S18) -> 0.0085590539 | W15: =AVERAGE(T12:T18) -> 0.0036827562 | X15: =AVERAGE(U12:U18) -> 0.027416465
B16: 44457 | D16: 6629870 | E16: =D16-C16-SUM(F16:K16) -> 6540280 | F16: 61622 | G16: 4708 | H16: 207 | I16: 56 | J16: 22164 | K16: 833 | L16: =G16-G15 -> 271 | M16: =H16-H15 -> -1 | N16: =I16-I15 -> 7 | O16: =J16-J15 -> 251 | P16: =MAX(0,MIN(G16,L16+$O16*G16/SUM($G16:$I16))) -> 508.72038 | Q16: =MAX(0,MIN(H16,M16+$O16*H16/SUM($G16:$I16))) -> 9.4520217 | R16: =MAX(0,MIN(I16,N16+$O16*I16/SUM($G16:$I16))) -> 9.8276001 | S16: =MIN(1,P16/F15) -> 0.0091700984 | T16: =MIN(1,Q16/G15) -> 0.0021302731 | U16: =MIN(1,R16/H15) -> 0.047248077 | V16: =AVERAGE(S13:S19) -> 0.0088521307 | W16: =AVERAGE(T13:T19) -> 0.0045050943 | X16: =AVERAGE(U13:U19) -> 0.021969017
B17: 44458 | D17: 6629870 | E17: =D17-C17-SUM(F17:K17) -> 6542795 | F17: 58619 | G17: 5000 | H17: 204 | I17: 55 | J17: 22363 | K17: 834 | L17: =G17-G16 -> 292 | M17: =H17-H16 -> -3 | N17: =I17-I16 -> -1 | O17: =J17-J16 -> 199 | P17: =MAX(0,MIN(G17,L17+$O17*G17/SUM($G17:$I17))) -> 481.19947 | Q17: =MAX(0,MIN(H17,M17+$O17*H17/SUM($G17:$I17))) -> 4.7193383 | R17: =MAX(0,MIN(I17,N17+$O17*I17/SUM($G17:$I17))) -> 1.0811941 | S17: =MIN(1,P17/F16) -> 0.0078088908 | T17: =MIN(1,Q17/G16) -> 0.0010024083 | U17: =MIN(1,R17/H16) -> 0.0052231601 | V17: =AVERAGE(S14:S20) -> 0.0092699877 | W17: =AVERAGE(T14:T20) -> 0.0044301789 | X17: =AVERAGE(U14:U20) -> 0.022199192
B18: 44459 | D18: 6629870 | E18: =D18-C18-SUM(F18:K18) -> 6549947 | F18: 50915 | G18: 5404 | H18: 209 | I18: 59 | J18: 22501 | K18: 835 | L18: =G18-G17 -> 404 | M18: =H18-H17 -> 5 | N18: =I18-I17 -> 4 | O18: =J18-J17 -> 138 | P18: =MAX(0,MIN(G18,L18+$O18*G18/SUM($G18:$I18))) -> 535.47955 | Q18: =MAX(0,MIN(H18,M18+$O18*H18/SUM($G18:$I18))) -> 10.084979 | R18: =MAX(0,MIN(I18,N18+$O18*I18/SUM($G18:$I18))) -> 5.4354725 | S18: =MIN(1,P18/F17) -> 0.0091349144 | T18: =MIN(1,Q18/G17) -> 0.0020169958 | U18: =MIN(1,R18/H17) -> 0.026644473 | V18: =AVERAGE(S15:S21) -> 0.0097230262 | W18: =AVERAGE(T15:T21) -> 0.0041048475 | X18: =AVERAGE(U15:U21) -> 0.017373153
B19: 44460 | D19: 6629870 | E19: =D19-C19-SUM(F19:K19) -> 6551445 | F19: 48829 | G19: 5696 | H19: 241 | I19: 60 | J19: 22763 | K19: 836 | L19: =G19-G18 -> 292 | M19: =H19-H18 -> 32 | N19: =I19-I18 -> 1 | O19: =J19-J18 -> 262 | P19: =MAX(0,MIN(G19,L19+$O19*G19/SUM($G19:$I19))) -> 540.84976 | Q19: =MAX(0,MIN(H19,M19+$O19*H19/SUM($G19:$I19))) -> 42.528931 | R19: =MAX(0,MIN(I19,N19+$O19*I19/SUM($G19:$I19))) -> 3.6213107 | S19: =MIN(1,P19/F18) -> 0.010622602 | T19: =MIN(1,Q19/G18) -> 0.0078698984 | U19: =MIN(1,R19/H18) -> 0.017326845 | V19: =AVERAGE(S16:S22) -> 0.010166202 | W19: =AVERAGE(T16:T22) -> 0.0040563657 | X19: =AVERAGE(U16:U22) -> 0.021851445
B20: 44461 | D20: 6629870 | E20: =D20-C20-SUM(F20:K20) -> 6538825 | F20: 60829 | G20: 5905 | H20: 257 | I20: 58 | J20: 23157 | K20: 839 | L20: =G20-G19 -> 209 | M20: =H20-H19 -> 16 | N20: =I20-I19 -> -2 | O20: =J20-J19 -> 394 | P20: =MAX(0,MIN(G20,L20+$O20*G20/SUM($G20:$I20))) -> 583.04662 | Q20: =MAX(0,MIN(H20,M20+$O20*H20/SUM($G20:$I20))) -> 32.279421 | R20: =MAX(0,MIN(I20,N20+$O20*I20/SUM($G20:$I20))) -> 1.673955 | S20: =MIN(1,P20/F19) -> 0.011940581 | T20: =MIN(1,Q20/G19) -> 0.0056670332 | U20: =MIN(1,R20/H19) -> 0.0069458713 | V20: =AVERAGE(S17:S23) -> 0.010859315 | W20: =AVERAGE(T17:T23) -> 0.0045973644 | X20: =AVERAGE(U17:U23) -> 0.016198765
... B28: 44469 | D28: 6629870 | E28: =D28-C28-SUM(F28:K28) -> 6527040 | F28: 65497 | G28: 10534 | H28: 398 | I28: 83 | J28: 25454 | K28: 864 | L28: =G28-G27 -> 1099 | M28: =H28-H27 -> 27 | N28: =I28-I27 -> 2 | O28: =J28-J27 -> 296 | P28: =MAX(0,MIN(G28,L28+$O28*G28/SUM($G28:$I28))) -> 1382.0744 | Q28: =MAX(0,MIN(H28,M28+$O28*H28/SUM($G28:$I28))) -> 37.695234 | R28: =MAX(0,MIN(I28,N28+$O28*I28/SUM($G28:$I28))) -> 4.2304131 | S28: =MIN(1,P28/F27) -> 0.022537986 | T28: =MIN(1,Q28/G27) -> 0.0039952553 | U28: =MIN(1,R28/H27) -> 0.011402731 | V28: =AVERAGE(S25:S31) -> 0.018206605 | W28: =AVERAGE(T25:T31) -> 0.0045123298 | X28: =AVERAGE(U25:U31) -> 0.021474087
B29: 44470 | C29: 2738168 | D29: 6629870 | E29: =D29-C29-SUM(F29:K29) -> 3790355 | F29: 62883 | G29: 10458 | H29: 395 | I29: 87 | J29: 26657 | K29: 867 | L29: =G29-G28 -> -76 | M29: =H29-H28 -> -3 | N29: =I29-I28 -> 4 | O29: =J29-J28 -> 1203 | P29: =MAX(0,MIN(G29,L29+$O29*G29/SUM($G29:$I29))) -> 1073.9976 | Q29: =MAX(0,MIN(H29,M29+$O29*H29/SUM($G29:$I29))) -> 40.435558 | R29: =MAX(0,MIN(I29,N29+$O29*I29/SUM($G29:$I29))) -> 13.566819 | S29: =MIN(1,P29/F28) -> 0.016397661 | T29: =MIN(1,Q29/G28) -> 0.0038385758 | U29: =MIN(1,R29/H28) -> 0.034087485 | V29: =AVERAGE(S26:S32) -> 0.018459778 | W29: =AVERAGE(T26:T32) -> 0.0040468772 | X29: =AVERAGE(U26:U32) -> 0.019766592
B30: 44471 | C30: 2783434 | D30: 6629870 | E30: =D30-C30-SUM(F30:K30) -> 3735463 | F30: 71224 | G30: 11061 | H30: 429 | I30: 97 | J30: 27293 | K30: 869 | L30: =G30-G29 -> 603 | M30: =H30-H29 -> 34 | N30: =I30-I29 -> 10 | O30: =J30-J29 -> 636 | P30: =MAX(0,MIN(G30,L30+$O30*G30/SUM($G30:$I30))) -> 1210.1283 | Q30: =MAX(0,MIN(H30,M30+$O30*H30/SUM($G30:$I30))) -> 57.547424 | R30: =MAX(0,MIN(I30,N30+$O30*I30/SUM($G30:$I30))) -> 15.324243 | S30: =MIN(1,P30/F29) -> 0.019244125 | T30: =MIN(1,Q30/G29) -> 0.0055027179 | U30: =MIN(1,R30/H29) -> 0.038795551 | V30: =AVERAGE(S27:S33) -> 0.019779845 | W30: =AVERAGE(T27:T33) -> 0.0040056564 | X30: =AVERAGE(U27:U33) -> 0.01857876 | Y30: =(C30-C29)/E29 -> 0.011942417 | Z30: =AVERAGE(Y27:Y33) -> 0.010648776
B31: 44472 | C31: 2819637 | D31: 6629870 | E31: =D31-C31-SUM(F31:K31) -> 3697830 | F31: 71275 | G31: 11207 | H31: 476 | I31: 98 | J31: 28475 | K31: 872 | L31: =G31-G30 -> 146 | M31: =H31-H30 -> 47 | N31: =I31-I30 -> 1 | O31: =J31-J30 -> 1182 | P31: =MAX(0,MIN(G31,L31+$O31*G31/SUM($G31:$I31))) -> 1270.41 | Q31: =MAX(0,MIN(H31,M31+$O31*H31/SUM($G31:$I31))) -> 94.757576 | R31: =MAX(0,MIN(I31,N31+$O31*I31/SUM($G31:$I31))) -> 10.832442 | S31: =MIN(1,P31/F30) -> 0.017836824 | T31: =MIN(1,Q31/G30) -> 0.0085668182 | U31: =MIN(1,R31/H30) -> 0.025250448 | V31: =AVERAGE(S28:S34) -> 0.020227464 | W31: =AVERAGE(T28:T34) -> 0.0044903623 | X31: =AVERAGE(U28:U34) -> 0.018182157 | Y31: =(C31-C30)/E30 -> 0.0096917035 | Z31: =AVERAGE(Y28:Y34) -> 0.011440147
A32: 1 | B32: 44473 | C32: 2845438 | D32: 6629870 | E32: =D32-C32-SUM(F32:K32) -> 3674149 | F32: 67789 | G32: 12113 | H32: 498 | I32: 96 | J32: 28911 | K32: 876 | L32: =G32-G31 -> 906 | M32: =H32-H31 -> 22 | N32: =I32-I31 -> -2 | O32: =J32-J31 -> 436 | P32: =MAX(0,MIN(G32,L32+$O32*G32/SUM($G32:$I32))) -> 1321.6188 | Q32: =MAX(0,MIN(H32,M32+$O32*H32/SUM($G32:$I32))) -> 39.087275 | R32: =MAX(0,MIN(I32,N32+$O32*I32/SUM($G32:$I32))) -> 1.2939325 | S32: =MIN(1,P32/F31) -> 0.01854253 | T32: =MIN(1,Q32/G31) -> 0.0034877554 | U32: =MIN(1,R32/H31) -> 0.0027183455 | V32: =AVERAGE(S29:S35) -> 0.020002466 | W32: =AVERAGE(T29:T35) -> 0.0046866916 | X32: =AVERAGE(U29:U35) -> 0.024211064 | Y32: =(C32-C31)/E31 -> 0.0069773354 | Z32: =AVERAGE(Y29:Y35) -> 0.012596397 | AA32: ='ori data'!AV119 -> 0.01361322 | AB32: ='ori data'!AW119 -> 0.023351457 | AE32: 0 | AF32: =Z32+AE32 -> 0.012596397 | AG32: ='opt vacc_sigma0.1'!L3+AE32 -> 0.02431008
A33: 2 | B33: 44474 | C33: 2896816 | D33: 6629870 | E33: =D33-C33-SUM(F33:K33) -> 3626614 | F33: 62189 | G33: 13746 | H33: 517 | I33: 101 | J33: 29007 | K33: 880 | L33: =G33-G32 -> 1633 | M33: =H33-H32 -> 19 | N33: =I33-I32 -> 5 | O33: =J33-J32 -> 96 | P33: =MAX(0,MIN(G33,L33+$O33*G33/SUM($G33:$I33))) -> 1724.8697 | Q33: =MAX(0,MIN(H33,M33+$O33*H33/SUM($G33:$I33))) -> 22.455305 | R33: =MAX(0,MIN(I33,N33+$O33*I33/SUM($G33:$I33))) -> 5.6750209 | S33: =MIN(1,P33/F32) -> 0.025444684 | T33: =MIN(1,Q33/G32) -> 0.0018538186 | U33: =MIN(1,R33/H32) -> 0.011395624 | V33: =AVERAGE(S30:S36) -> 0.020915166 | W33: =AVERAGE(T30:T36) -> 0.004719476 | X33: =AVERAGE(U30:U36) -> 0.019341423 | Y33: =(C33-C32)/E32 -> 0.013983646 | Z33: =AVERAGE(Y30:Y36) -> 0.013190538 | AA33: ='ori data'!AV120 -> 0.026563897 | AB33: ='ori data'!AW120 -> 0.023768685 | AE33: 0 | AF33: =Z33+AE33 -> 0.013190538 | AG33: ='opt vacc_sigma0.1'!L4+AE33 -> 0.024222336
A34: 3 | B34: 44475 | C34: 2949785 | D34: 6629870 | E34: =D34-C34-SUM(F34:K34) -> 3562970 | F34: 71451 | G34: 13787 | H34: 525 | I34: 94 | J34: 30367 | K34: 891 | L34: =G34-G33 -> 41 | M34: =H34-H33 -> 8 | N34: =I34-I33 -> -7 | O34: =J34-J33 -> 1360 | P34: =MAX(0,MIN(G34,L34+$O34*G34/SUM($G34:$I34))) -> 1342.5632 | Q34: =MAX(0,MIN(H34,M34+$O34*H34/SUM($G34:$I34))) -> 57.562682 | R34: =MAX(0,MIN(I34,N34+$O34*I34/SUM($G34:$I34))) -> 1.8740802 | S34: =MIN(1,P34/F33) -> 0.021588436 | T34: =MIN(1,Q34/G33) -> 0.0041875951 | U34: =MIN(1,R34/H33) -> 0.0036249134 | V34: =AVERAGE(S31:S37) -> 0.021656061 | W34: =AVERAGE(T31:T37) -> 0.0040207081 | X34: =AVERAGE(U31:U37) -> 0.016908012 | Y34: =(C34-C33)/E33 -> 0.014605635 | Z34: =AVERAGE(Y31:Y37) -> 0.014105239 | AA34: ='ori data'!AV121 -> 0.026831548 | AB34: ='ori data'!AW121 -> 0.024416678 | AE34: 0 | AF34: =Z34+AE34 -> 0.014105239 | AG34: ='opt vacc_sigma0.1'!L5+AE34 -> 0.024110737
A35: 4 | B35: 44476 | C35: 3015264 | D35: 6629870 | E35: =D35-C35-SUM(F35:K35) -> 3490102 | F35: 77238 | G35: 14391 | H35: 564 | I35: 115 | J35: 31303 | K35: 893 | L35: =G35-G34 -> 604 | M35: =H35-H34 -> 39 | N35: =I35-I34 -> 21 | O35: =J35-J34 -> 936 | P35: =MAX(0,MIN(G35,L35+$O35*G35/SUM($G35:$I35))) -> 1497.8272 | Q35: =MAX(0,MIN(H35,M35+$O35*H35/SUM($G35:$I35))) -> 74.030126 | R35: =MAX(0,MIN(I35,N35+$O35*I35/SUM($G35:$I35))) -> 28.142668 | S35: =MIN(1,P35/F34) -> 0.020962999 | T35: =MIN(1,Q35/G34) -> 0.0053695602 | U35: =MIN(1,R35/H34) -> 0.053605081 | V35: =AVERAGE(S32:S38) -> 0.022605274 | W35: =AVERAGE(T32:T38) -> 0.003273447 | X35: =AVERAGE(U32:U38) -> 0.016754732 | Y35: =(C35-C34)/E34 -> 0.018377646 | Z35: =AVERAGE(Y32:Y38) -> 0.015091189 | AA35: ='ori data'!AV122 -> 0.027577418 | AB35: ='ori data'!AW122 -> 0.025121909 | AE35: 0 | AF35: =Z35+AE35 -> 0.015091189 | AG35: ='opt vacc_sigma0.1'!L6+AE35 -> 0.024006797
A36: 5 | B36: 44477 | C36: 3073742 | D36: 6629870 | E36: =D36-C36-SUM(F36:K36) -> 3429485 | F36: 77554 | G36: 16085 | H36: 620 | I36: 114 | J36: 31372 | K36: 898 | L36: =G36-G35 -> 1694 | M36: =H36-H35 -> 56 | N36: =I36-I35 -> -1 | O36: =J36-J35 -> 69 | P36: =MAX(0,MIN(G36,L36+$O36*G36/SUM($G36:$I36))) -> 1759.9888 | Q36: =MAX(0,MIN(H36,M36+$O36*H36/SUM($G36:$I36))) -> 58.543552 | R36: =MAX(0,MIN(I36,N36+$O36*I36/SUM($G36:$I36))) -> 0 | S36: =MIN(1,P36/F35) -> 0.022786566 | T36: =MIN(1,Q36/G35) -> 0.004068067 | U36: =MIN(1,R36/H35) -> 0 | V36: =AVERAGE(S33:S39) -> 0.022779183 | W36: =AVERAGE(T33:T39) -> 0.0035895043 | X36: =AVERAGE(U33:U39) -> 0.019498774 | Y36: =(C36-C35)/E35 -> 0.016755384 | Z36: =AVERAGE(Y33:Y39) -> 0.015831503 | AA36: ='ori data'!AV123 -> 0.02778872 | AB36: ='ori data'!AW123 -> 0.025688985 | AE36: 0 | AF36: =Z36+AE36 -> 0.015831503 | AG36: ='opt vacc_sigma0.1'!L7+AE36 -> 0.023819631
A37: 6 | B37: 44478 | C37: 3136657 | D37: 6629870 | E37: =D37-C37-SUM(F37:K37) -> 3368758 | F37: 73443 | G37: 16500 | H37: 578 | I37: 117 | J37: 32914 | K37: 903 | L37: =G37-G36 -> 415 | M37: =H37-H36 -> -42 | N37: =I37-I36 -> 3 | O37: =J37-J36 -> 1542 | P37: =MAX(0,MIN(G37,L37+$O37*G37/SUM($G37:$I37))) -> 1894.6743 | Q37: =MAX(0,MIN(H37,M37+$O37*H37/SUM($G37:$I37))) -> 9.83344 | R37: =MAX(0,MIN(I37,N37+$O37*I37/SUM($G37:$I37))) -> 13.492236 | S37: =MIN(1,P37/F36) -> 0.024430388 | T37: =MIN(1,Q37/G36) -> 0.00061134224 | U37: =MIN(1,R37/H36) -> 0.021761671 | V37: =AVERAGE(S34:S40) -> 0.021834645 | W37: =AVERAGE(T34:T40) -> 0.0035263493 | X37: =AVERAGE(U34:U40) -> 0.021438533 | Y37: =(C37-C36)/E36 -> 0.01834532 | Z37: =AVERAGE(Y34:Y40) -> 0.016559196 | AA37: ='ori data'!AV124 -> 0.029017519 | AB37: ='ori data'!AW124 -> 0.0259455 | AE37: 0 | AF37: =Z37+AE37 -> 0.016559196 | AG37: ='opt vacc_sigma0.1'!L8+AE37 -> 0.023629749
A38: 7 | B38: 44479 | C38: 3192556 | D38: 6629870 | E38: =D38-C38-SUM(F38:K38) -> 3310325 | F38: 74105 | G38: 17603 | H38: 609 | I38: 126 | J38: 33638 | K38: 908 | L38: =G38-G37 -> 1103 | M38: =H38-H37 -> 31 | N38: =I38-I37 -> 9 | O38: =J38-J37 -> 724 | P38: =MAX(0,MIN(G38,L38+$O38*G38/SUM($G38:$I38))) -> 1797.9816 | Q38: =MAX(0,MIN(H38,M38+$O38*H38/SUM($G38:$I38))) -> 55.043843 | R38: =MAX(0,MIN(I38,N38+$O38*I38/SUM($G38:$I38))) -> 13.974588 | S38: =MIN(1,P38/F37) -> 0.02448132 | T38: =MIN(1,Q38/G37) -> 0.0033359905 | U38: =MIN(1,R38/H37) -> 0.024177488 | V38: =AVERAGE(S35:S41) -> 0.021818319 | W38: =AVERAGE(T35:T41) -> 0.0035136967 | X38: =AVERAGE(U35:U41) -> 0.023407357 | Y38: =(C38-C37)/E37 -> 0.016593356 | Z38: =AVERAGE(Y35:Y41) -> 0.017423507 | AA38: ='ori data'!AV125 -> 0.024461042 | AB38: ='ori data'!AW125 -> 0.026551033 | AE38: 0 | AF38: =Z38+AE38 -> 0.017423507 | AG38: ='opt vacc_sigma0.1'!L9+AE38 -> 0.023428194
A39: 8 | B39: 44480 | C39: 3232808 | D39: 6629870 | E39: =D39-C39-SUM(F39:K39) -> 3269454 | F39: 73138 | G39: 18198 | H39: 677 | I39: 133 | J39: 34546 | K39: 916 | L39: =G39-G38 -> 595 | M39: =H39-H38 -> 68 | N39: =I39-I38 -> 7 | O39: =J39-J38 -> 908 | P39: =MAX(0,MIN(G39,L39+$O39*G39/SUM($G39:$I39))) -> 1464.3068 | Q39: =MAX(0,MIN(H39,M39+$O39*H39/SUM($G39:$I39))) -> 100.33986 | R39: =MAX(0,MIN(I39,N39+$O39*I39/SUM($G39:$I39))) -> 13.353325 | S39: =MIN(1,P39/F38) -> 0.019759892 | T39: =MIN(1,Q39/G38) -> 0.0057001566 | U39: =MIN(1,R39/H38) -> 0.021926642 | V39: =AVERAGE(S36:S42) -> 0.022666122 | W39: =AVERAGE(T36:T42) -> 0.003349545 | X39: =AVERAGE(U36:U42) -> 0.019294317 | Y39: =(C39-C38)/E38 -> 0.012159531 | Z39: =AVERAGE(Y36:Y42) -> 0.01791683 | AA39: ='ori data'!AV126 -> 0.017582752 | AB39: ='ori data'!AW126 -> 0.027172354 | AC39: 0 | AD39: 0 | AE39: =(AD39-AD38)/E38 -> 0 | AF39: =Z39+AE39 -> 0.01791683 | AG39: ='opt vacc_sigma0.1'!L10+AE39 -> 0.023222737
A40: 9 | B40: 44481 | C40: 3295181 | D40: 6629870 | E40: =D40-C40-SUM(F40:K40) -> 3210282 | F40: 68509 | G40: 18804 | H40: 675 | I40: 144 | J40: 35351 | K40: 924 | L40: =G40-G39 -> 606 | M40: =H40-H39 -> -2 | N40: =I40-I39 -> 11 | O40: =J40-J39 -> 805 | P40: =MAX(0,MIN(G40,L40+$O40*G40/SUM($G40:$I40))) -> 1377.4019 | Q40: =MAX(0,MIN(H40,M40+$O40*H40/SUM($G40:$I40))) -> 25.69072 | R40: =MAX(0,MIN(I40,N40+$O40*I40/SUM($G40:$I40))) -> 16.907354 | S40: =MIN(1,P40/F39) -> 0.018832918 | T40: =MIN(1,Q40/G39) -> 0.0014117332 | U40: =MIN(1,R40/H39) -> 0.024973934 | V40: =AVERAGE(S37:S43) -> 0.023081364 | W40: =AVERAGE(T37:T43) -> 0.0028547876 | X40: =AVERAGE(U37:U43) -> 0.022345945 | Y40: =(C40-C39)/E39 -> 0.019077497 | Z40: =AVERAGE(Y37:Y43) -> 0.018746479 | AA40: ='ori data'!AV127 -> 0.028359502 | AB40: ='ori data'!AW127 -> 0.027939907 | AD40: =AD39+$AC$49/10 -> 720.5 | AE40: =(AD40-AD39)/E39 -> 0.00022037319 | AF40: =Z40+AE40 -> 0.018966852 | AG40: ='opt vacc_sigma0.1'!L11+AE40 -> 0.023243536
A41: 10 | B41: 44482 | C41: 3361492 | D41: 6629870 | E41: =D41-C41-SUM(F41:K41) -> 3131707 | F41: 79200 | G41: 19006 | H41: 705 | I41: 146 | J41: 36677 | K41: 937 | L41: =G41-G40 -> 202 | M41: =H41-H40 -> 30 | N41: =I41-I40 -> 2 | O41: =J41-J40 -> 1326 | P41: =MAX(0,MIN(G41,L41+$O41*G41/SUM($G41:$I41))) -> 1471.1724 | Q41: =MAX(0,MIN(H41,M41+$O41*H41/SUM($G41:$I41))) -> 77.078108 | R41: =MAX(0,MIN(I41,N41+$O41*I41/SUM($G41:$I41))) -> 11.749509 | S41: =MIN(1,P41/F40) -> 0.021474148 | T41: =MIN(1,Q41/G40) -> 0.0040990273 | U41: =MIN(1,R41/H40) -> 0.01740668 | V41: =AVERAGE(S38:S44) -> 0.023027039 | W41: =AVERAGE(T38:T44) -> 0.0039076154 | X41: =AVERAGE(U38:U44) -> 0.023004605 | Y41: =(C41-C40)/E40 -> 0.020655818 | Z41: =AVERAGE(Y38:Y44) -> 0.019534493 | AA41: ='ori data'!AV128 -> 0.031070276 | AB41: ='ori data'!AW128 -> 0.028653253 | AD41: =AD40+$AC$49/10 -> 1441 | AE41: =(AD41-AD40)/E40 -> 0.00022443511 | AF41: =Z41+AE41 -> 0.019758928 | AG41: ='opt vacc_sigma0.1'!L12+AE41 -> 0.023082098
A42: 11 | B42: 44483 | C42: 3429860 | D42: 6629870 | E42: =D42-C42-SUM(F42:K42) -> 3057538 | F42: 82762 | G42: 19004 | H42: 706 | I42: 147 | J42: 38905 | K42: 948 | L42: =G42-G41 -> -2 | M42: =H42-H41 -> 1 | N42: =I42-I41 -> 1 | O42: =J42-J41 -> 2228 | P42: =MAX(0,MIN(G42,L42+$O42*G42/SUM($G42:$I42))) -> 2130.2915 | Q42: =MAX(0,MIN(H42,M42+$O42*H42/SUM($G42:$I42))) -> 80.214786 | R42: =MAX(0,MIN(I42,N42+$O42*I42/SUM($G42:$I42))) -> 17.49373 | S42: =MIN(1,P42/F41) -> 0.02689762 | T42: =MIN(1,Q42/G41) -> 0.004220498 | U42: =MIN(1,R42/H41) -> 0.024813802 | V42: =AVERAGE(S39:S45) -> 0.022784659 | W42: =AVERAGE(T39:T45) -> 0.0034310453 | X42: =AVERAGE(U39:U45) -> 0.019550678 | Y42: =(C42-C41)/E41 -> 0.021830906 | Z42: =AVERAGE(Y39:Y45) -> 0.020085908 | AA42: ='ori data'!AV129 -> 0.031926668 | AB42: ='ori data'!AW129 -> 0.029015139 | AC42: 1728 | AD42: =AD41+$AC$49/10 -> 2161.5 | AE42: =(AD42-AD41)/E41 -> 0.00023006622 | AF42: =Z42+AE42 -> 0.020315974 | AG42: ='opt vacc_sigma0.1'!L13+AE42 -> 0.022934172
A43: 12 | B43: 44484 | C43: 3498847 | D43: 6629870 | E43: =D43-C43-SUM(F43:K43) -> 2995212 | F43: 73942 | G43: 20468 | H43: 695 | I43: 157 | J43: 39595 | K43: 954 | L43: =G43-G42 -> 1464 | M43: =H43-H42 -> -11 | N43: =I43-I42 -> 10 | O43: =J43-J42 -> 690 | P43: =MAX(0,MIN(G43,L43+$O43*G43/SUM($G43:$I43))) -> 2126.4259 | Q43: =MAX(0,MIN(H43,M43+$O43*H43/SUM($G43:$I43))) -> 11.492964 | R43: =MAX(0,MIN(I43,N43+$O43*I43/SUM($G43:$I43))) -> 15.081144 | S43: =MIN(1,P43/F42) -> 0.025693264 | T43: =MIN(1,Q43/G42) -> 0.00060476554 | U43: =MIN(1,R43/H42) -> 0.021361394 | V43: =AVERAGE(S40:S46) -> 0.023202359 | W43: =AVERAGE(T40:T46) -> 0.0037899773 | X43: =AVERAGE(U40:U46) -> 0.020848255 | Y43: =(C43-C42)/E42 -> 0.022562925 | Z43: =AVERAGE(Y40:Y46) -> 0.020574637 | AA43: ='ori data'!AV130 -> 0.033161593 | AB43: ='ori data'!AW130 -> 0.029334002 | AD43: =AD42+$AC$49/10 -> 2882 | AE43: =(AD43-AD42)/E42 -> 0.00023564711 | AF43: =Z43+AE43 -> 0.020810284 | AG43: ='opt vacc_sigma0.1'!L14+AE43 -> 0.022775113
A44: 13 | B44: 44485 | C44: 3570317 | D44: 6629870 | E44: =D44-C44-SUM(F44:K44) -> 2916503 | F44: 79214 | G44: 20682 | H44: 798 | I44: 163 | J44: 41232 | K44: 961 | L44: =G44-G43 -> 214 | M44: =H44-H43 -> 103 | N44: =I44-I43 -> 6 | O44: =J44-J43 -> 1637 | P44: =MAX(0,MIN(G44,L44+$O44*G44/SUM($G44:$I44))) -> 1778.3134 | Q44: =MAX(0,MIN(H44,M44+$O44*H44/SUM($G44:$I44))) -> 163.3579 | R44: =MAX(0,MIN(I44,N44+$O44*I44/SUM($G44:$I44))) -> 18.328744 | S44: =MIN(1,P44/F43) -> 0.024050112 | T44: =MIN(1,Q44/G43) -> 0.0079811363 | U44: =MIN(1,R44/H43) -> 0.026372293 | V44: =AVERAGE(S41:S47) -> 0.024167008 | W44: =AVERAGE(T41:T47) -> 0.0035883011 | X44: =AVERAGE(U41:U47) -> 0.018011925 | Y44: =(C44-C43)/E43 -> 0.023861416 | Z44: =AVERAGE(Y41:Y47) -> 0.021674524 | AA44: ='ori data'!AV131 -> 0.034010937 | AB44: ='ori data'!AW131 -> 0.030507944 | AD44: =AD43+$AC$49/10 -> 3602.5 | AE44: =(AD44-AD43)/E43 -> 0.00024055059 | AF44: =Z44+AE44 -> 0.021915075 | AG44: ='opt vacc_sigma0.1'!L15+AE44 -> 0.022636008
A45: 14 | B45: 44486 | C45: 3629969 | D45: 6629870 | E45: =D45-C45-SUM(F45:K45) -> 2860795 | F45: 73501 | G45: 22444 | H45: 777 | I45: 151 | J45: 41265 | K45: 968 | L45: =G45-G44 -> 1762 | M45: =H45-H44 -> -21 | N45: =I45-I44 -> -12 | O45: =J45-J44 -> 33 | P45: =MAX(0,MIN(G45,L45+$O45*G45/SUM($G45:$I45))) -> 1793.6897 | Q45: =MAX(0,MIN(H45,M45+$O45*H45/SUM($G45:$I45))) -> 0 | R45: =MAX(0,MIN(I45,N45+$O45*I45/SUM($G45:$I45))) -> 0 | T45: =MIN(1,Q45/G44) -> 0 | U45: =MIN(1,R45/H44) -> 0 | V45: =AVERAGE(S42:S48) -> 0.024802852 | W45: =AVERAGE(T42:T48) -> 0.0034047724 | X45: =AVERAGE(U42:U48) -> 0.017158431 | Y45: =(C45-C44)/E44 -> 0.020453262 | Z45: =AVERAGE(Y42:Y48) -> 0.022735849 | AA45: ='ori data'!AV132 -> 0.026994245 | AB45: ='ori data'!AW132 -> 0.031539824 | AD45: =AD44+$AC$49/10 -> 4323 | AE45: =(AD45-AD44)/E44 -> 0.00024704243 | AF45: =Z45+AE45 -> 0.022982891 | AG45: ='opt vacc_sigma0.1'!L16+AE45 -> 0.02250918
A46: 15 | B46: 44487 | C46: 3674542 | D46: 6629870 | E46: =D46-C46-SUM(F46:K46) -> 2818046 | F46: 69825 | G46: 21317 | H46: 851 | I46: 155 | J46: 44159 | K46: 975 | L46: =G46-G45 -> -1127 | M46: =H46-H45 -> 74 | N46: =I46-I45 -> 4 | O46: =J46-J45 -> 2894 | P46: =MAX(0,MIN(G46,L46+$O46*G46/SUM($G46:$I46))) -> 1636.5801 | Q46: =MAX(0,MIN(H46,M46+$O46*H46/SUM($G46:$I46))) -> 184.3254 | R46: =MAX(0,MIN(I46,N46+$O46*I46/SUM($G46:$I46))) -> 24.094521 | S46: =MIN(1,P46/F45) -> 0.022266093 | T46: =MIN(1,Q46/G45) -> 0.0082126806 | U46: =MIN(1,R46/H45) -> 0.03100968 | V46: =AVERAGE(S43:S49) -> 0.024711319 | W46: =AVERAGE(T43:T49) -> 0.0031709971 | X46: =AVERAGE(U43:U49) -> 0.014594754 | Y46: =(C46-C45)/E45 -> 0.015580634 | Z46: =AVERAGE(Y43:Y49) -> 0.0236201 | AA46: ='ori data'!AV133 -> 0.019814794 | AB46: ='ori data'!AW133 -> 0.032446016 | AD46: =AD45+$AC$49/10 -> 5043.5 | AE46: =(AD46-AD45)/E45 -> 0.00025185307 | AF46: =Z46+AE46 -> 0.023871953 | AG46: ='opt vacc_sigma0.1'!L17+AE46 -> 0.022374439
A47: 16 | B47: 44488 | C47: 3750000 | D47: 6629870 | E47: =D47-C47-SUM(F47:K47) -> 2741989 | F47: 68702 | G47: 21539 | H47: 784 | I47: 149 | J47: 45721 | K47: 986 | L47: =G47-G46 -> 222 | M47: =H47-H46 -> -67 | N47: =I47-I46 -> -6 | O47: =J47-J46 -> 1562 | P47: =MAX(0,MIN(G47,L47+$O47*G47/SUM($G47:$I47))) -> 1719.1484 | Q47: =MAX(0,MIN(H47,M47+$O47*H47/SUM($G47:$I47))) -> 0 | R47: =MAX(0,MIN(I47,N47+$O47*I47/SUM($G47:$I47))) -> 4.3567996 | S47: =MIN(1,P47/F46) -> 0.024620814 | T47: =MIN(1,Q47/G46) -> 0 | U47: =MIN(1,R47/H46) -> 0.0051196235 | V47: =AVERAGE(S44:S50) -> 0.024809751 | W47: =AVERAGE(T44:T50) -> 0.0035193174 | X47: =AVERAGE(U44:U50) -> 0.014374079 | Y47: =(C47-C46)/E46 -> 0.02677671 | Z47: =AVERAGE(Y44:Y50) -> 0.024767235 | AA47: ='ori data'!AV134 -> 0.036577098 | AB47: ='ori data'!AW134 -> 0.033544899 | AD47: =AD46+$AC$49/10 -> 5764 | AE47: =(AD47-AD46)/E46 -> 0.00025567361 | AF47: =Z47+AE47 -> 0.025022908 | AG47: ='opt vacc_sigma0.1'!L18+AE47 -> 0.022240799
A48: 17 | B48: 44489 | C48: 3827009 | D48: 6629870 | E48: =D48-C48-SUM(F48:K48) -> 2652935 | F48: 78928 | G48: 21661 | H48: 786 | I48: 147 | J48: 47406 | K48: 998 | L48: =G48-G47 -> 122 | M48: =H48-H47 -> 2 | N48: =I48-I47 -> -2 | O48: =J48-J47 -> 1685 | P48: =MAX(0,MIN(G48,L48+$O48*G48/SUM($G48:$I48))) -> 1737.4194 | Q48: =MAX(0,MIN(H48,M48+$O48*H48/SUM($G48:$I48))) -> 60.617775 | R48: =MAX(0,MIN(I48,N48+$O48*I48/SUM($G48:$I48))) -> 8.9628662 | S48: =MIN(1,P48/F47) -> 0.025289211 | T48: =MIN(1,Q48/G47) -> 0.0028143263 | U48: =MIN(1,R48/H47) -> 0.011432227 | V48: =AVERAGE(S45:S51) -> 0.024022271 | W48: =AVERAGE(T45:T51) -> 0.002630918 | X48: =AVERAGE(U45:U51) -> 0.012240507 | Y48: =(C48-C47)/E47 -> 0.028085087 | Z48: =AVERAGE(Y45:Y51) -> 0.025850144 | AA48: ='ori data'!AV135 -> 0.038293437 | AB48: ='ori data'!AW135 -> 0.034559753 | AD48: =AD47+$AC$49/10 -> 6484.5 | AE48: =(AD48-AD47)/E47 -> 0.00026276546 | AF48: =Z48+AE48 -> 0.026112909 | AG48: ='opt vacc_sigma0.1'!L19+AE48 -> 0.022102528
A49: 18 | B49: 44490 | C49: 3901346 | D49: 6629870 | E49: =D49-C49-SUM(F49:K49) -> 2575829 | F49: 79544 | G49: 21965 | H49: 779 | I49: 141 | J49: 49256 | K49: 1010 | L49: =G49-G48 -> 304 | M49: =H49-H48 -> -7 | N49: =I49-I48 -> -6 | O49: =J49-J48 -> 1850 | P49: =MAX(0,MIN(G49,L49+$O49*G49/SUM($G49:$I49))) -> 2079.6281 | Q49: =MAX(0,MIN(H49,M49+$O49*H49/SUM($G49:$I49))) -> 55.973563 | R49: =MAX(0,MIN(I49,N49+$O49*I49/SUM($G49:$I49))) -> 5.3982958 | S49: =MIN(1,P49/F48) -> 0.026348421 | T49: =MIN(1,Q49/G48) -> 0.0025840711 | U49: =MIN(1,R49/H48) -> 0.0068680608 | V49: =AVERAGE(S46:S52) -> 0.024209335 | W49: =AVERAGE(T46:T52) -> 0.00274757 | X49: =AVERAGE(U46:U52) -> 0.012651672 | Y49: =(C49-C48)/E48 -> 0.028020664 | Z49: =AVERAGE(Y46:Y52) -> 0.026643545 | AA49: ='ori data'!AV136 -> 0.038270009 | AB49: ='ori data'!AW136 -> 0.035390495 | AC49: 7205 | AD49: =AD48+$AC$49/10 -> 7205 | AE49: =(AD49-AD48)/E48 -> 0.000271586 | AF49: =Z49+AE49 -> 0.026915131 | AG49: ='opt vacc_sigma0.1'!L20+AE49 -> 0.021955912
